Workbook
Name IQ_CH: 110000
Name IQ_CQ: 5000
Name IQ_CY: 10000
Name IQ_DAILY: 500000
Name IQ_FH: 100000
Name IQ_FQ: 500
Name IQ_FY: 1000
Name IQ_LTM: 2000
Name IQ_MONTH: 15000
Name IQ_NTM: 6000
Name IQ_WEEK: 50000
Name IQ_YTD: 3000

Sheet Summary
B2: Summary
A4: x | B4: BLSH Standalone Summary
B5: Current share price | C5: 32.6 | E5: 46216
B6: Diluted shares outstanding (mm) | C6: 151.64835 | E6: 46216
B7: Market capitalization ($mm) | C7: =C5*C6 -> 4943.7361
B8: Total debt ($mm) | C8: 507 | E8: 46112
B9: Total cash ($mm) | C9: =76+728 -> 804 | E9: 46112
B10: Net debt ($mm) | C10: =C8-C9 -> -297 | E10: 46112
B11: Enterprise value ($mm) | C11: =C7+C10 -> 4646.7361
B13: EV / Revenue (2026P) | C13: =+Summary!C11/'P&L'!E12 -> 11.503359
B14: EV / EBITDA (2026P) | C14: =+C11/'P&L'!E37 -> 13.4688
A16: x | B16: COMPANY-SPECIFIC OPERATING ASSUMPTIONS
B17: Liquidity Service Growth | C17: Bull
B18: Volume Growth | C18: Bull
A20: x | B20: Pro Forma Summary
B21: Current share price | C21: 22.85 | E21: 46216
B22: Diluted shares outstanding (mm) | C22: =+C6+61.07 -> 212.71835 | E22: 46216 | F22: Using the disclosed structure $2.35B of newly-issued shares at a locked VWAP of $38.4797: $2.35B / $38.4797 = ≈ 61.07 million new Ordinary Shares
B23: Market capitalization ($mm) | C23: =C21*C22 -> 4860.6142
B24: Total debt ($mm) | C24: =+C8+1850 -> 2357 | E24: 46112 | F24: Bullish to assume Equiniti's existing $1.85B debt comprised of a $1.5B term loan (S + 3.75%, maturity December 2031), $350M of senior notes (8.5%, maturity November 2029) and $235M undrawn revolver (S + 3.75%, maturity December 2030)
B25: Total cash ($mm) | C25: =76+728 -> 804 | E25: 46112
B26: Net debt ($mm) | C26: =C24-C25 -> 1553 | E26: 46112
B27: Enterprise value ($mm) | C27: =C23+C26 -> 6413.6142
B29: Risk Profile
B30: Net Leverage | C30: =+C26/'P&L'!E45 -> 4.454055
B31: Interest Coverage | C31: =+'P&L'!E45 / 210 -> 1.6603383 | F31: Adjusted Net Income assumes $190M to $210M of interest expense, D&A, other and taxes of ~$30M
B33: EV / Revenue (2026P) | C33: =+Summary!C27/'P&L'!E41 -> 4.8626813
B34: EV / EBITDA (2026P) | C34: =+C27/'P&L'!E45 -> 18.394456
B36: Methodology | C36: EV | D36: Share Price | E36: Current Discount
B37: Comps — EV/EBITDA | C37: =+Valuation!C6 -> 12229.898 | D37: =+Valuation!D6 -> 50.19265 | E37: =+D37/$C$21 -1 -> 1.1966149
B38: Comps — EV/Revenue | C38: =+Valuation!C7 -> 27585.108 | D38: =+Valuation!D7 -> 122.37829 | E38: =+D38/$C$21 -1 -> 4.355724
B39: Sum-of-the-parts | C39: =+Valuation!C8 -> 20580.447 | D39: =+Valuation!D8 -> 89.449018 | E39: =+D39/$C$21 -1 -> 2.9146179
B40: DCF | C40: =+Valuation!C9 -> 11324.144 | D40: =+Valuation!D9 -> 45.934657 | E40: =+D40/$C$21 -1 -> 1.0102694

Sheet Valuation
B2: Valuation Summary — Football Field
B4: METHODOLOGY RANGE SUMMARY
B5: Methodology | C5: EV | D5: Share Price | E5: Source / tab
B6: Comps — EV/EBITDA | C6: =C15*Comps!J13 -> 12229.898 | D6: =+(C6-$C$16)/$C$17 -> 50.19265 | E6: Comps tab based on Modern Trading Platform median multiple
B7: Comps — EV/Revenue | C7: =C14*Comps!F13 -> 27585.108 | D7: =+(C7-$C$16)/$C$17 -> 122.37829 | E7: Comps tab based on Modern Trading Platform median multiple
B8: Sum-of-the-parts | C8: =+('P&L'!H9*Comps!E25)+('P&L'!H10*Comps!E44)+('P&L'!H11*Comps!E52)+('P&L'!H31*Comps!E29) -> 20580.447 | D8: =+(C8-$C$16)/$C$17 -> 89.449018 | E8: Trading Revenue * Modern Trading Platform + Liquidity Revenue * Tokenization Infra. + CoinDesk * Data and Index + Equiniti * Computershare
B9: DCF | C9: =+DCF!C25 -> 11324.144 | D9: =+(C9-$C$16)/$C$17 -> 45.934657 | E9: DCF tab
B10: 52-week trading range | D10: $21.76 - $118.00 | E10: Market data
B11: Analyst consensus target range | E11: [Street estimates source]
B14: Pro Forma Revenue 2029P | C14: ='P&L'!H41 -> 3065.012
B15: Pro Forma EBITDA 2026P | C15: ='P&L'!H45 -> 855.23759
B16: Less: net debt ($mm) | C16: =+Summary!C26 -> 1553
B17: Diluted shares (mm) | C17: =+Summary!C22 -> 212.71835

Sheet P&L
B2: Income Statement - Bullish (BLSH) Standalone
J4: =YEAR(J5) -> 2024 | K4: =YEAR(K5) -> 2024 | L4: =YEAR(L5) -> 2024 | M4: =YEAR(M5) -> 2024 | N4: =YEAR(N5) -> 2025 | O4: =YEAR(O5) -> 2025 | P4: =YEAR(P5) -> 2025 | Q4: =YEAR(Q5) -> 2025 | ... AG4: =YEAR(AG5) -> 2029
J5: 45354 | K5: =EOMONTH(J5,3) -> 45473 | L5: =EOMONTH(K5,3) -> 45565 | M5: =EOMONTH(L5,3) -> 45657 | N5: =EOMONTH(M5,3) -> 45747 | O5: =EOMONTH(N5,3) -> 45838 | P5: =EOMONTH(O5,3) -> 45930 | Q5: =EOMONTH(P5,3) -> 46022 | R5: =EOMONTH(Q5,3) -> 46112 | ... AG5: =EOMONTH(AF5,3) -> 47483
A6: x | B6: BLSH P&L Summary
B7: ($mm unless noted) | C7: 2024 | D7: 2025 | E7: 2026 | F7: 2027 | G7: 2028 | H7: 2029 | J7: ="Q" & INT((MONTH(J5)-1)/3)+1 & " " & YEAR(J5) -> Q1 2024 | K7: ="Q" & INT((MONTH(K5)-1)/3)+1 & " " & YEAR(K5) -> Q2 2024 | L7: ="Q" & INT((MONTH(L5)-1)/3)+1 & " " & YEAR(L5) -> Q3 2024 | M7: ="Q" & INT((MONTH(M5)-1)/3)+1 & " " & YEAR(M5) -> Q4 2024 | N7: ="Q" & INT((MONTH(N5)-1)/3)+1 & " " & YEAR(N5) -> Q1 2025 | O7: ="Q" & INT((MONTH(O5)-1)/3)+1 & " " & YEAR(O5) -> Q2 2025 | P7: ="Q" & INT((MONTH(P5)-1)/3)+1 & " " & YEAR(P5) -> Q3 2025 | Q7: ="Q" & INT((MONTH(Q5)-1)/3)+1 & " " & YEAR(Q5) -> Q4 2025 | ... AG7: ="Q" & INT((MONTH(AG5)-1)/3)+1 & " " & YEAR(AG5) -> Q4 2029
B8: Volume ($B) | D8: =+SUMIFS($J$8:$AG$8,$J$4:$AG$4,D$7) -> 796.2 | E8: =+SUMIFS($J$8:$AG$8,$J$4:$AG$4,E$7) -> 702.08683 | F8: =+SUMIFS($J$8:$AG$8,$J$4:$AG$4,F$7) -> 1387.4999 | G8: =+SUMIFS($J$8:$AG$8,$J$4:$AG$4,G$7) -> 3485.2421 | H8: =+SUMIFS($J$8:$AG$8,$J$4:$AG$4,H$7) -> 8754.5325 | N8: =+'Revenue Build'!C13 -> 252 | O8: =+'Revenue Build'!D13 -> 179.7 | P8: =+'Revenue Build'!E13 -> 142.2 | Q8: =+'Revenue Build'!F13 -> 222.3 | R8: =+'Revenue Build'!G13 -> 196.8 | S8: =+'Revenue Build'!H13 -> 130.8 | T8: =+'Revenue Build'!I13 -> 177.76145 | U8: =+'Revenue Build'!J13 -> 196.72538 | ... AG8: =+'Revenue Build'!V13 -> 2991.4963
B9: Transaction Revenue | C9: =+SUMIFS($J$9:$AG$9,$J$4:$AG$4,C$7) -> 153.254 | D9: =+SUMIFS($J$9:$AG$9,$J$4:$AG$4,D$7) -> 130.733 | E9: =+SUMIFS($J9:$AG9,$J$4:$AG$4,E$7) -> 139.549 | F9: =+SUMIFS($J9:$AG9,$J$4:$AG$4,F$7) -> 227.92504 | G9: =+SUMIFS($J9:$AG9,$J$4:$AG$4,G$7) -> 471.54494 | H9: =+SUMIFS($J9:$AG9,$J$4:$AG$4,H$7) -> 977.9252 | J9: =+'Income Statement'!J40 -> 44.474 | K9: =+'Income Statement'!K40 -> 34.909 | L9: =+'Income Statement'!L40 -> 32.875 | M9: =+'Income Statement'!M40 -> 40.996 | N9: =+'Income Statement'!N40 -> 42.043 | O9: =+'Income Statement'!O40 -> 24.056 | P9: =+'Income Statement'!P40 -> 26.705 | Q9: =+'Income Statement'!Q40 -> 37.929 | ... AG9: =+'Income Statement'!AG40 -> 314.93928
B10: Liquidity Subscription | C10: =+'Income Statement'!C41-C11 -> 23.784 | D10: =+'Income Statement'!D41-D11 -> 103.495 | E10: =+SUMIFS($J10:$AG10,$J$4:$AG$4,E$7) -> 236.84244 | F10: =+SUMIFS($J10:$AG10,$J$4:$AG$4,F$7) -> 361.08491 | G10: =+SUMIFS($J10:$AG10,$J$4:$AG$4,G$7) -> 634.0446 | H10: =+SUMIFS($J10:$AG10,$J$4:$AG$4,H$7) -> 1113.3463 | J10: =+'Income Statement'!J41 -> 8.8 | K10: =+'Income Statement'!K41 -> 25.8 | L10: =+'Income Statement'!L41 -> 11.5 | M10: =+'Income Statement'!M41 -> 13.684 | N10: =+'Income Statement'!N41 -> 19.741 | O10: =+'Income Statement'!O41 -> 31.9 | P10: =+'Income Statement'!P41 -> 49.3 | Q10: =+'Income Statement'!Q41 -> 54.554 | ... S10: =+'Income Statement'!S41 -> 62.689 | T10: =+'Revenue Build'!I35 -> 56.668945 | U10: =+'Revenue Build'!J35 -> 62.714497 | V10: =+'Revenue Build'!K35 -> 72.193078 | W10: =+'Revenue Build'!L35 -> 83.104239 | X10: =+'Revenue Build'!M35 -> 95.664497 | Y10: =+'Revenue Build'!N35 -> 110.1231 | Z10: =+'Revenue Build'!O35 -> 126.76695 | AA10: =+'Revenue Build'!P35 -> 145.92632 | ... AG10: =+'Revenue Build'!V35 -> 339.54657
B11: CoinDesk (Data, Insights, Indices) | C11: =27+9 -> 36 | D11: =34+18 -> 52 | E11: =+SUMIFS($J11:$AG11,$J$4:$AG$4,E$7) -> 27.554589 | F11: =+SUMIFS($J11:$AG11,$J$4:$AG$4,F$7) -> 59.235358 | G11: =+SUMIFS($J11:$AG11,$J$4:$AG$4,G$7) -> 65.420661 | H11: =+SUMIFS($J11:$AG11,$J$4:$AG$4,H$7) -> 72.533761 | T11: =+SUM('Revenue Build'!I31:I32) -> 13.615235 | U11: =+SUM('Revenue Build'!J31:J32) -> 13.939355 | V11: =+SUM('Revenue Build'!K31:K32) -> 14.275 | W11: =+SUM('Revenue Build'!L31:L32) -> 14.62258 | X11: =+SUM('Revenue Build'!M31:M32) -> 14.98252 | Y11: =+SUM('Revenue Build'!N31:N32) -> 15.355258 | Z11: =+SUM('Revenue Build'!O31:O32) -> 15.74125 | AA11: =+SUM('Revenue Build'!P31:P32) -> 16.140967 | ... AG11: =+SUM('Revenue Build'!V31:V32) -> 18.856079
B12: Total Adjusted Revenue | C12: =SUM(C9:C11) -> 213.038 | D12: =SUM(D9:D11) -> 286.228 | E12: =SUM(E9:E11) -> 403.94603 | F12: =SUM(F9:F11) -> 648.24531 | G12: =SUM(G9:G11) -> 1171.0102 | H12: =SUM(H9:H11) -> 2163.8053 | J12: =SUM(J9:J11) -> 53.274 | K12: =SUM(K9:K11) -> 60.709 | L12: =SUM(L9:L11) -> 44.375 | M12: =SUM(M9:M11) -> 54.68 | N12: =SUM(N9:N11) -> 61.784 | O12: =SUM(O9:O11) -> 55.956 | P12: =SUM(P9:P11) -> 76.005 | Q12: =SUM(Q9:Q11) -> 92.483 | ... AG12: =SUM(AG9:AG11) -> 673.34193
D13: =D12/C12-1 -> 0.34355373 | E13: =E12/D12-1 -> 0.41127364 | F13: =F12/E12-1 -> 0.60478198 | G13: =G12/F12-1 -> 0.80643065 | H13: =H12/G12-1 -> 0.84781078
B15: Administrative expenses | C15: =SUMIFS($J15:$AG15,$J$4:$AG$4,C$7) -> -153.119 | D15: =SUMIFS($J15:$AG15,$J$4:$AG$4,D$7) -> -182.188 | E15: =SUMIFS($J15:$AG15,$J$4:$AG$4,E$7) -> -219.16383 | F15: =SUMIFS($J15:$AG15,$J$4:$AG$4,F$7) -> -326.52288 | G15: =SUMIFS($J15:$AG15,$J$4:$AG$4,G$7) -> -542.46313 | H15: =SUMIFS($J15:$AG15,$J$4:$AG$4,H$7) -> -915.39376 | J15: ='Income Statement'!J13 -> -36.757 | K15: ='Income Statement'!K13 -> -39.662 | L15: ='Income Statement'!L13 -> -39.618 | M15: ='Income Statement'!M13 -> -37.082 | N15: ='Income Statement'!N13 -> -47.186 | O15: ='Income Statement'!O13 -> -43.017 | P15: ='Income Statement'!P13 -> -45.709 | Q15: ='Income Statement'!Q13 -> -46.276 | ... S15: ='Income Statement'!S13 -> -56.268 | T15: =-T12*T16 -> -56.038733 | U15: =-U12*U16 -> -58.577096 | V15: =-V12*V16 -> -67.048341 | W15: =-W12*W16 -> -77.302445 | X15: =-X12*X16 -> -85.249379 | Y15: =-Y12*Y16 -> -96.922714 | Z15: =-Z12*Z16 -> -110.79589 | AA15: =-AA12*AA16 -> -126.0608 | ... AG15: =-AG12*AG16 -> -276.03427
B16: % of revenue | C16: =-C15/C12 -> 0.71874032 | D16: =-D15/D12 -> 0.63651355 | E16: =-E15/E12 -> 0.5425572 | F16: 0.15 | G16: 0.13 | H16: 0.1 | J16: =-J15/J12 -> 0.68996133 | K16: =-K15/K12 -> 0.65331335 | L16: =-L15/L12 -> 0.8928 | M16: =-M15/M12 -> 0.67816386 | N16: =-N15/N12 -> 0.76372524 | O16: =-O15/O12 -> 0.76876474 | P16: =-P15/P12 -> 0.60139465 | Q16: =-Q15/Q12 -> 0.50037304 | ... S16: =-S15/S12 -> 0.60908535 | T16: =AVERAGE(P16:S16) - $AH$16 -> 0.53279614 | U16: =AVERAGE(Q16:T16) - $AH$16 -> 0.51564651 | V16: =AVERAGE(R16:U16) - $AH$16 -> 0.51946488 | W16: =AVERAGE(S16:V16) - $AH$16 -> 0.51924822 | X16: =AVERAGE(T16:W16) - $AH$16 -> 0.49678894 | Y16: =AVERAGE(U16:X16) - $AH$16 -> 0.48778714 | Z16: =AVERAGE(V16:Y16) - $AH$16 -> 0.48082229 | AA16: =AVERAGE(W16:Z16) - $AH$16 -> 0.47116165 | ... AG16: =AVERAGE(AC16:AF16) - $AH$16 -> 0.40994665 | AH16: 0.025
B17: Finance Expenses | C17: =SUMIFS($J17:$AG17,$J$4:$AG$4,C$7) -> -46.081 | D17: =SUMIFS($J17:$AG17,$J$4:$AG$4,D$7) -> -60.425 | E17: =SUMIFS($J17:$AG17,$J$4:$AG$4,E$7) -> -117.42302 | F17: =SUMIFS($J17:$AG17,$J$4:$AG$4,F$7) -> -116.68416 | G17: =SUMIFS($J17:$AG17,$J$4:$AG$4,G$7) -> -210.78184 | H17: =SUMIFS($J17:$AG17,$J$4:$AG$4,H$7) -> -389.48495 | J17: ='Income Statement'!J14 -> -9.916 | K17: ='Income Statement'!K14 -> -16.72 | L17: ='Income Statement'!L14 -> -6.81 | M17: ='Income Statement'!M14 -> -12.635 | N17: ='Income Statement'!N14 -> -15.063 | O17: ='Income Statement'!O14 -> -17.362 | P17: ='Income Statement'!P14 -> -13.608 | Q17: ='Income Statement'!Q14 -> -14.392 | ... S17: ='Income Statement'!S14 -> -32.513 | T17: =-T12*T18 -> -18.932142 | U17: =-U12*U18 -> -20.447879 | V17: =-V12*V18 -> -23.23295 | W17: =-W12*W18 -> -26.79728 | X17: =-X12*X18 -> -30.888144 | Y17: =-Y12*Y18 -> -35.765782 | Z17: =-Z12*Z18 -> -41.477405 | AA17: =-AA12*AA18 -> -48.159573 | ... AG17: =-AG12*AG18 -> -121.20155
B18: % of revenue | C18: =-C17/C12 -> 0.21630413 | D18: =-D17/D12 -> 0.21110793 | E18: =-E17/E12 -> 0.29068987 | F18: =-F17/F12 -> 0.18 | G18: =-G17/G12 -> 0.18 | H18: =-H17/H12 -> 0.18 | J18: =-J17/J12 -> 0.18613207 | K18: =-K17/K12 -> 0.27541221 | L18: =-L17/L12 -> 0.15346479 | M18: =-M17/M12 -> 0.23107169 | N18: =-N17/N12 -> 0.24380098 | O18: =-O17/O12 -> 0.31027951 | P18: =-P17/P12 -> 0.17904085 | Q18: =-Q17/Q12 -> 0.15561779 | ... S18: =-S17/S12 -> 0.35194413 | T18: =$AH$18 -> 0.18 | U18: =$AH$18 -> 0.18 | V18: =$AH$18 -> 0.18 | W18: =$AH$18 -> 0.18 | X18: =$AH$18 -> 0.18 | Y18: =$AH$18 -> 0.18 | Z18: =$AH$18 -> 0.18 | AA18: =$AH$18 -> 0.18 | ... AG18: =$AH$18 -> 0.18 | AH18: 0.18
B19: Other expenses | C19: =SUMIFS($J19:$AG19,$J$4:$AG$4,C$7) -> -38.529 | D19: =SUMIFS($J19:$AG19,$J$4:$AG$4,D$7) -> -52.369 | E19: =SUMIFS($J19:$AG19,$J$4:$AG$4,E$7) -> -63.688136 | F19: =SUMIFS($J19:$AG19,$J$4:$AG$4,F$7) -> -102.8223 | G19: =SUMIFS($J19:$AG19,$J$4:$AG$4,G$7) -> -185.87471 | H19: =SUMIFS($J19:$AG19,$J$4:$AG$4,H$7) -> -343.48823 | J19: ='Income Statement'!J15 -> -8.929 | K19: ='Income Statement'!K15 -> -9.063 | L19: ='Income Statement'!L15 -> -9.878 | M19: ='Income Statement'!M15 -> -10.659 | N19: ='Income Statement'!N15 -> -10.24 | O19: ='Income Statement'!O15 -> -13.291 | P19: ='Income Statement'!P15 -> -13.906 | Q19: ='Income Statement'!Q15 -> -14.932 | ... S19: ='Income Statement'!S15 -> -14.459 | T19: =-T12*T20 -> -17.164211 | U19: =-U12*U20 -> -17.976925 | V19: =-V12*V20 -> -20.321923 | W19: =-W12*W20 -> -23.648629 | X19: =-X12*X20 -> -27.359017 | Y19: =-Y12*Y20 -> -31.492729 | Z19: =-Z12*Z20 -> -36.536154 | AA19: =-AA12*AA20 -> -42.496509 | ... AG19: =-AG12*AG20 -> -106.8796
B20: % of revenue | C20: =-C19/C12 -> 0.18085506 | D20: =-D19/D12 -> 0.18296253 | E20: =-E19/E12 -> 0.15766496 | F20: =-F19/F12 -> 0.15861634 | G20: =-G19/G12 -> 0.15873023 | H20: =-H19/H12 -> 0.15874267 | J20: =-J19/J12 -> 0.16760521 | K20: =-K19/K12 -> 0.14928594 | L20: =-L19/L12 -> 0.22260282 | M20: =-M19/M12 -> 0.19493416 | N20: =-N19/N12 -> 0.1657387 | O20: =-O19/O12 -> 0.23752591 | P20: =-P19/P12 -> 0.18296165 | Q20: =-Q19/Q12 -> 0.1614567 | ... S20: =-S19/S12 -> 0.15651463 | T20: =AVERAGE(P20:S20) -> 0.16319115 | U20: =AVERAGE(Q20:T20) -> 0.15824852 | V20: =AVERAGE(R20:U20) -> 0.15744648 | W20: =AVERAGE(S20:V20) -> 0.15885019 | X20: =AVERAGE(T20:W20) -> 0.15943409 | Y20: =AVERAGE(U20:X20) -> 0.15849482 | Z20: =AVERAGE(V20:Y20) -> 0.15855639 | AA20: =AVERAGE(W20:Z20) -> 0.15883387 | ... AG20: =AVERAGE(AC20:AF20) -> 0.15873005
B21: OpEx | C21: =C15+C17+C19 -> -237.729 | D21: =D15+D17+D19 -> -294.982 | E21: =E15+E17+E19 -> -400.27498 | F21: =F15+F17+F19 -> -546.02933 | G21: =G15+G17+G19 -> -939.11968 | H21: =H15+H17+H19 -> -1648.3669 | J21: =J15+J17+J19 -> -55.602 | K21: =K15+K17+K19 -> -65.445 | L21: =L15+L17+L19 -> -56.306 | M21: =M15+M17+M19 -> -60.376 | N21: =N15+N17+N19 -> -72.489 | O21: =O15+O17+O19 -> -73.67 | P21: =P15+P17+P19 -> -73.223 | Q21: =Q15+Q17+Q19 -> -75.6 | ... AG21: =AG15+AG17+AG19 -> -504.11541
B23: EBITDA | C23: =+C12+C21 -> -24.691 | D23: =+D12+D21 -> -8.754 | E23: =+E12+E21 -> 3.6710457 | F23: =+F12+F21 -> 102.21598 | G23: =+G12+G21 -> 231.89052 | H23: =+H12+H21 -> 515.43833 | J23: =+J12+J21 -> -2.328 | K23: =+K12+K21 -> -4.736 | L23: =+L12+L21 -> -11.931 | M23: =+M12+M21 -> -5.696 | N23: =+N12+N21 -> -10.705 | O23: =+O12+O21 -> -17.714 | P23: =+P12+P21 -> 2.782 | Q23: =+Q12+Q21 -> 16.883 | ... AG23: =+AG12+AG21 -> 169.22652
A25: x | B25: Equiniti P&L Summary
B26: ($mm unless noted) | C26: 2024 | D26: 2025 | E26: 2026 | F26: 2027 | G26: 2028 | H26: 2029
B27: Issuer & Holder Services | E27: 685 | F27: =+E27*(1+F28) -> 705.55 | G27: =+F27*(1+G28) -> 719.661 | H27: =+G27*(1+H28) -> 734.05422
B28: Growth | F28: 0.03 | G28: 0.02 | H28: 0.02
B29: Interest Income | E29: 230 | F29: =+E29*(1+F30) -> 218.5 | G29: =+F29*(1+G30) -> 196.65 | H29: =+G29*(1+H30) -> 167.1525
B30: Growth | F30: -0.05 | G30: -0.1 | H30: -0.15
B31: Total Revenue | E31: =+E27+E29 -> 915 | F31: =+F27+F29 -> 924.05 | G31: =+G27+G29 -> 916.311 | H31: =+H27+H29 -> 901.20672
B33: OpEx | E33: -505 | F33: =+-F31*F34 -> -509.99481 | G33: =+-G31*G34 -> -505.72356 | H33: =+-H31*H34 -> -497.38732
B34: % of Revenue | E34: =+-E33/E31 -> 0.55191257 | F34: =+E34 -> 0.55191257 | G34: =+F34 -> 0.55191257 | H34: =+G34 -> 0.55191257
B35: CapEx | E35: -65 | F35: =+-F31*F36 -> -65.642896 | G35: =+-G31*G36 -> -65.093131 | H35: =+-H31*H36 -> -64.02015
B36: % of Revenue | E36: =+-E35/E31 -> 0.071038251 | F36: =+E36 -> 0.071038251 | G36: =+F36 -> 0.071038251 | H36: =+G36 -> 0.071038251
B37: EBITDA | E37: =+E31+E33+E35 -> 345 | F37: =+F31+F33+F35 -> 348.4123 | G37: =+G31+G33+G35 -> 345.49431 | H37: =+H31+H33+H35 -> 339.79926
A39: x | B39: Pro Forma P&L Summary (Excluding synergies)
C40: 2024 | D40: 2025 | E40: 2026 | F40: 2027 | G40: 2028 | H40: 2029
B41: Total Revenue | E41: =+E12+E31 -> 1318.946 | F41: =+F12+F31 -> 1572.2953 | G41: =+G12+G31 -> 2087.3212 | H41: =+H12+H31 -> 3065.012
B43: OpEx | E43: =+E21+E33 -> -905.27498 | F43: =+F21+F33 -> -1056.0241 | G43: =+G21+G33 -> -1444.8432 | H43: =+H21+H33 -> -2145.7543
B44: CapEx | E44: =+E35 -> -65 | F44: =+F35 -> -65.642896 | G44: =+G35 -> -65.093131 | H44: =+H35 -> -64.02015
B45: EBITDA | E45: =+E41+E43+E44 -> 348.67105 | F45: =+F41+F43+F44 -> 450.62827 | G45: =+G41+G43+G44 -> 577.38483 | H45: =+H41+H43+H44 -> 855.23759

Sheet Revenue Build
B2: Revenue Build
B4: Revenue Build | Z4: Notes
C5: 1 | D5: =+C5+1 -> 2 | E5: =+D5+1 -> 3 | F5: =+E5+1 -> 4 | G5: =+F5+1 -> 5 | H5: =+G5+1 -> 6 | I5: =+H5+1 -> 7 | J5: =+I5+1 -> 8 | K5: =+J5+1 -> 9 | ... V5: =+U5+1 -> 20
C6: 2025 | D6: =+IF(MOD(D5,4)=1,C6+1,C6) -> 2025 | E6: =+IF(MOD(E5,4)=1,D6+1,D6) -> 2025 | F6: =+IF(MOD(F5,4)=1,E6+1,E6) -> 2025 | G6: =+IF(MOD(G5,4)=1,F6+1,F6) -> 2026 | H6: =+IF(MOD(H5,4)=1,G6+1,G6) -> 2026 | I6: =+IF(MOD(I5,4)=1,H6+1,H6) -> 2026 | J6: =+IF(MOD(J5,4)=1,I6+1,I6) -> 2026 | K6: =+IF(MOD(K5,4)=1,J6+1,J6) -> 2027 | ... V6: =+IF(MOD(V5,4)=1,U6+1,U6) -> 2029
C7: =+"Q"&IF(MOD(C5,4)=0,4,MOD(C5,4)) -> Q1 | D7: =+"Q"&IF(MOD(D5,4)=0,4,MOD(D5,4)) -> Q2 | E7: =+"Q"&IF(MOD(E5,4)=0,4,MOD(E5,4)) -> Q3 | F7: =+"Q"&IF(MOD(F5,4)=0,4,MOD(F5,4)) -> Q4 | G7: =+"Q"&IF(MOD(G5,4)=0,4,MOD(G5,4)) -> Q1 | H7: =+"Q"&IF(MOD(H5,4)=0,4,MOD(H5,4)) -> Q2 | I7: =+"Q"&IF(MOD(I5,4)=0,4,MOD(I5,4)) -> Q3 | J7: =+"Q"&IF(MOD(J5,4)=0,4,MOD(J5,4)) -> Q4 | ... V7: =+"Q"&IF(MOD(V5,4)=0,4,MOD(V5,4)) -> Q4
C8: =+C7 & " " &C6 -> Q1 2025 | D8: =+D7 & " " &D6 -> Q2 2025 | E8: =+E7 & " " &E6 -> Q3 2025 | F8: =+F7 & " " &F6 -> Q4 2025 | G8: =+G7 & " " &G6 -> Q1 2026 | H8: =+H7 & " " &H6 -> Q2 2026 | I8: =+I7 & " " &I6 -> Q3 2026 | J8: =+J7 & " " &J6 -> Q4 2026 | ... V8: =+V7 & " " &V6 -> Q4 2029
B9: Volume ($Bs)
B10: Spot | C10: =+SUMIFS('Monthly Metrics'!$C17:$BJ17,'Monthly Metrics'!$C$7:$BJ$7,'Revenue Build'!C$7,'Monthly Metrics'!$C$6:$BJ$6,'Revenue Build'!C$6) -> 229.6 | D10: =+SUMIFS('Monthly Metrics'!$C17:$BJ17,'Monthly Metrics'!$C$7:$BJ$7,'Revenue Build'!D$7,'Monthly Metrics'!$C$6:$BJ$6,'Revenue Build'!D$6) -> 163 | E10: =+SUMIFS('Monthly Metrics'!$C17:$BJ17,'Monthly Metrics'!$C$7:$BJ$7,'Revenue Build'!E$7,'Monthly Metrics'!$C$6:$BJ$6,'Revenue Build'!E$6) -> 130.4 | F10: =+SUMIFS('Monthly Metrics'!$C17:$BJ17,'Monthly Metrics'!$C$7:$BJ$7,'Revenue Build'!F$7,'Monthly Metrics'!$C$6:$BJ$6,'Revenue Build'!F$6) -> 205 | G10: =+SUMIFS('Monthly Metrics'!$C17:$BJ17,'Monthly Metrics'!$C$7:$BJ$7,'Revenue Build'!G$7,'Monthly Metrics'!$C$6:$BJ$6,'Revenue Build'!G$6) -> 175.7 | H10: =+SUMIFS('Monthly Metrics'!$C17:$BJ17,'Monthly Metrics'!$C$7:$BJ$7,'Revenue Build'!H$7,'Monthly Metrics'!$C$6:$BJ$6,'Revenue Build'!H$6) -> 113.5 | I10: =+SUMIFS('Monthly Metrics'!$C17:$BJ17,'Monthly Metrics'!$C$7:$BJ$7,'Revenue Build'!I$7,'Monthly Metrics'!$C$6:$BJ$6,'Revenue Build'!I$6) -> 159.57758 | J10: =+SUMIFS('Monthly Metrics'!$C17:$BJ17,'Monthly Metrics'!$C$7:$BJ$7,'Revenue Build'!J$7,'Monthly Metrics'!$C$6:$BJ$6,'Revenue Build'!J$6) -> 176.60162 | ... V10: =+SUMIFS('Monthly Metrics'!$C17:$BJ17,'Monthly Metrics'!$C$7:$BJ$7,'Revenue Build'!V$7,'Monthly Metrics'!$C$6:$BJ$6,'Revenue Build'!V$6) -> 2685.4851
B11: Options | C11: =+SUMIFS('Monthly Metrics'!$C18:$BJ18,'Monthly Metrics'!$C$7:$BJ$7,'Revenue Build'!C$7,'Monthly Metrics'!$C$6:$BJ$6,'Revenue Build'!C$6) -> 0 | D11: =+SUMIFS('Monthly Metrics'!$C18:$BJ18,'Monthly Metrics'!$C$7:$BJ$7,'Revenue Build'!D$7,'Monthly Metrics'!$C$6:$BJ$6,'Revenue Build'!D$6) -> 0 | E11: =+SUMIFS('Monthly Metrics'!$C18:$BJ18,'Monthly Metrics'!$C$7:$BJ$7,'Revenue Build'!E$7,'Monthly Metrics'!$C$6:$BJ$6,'Revenue Build'!E$6) -> 0 | F11: =+SUMIFS('Monthly Metrics'!$C18:$BJ18,'Monthly Metrics'!$C$7:$BJ$7,'Revenue Build'!F$7,'Monthly Metrics'!$C$6:$BJ$6,'Revenue Build'!F$6) -> 9 | G11: =+SUMIFS('Monthly Metrics'!$C18:$BJ18,'Monthly Metrics'!$C$7:$BJ$7,'Revenue Build'!G$7,'Monthly Metrics'!$C$6:$BJ$6,'Revenue Build'!G$6) -> 11.6 | H11: =+SUMIFS('Monthly Metrics'!$C18:$BJ18,'Monthly Metrics'!$C$7:$BJ$7,'Revenue Build'!H$7,'Monthly Metrics'!$C$6:$BJ$6,'Revenue Build'!H$6) -> 8.8 | I11: =+SUMIFS('Monthly Metrics'!$C18:$BJ18,'Monthly Metrics'!$C$7:$BJ$7,'Revenue Build'!I$7,'Monthly Metrics'!$C$6:$BJ$6,'Revenue Build'!I$6) -> 7.2816797 | J11: =+SUMIFS('Monthly Metrics'!$C18:$BJ18,'Monthly Metrics'!$C$7:$BJ$7,'Revenue Build'!J$7,'Monthly Metrics'!$C$6:$BJ$6,'Revenue Build'!J$6) -> 8.0585033 | ... V11: =+SUMIFS('Monthly Metrics'!$C18:$BJ18,'Monthly Metrics'!$C$7:$BJ$7,'Revenue Build'!V$7,'Monthly Metrics'!$C$6:$BJ$6,'Revenue Build'!V$6) -> 122.54129
B12: Perps | C12: =+SUMIFS('Monthly Metrics'!$C19:$BJ19,'Monthly Metrics'!$C$7:$BJ$7,'Revenue Build'!C$7,'Monthly Metrics'!$C$6:$BJ$6,'Revenue Build'!C$6) -> 22.4 | D12: =+SUMIFS('Monthly Metrics'!$C19:$BJ19,'Monthly Metrics'!$C$7:$BJ$7,'Revenue Build'!D$7,'Monthly Metrics'!$C$6:$BJ$6,'Revenue Build'!D$6) -> 16.7 | E12: =+SUMIFS('Monthly Metrics'!$C19:$BJ19,'Monthly Metrics'!$C$7:$BJ$7,'Revenue Build'!E$7,'Monthly Metrics'!$C$6:$BJ$6,'Revenue Build'!E$6) -> 11.8 | F12: =+SUMIFS('Monthly Metrics'!$C19:$BJ19,'Monthly Metrics'!$C$7:$BJ$7,'Revenue Build'!F$7,'Monthly Metrics'!$C$6:$BJ$6,'Revenue Build'!F$6) -> 8.3 | G12: =+SUMIFS('Monthly Metrics'!$C19:$BJ19,'Monthly Metrics'!$C$7:$BJ$7,'Revenue Build'!G$7,'Monthly Metrics'!$C$6:$BJ$6,'Revenue Build'!G$6) -> 9.5 | H12: =+SUMIFS('Monthly Metrics'!$C19:$BJ19,'Monthly Metrics'!$C$7:$BJ$7,'Revenue Build'!H$7,'Monthly Metrics'!$C$6:$BJ$6,'Revenue Build'!H$6) -> 8.5 | I12: =+SUMIFS('Monthly Metrics'!$C19:$BJ19,'Monthly Metrics'!$C$7:$BJ$7,'Revenue Build'!I$7,'Monthly Metrics'!$C$6:$BJ$6,'Revenue Build'!I$6) -> 10.902192 | J12: =+SUMIFS('Monthly Metrics'!$C19:$BJ19,'Monthly Metrics'!$C$7:$BJ$7,'Revenue Build'!J$7,'Monthly Metrics'!$C$6:$BJ$6,'Revenue Build'!J$6) -> 12.065259 | ... V12: =+SUMIFS('Monthly Metrics'!$C19:$BJ19,'Monthly Metrics'!$C$7:$BJ$7,'Revenue Build'!V$7,'Monthly Metrics'!$C$6:$BJ$6,'Revenue Build'!V$6) -> 183.46986
B13: Total Volume | C13: =SUM(C10:C12) -> 252 | D13: =SUM(D10:D12) -> 179.7 | E13: =SUM(E10:E12) -> 142.2 | F13: =SUM(F10:F12) -> 222.3 | G13: =SUM(G10:G12) -> 196.8 | H13: =SUM(H10:H12) -> 130.8 | I13: =SUM(I10:I12) -> 177.76145 | J13: =SUM(J10:J12) -> 196.72538 | ... V13: =SUM(V10:V12) -> 2991.4963
B14: YoY Growth | G14: =+G13/C13-1 -> -0.21904762 | H14: =+H13/D13-1 -> -0.2721202 | I14: =+I13/E13-1 -> 0.2500805 | J14: =+J13/F13-1 -> -0.11504552 | K14: =+K13/G13-1 -> 0.20743391 | L14: =+L13/H13-1 -> 1.2870766 | M14: =+M13/I13-1 -> 1.1186093 | N14: =+N13/J13-1 -> 1.4100612 | ... V14: =+V13/R13-1 -> 1.5118864
B15: Trading Spread (bps)
B16: Spot | C16: =+AVERAGEIFS('Monthly Metrics'!$C26:$T26,'Monthly Metrics'!$C$7:$T$7,'Revenue Build'!C$7,'Monthly Metrics'!$C$6:$T$6,'Revenue Build'!C$6) -> 1.9933333 | D16: =+AVERAGEIFS('Monthly Metrics'!$C26:$T26,'Monthly Metrics'!$C$7:$T$7,'Revenue Build'!D$7,'Monthly Metrics'!$C$6:$T$6,'Revenue Build'!D$6) -> 1.5933333 | E16: =+AVERAGEIFS('Monthly Metrics'!$C26:$T26,'Monthly Metrics'!$C$7:$T$7,'Revenue Build'!E$7,'Monthly Metrics'!$C$6:$T$6,'Revenue Build'!E$6) -> 2.09 | F16: =+AVERAGEIFS('Monthly Metrics'!$C26:$T26,'Monthly Metrics'!$C$7:$T$7,'Revenue Build'!F$7,'Monthly Metrics'!$C$6:$T$6,'Revenue Build'!F$6) -> 1.8366667 | G16: =+AVERAGEIFS('Monthly Metrics'!$C26:$T26,'Monthly Metrics'!$C$7:$T$7,'Revenue Build'!G$7,'Monthly Metrics'!$C$6:$T$6,'Revenue Build'!G$6) -> 1.99 | H16: =+AVERAGEIFS('Monthly Metrics'!$C26:$T26,'Monthly Metrics'!$C$7:$T$7,'Revenue Build'!H$7,'Monthly Metrics'!$C$6:$T$6,'Revenue Build'!H$6) -> 2.43 | I16: =+AVERAGE(C16:H16) * ( 1- $W$16) -> 2.0883333 | J16: =+I16 * (1+$W$16) -> 1.9839167 | K16: =+J16 * (1+$W$16) -> 1.8847208 | L16: =+K16 * (1+$W$16) -> 1.7904848 | M16: =+L16 * (1+$W$16) -> 1.7009606 | N16: =+M16 * (1+$W$16) -> 1.6159125 | O16: =+N16 * (1+$W$16) -> 1.5351169 | P16: =+O16 * (1+$W$16) -> 1.4583611 | Q16: =+P16 * (1+$W$16) -> 1.385443 | ... V16: =+U16 * (1+$W$16) -> 1.0720294 | W16: -0.05 | X16: Taper | Z16: Bullish consistently states that they intend to offer the lowest spreads and high liquidity.
B17: Options | E17: =+AVERAGEIFS('Monthly Metrics'!$C27:$T27,'Monthly Metrics'!$C$7:$T$7,'Revenue Build'!E$7,'Monthly Metrics'!$C$6:$T$6,'Revenue Build'!E$6) -> 0.965 | F17: =+AVERAGEIFS('Monthly Metrics'!$C27:$T27,'Monthly Metrics'!$C$7:$T$7,'Revenue Build'!F$7,'Monthly Metrics'!$C$6:$T$6,'Revenue Build'!F$6) -> 1.43 | G17: =+AVERAGEIFS('Monthly Metrics'!$C27:$T27,'Monthly Metrics'!$C$7:$T$7,'Revenue Build'!G$7,'Monthly Metrics'!$C$6:$T$6,'Revenue Build'!G$6) -> 2.0766667 | H17: =+AVERAGEIFS('Monthly Metrics'!$C27:$T27,'Monthly Metrics'!$C$7:$T$7,'Revenue Build'!H$7,'Monthly Metrics'!$C$6:$T$6,'Revenue Build'!H$6) -> 1.58 | I17: =+AVERAGE(C17:H17) * ( 1- $W$16) -> 1.5885625 | J17: =+I17 * (1+$W$16) -> 1.5091344 | K17: =+J17 * (1+$W$16) -> 1.4336777 | L17: =+K17 * (1+$W$16) -> 1.3619938 | M17: =+L17 * (1+$W$16) -> 1.2938941 | N17: =+M17 * (1+$W$16) -> 1.2291994 | O17: =+N17 * (1+$W$16) -> 1.1677394 | P17: =+O17 * (1+$W$16) -> 1.1093524 | Q17: =+P17 * (1+$W$16) -> 1.0538848 | ... V17: =+U17 * (1+$W$16) -> 0.81547598
B18: Perps | C18: =+AVERAGEIFS('Monthly Metrics'!$C28:$T28,'Monthly Metrics'!$C$7:$T$7,'Revenue Build'!C$7,'Monthly Metrics'!$C$6:$T$6,'Revenue Build'!C$6) -> -1.6166667 | D18: =+AVERAGEIFS('Monthly Metrics'!$C28:$T28,'Monthly Metrics'!$C$7:$T$7,'Revenue Build'!D$7,'Monthly Metrics'!$C$6:$T$6,'Revenue Build'!D$6) -> -1.1833333 | E18: =+AVERAGEIFS('Monthly Metrics'!$C28:$T28,'Monthly Metrics'!$C$7:$T$7,'Revenue Build'!E$7,'Monthly Metrics'!$C$6:$T$6,'Revenue Build'!E$6) -> -0.41333333 | F18: =+AVERAGEIFS('Monthly Metrics'!$C28:$T28,'Monthly Metrics'!$C$7:$T$7,'Revenue Build'!F$7,'Monthly Metrics'!$C$6:$T$6,'Revenue Build'!F$6) -> -1.0333333 | G18: =+AVERAGEIFS('Monthly Metrics'!$C28:$T28,'Monthly Metrics'!$C$7:$T$7,'Revenue Build'!G$7,'Monthly Metrics'!$C$6:$T$6,'Revenue Build'!G$6) -> -0.05 | H18: =+AVERAGEIFS('Monthly Metrics'!$C28:$T28,'Monthly Metrics'!$C$7:$T$7,'Revenue Build'!H$7,'Monthly Metrics'!$C$6:$T$6,'Revenue Build'!H$6) -> -0.11333333 | I18: =+AVERAGE(C18:H18) * ( 1- $W$16) -> -0.77175 | J18: =+I18 * (1+$W$16) -> -0.7331625 | K18: =+J18 * (1+$W$16) -> -0.69650437 | L18: =+K18 * (1+$W$16) -> -0.66167916 | M18: =+L18 * (1+$W$16) -> -0.6285952 | N18: =+M18 * (1+$W$16) -> -0.59716544 | O18: =+N18 * (1+$W$16) -> -0.56730717 | P18: =+O18 * (1+$W$16) -> -0.53894181 | Q18: =+P18 * (1+$W$16) -> -0.51199472 | ... V18: =+U18 * (1+$W$16) -> -0.39617175
B19: Average Trading Spread | C19: =+AVERAGE(C16:C18) -> 0.18833333 | D19: =+AVERAGE(D16:D18) -> 0.205 | E19: =+AVERAGE(E16:E18) -> 0.88055556 | F19: =+AVERAGE(F16:F18) -> 0.74444444 | G19: =+AVERAGE(G16:G18) -> 1.3388889 | H19: =+AVERAGE(H16:H18) -> 1.2988889 | I19: =+AVERAGE(I16:I18) -> 0.96838194 | J19: =+AVERAGE(J16:J18) -> 0.91996285 | ... V19: =+AVERAGE(V16:V18) -> 0.4971112
B20: Spread Revenue ($Ms)
B21: Spot | H21: =+(H10*(H16/10000)) * 1000 -> 27.5805 | I21: =+(I10*(I16/10000)) * 1000 -> 33.325117 | J21: =+(J10*(J16/10000)) * 1000 -> 35.036289 | K21: =+(K10*(K16/10000)) * 1000 -> 40.204048 | L21: =+(L10*(L16/10000)) * 1000 -> 48.083202 | M21: =+(M10*(M16/10000)) * 1000 -> 57.506507 | N21: =+(N10*(N16/10000)) * 1000 -> 68.776583 | O21: =+(O10*(O16/10000)) * 1000 -> 82.255359 | ... V21: =+(V10*(V16/10000)) * 1000 -> 287.89189
B22: Options | H22: =+(H11*(H17/10000)) * 1000 -> 1.3904 | I22: =+(I11*(I17/10000)) * 1000 -> 1.1567403 | J22: =+(J11*(J17/10000)) * 1000 -> 1.2161364 | K22: =+(K11*(K17/10000)) * 1000 -> 1.3955133 | L22: =+(L11*(L17/10000)) * 1000 -> 1.6690048 | M22: =+(M11*(M17/10000)) * 1000 -> 1.9960949 | N22: =+(N11*(N17/10000)) * 1000 -> 2.3872879 | O22: =+(O11*(O17/10000)) * 1000 -> 2.8551465 | ... V22: =+(V11*(V17/10000)) * 1000 -> 9.9929481
B23: Perps | H23: =+(H12*(H18/10000)) * 1000 -> -0.096333333 | I23: =+(I12*(I18/10000)) * 1000 -> -0.8413767 | J23: =+(J12*(J18/10000)) * 1000 -> -0.88457956 | K23: =+(K12*(K18/10000)) * 1000 -> -1.0150527 | L23: =+(L12*(L18/10000)) * 1000 -> -1.2139818 | M23: =+(M12*(M18/10000)) * 1000 -> -1.4518969 | N23: =+(N12*(N18/10000)) * 1000 -> -1.7364384 | O23: =+(O12*(O18/10000)) * 1000 -> -2.0767441 | ... V23: =+(V12*(V18/10000)) * 1000 -> -7.2685575
B24: Total Spread Revenue | H24: =SUM(H21:H23) -> 28.874567 | I24: =SUM(I21:I23) -> 33.640481 | J24: =SUM(J21:J23) -> 35.367846 | K24: =SUM(K21:K23) -> 40.584508 | L24: =SUM(L21:L23) -> 48.538225 | M24: =SUM(M21:M23) -> 58.050705 | N24: =SUM(N21:N23) -> 69.427432 | O24: =SUM(O21:O23) -> 83.033761 | ... V24: =SUM(V21:V23) -> 290.61628
B26: Transaction Income ($Ms) | C26: ='Income Statement'!N35 -> 0.563 | D26: ='Income Statement'!O35 -> 0.4 | E26: ='Income Statement'!P35 -> 0.8 | F26: ='Income Statement'!Q35 -> 1.642 | G26: ='Income Statement'!R35 -> 2.712 | H26: =(H13*1000)*(H27/10000) -> 0.81757431 | I26: =(I13*1000)*(I27/10000) -> 1.2539037 | J26: =(J13*1000)*(J27/10000) -> 1.5776276 | K26: =(K13*1000)*(K27/10000) -> 2.0193567 | L26: =(L13*1000)*(L27/10000) -> 2.6087347 | M26: =(M13*1000)*(M27/10000) -> 2.9030771 | N26: =(N13*1000)*(N27/10000) -> 3.793005 | O26: =(O13*1000)*(O27/10000) -> 4.8880685 | ... V26: =(V13*1000)*(V27/10000) -> 24.323
B27: Take Rate (bps) | C27: =(C26/(C13*1000)) * 10000 -> 0.02234127 | D27: =(D26/(D13*1000)) * 10000 -> 0.022259321 | E27: =(E26/(E13*1000)) * 10000 -> 0.05625879 | F27: =(F26/(F13*1000)) * 10000 -> 0.073864148 | G27: =(G26/(G13*1000)) * 10000 -> 0.13780488 | H27: =AVERAGE(C27:G27) -> 0.062505681 | I27: =AVERAGE(D27:H27) -> 0.070538564 | J27: =AVERAGE(E27:I27) -> 0.080194412 | K27: =AVERAGE(F27:J27) -> 0.084981537 | L27: =AVERAGE(G27:K27) -> 0.087205014 | M27: =AVERAGE(H27:L27) -> 0.077085042 | N27: =AVERAGE(I27:M27) -> 0.080000914 | O27: =AVERAGE(J27:N27) -> 0.081893384 | ... V27: =AVERAGE(Q27:U27) -> 0.081307138
B29: Total Transaction Revenue | H29: =H24+H26 -> 29.692141 | I29: =I24+I26 -> 34.894384 | J29: =J24+J26 -> 36.945474 | K29: =K24+K26 -> 42.603865 | L29: =L24+L26 -> 51.14696 | M29: =M24+M26 -> 60.953782 | N29: =N24+N26 -> 73.220437 | O29: =O24+O26 -> 87.921829 | ... V29: =V24+V26 -> 314.93928
B31: CoinDesk (Data, Insights, Indiies) | G31: =34/4 -> 8.5 | H31: =G31*(1+((1+$C$33)^(1/4)-1)) -> 8.8022436 | I31: =H31*(1+((1+$C$33)^(1/4)-1)) -> 9.1152345 | J31: =I31*(1+((1+$C$33)^(1/4)-1)) -> 9.4393547 | K31: =J31*(1+((1+$C$33)^(1/4)-1)) -> 9.775 | L31: =K31*(1+((1+$C$33)^(1/4)-1)) -> 10.12258 | M31: =L31*(1+((1+$C$33)^(1/4)-1)) -> 10.48252 | N31: =M31*(1+((1+$C$33)^(1/4)-1)) -> 10.855258 | O31: =N31*(1+((1+$C$33)^(1/4)-1)) -> 11.24125 | ... V31: =U31*(1+((1+$C$33)^(1/4)-1)) -> 14.356079 | Z31: CoinDesk (Data [incl. CCData] + Insights + Indices), separated from Conferences, is anchored to a ~$29M FY24 run-rate — built from the acquisition footnotes' pro-forma disclosures (original CoinDesk ~$28–29M standalone + CCData ~$5M, netted for overlap) — then grown at an assumed ~15–20%/yr (midpoint ~17.5%) to arrive at a ~$34M FY2025 estimate, ex-conferences.
B32: Conferences | H32: =18/4 -> 4.5 | I32: =18/4 -> 4.5 | J32: =18/4 -> 4.5 | K32: =18/4 -> 4.5 | L32: =18/4 -> 4.5 | M32: =18/4 -> 4.5 | N32: =18/4 -> 4.5 | O32: =18/4 -> 4.5 | ... V32: =18/4 -> 4.5 | Z32: Two conferences annually, generating $9M based on 2025 Hong Kong Consensus revenue.
B33: CoinDesk Growth Rate | C33: 0.15
B35: Liquidity Services | G35: ='Income Statement'!R41-G31 -> 46.27 | H35: =G35*(1+((1+H36)^(1/4)-1)) -> 51.206172 | I35: =H35*(1+((1+I36)^(1/4)-1)) -> 56.668945 | J35: =I35*(1+((1+J36)^(1/4)-1)) -> 62.714497 | K35: =J35*(1+((1+K36)^(1/4)-1)) -> 72.193078 | L35: =K35*(1+((1+L36)^(1/4)-1)) -> 83.104239 | M35: =L35*(1+((1+M36)^(1/4)-1)) -> 95.664497 | N35: =M35*(1+((1+N36)^(1/4)-1)) -> 110.1231 | O35: =N35*(1+((1+O36)^(1/4)-1)) -> 126.76695 | ... V35: =U35*(1+((1+V36)^(1/4)-1)) -> 339.54657
B36: CoinDesk Annual Growth Rate | H36: =INDEX('Scenario & Sensitivity'!$C$16:$F$18,MATCH(Summary!$C$17,'Scenario & Sensitivity'!$B$16:$B$18,0),MATCH(_xlfn.NUMBERVALUE(RIGHT('Revenue Build'!H$8,4)),'Scenario & Sensitivity'!$C$15:$F$15,0)) -> 0.5 | I36: =INDEX('Scenario & Sensitivity'!$C$16:$F$18,MATCH(Summary!$C$17,'Scenario & Sensitivity'!$B$16:$B$18,0),MATCH(_xlfn.NUMBERVALUE(RIGHT('Revenue Build'!I$8,4)),'Scenario & Sensitivity'!$C$15:$F$15,0)) -> 0.5 | J36: =INDEX('Scenario & Sensitivity'!$C$16:$F$18,MATCH(Summary!$C$17,'Scenario & Sensitivity'!$B$16:$B$18,0),MATCH(_xlfn.NUMBERVALUE(RIGHT('Revenue Build'!J$8,4)),'Scenario & Sensitivity'!$C$15:$F$15,0)) -> 0.5 | K36: =INDEX('Scenario & Sensitivity'!$C$16:$F$18,MATCH(Summary!$C$17,'Scenario & Sensitivity'!$B$16:$B$18,0),MATCH(_xlfn.NUMBERVALUE(RIGHT('Revenue Build'!K$8,4)),'Scenario & Sensitivity'!$C$15:$F$15,0)) -> 0.75594322 | L36: =INDEX('Scenario & Sensitivity'!$C$16:$F$18,MATCH(Summary!$C$17,'Scenario & Sensitivity'!$B$16:$B$18,0),MATCH(_xlfn.NUMBERVALUE(RIGHT('Revenue Build'!L$8,4)),'Scenario & Sensitivity'!$C$15:$F$15,0)) -> 0.75594322 | M36: =INDEX('Scenario & Sensitivity'!$C$16:$F$18,MATCH(Summary!$C$17,'Scenario & Sensitivity'!$B$16:$B$18,0),MATCH(_xlfn.NUMBERVALUE(RIGHT('Revenue Build'!M$8,4)),'Scenario & Sensitivity'!$C$15:$F$15,0)) -> 0.75594322 | N36: =INDEX('Scenario & Sensitivity'!$C$16:$F$18,MATCH(Summary!$C$17,'Scenario & Sensitivity'!$B$16:$B$18,0),MATCH(_xlfn.NUMBERVALUE(RIGHT('Revenue Build'!N$8,4)),'Scenario & Sensitivity'!$C$15:$F$15,0)) -> 0.75594322 | O36: =INDEX('Scenario & Sensitivity'!$C$16:$F$18,MATCH(Summary!$C$17,'Scenario & Sensitivity'!$B$16:$B$18,0),MATCH(_xlfn.NUMBERVALUE(RIGHT('Revenue Build'!O$8,4)),'Scenario & Sensitivity'!$C$15:$F$15,0)) -> 0.75594322 | ... V36: =INDEX('Scenario & Sensitivity'!$C$16:$F$18,MATCH(Summary!$C$17,'Scenario & Sensitivity'!$B$16:$B$18,0),MATCH(_xlfn.NUMBERVALUE(RIGHT('Revenue Build'!V$8,4)),'Scenario & Sensitivity'!$C$15:$F$15,0)) -> 0.75594322
B38: Subscriptions and Services Revenue | H38: =H31+H32+H35 -> 64.508416 | I38: =I31+I32+I35 -> 70.28418 | J38: =J31+J32+J35 -> 76.653852 | K38: =K31+K32+K35 -> 86.468078 | L38: =L31+L32+L35 -> 97.726819 | M38: =M31+M32+M35 -> 110.64702 | N38: =N31+N32+N35 -> 125.47835 | O38: =O31+O32+O35 -> 142.5082 | ... V38: =V31+V32+V35 -> 358.40265

Sheet Scenario & Sensitivity
B2: Scenario & Sensitivity Analysis
B4: SCENARIOS
B6: Transaction Volume Growth | C6: 2026 | D6: =C6+1 -> 2027 | E6: =D6+1 -> 2028 | F6: =E6+1 -> 2029 | H6: Notes
B7: Bull | C7: 0.5 | D7: =$C$12 -> 1.5118864 | E7: =$C$12 -> 1.5118864 | F7: =$C$12 -> 1.5118864 | H7: Based on McKinsey tokenization market growth by 2030 (Including: Bonds, loans, funds and Equities = $2-4T) [Most conservative estimate: https://a16zcrypto.com/posts/article/tokenized-asset-rwa-market-data-charts/]
B8: Base | C8: 0.25 | D8: =D7/2 -> 0.75594322 | E8: =E7/2 -> 0.75594322 | F8: =F7/2 -> 0.75594322 | H8: 50% haircut to Bull
B9: Bear | C9: 0.15 | D9: =C9-0.025 -> 0.125 | E9: =D9-0.025 -> 0.1 | F9: =E9-0.025 -> 0.075 | H9: Taper 2.5%
B11: TAM Growth by 2030 | C11: 100
B12: CAGR | C12: =(C11^(1/5)) -1 -> 1.5118864
B15: Liquidity Service Growth | C15: 2026 | D15: =C15+1 -> 2027 | E15: =D15+1 -> 2028 | F15: =E15+1 -> 2029 | H15: Notes
B16: Bull | C16: 0.5 | D16: =+D7*0.5 -> 0.75594322 | E16: =+E7*0.5 -> 0.75594322 | F16: =+F7*0.5 -> 0.75594322 | H16: Q1'26 runrate already 50%+, without the Equiniti cross sell opps. / Forecasted .5 beta to volume growth rate as this take a sales effort
B17: Base | C17: 0.25 | D17: 0.2 | E17: 0.2 | F17: 0.2 | H17: Management post Equiniti: 20% revenue growth from tokenization and blockchain services
B18: Bear | C18: 0.15 | D18: =C18-0.025 -> 0.125 | E18: =D18-0.025 -> 0.1 | F18: =E18-0.025 -> 0.075 | H18: Taper 2.5%
C20: =LEFT(C21,2) -> Q1 | D20: =LEFT(D21,2) -> Q2 | E20: =LEFT(E21,2) -> Q3 | F20: =LEFT(F21,2) -> Q4 | H20: =LEFT(H21,2) -> Q1
C21: ='Income Statement'!J6 -> Q1 2024 | D21: ='Income Statement'!K6 -> Q2 2024 | E21: ='Income Statement'!L6 -> Q3 2024 | F21: ='Income Statement'!M6 -> Q4 2024 | H21: ='Income Statement'!N6 -> Q1 2025
B22: Subscriptions and services revenue | C22: ='Income Statement'!J41 -> 8.8 | D22: ='Income Statement'!K41 -> 25.8 | E22: ='Income Statement'!L41 -> 11.5 | F22: ='Income Statement'!M41 -> 13.684 | H22: ='Income Statement'!N41 -> 19.741
B23: CoinDesk | C23: =C22-C24-C25 -> 5.3 | D23: =D22-D24-D25 -> 13.3 | E23: =E22-E24-E25 -> 8 | F23: =F22-F24-F25 -> 10.184 | H23: =AVERAGE(C23:F23) -> 9.196
B24: Confrences | D24: =9 -> 9 | H24: =9 -> 9
B25: Liquidity Services | C25: =14/4 -> 3.5 | D25: =14/4 -> 3.5 | E25: =14/4 -> 3.5 | F25: =14/4 -> 3.5

Sheet P&L Inputs >>

Sheet Income Statement
B2: Income Statement - Bullish (BLSH) Standalone
J3: =YEAR(J4) -> 2024 | K3: =YEAR(K4) -> 2024 | L3: =YEAR(L4) -> 2024 | M3: =YEAR(M4) -> 2024 | N3: =YEAR(N4) -> 2025 | O3: =YEAR(O4) -> 2025 | P3: =YEAR(P4) -> 2025 | Q3: =YEAR(Q4) -> 2025 | ... AG3: =YEAR(AG4) -> 2029
J4: 45354 | K4: =EOMONTH(J4,3) -> 45473 | L4: =EOMONTH(K4,3) -> 45565 | M4: =EOMONTH(L4,3) -> 45657 | N4: =EOMONTH(M4,3) -> 45747 | O4: =EOMONTH(N4,3) -> 45838 | P4: =EOMONTH(O4,3) -> 45930 | Q4: =EOMONTH(P4,3) -> 46022 | R4: =EOMONTH(Q4,3) -> 46112 | ... AG4: =EOMONTH(AF4,3) -> 47483
B5: P&L (as reported)
B6: ($mm unless noted) | C6: 2024 | D6: 2025 | E6: 2026 | F6: 2027 | G6: 2028 | H6: 2029 | J6: ="Q" & INT((MONTH(J4)-1)/3)+1 & " " & YEAR(J4) -> Q1 2024 | K6: ="Q" & INT((MONTH(K4)-1)/3)+1 & " " & YEAR(K4) -> Q2 2024 | L6: ="Q" & INT((MONTH(L4)-1)/3)+1 & " " & YEAR(L4) -> Q3 2024 | M6: ="Q" & INT((MONTH(M4)-1)/3)+1 & " " & YEAR(M4) -> Q4 2024 | N6: ="Q" & INT((MONTH(N4)-1)/3)+1 & " " & YEAR(N4) -> Q1 2025 | O6: ="Q" & INT((MONTH(O4)-1)/3)+1 & " " & YEAR(O4) -> Q2 2025 | P6: ="Q" & INT((MONTH(P4)-1)/3)+1 & " " & YEAR(P4) -> Q3 2025 | Q6: ="Q" & INT((MONTH(Q4)-1)/3)+1 & " " & YEAR(Q4) -> Q4 2025 | ... AG6: ="Q" & INT((MONTH(AG4)-1)/3)+1 & " " & YEAR(AG4) -> Q4 2029
B7: Digital assets sales | C7: =SUMIFS($J7:$V7,$J$3:$V$3,C$6) -> 250201.28 | D7: =SUMIFS($J7:$V7,$J$3:$V$3,D$6) -> 244811.39 | E7: =SUMIFS($J7:$V7,$J$3:$V$3,E$6) -> 84397.834 | F7: =SUMIFS($J7:$V7,$J$3:$V$3,F$6) -> 0 | G7: =SUMIFS($J7:$V7,$J$3:$V$3,G$6) -> 0 | H7: =SUMIFS($J7:$V7,$J$3:$V$3,H$6) -> 0 | J7: 80404.577 | K7: 49578.206 | L7: 54192.368 | M7: 66026.131 | N7: 80236.157 | O7: 58630.645 | P7: 41599.507 | Q7: 64345.078 | R7: 51812.747 | S7: 32585.087
B8: Cost of digital assets derecognized | C8: =SUMIFS($J8:$V8,$J$3:$V$3,C$6) -> -250104.77 | D8: =SUMIFS($J8:$V8,$J$3:$V$3,D$6) -> -244733.09 | E8: =SUMIFS($J8:$V8,$J$3:$V$3,E$6) -> -84362.303 | F8: =SUMIFS($J8:$V8,$J$3:$V$3,F$6) -> 0 | G8: =SUMIFS($J8:$V8,$J$3:$V$3,G$6) -> 0 | H8: =SUMIFS($J8:$V8,$J$3:$V$3,H$6) -> 0 | J8: -80375.573 | K8: -49556.478 | L8: -54171.381 | M8: -66001.337 | N8: -80209.641 | O8: -58615.273 | P8: -41584.605 | Q8: -64323.568 | R8: -51792.742 | S8: -32569.561
B9: Other revenues | C9: =SUMIFS($J9:$V9,$J$3:$V$3,C$6) -> 61.968 | D9: =SUMIFS($J9:$V9,$J$3:$V$3,D$6) -> 158.941 | E9: =SUMIFS($J9:$V9,$J$3:$V$3,E$6) -> 122.433 | F9: =SUMIFS($J9:$V9,$J$3:$V$3,F$6) -> 0 | G9: =SUMIFS($J9:$V9,$J$3:$V$3,G$6) -> 0 | H9: =SUMIFS($J9:$V9,$J$3:$V$3,H$6) -> 0 | J9: 9.366 | K9: 26.257 | L9: 11.872 | M9: 14.473 | N9: 20.304 | O9: 32.292 | P9: 50.15 | Q9: 56.195 | R9: 57.482 | S9: 64.951
B10: Change in fair value of digital assets held, net | C10: =SUMIFS($J10:$V10,$J$3:$V$3,C$6) -> 207.043 | D10: =SUMIFS($J10:$V10,$J$3:$V$3,D$6) -> -674.968 | E10: =SUMIFS($J10:$V10,$J$3:$V$3,E$6) -> -804.198 | F10: =SUMIFS($J10:$V10,$J$3:$V$3,F$6) -> 0 | G10: =SUMIFS($J10:$V10,$J$3:$V$3,G$6) -> 0 | H10: =SUMIFS($J10:$V10,$J$3:$V$3,H$6) -> 0 | J10: 162.174 | K10: -99.372 | L10: -41.788 | M10: 186.029 | N10: -246.762 | O10: 68.409 | P10: -11.44 | Q10: -485.175 | R10: -559.584 | S10: -244.614
B11: Net spread related income and change in fair value of perpetual futures on the Exchange | C11: =SUMIFS($J11:$V11,$J$3:$V$3,C$6) -> -17.138 | D11: =SUMIFS($J11:$V11,$J$3:$V$3,D$6) -> -7.179 | E11: =SUMIFS($J11:$V11,$J$3:$V$3,E$6) -> -0.945 | F11: =SUMIFS($J11:$V11,$J$3:$V$3,F$6) -> 0 | G11: =SUMIFS($J11:$V11,$J$3:$V$3,G$6) -> 0 | H11: =SUMIFS($J11:$V11,$J$3:$V$3,H$6) -> 0 | J11: -4.22 | K11: -4.797 | L11: -4.893 | M11: -3.228 | N11: -3.702 | O11: -1.989 | P11: -0.602 | Q11: -0.886 | R11: 0.035 | S11: -0.98
B12: Change in fair value of investment in financial assets | C12: =SUMIFS($J12:$V12,$J$3:$V$3,C$6) -> 29.453 | D12: =SUMIFS($J12:$V12,$J$3:$V$3,D$6) -> -36.035 | E12: =SUMIFS($J12:$V12,$J$3:$V$3,E$6) -> -122.951 | F12: =SUMIFS($J12:$V12,$J$3:$V$3,F$6) -> 0 | G12: =SUMIFS($J12:$V12,$J$3:$V$3,G$6) -> 0 | H12: =SUMIFS($J12:$V12,$J$3:$V$3,H$6) -> 0 | J12: 0.349 | K12: -0.738 | L12: 2.473 | M12: 27.369 | N12: -71.81 | O12: 86.359 | P12: 54.971 | Q12: -105.555 | R12: -92.373 | S12: -30.578
B13: Administrative expenses | C13: =SUMIFS($J13:$V13,$J$3:$V$3,C$6) -> -153.119 | D13: =SUMIFS($J13:$V13,$J$3:$V$3,D$6) -> -182.188 | E13: =SUMIFS($J13:$V13,$J$3:$V$3,E$6) -> -104.548 | F13: =SUMIFS($J13:$V13,$J$3:$V$3,F$6) -> 0 | G13: =SUMIFS($J13:$V13,$J$3:$V$3,G$6) -> 0 | H13: =SUMIFS($J13:$V13,$J$3:$V$3,H$6) -> 0 | J13: -36.757 | K13: -39.662 | L13: -39.618 | M13: -37.082 | N13: -47.186 | O13: -43.017 | P13: -45.709 | Q13: -46.276 | R13: -48.28 | S13: -56.268
B14: Other expenses | C14: =SUMIFS($J14:$V14,$J$3:$V$3,C$6) -> -46.081 | D14: =SUMIFS($J14:$V14,$J$3:$V$3,D$6) -> -60.425 | E14: =SUMIFS($J14:$V14,$J$3:$V$3,E$6) -> -78.043 | F14: =SUMIFS($J14:$V14,$J$3:$V$3,F$6) -> 0 | G14: =SUMIFS($J14:$V14,$J$3:$V$3,G$6) -> 0 | H14: =SUMIFS($J14:$V14,$J$3:$V$3,H$6) -> 0 | J14: -9.916 | K14: -16.72 | L14: -6.81 | M14: -12.635 | N14: -15.063 | O14: -17.362 | P14: -13.608 | Q14: -14.392 | R14: -45.53 | S14: -32.513
B15: Finance expense | C15: =SUMIFS($J15:$V15,$J$3:$V$3,C$6) -> -38.529 | D15: =SUMIFS($J15:$V15,$J$3:$V$3,D$6) -> -52.369 | E15: =SUMIFS($J15:$V15,$J$3:$V$3,E$6) -> -28.547 | F15: =SUMIFS($J15:$V15,$J$3:$V$3,F$6) -> 0 | G15: =SUMIFS($J15:$V15,$J$3:$V$3,G$6) -> 0 | H15: =SUMIFS($J15:$V15,$J$3:$V$3,H$6) -> 0 | J15: -8.929 | K15: -9.063 | L15: -9.878 | M15: -10.659 | N15: -10.24 | O15: -13.291 | P15: -13.906 | Q15: -14.932 | R15: -14.088 | S15: -14.459
B16: Change in fair value of derivatives | C16: =SUMIFS($J16:$V16,$J$3:$V$3,C$6) -> -12.19 | D16: =SUMIFS($J16:$V16,$J$3:$V$3,D$6) -> 9.609 | E16: =SUMIFS($J16:$V16,$J$3:$V$3,E$6) -> 91.58 | F16: =SUMIFS($J16:$V16,$J$3:$V$3,F$6) -> 0 | G16: =SUMIFS($J16:$V16,$J$3:$V$3,G$6) -> 0 | H16: =SUMIFS($J16:$V16,$J$3:$V$3,H$6) -> 0 | J16: -0.526 | K16: 0.175 | L16: 1.028 | M16: -12.867 | N16: 0 | O16: -2.379 | P16: -5.533 | Q16: 17.521 | R16: 69.197 | S16: 22.383
B17: Change in fair value of financial liability at FVTPL | C17: =SUMIFS($J17:$V17,$J$3:$V$3,C$6) -> -43.35 | D17: =SUMIFS($J17:$V17,$J$3:$V$3,D$6) -> -20.1 | E17: =SUMIFS($J17:$V17,$J$3:$V$3,E$6) -> 4.2 | F17: =SUMIFS($J17:$V17,$J$3:$V$3,F$6) -> 0 | G17: =SUMIFS($J17:$V17,$J$3:$V$3,G$6) -> 0 | H17: =SUMIFS($J17:$V17,$J$3:$V$3,H$6) -> 0 | J17: -35.6 | K17: 6.1 | L17: 0.1 | M17: -13.95 | N17: -0.9 | O17: -15.25 | P17: -10.85 | Q17: 6.9 | R17: 8.5 | S17: -4.3
B18: Income/(loss) before income tax | C18: =SUMIFS($J18:$V18,$J$3:$V$3,C$6) -> 84.57 | D18: =SUMIFS($J18:$V18,$J$3:$V$3,D$6) -> -786.414 | E18: =SUMIFS($J18:$V18,$J$3:$V$3,E$6) -> -885.488 | F18: =SUMIFS($J18:$V18,$J$3:$V$3,F$6) -> 0 | G18: =SUMIFS($J18:$V18,$J$3:$V$3,G$6) -> 0 | H18: =SUMIFS($J18:$V18,$J$3:$V$3,H$6) -> 0 | J18: =J7+J8+J9+J10+J11+J12+J13+J14+J15+J16+J17 -> 104.945 | K18: =K7+K8+K9+K10+K11+K12+K13+K14+K15+K16+K17 -> -116.092 | L18: =L7+L8+L9+L10+L11+L12+L13+L14+L15+L16+L17 -> -66.527 | M18: =M7+M8+M9+M10+M11+M12+M13+M14+M15+M16+M17 -> 162.244 | N18: =N7+N8+N9+N10+N11+N12+N13+N14+N15+N16+N17 -> -348.843 | O18: =O7+O8+O9+O10+O11+O12+O13+O14+O15+O16+O17 -> 109.144 | P18: =P7+P8+P9+P10+P11+P12+P13+P14+P15+P16+P17 -> 18.375 | Q18: =Q7+Q8+Q9+Q10+Q11+Q12+Q13+Q14+Q15+Q16+Q17 -> -565.09 | ... AG18: =AG7+AG8+AG9+AG10+AG11+AG12+AG13+AG14+AG15+AG16+AG17 -> 0
B19: Income tax benefit/(expense) | C19: =SUMIFS($J19:$V19,$J$3:$V$3,C$6) -> -5.005 | D19: =SUMIFS($J19:$V19,$J$3:$V$3,D$6) -> 0.502 | E19: =SUMIFS($J19:$V19,$J$3:$V$3,E$6) -> -0.23 | F19: =SUMIFS($J19:$V19,$J$3:$V$3,F$6) -> 0 | G19: =SUMIFS($J19:$V19,$J$3:$V$3,G$6) -> 0 | H19: =SUMIFS($J19:$V19,$J$3:$V$3,H$6) -> 0 | J19: -0.176 | K19: -0.302 | L19: -0.745 | M19: -3.782 | N19: -0.221 | O19: -0.876 | P19: 0.076 | Q19: 1.523 | R19: -0.226 | S19: -0.004
B20: Net income/(loss) (IFRS) | C20: =SUMIFS($J20:$V20,$J$3:$V$3,C$6) -> 79.565 | D20: =SUMIFS($J20:$V20,$J$3:$V$3,D$6) -> -785.912 | E20: =SUMIFS($J20:$V20,$J$3:$V$3,E$6) -> -885.718 | F20: =SUMIFS($J20:$V20,$J$3:$V$3,F$6) -> 0 | G20: =SUMIFS($J20:$V20,$J$3:$V$3,G$6) -> 0 | H20: =SUMIFS($J20:$V20,$J$3:$V$3,H$6) -> 0 | J20: =J18+J19 -> 104.769 | K20: =K18+K19 -> -116.394 | L20: =L18+L19 -> -67.272 | M20: =M18+M19 -> 158.462 | N20: =N18+N19 -> -349.064 | O20: =SUM(O18:O19) -> 108.268 | P20: =P18+P19 -> 18.451 | Q20: =Q18+Q19 -> -563.567 | R20: =R18+R19 -> -604.862 | S20: =S18+S19 -> -280.856 | T20: =T18+T19 -> 0 | U20: =U18+U19 -> 0 | V20: =V18+V19 -> 0 | W20: =W18+W19 -> 0 | ... AG20: =AG18+AG19 -> 0
B22: Memo: Attributable to Owners of the Group | K22: -115.346 | L22: -66.732 | M22: 157.033 | N22: -343.994 | O22: 107.513 | P22: 18.397 | Q22: -546.598 | R22: -581.713
B23: Memo: Attributable to Non-controlling interests | K23: -1.048 | L23: -0.54 | M23: 1.429 | N23: -4.628 | O23: 0.755 | P23: 0.054 | Q23: -16.969 | R23: -23.149
B24: Memo: Weighted avg. shares outstanding - Basic (mm) | K24: 112.5 | L24: 112.5 | M24: 113.153 | N24: 113.215 | O24: 113.215 | P24: 133.066 | Q24: 150.924 | R24: 151.146
B25: Memo: Weighted avg. shares outstanding - Diluted (mm) | K25: 112.5 | L25: 112.5 | M25: 115.889 | N25: 113.215 | O25: 115.951 | P25: 140.157 | Q25: 150.924 | R25: 151.146
B26: Memo: EPS - Basic ($) | K26: -1.03 | L26: -0.59 | M26: 1.4 | N26: -3.04 | O26: 0.95 | P26: 0.14 | Q26: -3.73 | R26: -3.85
B27: Memo: EPS - Diluted ($) | K27: -1.03 | L27: -0.59 | M27: 1.37 | N27: -3.04 | O27: 0.93 | P27: 0.1 | Q27: -3.73 | R27: -3.85
B29: BLOCK 2 - BRIDGE: DIGITAL ASSETS SALES -> ADJUSTED TRANSACTION REVENUE
B30: Digital assets sales | J30: =J7 -> 80404.577 | K30: =K7 -> 49578.206 | L30: =L7 -> 54192.368 | M30: =M7 -> 66026.131 | N30: =N7 -> 80236.157 | O30: =O7 -> 58630.645 | P30: =P7 -> 41599.507 | Q30: =Q7 -> 64345.078 | ... AG30: =AG7 -> 0
B31: (-) Digital asset sales on venues other than Exchange | C31: =SUMIFS($J31:$V31,$J$3:$V$3,C$6) -> -21.824 | D31: =SUMIFS($J31:$V31,$J$3:$V$3,D$6) -> -396.446 | E31: =SUMIFS($J31:$V31,$J$3:$V$3,E$6) -> 0 | F31: =SUMIFS($J31:$V31,$J$3:$V$3,F$6) -> 0 | G31: =SUMIFS($J31:$V31,$J$3:$V$3,G$6) -> 0 | H31: =SUMIFS($J31:$V31,$J$3:$V$3,H$6) -> 0 | J31: =-14.5-K31 -> -5.7 | K31: -8.8 | L31: -5.2 | M31: -2.124 | N31: -303.863 | O31: -30.1 | P31: -25.9 | Q31: -36.583 | R31: 0 | S31: 0
B32: Digital asset sales - on our Exchange (subtotal) | C32: =SUMIFS($J32:$V32,$J$3:$V$3,C$6) -> 250179.46 | D32: =SUMIFS($J32:$V32,$J$3:$V$3,D$6) -> 244414.94 | E32: =SUMIFS($J32:$V32,$J$3:$V$3,E$6) -> 84397.834 | F32: =SUMIFS($J32:$V32,$J$3:$V$3,F$6) -> 0 | G32: =SUMIFS($J32:$V32,$J$3:$V$3,G$6) -> 0 | H32: =SUMIFS($J32:$V32,$J$3:$V$3,H$6) -> 0 | J32: =J30+J31 -> 80398.877 | K32: =K30+K31 -> 49569.406 | L32: =L30+L31 -> 54187.168 | M32: =M30+M31 -> 66024.007 | N32: =N30+N31 -> 79932.294 | O32: =O30+O31 -> 58600.545 | P32: =P30+P31 -> 41573.607 | Q32: =Q30+Q31 -> 64308.495 | ... AG32: =AG30+AG31 -> 0
B33: Cost of digital assets derecognized | C33: =SUMIFS($J33:$V33,$J$3:$V$3,C$6) -> -250082.93 | D33: =SUMIFS($J33:$V33,$J$3:$V$3,D$6) -> -244336.49 | E33: =SUMIFS($J33:$V33,$J$3:$V$3,E$6) -> -84362.303 | F33: =SUMIFS($J33:$V33,$J$3:$V$3,F$6) -> 0 | G33: =SUMIFS($J33:$V33,$J$3:$V$3,G$6) -> 0 | H33: =SUMIFS($J33:$V33,$J$3:$V$3,H$6) -> 0 | J33: =-129917.5-K33 -> -80369.9 | K33: =-49547.6 -> -49547.6 | L33: =-54166.2 -> -54166.2 | M33: =-65999.234 -> -65999.234 | N33: =-138490.9-O33 -> -79905.8 | O33: =-58585.1 -> -58585.1 | P33: =-41558.6 -> -41558.6 | Q33: =-64286.992 -> -64286.992 | R33: =R8 -> -51792.742 | S33: =S8 -> -32569.561
B34: (+) Change in FV of digital asset inventories, arising from purchase on our Exchange | C34: =SUMIFS($J34:$V34,$J$3:$V$3,C$6) -> 71.662 | D34: =SUMIFS($J34:$V34,$J$3:$V$3,D$6) -> 56.058 | E34: =SUMIFS($J34:$V34,$J$3:$V$3,E$6) -> 27.472 | F34: =SUMIFS($J34:$V34,$J$3:$V$3,F$6) -> 0 | G34: =SUMIFS($J34:$V34,$J$3:$V$3,G$6) -> 0 | H34: =SUMIFS($J34:$V34,$J$3:$V$3,H$6) -> 0 | J34: =36.6 -K34 -> 19.1 | K34: 17.5 | L34: 16.4 | M34: 18.662 | N34: 18.688 | O34: 10.2 | P34: 11.5 | Q34: 15.67 | R34: 15.265 | S34: =27.472-R34 -> 12.207
B35: (+) Transaction income | C35: =SUMIFS($J35:$V35,$J$3:$V$3,C$6) -> 2.189 | D35: =SUMIFS($J35:$V35,$J$3:$V$3,D$6) -> 3.405 | E35: =SUMIFS($J35:$V35,$J$3:$V$3,E$6) -> 4.974 | F35: =SUMIFS($J35:$V35,$J$3:$V$3,F$6) -> 0 | G35: =SUMIFS($J35:$V35,$J$3:$V$3,G$6) -> 0 | H35: =SUMIFS($J35:$V35,$J$3:$V$3,H$6) -> 0 | J35: =1-K35 -> 0.6 | K35: 0.4 | L35: 0.4 | M35: 0.789 | N35: 0.563 | O35: 0.4 | P35: 0.8 | Q35: 1.642 | R35: 2.712 | S35: =4.974-R35 -> 2.262
B36: (+) Net spread related income and change in FV of perpetual futures | C36: =SUMIFS($J36:$V36,$J$3:$V$3,C$6) -> -17.121 | D36: =SUMIFS($J36:$V36,$J$3:$V$3,D$6) -> -7.179 | E36: =SUMIFS($J36:$V36,$J$3:$V$3,E$6) -> -0.945 | F36: =SUMIFS($J36:$V36,$J$3:$V$3,F$6) -> 0 | G36: =SUMIFS($J36:$V36,$J$3:$V$3,G$6) -> 0 | H36: =SUMIFS($J36:$V36,$J$3:$V$3,H$6) -> 0 | J36: =-9-K36 -> -4.203 | K36: =K11 -> -4.797 | L36: =L11 -> -4.893 | M36: =M11 -> -3.228 | N36: =N11 -> -3.702 | O36: =O11 -> -1.989 | P36: =P11 -> -0.602 | Q36: =Q11 -> -0.886 | R36: =R11 -> 0.035 | ... AG36: =AG11 -> 0
B37: Adjusted Transaction Revenue | C37: =SUMIFS($J37:$AG37,$J$3:$AG$3,C$6) -> 153.254 | D37: =SUMIFS($J37:$AG37,$J$3:$AG$3,D$6) -> 130.733 | E37: =SUMIFS($J37:$AG37,$J$3:$AG$3,E$6) -> 139.549 | F37: =SUMIFS($J37:$AG37,$J$3:$AG$3,F$6) -> 227.92504 | G37: =SUMIFS($J37:$AG37,$J$3:$AG$3,G$6) -> 471.54494 | H37: =SUMIFS($J37:$AG37,$J$3:$AG$3,H$6) -> 977.9252 | J37: =SUM(J32:J36) -> 44.474 | K37: =SUM(K32:K36) -> 34.909 | L37: =SUM(L32:L36) -> 32.875 | M37: =SUM(M32:M36) -> 40.996 | N37: =SUM(N32:N36) -> 42.043 | O37: =SUM(O32:O36) -> 24.056 | P37: =SUM(P32:P36) -> 26.705 | Q37: =SUM(Q32:Q36) -> 37.929 | R37: =SUM(R32:R36) -> 38.017 | S37: ='Revenue Build'!H29 -> 29.692141 | T37: ='Revenue Build'!I29 -> 34.894384 | U37: ='Revenue Build'!J29 -> 36.945474 | V37: ='Revenue Build'!K29 -> 42.603865 | W37: ='Revenue Build'!L29 -> 51.14696 | X37: ='Revenue Build'!M29 -> 60.953782 | Y37: ='Revenue Build'!N29 -> 73.220437 | Z37: ='Revenue Build'!O29 -> 87.921829 | ... AG37: ='Revenue Build'!V29 -> 314.93928
B39: BLOCK 3 - BRIDGE: ADJUSTED TRANSACTION REVENUE -> ADJUSTED REVENUE
B40: Adjusted Transaction Revenue | C40: =C37 -> 153.254 | D40: =D37 -> 130.733 | E40: =E37 -> 139.549 | F40: =F37 -> 227.92504 | G40: =G37 -> 471.54494 | H40: =H37 -> 977.9252 | J40: =J37 -> 44.474 | K40: =K37 -> 34.909 | L40: =L37 -> 32.875 | M40: =M37 -> 40.996 | N40: =N37 -> 42.043 | O40: =O37 -> 24.056 | P40: =P37 -> 26.705 | Q40: =Q37 -> 37.929 | ... AG40: =AG37 -> 314.93928
B41: (+) Subscriptions and services revenue | C41: =SUMIFS($J41:$AG41,$J$3:$AG$3,C$6) -> 59.784 | D41: =SUMIFS($J41:$AG41,$J$3:$AG$3,D$6) -> 155.495 | E41: =SUMIFS($J41:$AG41,$J$3:$AG$3,E$6) -> 264.39703 | F41: =SUMIFS($J41:$AG41,$J$3:$AG$3,F$6) -> 420.32027 | G41: =SUMIFS($J41:$AG41,$J$3:$AG$3,G$6) -> 699.46526 | H41: =SUMIFS($J41:$AG41,$J$3:$AG$3,H$6) -> 1185.8801 | J41: =34.6-K41 -> 8.8 | K41: 25.8 | L41: 11.5 | M41: 13.684 | N41: 19.741 | O41: 31.9 | P41: 49.3 | Q41: 54.554 | R41: 54.77 | S41: =117.459-R41 -> 62.689 | T41: ='Revenue Build'!I38 -> 70.28418 | U41: ='Revenue Build'!J38 -> 76.653852 | V41: ='Revenue Build'!K38 -> 86.468078 | W41: ='Revenue Build'!L38 -> 97.726819 | X41: ='Revenue Build'!M38 -> 110.64702 | Y41: ='Revenue Build'!N38 -> 125.47835 | Z41: ='Revenue Build'!O38 -> 142.5082 | AA41: ='Revenue Build'!P38 -> 162.06729 | ... AG41: ='Revenue Build'!V38 -> 358.40265
B42: (+) Change in FV of investment in financial assets (pre-2024 only) | C42: =SUMIFS($J42:$AG42,$J$3:$AG$3,C$6) -> 0.2 | D42: =SUMIFS($J42:$AG42,$J$3:$AG$3,D$6) -> 0 | E42: =SUMIFS($J42:$AG42,$J$3:$AG$3,E$6) -> 0 | F42: =SUMIFS($J42:$AG42,$J$3:$AG$3,F$6) -> 0 | G42: =SUMIFS($J42:$AG42,$J$3:$AG$3,G$6) -> 0 | H42: =SUMIFS($J42:$AG42,$J$3:$AG$3,H$6) -> 0 | J42: =0.2 -K42 -> 0.2 | K42: 0 | L42: 0 | M42: 0 | N42: 0 | O42: 0 | P42: 0 | Q42: 0 | R42: 0 | S42: 0
B43: (+) Revaluation of digital assets held as investments | C43: =SUMIFS($J43:$AG43,$J$3:$AG$3,C$6) -> 0.703 | D43: =SUMIFS($J43:$AG43,$J$3:$AG$3,D$6) -> 2.168 | E43: =SUMIFS($J43:$AG43,$J$3:$AG$3,E$6) -> 0.089 | F43: =SUMIFS($J43:$AG43,$J$3:$AG$3,F$6) -> 0 | G43: =SUMIFS($J43:$AG43,$J$3:$AG$3,G$6) -> 0 | H43: =SUMIFS($J43:$AG43,$J$3:$AG$3,H$6) -> 0 | K43: 0 | L43: 0.2 | M43: 0.503 | N43: 0.643 | O43: 1 | P43: 0.5 | Q43: 0.025 | R43: 0.039 | S43: 0.05
B44: Adjusted Revenue | C44: =SUM(C40:C43) -> 213.941 | D44: =SUM(D40:D43) -> 288.396 | E44: =SUM(E40:E43) -> 404.03503 | F44: =SUM(F40:F43) -> 648.24531 | G44: =SUM(G40:G43) -> 1171.0102 | H44: =SUM(H40:H43) -> 2163.8053 | J44: =SUM(J40:J43) -> 53.474 | K44: =K40+K41+K42+K43 -> 60.709 | L44: =L40+L41+L42+L43 -> 44.575 | M44: =M40+M41+M42+M43 -> 55.183 | N44: =N40+N41+N42+N43 -> 62.427 | O44: =O40+O41+O42+O43 -> 56.956 | P44: =P40+P41+P42+P43 -> 76.505 | Q44: =Q40+Q41+Q42+Q43 -> 92.508 | R44: =R40+R41+R42+R43 -> 92.826 | ... AG44: =AG40+AG41+AG42+AG43 -> 673.34193
B46: BLOCK 4 - BRIDGE: NET INCOME/(LOSS) -> ADJUSTED EBITDA
B47: Net income/(loss) (IFRS) | C47: =SUMIFS($J47:$V47,$J$3:$V$3,C$6) -> 79.565 | D47: =SUMIFS($J47:$V47,$J$3:$V$3,D$6) -> -785.912 | E47: =SUMIFS($J47:$V47,$J$3:$V$3,E$6) -> -885.718 | F47: =SUMIFS($J47:$V47,$J$3:$V$3,F$6) -> 0 | G47: =SUMIFS($J47:$V47,$J$3:$V$3,G$6) -> 0 | H47: =SUMIFS($J47:$V47,$J$3:$V$3,H$6) -> 0 | J47: =J20 -> 104.769 | K47: =K20 -> -116.394 | L47: =L20 -> -67.272 | M47: =M20 -> 158.462 | N47: =N20 -> -349.064 | O47: =O20 -> 108.268 | P47: =P20 -> 18.451 | Q47: =Q20 -> -563.567 | ... AG47: =AG20 -> 0
B48: Adjusted to exclude the following:
B49: (-) Digital asset sales on other venues | C49: =SUMIFS($J49:$V49,$J$3:$V$3,C$6) -> -21.824 | D49: =SUMIFS($J49:$V49,$J$3:$V$3,D$6) -> -396.446 | E49: =SUMIFS($J49:$V49,$J$3:$V$3,E$6) -> 0 | F49: =SUMIFS($J49:$V49,$J$3:$V$3,F$6) -> 0 | G49: =SUMIFS($J49:$V49,$J$3:$V$3,G$6) -> 0 | H49: =SUMIFS($J49:$V49,$J$3:$V$3,H$6) -> 0 | J49: =J31 -> -5.7 | K49: =K31 -> -8.8 | L49: =L31 -> -5.2 | M49: =M31 -> -2.124 | N49: =N31 -> -303.863 | O49: =O31 -> -30.1 | P49: =P31 -> -25.9 | Q49: =Q31 -> -36.583 | ... AG49: =AG31 -> 0
B50: (+) Cost of digital assets derecognized on other venues | C50: =SUMIFS($J50:$V50,$J$3:$V$3,C$6) -> 16.203 | D50: =SUMIFS($J50:$V50,$J$3:$V$3,D$6) -> 396.601 | E50: =SUMIFS($J50:$V50,$J$3:$V$3,E$6) -> 0 | F50: =SUMIFS($J50:$V50,$J$3:$V$3,F$6) -> 0 | G50: =SUMIFS($J50:$V50,$J$3:$V$3,G$6) -> 0 | H50: =SUMIFS($J50:$V50,$J$3:$V$3,H$6) -> 0 | K50: 8.9 | L50: 5.2 | M50: 2.103 | N50: 303.825 | O50: 30.2 | P50: 26 | Q50: 36.576 | R50: 0 | S50: 0
B51: (+/-) Loss/(Gain) from changes in FV of digital assets inventories net payable to customers | C51: =SUMIFS($J51:$V51,$J$3:$V$3,C$6) -> 9.058 | D51: =SUMIFS($J51:$V51,$J$3:$V$3,D$6) -> 208.608 | E51: =SUMIFS($J51:$V51,$J$3:$V$3,E$6) -> 216.177 | F51: =SUMIFS($J51:$V51,$J$3:$V$3,F$6) -> 0 | G51: =SUMIFS($J51:$V51,$J$3:$V$3,G$6) -> 0 | H51: =SUMIFS($J51:$V51,$J$3:$V$3,H$6) -> 0 | K51: 102.1 | L51: 38.7 | M51: -131.742 | N51: 115.267 | O51: -22.8 | P51: -4.1 | Q51: 120.241 | R51: 150.924 | S51: =216.177-R51 -> 65.253
B52: (+) Income tax expense | C52: =SUMIFS($J52:$V52,$J$3:$V$3,C$6) -> 5.005 | D52: =SUMIFS($J52:$V52,$J$3:$V$3,D$6) -> -0.502 | E52: =SUMIFS($J52:$V52,$J$3:$V$3,E$6) -> 0.23 | F52: =SUMIFS($J52:$V52,$J$3:$V$3,F$6) -> 0 | G52: =SUMIFS($J52:$V52,$J$3:$V$3,G$6) -> 0 | H52: =SUMIFS($J52:$V52,$J$3:$V$3,H$6) -> 0 | J52: =-J19 -> 0.176 | K52: =-K19 -> 0.302 | L52: =-L19 -> 0.745 | M52: =-M19 -> 3.782 | N52: =-N19 -> 0.221 | O52: =-O19 -> 0.876 | P52: =-P19 -> -0.076 | Q52: =-Q19 -> -1.523 | ... AG52: =-AG19 -> 0
B53: (+) Finance expenses | C53: =SUMIFS($J53:$V53,$J$3:$V$3,C$6) -> 38.529 | D53: =SUMIFS($J53:$V53,$J$3:$V$3,D$6) -> 52.369 | E53: =SUMIFS($J53:$V53,$J$3:$V$3,E$6) -> 28.547 | F53: =SUMIFS($J53:$V53,$J$3:$V$3,F$6) -> 0 | G53: =SUMIFS($J53:$V53,$J$3:$V$3,G$6) -> 0 | H53: =SUMIFS($J53:$V53,$J$3:$V$3,H$6) -> 0 | J53: =-J15 -> 8.929 | K53: =-K15 -> 9.063 | L53: =-L15 -> 9.878 | M53: =-M15 -> 10.659 | N53: =-N15 -> 10.24 | O53: =-O15 -> 13.291 | P53: =-P15 -> 13.906 | Q53: =-Q15 -> 14.932 | ... AG53: =-AG15 -> 0
B54: (+) Employee share-based payment expenses | C54: =SUMIFS($J54:$V54,$J$3:$V$3,C$6) -> 19.299 | D54: =SUMIFS($J54:$V54,$J$3:$V$3,D$6) -> 15.58 | E54: =SUMIFS($J54:$V54,$J$3:$V$3,E$6) -> 10.634 | F54: =SUMIFS($J54:$V54,$J$3:$V$3,F$6) -> 0 | G54: =SUMIFS($J54:$V54,$J$3:$V$3,G$6) -> 0 | H54: =SUMIFS($J54:$V54,$J$3:$V$3,H$6) -> 0 | K54: 8.9 | L54: 5.7 | M54: 4.699 | N54: 5.133 | O54: 3.3 | P54: 3.1 | Q54: 4.047 | R54: 5.603 | S54: =10.634-R54 -> 5.031
B55: (+) Other share-based payment expenses | C55: =SUMIFS($J55:$V55,$J$3:$V$3,C$6) -> 0 | D55: =SUMIFS($J55:$V55,$J$3:$V$3,D$6) -> 0.628 | E55: =SUMIFS($J55:$V55,$J$3:$V$3,E$6) -> 23.029 | F55: =SUMIFS($J55:$V55,$J$3:$V$3,F$6) -> 0 | G55: =SUMIFS($J55:$V55,$J$3:$V$3,G$6) -> 0 | H55: =SUMIFS($J55:$V55,$J$3:$V$3,H$6) -> 0 | K55: 0 | L55: 0 | M55: 0 | N55: 0 | O55: 0 | P55: 0 | Q55: 0.628 | R55: 15.438 | S55: =23.029-R55 -> 7.591
B56: (+/-) Change in FV of loan and other receivables - digital assets | C56: =SUMIFS($J56:$V56,$J$3:$V$3,C$6) -> -40.01 | D56: =SUMIFS($J56:$V56,$J$3:$V$3,D$6) -> 24.968 | E56: =SUMIFS($J56:$V56,$J$3:$V$3,E$6) -> -2.369 | F56: =SUMIFS($J56:$V56,$J$3:$V$3,F$6) -> 0 | G56: =SUMIFS($J56:$V56,$J$3:$V$3,G$6) -> 0 | H56: =SUMIFS($J56:$V56,$J$3:$V$3,H$6) -> 0 | K56: 11.8 | L56: -3.3 | M56: -48.51 | N56: 21.4 | O56: -55 | P56: -5.7 | Q56: 64.268 | R56: 73.236 | S56: =-2.369-R56 -> -75.605
B57: (+/-) Change in FV of digital assets loan payable | C57: =SUMIFS($J57:$V57,$J$3:$V$3,C$6) -> 14.439 | D57: =SUMIFS($J57:$V57,$J$3:$V$3,D$6) -> 0.022 | E57: =SUMIFS($J57:$V57,$J$3:$V$3,E$6) -> 85.379 | F57: =SUMIFS($J57:$V57,$J$3:$V$3,F$6) -> 0 | G57: =SUMIFS($J57:$V57,$J$3:$V$3,G$6) -> 0 | H57: =SUMIFS($J57:$V57,$J$3:$V$3,H$6) -> 0 | K57: -1.5 | L57: 1.6 | M57: 14.339 | N57: -13.305 | O57: 12.8 | P57: 3.4 | Q57: -2.873 | R57: -0.28 | S57: =85.379-R57 -> 85.659
B58: (+/-) Change in FV of derivatives | C58: =SUMIFS($J58:$V58,$J$3:$V$3,C$6) -> 12.19 | D58: =SUMIFS($J58:$V58,$J$3:$V$3,D$6) -> -9.609 | E58: =SUMIFS($J58:$V58,$J$3:$V$3,E$6) -> -91.58 | F58: =SUMIFS($J58:$V58,$J$3:$V$3,F$6) -> 0 | G58: =SUMIFS($J58:$V58,$J$3:$V$3,G$6) -> 0 | H58: =SUMIFS($J58:$V58,$J$3:$V$3,H$6) -> 0 | J58: =-J16 -> 0.526 | K58: =-K16 -> -0.175 | L58: =-L16 -> -1.028 | M58: =-M16 -> 12.867 | N58: =-N16 -> 0 | O58: =-O16 -> 2.379 | P58: =-P16 -> 5.533 | Q58: =-Q16 -> -17.521 | ... AG58: =-AG16 -> 0
B59: (+/-) Change in FV of financial liability at FVTPL | C59: =SUMIFS($J59:$V59,$J$3:$V$3,C$6) -> 43.35 | D59: =SUMIFS($J59:$V59,$J$3:$V$3,D$6) -> 20.1 | E59: =SUMIFS($J59:$V59,$J$3:$V$3,E$6) -> -4.2 | F59: =SUMIFS($J59:$V59,$J$3:$V$3,F$6) -> 0 | G59: =SUMIFS($J59:$V59,$J$3:$V$3,G$6) -> 0 | H59: =SUMIFS($J59:$V59,$J$3:$V$3,H$6) -> 0 | J59: =-J17 -> 35.6 | K59: =-K17 -> -6.1 | L59: =-L17 -> -0.1 | M59: =-M17 -> 13.95 | N59: =-N17 -> 0.9 | O59: =-O17 -> 15.25 | P59: =-P17 -> 10.85 | Q59: =-Q17 -> -6.9 | ... AG59: =-AG17 -> 0
B60: (+/-) Change in FV of investments in financial assets | C60: =SUMIFS($J60:$V60,$J$3:$V$3,C$6) -> -29.453 | D60: =SUMIFS($J60:$V60,$J$3:$V$3,D$6) -> 36.035 | E60: =SUMIFS($J60:$V60,$J$3:$V$3,E$6) -> 122.951 | F60: =SUMIFS($J60:$V60,$J$3:$V$3,F$6) -> 0 | G60: =SUMIFS($J60:$V60,$J$3:$V$3,G$6) -> 0 | H60: =SUMIFS($J60:$V60,$J$3:$V$3,H$6) -> 0 | J60: =-J12 -> -0.349 | K60: =-K12 -> 0.738 | L60: =-L12 -> -2.473 | M60: =-M12 -> -27.369 | N60: =-N12 -> 71.81 | O60: =-O12 -> -86.359 | P60: =-P12 -> -54.971 | Q60: =-Q12 -> 105.555 | ... AG60: =-AG12 -> 0
B61: (+) Impairment losses of digital assets held - intangible assets | C61: =SUMIFS($J61:$V61,$J$3:$V$3,C$6) -> 24.246 | D61: =SUMIFS($J61:$V61,$J$3:$V$3,D$6) -> 497.397 | E61: =SUMIFS($J61:$V61,$J$3:$V$3,E$6) -> 532.483 | F61: =SUMIFS($J61:$V61,$J$3:$V$3,F$6) -> 0 | G61: =SUMIFS($J61:$V61,$J$3:$V$3,G$6) -> 0 | H61: =SUMIFS($J61:$V61,$J$3:$V$3,H$6) -> 0 | K61: 4.5 | L61: 21.2 | M61: -1.454 | N61: 142.088 | O61: 6.7 | P61: 29.4 | Q61: 319.209 | R61: 350.97 | S61: =532.483-R61 -> 181.513
B62: (+) Impairment of right-of-use assets | C62: =SUMIFS($J62:$V62,$J$3:$V$3,C$6) -> 1 | D62: =SUMIFS($J62:$V62,$J$3:$V$3,D$6) -> 0 | E62: =SUMIFS($J62:$V62,$J$3:$V$3,E$6) -> 0.591 | F62: =SUMIFS($J62:$V62,$J$3:$V$3,F$6) -> 0 | G62: =SUMIFS($J62:$V62,$J$3:$V$3,G$6) -> 0 | H62: =SUMIFS($J62:$V62,$J$3:$V$3,H$6) -> 0 | K62: 1 | L62: 0 | M62: 0 | N62: 0 | O62: 0 | P62: 0 | Q62: 0 | R62: 0.591 | S62: =0.591-R62 -> 0
B63: (+) Impairment of digital assets | C63: =SUMIFS($J63:$V63,$J$3:$V$3,C$6) -> 0 | D63: =SUMIFS($J63:$V63,$J$3:$V$3,D$6) -> 0 | E63: =SUMIFS($J63:$V63,$J$3:$V$3,E$6) -> 8.239 | F63: =SUMIFS($J63:$V63,$J$3:$V$3,F$6) -> 0 | G63: =SUMIFS($J63:$V63,$J$3:$V$3,G$6) -> 0 | H63: =SUMIFS($J63:$V63,$J$3:$V$3,H$6) -> 0 | K63: 0 | L63: 0 | M63: 0 | N63: 0 | O63: 0 | P63: 0 | Q63: 0 | R63: 8.239 | S63: =8.239-R63 -> 0
B64: (+) Non-recurring expenses | C64: =SUMIFS($J64:$V64,$J$3:$V$3,C$6) -> 7.329 | D64: =SUMIFS($J64:$V64,$J$3:$V$3,D$6) -> 29.145 | E64: =SUMIFS($J64:$V64,$J$3:$V$3,E$6) -> 17.824 | F64: =SUMIFS($J64:$V64,$J$3:$V$3,F$6) -> 0 | G64: =SUMIFS($J64:$V64,$J$3:$V$3,G$6) -> 0 | H64: =SUMIFS($J64:$V64,$J$3:$V$3,H$6) -> 0 | K64: -0.3 | L64: 3 | M64: 4.629 | N64: 7.085 | O64: 7.4 | P64: 7.3 | Q64: 7.36 | R64: 5.487 | S64: =17.824-R64 -> 12.337
B65: (+) Depreciation and amortization | C65: =SUMIFS($J65:$V65,$J$3:$V$3,C$6) -> 2.677 | D65: =SUMIFS($J65:$V65,$J$3:$V$3,D$6) -> 3.065 | E65: =SUMIFS($J65:$V65,$J$3:$V$3,E$6) -> 1.541 | F65: =SUMIFS($J65:$V65,$J$3:$V$3,F$6) -> 0 | G65: =SUMIFS($J65:$V65,$J$3:$V$3,G$6) -> 0 | H65: =SUMIFS($J65:$V65,$J$3:$V$3,H$6) -> 0 | K65: 0.8 | L65: 0.9 | M65: 0.977 | N65: 0.789 | O65: 0.8 | P65: 0.9 | Q65: 0.576 | R65: 0.772 | S65: =1.541-R65 -> 0.769
B66: Adjusted to include the following:
B67: (+) Revaluation of digital assets held as investments | C67: =SUMIFS($J67:$V67,$J$3:$V$3,C$6) -> 0.703 | D67: =SUMIFS($J67:$V67,$J$3:$V$3,D$6) -> 2.168 | E67: =SUMIFS($J67:$V67,$J$3:$V$3,E$6) -> 0.089 | F67: =SUMIFS($J67:$V67,$J$3:$V$3,F$6) -> 0 | G67: =SUMIFS($J67:$V67,$J$3:$V$3,G$6) -> 0 | H67: =SUMIFS($J67:$V67,$J$3:$V$3,H$6) -> 0 | J67: =J43 -> 0 | K67: =K43 -> 0 | L67: =L43 -> 0.2 | M67: =M43 -> 0.503 | N67: =N43 -> 0.643 | O67: =O43 -> 1 | P67: =P43 -> 0.5 | Q67: =Q43 -> 0.025 | ... AG67: =AG43 -> 0
B68: Adjusted EBITDA | C68: =SUMIFS($J68:$V68,$J$3:$V$3,C$6) -> 52.255 | D68: =SUMIFS($J68:$V68,$J$3:$V$3,D$6) -> 94.217 | E68: =SUMIFS($J68:$V68,$J$3:$V$3,E$6) -> 63.847 | F68: =SUMIFS($J68:$V68,$J$3:$V$3,F$6) -> 0 | G68: =SUMIFS($J68:$V68,$J$3:$V$3,G$6) -> 0 | H68: =SUMIFS($J68:$V68,$J$3:$V$3,H$6) -> 0 | J68: 13.9 | K68: =K47+K49+K50+K51+K52+K53+K54+K55+K56+K57+K58+K59+K60+K61+K62+K63+K64+K65+K67 -> 14.834 | L68: =L47+L49+L50+L51+L52+L53+L54+L55+L56+L57+L58+L59+L60+L61+L62+L63+L64+L65+L67 -> 7.75 | M68: =M47+M49+M50+M51+M52+M53+M54+M55+M56+M57+M58+M59+M60+M61+M62+M63+M64+M65+M67 -> 15.771 | N68: =N47+N49+N50+N51+N52+N53+N54+N55+N56+N57+N58+N59+N60+N61+N62+N63+N64+N65+N67 -> 13.169 | O68: =O47+O49+O50+O51+O52+O53+O54+O55+O56+O57+O58+O59+O60+O61+O62+O63+O64+O65+O67 -> 8.005 | P68: =P47+P49+P50+P51+P52+P53+P54+P55+P56+P57+P58+P59+P60+P61+P62+P63+P64+P65+P67 -> 28.593 | Q68: =Q47+Q49+Q50+Q51+Q52+Q53+Q54+Q55+Q56+Q57+Q58+Q59+Q60+Q61+Q62+Q63+Q64+Q65+Q67 -> 44.45 | R68: =R47+R49+R50+R51+R52+R53+R54+R55+R56+R57+R58+R59+R60+R61+R62+R63+R64+R65+R67 -> 35.147 | ... AG68: =AG47+AG49+AG50+AG51+AG52+AG53+AG54+AG55+AG56+AG57+AG58+AG59+AG60+AG61+AG62+AG63+AG64+AG65+AG67 -> 0
B70: BLOCK 5 - BRIDGE: ADJUSTED EBITDA -> ADJUSTED NET INCOME
B71: Adjusted EBITDA | C71: =SUMIFS($J71:$V71,$J$3:$V$3,C$6) -> 52.255 | D71: =SUMIFS($J71:$V71,$J$3:$V$3,D$6) -> 94.217 | E71: =SUMIFS($J71:$V71,$J$3:$V$3,E$6) -> 63.847 | F71: =SUMIFS($J71:$V71,$J$3:$V$3,F$6) -> 0 | G71: =SUMIFS($J71:$V71,$J$3:$V$3,G$6) -> 0 | H71: =SUMIFS($J71:$V71,$J$3:$V$3,H$6) -> 0 | J71: =J68 -> 13.9 | K71: =K68 -> 14.834 | L71: =L68 -> 7.75 | M71: =M68 -> 15.771 | N71: =N68 -> 13.169 | O71: =O68 -> 8.005 | P71: =P68 -> 28.593 | Q71: =Q68 -> 44.45 | ... AG71: =AG68 -> 0
B72: (-) Finance expenses | C72: =SUMIFS($J72:$V72,$J$3:$V$3,C$6) -> -38.529 | D72: =SUMIFS($J72:$V72,$J$3:$V$3,D$6) -> -52.369 | E72: =SUMIFS($J72:$V72,$J$3:$V$3,E$6) -> -28.547 | F72: =SUMIFS($J72:$V72,$J$3:$V$3,F$6) -> 0 | G72: =SUMIFS($J72:$V72,$J$3:$V$3,G$6) -> 0 | H72: =SUMIFS($J72:$V72,$J$3:$V$3,H$6) -> 0 | J72: =J15 -> -8.929 | K72: =K15 -> -9.063 | L72: =L15 -> -9.878 | M72: =M15 -> -10.659 | N72: =N15 -> -10.24 | O72: =O15 -> -13.291 | P72: =P15 -> -13.906 | Q72: =Q15 -> -14.932 | ... AG72: =AG15 -> 0
B73: (-) Depreciation and amortization | C73: =SUMIFS($J73:$V73,$J$3:$V$3,C$6) -> -2.677 | D73: =SUMIFS($J73:$V73,$J$3:$V$3,D$6) -> -3.065 | E73: =SUMIFS($J73:$V73,$J$3:$V$3,E$6) -> -1.541 | F73: =SUMIFS($J73:$V73,$J$3:$V$3,F$6) -> 0 | G73: =SUMIFS($J73:$V73,$J$3:$V$3,G$6) -> 0 | H73: =SUMIFS($J73:$V73,$J$3:$V$3,H$6) -> 0 | J73: =-J65 -> 0 | K73: =-K65 -> -0.8 | L73: =-L65 -> -0.9 | M73: =-M65 -> -0.977 | N73: =-N65 -> -0.789 | O73: =-O65 -> -0.8 | P73: =-P65 -> -0.9 | Q73: =-Q65 -> -0.576 | ... AG73: =-AG65 -> 0
B74: (+/-) Tax effect of adjusted net income before taxes | C74: =SUMIFS($J74:$V74,$J$3:$V$3,C$6) -> -0.196 | D74: =SUMIFS($J74:$V74,$J$3:$V$3,D$6) -> -0.079 | E74: =SUMIFS($J74:$V74,$J$3:$V$3,E$6) -> 0.009 | F74: =SUMIFS($J74:$V74,$J$3:$V$3,F$6) -> 0 | G74: =SUMIFS($J74:$V74,$J$3:$V$3,G$6) -> 0 | H74: =SUMIFS($J74:$V74,$J$3:$V$3,H$6) -> 0 | K74: 0 | L74: -0.1 | M74: -0.096 | N74: -0.001 | O74: 0 | P74: 0 | Q74: -0.078 | R74: 0.008 | S74: =0.009-R74 -> 0.001
B75: Adjusted Net Income | C75: =SUMIFS($J75:$V75,$J$3:$V$3,C$6) -> 9.782 | D75: =SUMIFS($J75:$V75,$J$3:$V$3,D$6) -> 38.704 | E75: =SUMIFS($J75:$V75,$J$3:$V$3,E$6) -> 33.768 | F75: =SUMIFS($J75:$V75,$J$3:$V$3,F$6) -> 0 | G75: =SUMIFS($J75:$V75,$J$3:$V$3,G$6) -> 0 | H75: =SUMIFS($J75:$V75,$J$3:$V$3,H$6) -> 0 | J75: 3.9 | K75: =K71+K72+K73+K74 -> 4.971 | L75: =L71+L72+L73+L74 -> -3.128 | M75: =M71+M72+M73+M74 -> 4.039 | N75: =N71+N72+N73+N74 -> 2.139 | O75: =O71+O72+O73+O74 -> -6.086 | P75: =P71+P72+P73+P74 -> 13.787 | Q75: =Q71+Q72+Q73+Q74 -> 28.864 | R75: =R71+R72+R73+R74 -> 20.295 | ... AG75: =AG71+AG72+AG73+AG74 -> 0
B76: Adjusted Net Income margin % (of Adjusted Revenue) | C76: =IFERROR(C75/C44,"-") -> 0.045722886 | D76: =IFERROR(D75/D44,"-") -> 0.13420436 | E76: =IFERROR(E75/E44,"-") -> 0.083576912 | F76: =IFERROR(F75/F44,"-") -> 0 | G76: =IFERROR(G75/G44,"-") -> 0 | H76: =IFERROR(H75/H44,"-") -> 0 | J76: =IFERROR(J75/J44,"-") -> 0.07293264 | K76: =IFERROR(K75/K44,"-") -> 0.081882423 | L76: =IFERROR(L75/L44,"-") -> -0.070173864 | M76: =IFERROR(M75/M44,"-") -> 0.073192831 | N76: =IFERROR(N75/N44,"-") -> 0.03426402 | O76: =IFERROR(O75/O44,"-") -> -0.10685441 | P76: =IFERROR(P75/P44,"-") -> 0.18021044 | Q76: =IFERROR(Q75/Q44,"-") -> 0.31201626 | ... AG76: =IFERROR(AG75/AG44,"-") -> 0
B78: BLOCK 6 - BRIDGE: IFRS CORE OPERATING EXPENSE -> ADJUSTED OPERATING EXPENSE
B79: IFRS Core Operating Expense (= Administrative expenses + Other expenses) | C79: =SUMIFS($J79:$V79,$J$3:$V$3,C$6) -> 199.2 | D79: =SUMIFS($J79:$V79,$J$3:$V$3,D$6) -> 242.613 | E79: =SUMIFS($J79:$V79,$J$3:$V$3,E$6) -> 182.591 | F79: =SUMIFS($J79:$V79,$J$3:$V$3,F$6) -> 0 | G79: =SUMIFS($J79:$V79,$J$3:$V$3,G$6) -> 0 | H79: =SUMIFS($J79:$V79,$J$3:$V$3,H$6) -> 0 | J79: =-(J13+J14) -> 46.673 | K79: =-(K13+K14) -> 56.382 | L79: =-(L13+L14) -> 46.428 | M79: =-(M13+M14) -> 49.717 | N79: =-(N13+N14) -> 62.249 | O79: =-(O13+O14) -> 60.379 | P79: =-(P13+P14) -> 59.317 | Q79: =-(Q13+Q14) -> 60.668 | ... AG79: =-(AG13+AG14) -> 0
B80: (-) Employee share-based compensation expense | C80: =SUMIFS($J80:$V80,$J$3:$V$3,C$6) -> 19.299 | D80: =SUMIFS($J80:$V80,$J$3:$V$3,D$6) -> 15.58 | E80: =SUMIFS($J80:$V80,$J$3:$V$3,E$6) -> 10.634 | F80: =SUMIFS($J80:$V80,$J$3:$V$3,F$6) -> 0 | G80: =SUMIFS($J80:$V80,$J$3:$V$3,G$6) -> 0 | H80: =SUMIFS($J80:$V80,$J$3:$V$3,H$6) -> 0 | K80: 8.9 | L80: 5.7 | M80: 4.699 | N80: 5.133 | O80: 3.3 | P80: 3.1 | Q80: 4.047 | R80: 5.603 | S80: =10.634-R80 -> 5.031
B81: (-) Other share-based compensation expense | C81: =SUMIFS($J81:$V81,$J$3:$V$3,C$6) -> 0 | D81: =SUMIFS($J81:$V81,$J$3:$V$3,D$6) -> 0.628 | E81: =SUMIFS($J81:$V81,$J$3:$V$3,E$6) -> 23.029 | F81: =SUMIFS($J81:$V81,$J$3:$V$3,F$6) -> 0 | G81: =SUMIFS($J81:$V81,$J$3:$V$3,G$6) -> 0 | H81: =SUMIFS($J81:$V81,$J$3:$V$3,H$6) -> 0 | K81: 0 | L81: 0 | M81: 0 | N81: 0 | O81: 0 | P81: 0 | Q81: 0.628 | R81: 15.438 | S81: =23.029-R81 -> 7.591
B82: (-) Non-recurring expenses - legal and professional fees | C82: =SUMIFS($J82:$V82,$J$3:$V$3,C$6) -> 6.022 | D82: =SUMIFS($J82:$V82,$J$3:$V$3,D$6) -> 25.233 | E82: =SUMIFS($J82:$V82,$J$3:$V$3,E$6) -> 15.573 | F82: =SUMIFS($J82:$V82,$J$3:$V$3,F$6) -> 0 | G82: =SUMIFS($J82:$V82,$J$3:$V$3,G$6) -> 0 | H82: =SUMIFS($J82:$V82,$J$3:$V$3,H$6) -> 0 | K82: 0.6 | L82: 1.1 | M82: 4.322 | N82: 6.047 | O82: 6.3 | P82: 6.5 | Q82: 6.386 | R82: 4.04 | S82: =15.573-R82 -> 11.533
B83: (-) Non-recurring expenses - compensation and benefits | C83: =SUMIFS($J83:$V83,$J$3:$V$3,C$6) -> 2.208 | D83: =SUMIFS($J83:$V83,$J$3:$V$3,D$6) -> 3.912 | E83: =SUMIFS($J83:$V83,$J$3:$V$3,E$6) -> 1.842 | F83: =SUMIFS($J83:$V83,$J$3:$V$3,F$6) -> 0 | G83: =SUMIFS($J83:$V83,$J$3:$V$3,G$6) -> 0 | H83: =SUMIFS($J83:$V83,$J$3:$V$3,H$6) -> 0 | K83: 0.1 | L83: 1.8 | M83: 0.308 | N83: 1.038 | O83: 1.1 | P83: 0.8 | Q83: 0.974 | R83: 1.447 | S83: =1.842-R83 -> 0.395
B84: (-) Depreciation and amortization expense | C84: =SUMIFS($J84:$V84,$J$3:$V$3,C$6) -> 2.677 | D84: =SUMIFS($J84:$V84,$J$3:$V$3,D$6) -> 3.065 | E84: =SUMIFS($J84:$V84,$J$3:$V$3,E$6) -> 1.541 | F84: =SUMIFS($J84:$V84,$J$3:$V$3,F$6) -> 0 | G84: =SUMIFS($J84:$V84,$J$3:$V$3,G$6) -> 0 | H84: =SUMIFS($J84:$V84,$J$3:$V$3,H$6) -> 0 | J84: =J65 -> 0 | K84: =K65 -> 0.8 | L84: =L65 -> 0.9 | M84: =M65 -> 0.977 | N84: =N65 -> 0.789 | O84: =O65 -> 0.8 | P84: =P65 -> 0.9 | Q84: =Q65 -> 0.576 | ... AG84: =AG65 -> 0
B85: (-) Impairment of right-of-use assets | C85: =SUMIFS($J85:$V85,$J$3:$V$3,C$6) -> 0 | D85: =SUMIFS($J85:$V85,$J$3:$V$3,D$6) -> 0 | E85: =SUMIFS($J85:$V85,$J$3:$V$3,E$6) -> 0.591 | F85: =SUMIFS($J85:$V85,$J$3:$V$3,F$6) -> 0 | G85: =SUMIFS($J85:$V85,$J$3:$V$3,G$6) -> 0 | H85: =SUMIFS($J85:$V85,$J$3:$V$3,H$6) -> 0 | R85: 0.591 | S85: =0.591-R85 -> 0
B86: (-) Impairment of digital assets | C86: =SUMIFS($J86:$V86,$J$3:$V$3,C$6) -> 0 | D86: =SUMIFS($J86:$V86,$J$3:$V$3,D$6) -> 0 | E86: =SUMIFS($J86:$V86,$J$3:$V$3,E$6) -> 8.239 | F86: =SUMIFS($J86:$V86,$J$3:$V$3,F$6) -> 0 | G86: =SUMIFS($J86:$V86,$J$3:$V$3,G$6) -> 0 | H86: =SUMIFS($J86:$V86,$J$3:$V$3,H$6) -> 0 | R86: 8.239 | S86: =8.239-R86 -> 0
B87: Adjusted Operating Expense | C87: =SUMIFS($J87:$V87,$J$3:$V$3,C$6) -> 161.821 | D87: =SUMIFS($J87:$V87,$J$3:$V$3,D$6) -> 194.195 | E87: =SUMIFS($J87:$V87,$J$3:$V$3,E$6) -> 121.142 | F87: =SUMIFS($J87:$V87,$J$3:$V$3,F$6) -> 0 | G87: =SUMIFS($J87:$V87,$J$3:$V$3,G$6) -> 0 | H87: =SUMIFS($J87:$V87,$J$3:$V$3,H$6) -> 0 | J87: 39.5 | K87: =K79-(K80+K81+K82+K83+K84+K85+K86) -> 45.982 | L87: =L79-(L80+L81+L82+L83+L84+L85+L86) -> 36.928 | M87: =M79-(M80+M81+M82+M83+M84+M85+M86) -> 39.411 | N87: =N79-(N80+N81+N82+N83+N84+N85+N86) -> 49.242 | O87: =O79-(O80+O81+O82+O83+O84+O85+O86) -> 48.879 | P87: =P79-(P80+P81+P82+P83+P84+P85+P86) -> 48.017 | Q87: =Q79-(Q80+Q81+Q82+Q83+Q84+Q85+Q86) -> 48.057 | R87: =R79-(R80+R81+R82+R83+R84+R85+R86) -> 57.68 | ... AG87: =AG79-(AG80+AG81+AG82+AG83+AG84+AG85+AG86) -> 0
B89: KEY PERFORMANCE INDICATORS (actuals only - source: Shareholder Update slide 11)
B90: BTC price (daily average, $000s) | N90: 93.5 | O90: 98.5 | P90: 114.4 | Q90: 100 | R90: 76.4
B91: Annualized BTC volatility (spot) | N91: 0.474 | O91: 0.353 | P91: 0.26 | Q91: 0.405 | R91: 0.47
B92: Avg. daily trading volume - spot ($mm) | N92: 2550.5 | O92: 1791.1 | P92: 1417.6 | Q92: 2228.8 | R92: 1952.2
B93: Avg. daily trading volume - perpetual futures ($mm) | N93: 248.8 | O93: 182.6 | P93: 128 | Q93: 90 | R93: 105.5
B94: Avg. daily trading volume - options ($mm) | Q94: 98.5 | R94: 128.8
B95: Headcount (period end) | N95: 406 | O95: 406 | P95: 409 | Q95: 414 | R95: 405

Sheet Balance Sheet
B2: Balance Sheet - Bullish (BLSH) Standalone, IFRS Basis
B3: Quarterly figures as reported in each Form 6-K / earnings release (Q2'25, Q3'25, Q4'25, Q1'26 releases) and Dec-24 comparative. 1Q24-3Q24 and 1Q25 point-in-time balance sheets were not disclosed in the sourced documents and are left blank rather than estimated. Annual (FY) columns show the year-end (4Q) snapshot, not a sum, since the Balance Sheet is a point-in-time statement - unlike the Income Statement and Cash Flow tabs. No pro forma / Equiniti effects included anywhere on this tab.
J5: =YEAR(J6) -> 2024 | K5: =YEAR(K6) -> 2024 | L5: =YEAR(L6) -> 2024 | M5: =YEAR(M6) -> 2024 | N5: =YEAR(N6) -> 2025 | O5: =YEAR(O6) -> 2025 | P5: =YEAR(P6) -> 2025 | Q5: =YEAR(Q6) -> 2025 | ... V5: =YEAR(V6) -> 2027
J6: 45354 | K6: =EOMONTH(J6,3) -> 45473 | L6: =EOMONTH(K6,3) -> 45565 | M6: =EOMONTH(L6,3) -> 45657 | N6: =EOMONTH(M6,3) -> 45747 | O6: =EOMONTH(N6,3) -> 45838 | P6: =EOMONTH(O6,3) -> 45930 | Q6: =EOMONTH(P6,3) -> 46022 | R6: =EOMONTH(Q6,3) -> 46112 | ... V6: =EOMONTH(U6,3) -> 46477
B7: QUARTERLY BALANCE SHEET, WITH YEAR-END (4Q) SNAPSHOT IN ANNUAL COLUMNS
B8: ($000s unless noted) | C8: 2024 | D8: 2025 | E8: =D8+1 -> 2026 | F8: =E8+1 -> 2027 | G8: =F8+1 -> 2028 | H8: =G8+1 -> 2029 | J8: 1Q24A | K8: 2Q24A | L8: 3Q24A | M8: 4Q24A | N8: 1Q25A | O8: 2Q25A | P8: 3Q25A | Q8: 4Q25A | R8: 1Q26A | S8: 2Q26P | T8: 3Q26P | U8: 4Q26P | V8: 1Q27P
B9: ASSETS
B10: Non-current assets
B11: Goodwill | C11: =IF(M11="","",M11) -> 61475 | D11: =IF(Q11="","",Q11) -> 63062 | E11: =IF(U11="","",U11) | M11: 61475 | O11: 63458 | P11: 63023 | Q11: 63062 | R11: 62682 | S11: 62648
B12: Other intangible assets | C12: =IF(M12="","",M12) -> 33298 | D12: =IF(Q12="","",Q12) -> 31104 | E12: =IF(U12="","",U12) | M12: 33298 | O12: 32232 | P12: 31661 | Q12: 31104 | R12: 30535 | S12: 29978
B13: Property and equipment and right-of-use assets | C13: =IF(M13="","",M13) -> 14118 | D13: =IF(Q13="","",Q13) -> 28369 | E13: =IF(U13="","",U13) | M13: 14118 | O13: 14856 | P13: 12206 | Q13: 28369 | R13: 26465 | S13: 27541
B14: Deferred tax assets | C14: =IF(M14="","",M14) -> 2088 | D14: =IF(Q14="","",Q14) -> 2865 | E14: =IF(U14="","",U14) | M14: 2088 | O14: 2519 | P14: 2894 | Q14: 2865 | R14: 2995 | S14: 2823
B15: Other assets (non-current) | C15: =IF(M15="","",M15) -> 22087 | D15: =IF(Q15="","",Q15) -> 21311 | E15: =IF(U15="","",U15) | M15: 22087 | O15: 20583 | P15: 22237 | Q15: 21311 | R15: 17662 | S15: 26074
B16: Restricted cash (non-current) | C16: =IF(M16="","",M16) -> 1968 | D16: =IF(Q16="","",Q16) -> 5727 | E16: =IF(U16="","",U16) | M16: 1968 | O16: 1968 | P16: 1968 | Q16: 5727 | R16: 5840 | S16: 5817
B17: Total non-current assets | C17: =IF(M17="","",M17) -> 135034 | D17: =IF(Q17="","",Q17) -> 152438 | E17: =IF(U17="","",U17) -> 0 | J17: =J11+J12+J13+J14+J15+J16 -> 0 | K17: =K11+K12+K13+K14+K15+K16 -> 0 | L17: =L11+L12+L13+L14+L15+L16 -> 0 | M17: =M11+M12+M13+M14+M15+M16 -> 135034 | N17: =N11+N12+N13+N14+N15+N16 -> 0 | O17: =O11+O12+O13+O14+O15+O16 -> 135616 | P17: =P11+P12+P13+P14+P15+P16 -> 133989 | Q17: =Q11+Q12+Q13+Q14+Q15+Q16 -> 152438 | ... V17: =V11+V12+V13+V14+V15+V16 -> 0
B19: Current assets
B20: Digital assets held - inventories | C20: =IF(M20="","",M20) -> 573876 | D20: =IF(Q20="","",Q20) -> 206178 | E20: =IF(U20="","",U20) | M20: 573876 | O20: 231870 | P20: 254203 | Q20: 206178 | R20: 142698 | S20: 139131
B21: Digital assets held - intangible assets | C21: =IF(M21="","",M21) -> 1878268 | D21: =IF(Q21="","",Q21) -> 1537071 | E21: =IF(U21="","",U21) | M21: 1878268 | O21: 1957402 | P21: 2094385 | Q21: 1537071 | R21: 1298611 | S21: 1133596
B22: Digital assets held - financial assets | C22: =IF(M22="","",M22) -> 132649 | D22: =IF(Q22="","",Q22) -> 1037915 | E22: =IF(U22="","",U22) | M22: 132649 | O22: 106020 | P22: 1189097 | Q22: 1037915 | R22: 863306 | S22: 952626
B23: Loan and other receivables - digital assets | C23: =IF(M23="","",M23) -> 166388 | D23: =IF(Q23="","",Q23) -> 446481 | E23: =IF(U23="","",U23) | M23: 166388 | O23: 310927 | P23: 436720 | Q23: 446481 | R23: 395684 | S23: 269111
B24: Derivative financial instruments | C24: =IF(M24="","",M24) -> 0 | D24: =IF(Q24="","",Q24) -> 0 | E24: =IF(U24="","",U24) | M24: 0 | O24: 181 | P24: 20 | Q24: 0 | R24: 6298 | S24: 0
B25: Investments in financial assets | C25: =IF(M25="","",M25) -> 86173 | D25: =IF(Q25="","",Q25) -> 404144 | E25: =IF(U25="","",U25) | M25: 86173 | O25: 422470 | P25: 375845 | Q25: 404144 | R25: 266640 | S25: 226237
B26: Other assets (current) | C26: =IF(M26="","",M26) -> 21209 | D26: =IF(Q26="","",Q26) -> 47502 | E26: =IF(U26="","",U26) | M26: 21209 | O26: 19133 | P26: 38590 | Q26: 47502 | R26: 55945 | S26: 64687
B27: Customer segregated cash | C27: =IF(M27="","",M27) -> 6382 | D27: =IF(Q27="","",Q27) -> 20044 | E27: =IF(U27="","",U27) | M27: 6382 | O27: 4138 | P27: 14550 | Q27: 20044 | R27: 55640 | S27: 52724
B28: Restricted cash (current) | C28: =IF(M28="","",M28) -> 15893 | D28: =IF(Q28="","",Q28) -> 16839 | E28: =IF(U28="","",U28) | M28: 15893 | O28: 16193 | P28: 16676 | Q28: 16839 | R28: 17003 | S28: 17106
B29: Cash and cash equivalents | C29: =IF(M29="","",M29) -> 31540 | D29: =IF(Q29="","",Q29) -> 87892 | E29: =IF(U29="","",U29) | M29: 31540 | O29: 35560 | P29: 69307 | Q29: 87892 | R29: 76052 | S29: 86614
B30: Total current assets | C30: =IF(M30="","",M30) -> 2912378 | D30: =IF(Q30="","",Q30) -> 3804066 | E30: =IF(U30="","",U30) -> 0 | J30: =J20+J21+J22+J23+J24+J25+J26+J27+J28+J29 -> 0 | K30: =K20+K21+K22+K23+K24+K25+K26+K27+K28+K29 -> 0 | L30: =L20+L21+L22+L23+L24+L25+L26+L27+L28+L29 -> 0 | M30: =M20+M21+M22+M23+M24+M25+M26+M27+M28+M29 -> 2912378 | N30: =N20+N21+N22+N23+N24+N25+N26+N27+N28+N29 -> 0 | O30: =O20+O21+O22+O23+O24+O25+O26+O27+O28+O29 -> 3103894 | P30: =P20+P21+P22+P23+P24+P25+P26+P27+P28+P29 -> 4489393 | Q30: =Q20+Q21+Q22+Q23+Q24+Q25+Q26+Q27+Q28+Q29 -> 3804066 | ... V30: =V20+V21+V22+V23+V24+V25+V26+V27+V28+V29 -> 0
B31: Total assets | C31: =IF(M31="","",M31) -> 3047412 | D31: =IF(Q31="","",Q31) -> 3956504 | E31: =IF(U31="","",U31) -> 0 | J31: =J17+J30 -> 0 | K31: =K17+K30 -> 0 | L31: =L17+L30 -> 0 | M31: =M17+M30 -> 3047412 | N31: =N17+N30 -> 0 | O31: =O17+O30 -> 3239510 | P31: =P17+P30 -> 4623382 | Q31: =Q17+Q30 -> 3956504 | ... V31: =V17+V30 -> 0
B33: LIABILITIES
B34: Non-current liabilities
B35: Borrowings from related parties | C35: =IF(M35="","",M35) -> 482450 | D35: =IF(Q35="","",Q35) -> 505600 | E35: =IF(U35="","",U35) | M35: 482450 | O35: 496900 | P35: 513850 | Q35: 505600 | R35: 482850 | S35: 495650
B36: Convertible redeemable preference shares | C36: =IF(M36="","",M36) -> 47879 | D36: =IF(Q36="","",Q36) -> 0 | E36: =IF(U36="","",U36) | M36: 47879 | O36: 47879 | P36: 0 | Q36: 0 | R36: 0 | S36: 0
B37: Digital assets loan payable (non-current) | C37: =IF(M37="","",M37) -> 20613 | D37: =IF(Q37="","",Q37) -> 5267 | E37: =IF(U37="","",U37) | M37: 20613 | O37: 6111 | P37: 8012 | Q37: 5267 | R37: 4885 | S37: 2916
B38: Lease liabilities (non-current) | C38: =IF(M38="","",M38) -> 10756 | D38: =IF(Q38="","",Q38) -> 14378 | E38: =IF(U38="","",U38) | M38: 10756 | O38: 11073 | P38: 7695 | Q38: 14378 | R38: 12817 | S38: 13064
B39: Deferred tax liabilities | C39: =IF(M39="","",M39) -> 6 | D39: =IF(Q39="","",Q39) -> 18 | E39: =IF(U39="","",U39) | M39: 6 | O39: 126 | P39: 0 | Q39: 18 | R39: 18 | S39: 1
B40: Other payables (non-current) | C40: =IF(M40="","",M40) | D40: =IF(Q40="","",Q40) -> 3000 | E40: =IF(U40="","",U40) | Q40: 3000 | R40: 0 | S40: 0
B41: Total non-current liabilities | C41: =IF(M41="","",M41) -> 561704 | D41: =IF(Q41="","",Q41) -> 528263 | E41: =IF(U41="","",U41) -> 0 | J41: =J35+J36+J37+J38+J39+J40 -> 0 | K41: =K35+K36+K37+K38+K39+K40 -> 0 | L41: =L35+L36+L37+L38+L39+L40 -> 0 | M41: =M35+M36+M37+M38+M39+M40 -> 561704 | N41: =N35+N36+N37+N38+N39+N40 -> 0 | O41: =O35+O36+O37+O38+O39+O40 -> 562089 | P41: =P35+P36+P37+P38+P39+P40 -> 529557 | Q41: =Q35+Q36+Q37+Q38+Q39+Q40 -> 528263 | ... V41: =V35+V36+V37+V38+V39+V40 -> 0
B43: Current liabilities
B44: Customer segregated cash liabilities | C44: =IF(M44="","",M44) -> 6382 | D44: =IF(Q44="","",Q44) -> 20044 | E44: =IF(U44="","",U44) | M44: 6382 | O44: 4138 | P44: 14550 | Q44: 20044 | R44: 55640 | S44: 52724
B45: Borrowings (current) | C45: =IF(M45="","",M45) -> 25000 | D45: =IF(Q45="","",Q45) -> 49982 | E45: =IF(U45="","",U45) | M45: 25000 | O45: 73173 | P45: 50000 | Q45: 49982 | R45: 0 | S45: 11
B46: Digital assets loan payable (current) | C46: =IF(M46="","",M46) -> 0 | D46: =IF(Q46="","",Q46) -> 334 | E46: =IF(U46="","",U46) | M46: 0 | O46: 273 | P46: 445 | Q46: 334 | R46: 334 | S46: 66
B47: Lease liabilities (current) | C47: =IF(M47="","",M47) -> 4246 | D47: =IF(Q47="","",Q47) -> 5524 | E47: =IF(U47="","",U47) | M47: 4246 | O47: 4533 | P47: 2566 | Q47: 5524 | R47: 6213 | S47: 6446
B48: Other payables (current) | C48: =IF(M48="","",M48) -> 49421 | D48: =IF(Q48="","",Q48) -> 54028 | E48: =IF(U48="","",U48) | M48: 49421 | O48: 44104 | P48: 48212 | Q48: 54028 | R48: 58092 | S48: 61697
B49: Derivative financial instruments | S49: 4108
B50: Total current liabilities | C50: =IF(M50="","",M50) -> 85049 | D50: =IF(Q50="","",Q50) -> 129912 | E50: =IF(U50="","",U50) -> 0 | J50: =SUM(J44:J49) -> 0 | K50: =SUM(K44:K49) -> 0 | L50: =SUM(L44:L49) -> 0 | M50: =SUM(M44:M49) -> 85049 | N50: =SUM(N44:N49) -> 0 | O50: =SUM(O44:O49) -> 126221 | P50: =SUM(P44:P49) -> 115773 | Q50: =SUM(Q44:Q49) -> 129912 | ... S50: =SUM(S44:S49) -> 125052 | T50: =T44+T45+T46+T47+T48 -> 0 | U50: =U44+U45+U46+U47+U48 -> 0 | V50: =V44+V45+V46+V47+V48 -> 0
B51: Total liabilities | C51: =IF(M51="","",M51) -> 646753 | D51: =IF(Q51="","",Q51) -> 658175 | E51: =IF(U51="","",U51) -> 0 | J51: =J41+J50 -> 0 | K51: =K41+K50 -> 0 | L51: =L41+L50 -> 0 | M51: =M41+M50 -> 646753 | N51: =N41+N50 -> 0 | O51: =O41+O50 -> 688310 | P51: =P41+P50 -> 645330 | Q51: =Q41+Q50 -> 658175 | ... V51: =V41+V50 -> 0
B52: Net assets | C52: =IF(M52="","",M52) -> 2400659 | D52: =IF(Q52="","",Q52) -> 3298329 | E52: =IF(U52="","",U52) -> 0 | J52: =J31-J51 -> 0 | K52: =K31-K51 -> 0 | L52: =L31-L51 -> 0 | M52: =M31-M51 -> 2400659 | N52: =N31-N51 -> 0 | O52: =O31-O51 -> 2551200 | P52: =P31-P51 -> 3978052 | Q52: =Q31-Q51 -> 3298329 | ... V52: =V31-V51 -> 0
B54: EQUITY
B55: Share capital and share premium | C55: =IF(M55="","",M55) -> 3821537 | D55: =IF(Q55="","",Q55) -> 5110063 | E55: =IF(U55="","",U55) | M55: 3821537 | O55: 3821537 | P55: 5105631 | Q55: 5110063 | R55: 5119254 | S55: 5124909
B56: Option premium on convertible redeemable preference shares | C56: =IF(M56="","",M56) -> 18399 | D56: =IF(Q56="","",Q56) -> 0 | E56: =IF(U56="","",U56) | M56: 18399 | O56: 18399 | P56: 0 | Q56: 0 | R56: 0 | S56: 0
B57: Reserves | C57: =IF(M57="","",M57) -> 858797 | D57: =IF(Q57="","",Q57) -> 774224 | E57: =IF(U57="","",U57) | M57: 858797 | O57: 1073863 | P57: 1101668 | Q57: 774224 | R57: 390214 | S57: 414108
B58: Accumulated deficit | C58: =IF(M58="","",M58) -> -2309053 | D58: =IF(Q58="","",Q58) -> -2668100 | E58: =IF(U58="","",U58) | M58: -2309053 | O58: -2375625 | P58: -2290225 | Q58: -2668100 | R58: -2860139 | S58: -3123985
B59: Total shareholders' equity (owners of the Group) | C59: =IF(M59="","",M59) -> 2389680 | D59: =IF(Q59="","",Q59) -> 3216187 | E59: =IF(U59="","",U59) -> 0 | J59: =J55+J56+J57+J58 -> 0 | K59: =K55+K56+K57+K58 -> 0 | L59: =L55+L56+L57+L58 -> 0 | M59: =M55+M56+M57+M58 -> 2389680 | N59: =N55+N56+N57+N58 -> 0 | O59: =O55+O56+O57+O58 -> 2538174 | P59: =P55+P56+P57+P58 -> 3917074 | Q59: =Q55+Q56+Q57+Q58 -> 3216187 | ... V59: =V55+V56+V57+V58 -> 0
B60: Non-controlling interests | C60: =IF(M60="","",M60) -> 10979 | D60: =IF(Q60="","",Q60) -> 82142 | E60: =IF(U60="","",U60) | M60: 10979 | O60: 13140 | P60: 60978 | Q60: 82142 | R60: 53878 | S60: 44998
B61: Total equity | C61: =IF(M61="","",M61) -> 2400659 | D61: =IF(Q61="","",Q61) -> 3298329 | E61: =IF(U61="","",U61) -> 0 | J61: =J59+J60 -> 0 | K61: =K59+K60 -> 0 | L61: =L59+L60 -> 0 | M61: =M59+M60 -> 2400659 | N61: =N59+N60 -> 0 | O61: =O59+O60 -> 2551314 | P61: =P59+P60 -> 3978052 | Q61: =Q59+Q60 -> 3298329 | ... V61: =V59+V60 -> 0
B62: Balance check (Total equity + Total liabilities - Total assets, should = 0) | J62: =IF(J31="","",J61+J51-J31) -> 0 | K62: =IF(K31="","",K61+K51-K31) -> 0 | L62: =IF(L31="","",L61+L51-L31) -> 0 | M62: =IF(M31="","",M61+M51-M31) -> 0 | N62: =IF(N31="","",N61+N51-N31) -> 0 | O62: =IF(O31="","",O61+O51-O31) -> 114 | P62: =IF(P31="","",P61+P51-P31) -> 0 | Q62: =IF(Q31="","",Q61+Q51-Q31) -> 0 | ... V62: =IF(V31="","",V61+V51-V31) -> 0
B65: LIQUID ASSETS BRIDGE (non-IFRS, as disclosed in earnings releases)
B66: Gross liquid assets ($mm) | C66: =IF(M66="","",M66) -> 2868.9 | D66: =IF(Q66="","",Q66) -> 3719.7 | E66: =IF(U66="","",U66) | M66: 2868.9 | O66: 3064.2 | P66: 4419.5 | Q66: 3719.7 | R66: 3043 | S66: 2807.315
B67: Net liquid assets ($mm) | C67: =IF(M67="","",M67) -> 1696.1 | D67: =IF(Q67="","",Q67) -> 2859.7 | E67: =IF(U67="","",U67) | M67: 1696.1 | O67: 2179.3 | P67: 3485 | Q67: 2859.7 | R67: 2271.8 | S67: 2101.571
B69: SOURCES
B70: Dec-24 and Jun-25 balance sheets: Bullish 2Q'25 earnings release (Form 6-K, filed ~Aug 2025), "Condensed Consolidated Balance Sheets (Unaudited) as of June 30, 2025 and December 31, 2024."
B71: Sep-25 balance sheet: Bullish 3Q'25 earnings release, "Condensed Consolidated Balance Sheets (Unaudited) as of September 30, 2025 and December 31, 2024."
B72: Dec-25 balance sheet: Bullish 4Q'25 / FY2025 earnings release (Feb 5, 2026), "Condensed Consolidated Balance Sheets (Unaudited) as of December 31, 2025 and December 31, 2024."
B73: Mar-26 balance sheet: Bullish 1Q'26 earnings release (May 14, 2026), "Condensed Consolidated Balance Sheets (Unaudited) as of March 31, 2026 and December 31, 2025."
B74: 1Q24-3Q24 and 1Q25 quarter-end balance sheets were not disclosed in any of the four sourced earnings releases - left blank rather than estimated. Pull from the relevant Form 6-K if needed.
B75: Gross/Net liquid assets: each release's "Gross and Net Liquid Assets" reconciliation table. Dec-24 figure shown uses the most recently restated value (from the 3Q'25/4Q'25 releases); the 2Q'25 release reported a slightly different Dec-24 Net Liquid Assets figure ($1,699.4mm vs. $1,696.1mm) before methodology/rounding was reconciled - noted here for transparency.
B76: FY2026E-FY2029E columns intentionally left blank pending the Week 3 model build - do not treat as zero.
B78: Legend: blue = actual reported figure (sourced). Yellow fill = forecast input cell, left blank pending Week 3/4 modeling. Grey/blank = not disclosed in source documents. Black = formula. Rows nested under a bold subtotal can be collapsed using the outline (+/-) controls to the left of the row numbers.

Sheet Cash Flow Statement
B2: Cash Flow Statement - Bullish (BLSH) Standalone, IFRS Basis
B3: Quarterly figures as reported in the Condensed Consolidated Statements of Cash Flows in each Form 6-K / earnings release. Direct 3-month actuals are available for 2Q24, 3Q24, 1Q25, 2Q25, 3Q25 and 1Q26 (both the quarter itself and its prior-year comparative were disclosed in the sourced releases). 1Q24, 4Q24 and 4Q25 were not disclosed as standalone 3-month figures in any of the sourced documents and are left blank rather than estimated - pull from the 20-F (FY2025 annual report) or the relevant Form 6-K if needed. Because of the missing 4Q24 and 4Q25 quarters, FY2024A and FY2025A annual sums below are partial (understated) - see Sources. No pro forma / Equiniti effects included.
J5: =YEAR(J6) -> 2024 | K5: =YEAR(K6) -> 2024 | L5: =YEAR(L6) -> 2024 | M5: =YEAR(M6) -> 2024 | N5: =YEAR(N6) -> 2025 | O5: =YEAR(O6) -> 2025 | P5: =YEAR(P6) -> 2025 | Q5: =YEAR(Q6) -> 2025 | ... V5: =YEAR(V6) -> 2027
J6: 45354 | K6: =EOMONTH(J6,3) -> 45473 | L6: =EOMONTH(K6,3) -> 45565 | M6: =EOMONTH(L6,3) -> 45657 | N6: =EOMONTH(M6,3) -> 45747 | O6: =EOMONTH(N6,3) -> 45838 | P6: =EOMONTH(O6,3) -> 45930 | Q6: =EOMONTH(P6,3) -> 46022 | R6: =EOMONTH(Q6,3) -> 46112 | ... V6: =EOMONTH(U6,3) -> 46477
B7: QUARTERLY + ANNUAL CASH FLOW STATEMENT
B8: ($000s unless noted) | C8: 2024 | D8: 2025 | E8: =D8+1 -> 2026 | F8: =E8+1 -> 2027 | G8: =F8+1 -> 2028 | H8: =G8+1 -> 2029 | J8: ="Q" & INT((MONTH(J6)-1)/3)+1 & " " & YEAR(J6) -> Q1 2024 | K8: ="Q" & INT((MONTH(K6)-1)/3)+1 & " " & YEAR(K6) -> Q2 2024 | L8: ="Q" & INT((MONTH(L6)-1)/3)+1 & " " & YEAR(L6) -> Q3 2024 | M8: ="Q" & INT((MONTH(M6)-1)/3)+1 & " " & YEAR(M6) -> Q4 2024 | N8: ="Q" & INT((MONTH(N6)-1)/3)+1 & " " & YEAR(N6) -> Q1 2025 | O8: ="Q" & INT((MONTH(O6)-1)/3)+1 & " " & YEAR(O6) -> Q2 2025 | P8: ="Q" & INT((MONTH(P6)-1)/3)+1 & " " & YEAR(P6) -> Q3 2025 | Q8: ="Q" & INT((MONTH(Q6)-1)/3)+1 & " " & YEAR(Q6) -> Q4 2025 | ... V8: ="Q" & INT((MONTH(V6)-1)/3)+1 & " " & YEAR(V6) -> Q1 2027
B9: OPERATING ACTIVITIES
B10: Net income/(loss) (IFRS) | C10: =SUMIFS($J10:$V10,$J$5:$V$5,C$8) -> -183666 | D10: =SUMIFS($J10:$V10,$J$5:$V$5,D$8) -> -221903 | E10: =SUMIFS($J10:$V10,$J$5:$V$5,E$8) -> -604862 | F10: =SUMIFS($J10:$V10,$J$5:$V$5,F$8) -> 0 | G10: =SUMIFS($J10:$V10,$J$5:$V$5,G$8) -> 0 | H10: =SUMIFS($J10:$V10,$J$5:$V$5,H$8) -> 0 | J10: -116394 | L10: -67272 | N10: -348622 | O10: 108268 | P10: 18451 | R10: -604862
B11: Adjustments for:
B12: Interest income | C12: =SUMIFS($J12:$V12,$J$5:$V$5,C$8) -> -4038 | D12: =SUMIFS($J12:$V12,$J$5:$V$5,D$8) -> -10329 | E12: =SUMIFS($J12:$V12,$J$5:$V$5,E$8) -> -5686 | F12: =SUMIFS($J12:$V12,$J$5:$V$5,F$8) -> 0 | G12: =SUMIFS($J12:$V12,$J$5:$V$5,G$8) -> 0 | H12: =SUMIFS($J12:$V12,$J$5:$V$5,H$8) -> 0 | J12: -1958 | L12: -2080 | N12: -2632 | O12: -3394 | P12: -4303 | R12: -5686
B13: Debt / loan interest expense | C13: =SUMIFS($J13:$V13,$J$5:$V$5,C$8) -> 18314 | D13: =SUMIFS($J13:$V13,$J$5:$V$5,D$8) -> 36654 | E13: =SUMIFS($J13:$V13,$J$5:$V$5,E$8) -> 13777 | F13: =SUMIFS($J13:$V13,$J$5:$V$5,F$8) -> 0 | G13: =SUMIFS($J13:$V13,$J$5:$V$5,G$8) -> 0 | H13: =SUMIFS($J13:$V13,$J$5:$V$5,H$8) -> 0 | J13: 8715 | L13: 9599 | N13: 9987 | O13: 13013 | P13: 13654 | R13: 13777
B14: Lease interest expense | C14: =SUMIFS($J14:$V14,$J$5:$V$5,C$8) -> 627 | D14: =SUMIFS($J14:$V14,$J$5:$V$5,D$8) -> 783 | E14: =SUMIFS($J14:$V14,$J$5:$V$5,E$8) -> 311 | F14: =SUMIFS($J14:$V14,$J$5:$V$5,F$8) -> 0 | G14: =SUMIFS($J14:$V14,$J$5:$V$5,G$8) -> 0 | H14: =SUMIFS($J14:$V14,$J$5:$V$5,H$8) -> 0 | J14: 348 | L14: 279 | N14: 253 | O14: 278 | P14: 252 | R14: 311
B15: Net foreign exchange (gain)/loss | C15: =SUMIFS($J15:$V15,$J$5:$V$5,C$8) -> 58 | D15: =SUMIFS($J15:$V15,$J$5:$V$5,D$8) -> 0 | E15: =SUMIFS($J15:$V15,$J$5:$V$5,E$8) -> 0 | F15: =SUMIFS($J15:$V15,$J$5:$V$5,F$8) -> 0 | G15: =SUMIFS($J15:$V15,$J$5:$V$5,G$8) -> 0 | H15: =SUMIFS($J15:$V15,$J$5:$V$5,H$8) -> 0 | J15: 29 | L15: 29 | N15: -262 | O15: 218 | P15: 44 | R15: 0
B16: Share-based payments expense | C16: =SUMIFS($J16:$V16,$J$5:$V$5,C$8) -> 14598 | D16: =SUMIFS($J16:$V16,$J$5:$V$5,D$8) -> 11519 | E16: =SUMIFS($J16:$V16,$J$5:$V$5,E$8) -> 5603 | F16: =SUMIFS($J16:$V16,$J$5:$V$5,F$8) -> 0 | G16: =SUMIFS($J16:$V16,$J$5:$V$5,G$8) -> 0 | H16: =SUMIFS($J16:$V16,$J$5:$V$5,H$8) -> 0 | J16: 8900 | L16: 5698 | N16: 5133 | O16: 3256 | P16: 3130 | R16: 5603
B17: Depreciation of property and equipment and right-of-use assets | C17: =SUMIFS($J17:$V17,$J$5:$V$5,C$8) -> 3254 | D17: =SUMIFS($J17:$V17,$J$5:$V$5,D$8) -> 4431 | E17: =SUMIFS($J17:$V17,$J$5:$V$5,E$8) -> 1670 | F17: =SUMIFS($J17:$V17,$J$5:$V$5,F$8) -> 0 | G17: =SUMIFS($J17:$V17,$J$5:$V$5,G$8) -> 0 | H17: =SUMIFS($J17:$V17,$J$5:$V$5,H$8) -> 0 | J17: 1752 | L17: 1502 | N17: 1498 | O17: 1632 | P17: 1301 | R17: 1670
B18: Amortization of other intangible assets | C18: =SUMIFS($J18:$V18,$J$5:$V$5,C$8) -> 1084 | D18: =SUMIFS($J18:$V18,$J$5:$V$5,D$8) -> 1687 | E18: =SUMIFS($J18:$V18,$J$5:$V$5,E$8) -> 557 | F18: =SUMIFS($J18:$V18,$J$5:$V$5,F$8) -> 0 | G18: =SUMIFS($J18:$V18,$J$5:$V$5,G$8) -> 0 | H18: =SUMIFS($J18:$V18,$J$5:$V$5,H$8) -> 0 | J18: 542 | L18: 542 | N18: 616 | O18: 557 | P18: 514 | R18: 557
B19: Impairment of right-of-use asset | C19: =SUMIFS($J19:$V19,$J$5:$V$5,C$8) -> 956 | D19: =SUMIFS($J19:$V19,$J$5:$V$5,D$8) -> 0 | E19: =SUMIFS($J19:$V19,$J$5:$V$5,E$8) -> 591 | F19: =SUMIFS($J19:$V19,$J$5:$V$5,F$8) -> 0 | G19: =SUMIFS($J19:$V19,$J$5:$V$5,G$8) -> 0 | H19: =SUMIFS($J19:$V19,$J$5:$V$5,H$8) -> 0 | J19: 956 | L19: 0 | N19: 0 | O19: 0 | P19: 0 | R19: 591
B20: (Gain)/loss from revaluation of digital assets and investments in financial assets at FVTPL, net | C20: =SUMIFS($J20:$V20,$J$5:$V$5,C$8) -> 112545 | D20: =SUMIFS($J20:$V20,$J$5:$V$5,D$8) -> -50050 | E20: =SUMIFS($J20:$V20,$J$5:$V$5,E$8) -> 226419 | F20: =SUMIFS($J20:$V20,$J$5:$V$5,F$8) -> 0 | G20: =SUMIFS($J20:$V20,$J$5:$V$5,G$8) -> 0 | H20: =SUMIFS($J20:$V20,$J$5:$V$5,H$8) -> 0 | J20: 95445 | L20: 17100 | N20: 176484 | O20: -159120 | P20: -67414 | R20: 226419
B21: Derecognition of lease | C21: =SUMIFS($J21:$V21,$J$5:$V$5,C$8) -> 0 | D21: =SUMIFS($J21:$V21,$J$5:$V$5,D$8) -> -416 | E21: =SUMIFS($J21:$V21,$J$5:$V$5,E$8) -> 0 | F21: =SUMIFS($J21:$V21,$J$5:$V$5,F$8) -> 0 | G21: =SUMIFS($J21:$V21,$J$5:$V$5,G$8) -> 0 | H21: =SUMIFS($J21:$V21,$J$5:$V$5,H$8) -> 0 | P21: -416
B22: Change in fair value of financial liability at FVTPL | C22: =SUMIFS($J22:$V22,$J$5:$V$5,C$8) -> -6200 | D22: =SUMIFS($J22:$V22,$J$5:$V$5,D$8) -> 27000 | E22: =SUMIFS($J22:$V22,$J$5:$V$5,E$8) -> -8482 | F22: =SUMIFS($J22:$V22,$J$5:$V$5,F$8) -> 0 | G22: =SUMIFS($J22:$V22,$J$5:$V$5,G$8) -> 0 | H22: =SUMIFS($J22:$V22,$J$5:$V$5,H$8) -> 0 | J22: -6100 | L22: -100 | N22: 900 | O22: 15250 | P22: 10850 | R22: -8482
B23: Impairment losses of digital assets | C23: =SUMIFS($J23:$V23,$J$5:$V$5,C$8) -> 25677 | D23: =SUMIFS($J23:$V23,$J$5:$V$5,D$8) -> 178234 | E23: =SUMIFS($J23:$V23,$J$5:$V$5,E$8) -> 359209 | F23: =SUMIFS($J23:$V23,$J$5:$V$5,F$8) -> 0 | G23: =SUMIFS($J23:$V23,$J$5:$V$5,G$8) -> 0 | H23: =SUMIFS($J23:$V23,$J$5:$V$5,H$8) -> 0 | J23: 4490 | L23: 21187 | N23: 142088 | O23: 6731 | P23: 29415 | R23: 359209
B24: Operating cash flows before changes in operating assets and liabilities | C24: =SUMIFS($J24:$V24,$J$5:$V$5,C$8) -> -16791 | D24: =SUMIFS($J24:$V24,$J$5:$V$5,D$8) -> -22390 | E24: =SUMIFS($J24:$V24,$J$5:$V$5,E$8) -> -10893 | F24: =SUMIFS($J24:$V24,$J$5:$V$5,F$8) -> 0 | G24: =SUMIFS($J24:$V24,$J$5:$V$5,G$8) -> 0 | H24: =SUMIFS($J24:$V24,$J$5:$V$5,H$8) -> 0 | J24: =J10+J12+J13+J14+J15+J16+J17+J18+J19+J20+J21+J22+J23 -> -3275 | K24: =K10+K12+K13+K14+K15+K16+K17+K18+K19+K20+K21+K22+K23 -> 0 | L24: =L10+L12+L13+L14+L15+L16+L17+L18+L19+L20+L21+L22+L23 -> -13516 | M24: =M10+M12+M13+M14+M15+M16+M17+M18+M19+M20+M21+M22+M23 -> 0 | N24: =N10+N12+N13+N14+N15+N16+N17+N18+N19+N20+N21+N22+N23 -> -14557 | O24: =O10+O12+O13+O14+O15+O16+O17+O18+O19+O20+O21+O22+O23 -> -13311 | P24: =P10+P12+P13+P14+P15+P16+P17+P18+P19+P20+P21+P22+P23 -> 5478 | Q24: =Q10+Q12+Q13+Q14+Q15+Q16+Q17+Q18+Q19+Q20+Q21+Q22+Q23 -> 0 | ... V24: =V10+V12+V13+V14+V15+V16+V17+V18+V19+V20+V21+V22+V23 -> 0
B25: Changes in operating assets and liabilities:
B26: (Increase)/decrease in other assets | C26: =SUMIFS($J26:$V26,$J$5:$V$5,C$8) -> 1297 | D26: =SUMIFS($J26:$V26,$J$5:$V$5,D$8) -> -15147 | E26: =SUMIFS($J26:$V26,$J$5:$V$5,E$8) -> -21737 | F26: =SUMIFS($J26:$V26,$J$5:$V$5,F$8) -> 0 | G26: =SUMIFS($J26:$V26,$J$5:$V$5,G$8) -> 0 | H26: =SUMIFS($J26:$V26,$J$5:$V$5,H$8) -> 0 | K26: 2007 | L26: -710 | N26: 1184 | O26: 1835 | P26: -18166 | R26: -21737
B27: Increase in deferred tax assets | C27: =SUMIFS($J27:$V27,$J$5:$V$5,C$8) -> -1502 | D27: =SUMIFS($J27:$V27,$J$5:$V$5,D$8) -> -806 | E27: =SUMIFS($J27:$V27,$J$5:$V$5,E$8) -> -130 | F27: =SUMIFS($J27:$V27,$J$5:$V$5,F$8) -> 0 | G27: =SUMIFS($J27:$V27,$J$5:$V$5,G$8) -> 0 | H27: =SUMIFS($J27:$V27,$J$5:$V$5,H$8) -> 0 | K27: -1129 | L27: -373 | N27: -268 | O27: -163 | P27: -375 | R27: -130
B28: (Increase)/decrease in digital assets held - inventories | C28: =SUMIFS($J28:$V28,$J$5:$V$5,C$8) -> -5037 | D28: =SUMIFS($J28:$V28,$J$5:$V$5,D$8) -> 261774 | E28: =SUMIFS($J28:$V28,$J$5:$V$5,E$8) -> 6005 | F28: =SUMIFS($J28:$V28,$J$5:$V$5,F$8) -> 0 | G28: =SUMIFS($J28:$V28,$J$5:$V$5,G$8) -> 0 | H28: =SUMIFS($J28:$V28,$J$5:$V$5,H$8) -> 0 | K28: -31825 | L28: 26788 | N28: 282844 | O28: -9464 | P28: -11606 | R28: 6005
B29: (Increase)/decrease in digital assets held - financial assets | C29: =SUMIFS($J29:$V29,$J$5:$V$5,C$8) -> -17503 | D29: =SUMIFS($J29:$V29,$J$5:$V$5,D$8) -> -2645719 | E29: =SUMIFS($J29:$V29,$J$5:$V$5,E$8) -> -307298 | F29: =SUMIFS($J29:$V29,$J$5:$V$5,F$8) -> 0 | G29: =SUMIFS($J29:$V29,$J$5:$V$5,G$8) -> 0 | H29: =SUMIFS($J29:$V29,$J$5:$V$5,H$8) -> 0 | K29: 13104 | L29: -30607 | N29: -264599 | O29: -560705 | P29: -1820415 | R29: -307298
B30: (Increase)/decrease in loan and other receivables - digital assets | C30: =SUMIFS($J30:$V30,$J$5:$V$5,C$8) -> 28746 | D30: =SUMIFS($J30:$V30,$J$5:$V$5,D$8) -> 2375485 | E30: =SUMIFS($J30:$V30,$J$5:$V$5,E$8) -> 391604 | F30: =SUMIFS($J30:$V30,$J$5:$V$5,F$8) -> 0 | G30: =SUMIFS($J30:$V30,$J$5:$V$5,G$8) -> 0 | H30: =SUMIFS($J30:$V30,$J$5:$V$5,H$8) -> 0 | K30: 33157 | L30: -4411 | N30: -3123 | O30: 596379 | P30: 1782229 | R30: 391604
B31: Increase/(decrease) in other payables | C31: =SUMIFS($J31:$V31,$J$5:$V$5,C$8) -> 3494 | D31: =SUMIFS($J31:$V31,$J$5:$V$5,D$8) -> -1807 | E31: =SUMIFS($J31:$V31,$J$5:$V$5,E$8) -> -4292 | F31: =SUMIFS($J31:$V31,$J$5:$V$5,F$8) -> 0 | G31: =SUMIFS($J31:$V31,$J$5:$V$5,G$8) -> 0 | H31: =SUMIFS($J31:$V31,$J$5:$V$5,H$8) -> 0 | K31: -6046 | L31: 9540 | N31: -7438 | O31: 2165 | P31: 3466 | R31: -4292
B32: Increase/(decrease) in customer segregated cash liabilities | C32: =SUMIFS($J32:$V32,$J$5:$V$5,C$8) -> 6961 | D32: =SUMIFS($J32:$V32,$J$5:$V$5,D$8) -> 8168 | E32: =SUMIFS($J32:$V32,$J$5:$V$5,E$8) -> 35596 | F32: =SUMIFS($J32:$V32,$J$5:$V$5,F$8) -> 0 | G32: =SUMIFS($J32:$V32,$J$5:$V$5,G$8) -> 0 | H32: =SUMIFS($J32:$V32,$J$5:$V$5,H$8) -> 0 | K32: 5525 | L32: 1436 | N32: 216 | O32: -2460 | P32: 10412 | R32: 35596
B33: Increase/(decrease) in deferred tax liabilities | C33: =SUMIFS($J33:$V33,$J$5:$V$5,C$8) -> -16 | D33: =SUMIFS($J33:$V33,$J$5:$V$5,D$8) -> -6 | E33: =SUMIFS($J33:$V33,$J$5:$V$5,E$8) -> 1 | F33: =SUMIFS($J33:$V33,$J$5:$V$5,F$8) -> 0 | G33: =SUMIFS($J33:$V33,$J$5:$V$5,G$8) -> 0 | H33: =SUMIFS($J33:$V33,$J$5:$V$5,H$8) -> 0 | K33: -14 | L33: -2 | N33: 10 | O33: -4 | P33: -12 | R33: 1
B34: Interest received | C34: =SUMIFS($J34:$V34,$J$5:$V$5,C$8) -> 4038 | D34: =SUMIFS($J34:$V34,$J$5:$V$5,D$8) -> 7251 | E34: =SUMIFS($J34:$V34,$J$5:$V$5,E$8) -> 2067 | F34: =SUMIFS($J34:$V34,$J$5:$V$5,F$8) -> 0 | G34: =SUMIFS($J34:$V34,$J$5:$V$5,G$8) -> 0 | H34: =SUMIFS($J34:$V34,$J$5:$V$5,H$8) -> 0 | K34: 1958 | L34: 2080 | N34: 2152 | O34: 2733 | P34: 2366 | R34: 2067
B35: Net cash provided by/(used in) operating activities | C35: =SUMIFS($J35:$V35,$J$5:$V$5,C$8) -> 3687 | D35: =SUMIFS($J35:$V35,$J$5:$V$5,D$8) -> -33197 | E35: =SUMIFS($J35:$V35,$J$5:$V$5,E$8) -> 90923 | F35: =SUMIFS($J35:$V35,$J$5:$V$5,F$8) -> 0 | G35: =SUMIFS($J35:$V35,$J$5:$V$5,G$8) -> 0 | H35: =SUMIFS($J35:$V35,$J$5:$V$5,H$8) -> 0 | J35: =J24+J26+J27+J28+J29+J30+J31+J32+J33+J34 -> -3275 | K35: =K24+K26+K27+K28+K29+K30+K31+K32+K33+K34 -> 16737 | L35: =L24+L26+L27+L28+L29+L30+L31+L32+L33+L34 -> -9775 | M35: =M24+M26+M27+M28+M29+M30+M31+M32+M33+M34 -> 0 | N35: =N24+N26+N27+N28+N29+N30+N31+N32+N33+N34 -> -3579 | O35: =O24+O26+O27+O28+O29+O30+O31+O32+O33+O34 -> 17005 | P35: =P24+P26+P27+P28+P29+P30+P31+P32+P33+P34 -> -46623 | Q35: =Q24+Q26+Q27+Q28+Q29+Q30+Q31+Q32+Q33+Q34 -> 0 | ... V35: =V24+V26+V27+V28+V29+V30+V31+V32+V33+V34 -> 0
B37: INVESTING ACTIVITIES
B38: Purchase of investment in financial assets | C38: =SUMIFS($J38:$V38,$J$5:$V$5,C$8) -> 0 | D38: =SUMIFS($J38:$V38,$J$5:$V$5,D$8) -> -4620 | E38: =SUMIFS($J38:$V38,$J$5:$V$5,E$8) -> -6449 | F38: =SUMIFS($J38:$V38,$J$5:$V$5,F$8) -> 0 | G38: =SUMIFS($J38:$V38,$J$5:$V$5,G$8) -> 0 | H38: =SUMIFS($J38:$V38,$J$5:$V$5,H$8) -> 0 | N38: -1275 | O38: 0 | P38: -3345 | R38: -6449
B39: Proceeds on investment in financial assets | C39: =SUMIFS($J39:$V39,$J$5:$V$5,C$8) -> 6 | D39: =SUMIFS($J39:$V39,$J$5:$V$5,D$8) -> 48213 | E39: =SUMIFS($J39:$V39,$J$5:$V$5,E$8) -> 0 | F39: =SUMIFS($J39:$V39,$J$5:$V$5,F$8) -> 0 | G39: =SUMIFS($J39:$V39,$J$5:$V$5,G$8) -> 0 | H39: =SUMIFS($J39:$V39,$J$5:$V$5,H$8) -> 0 | L39: 6 | N39: 0 | O39: 0 | P39: 48213 | R39: 0
B40: Purchase of investment in derivative financial instruments | C40: =SUMIFS($J40:$V40,$J$5:$V$5,C$8) -> 1654 | D40: =SUMIFS($J40:$V40,$J$5:$V$5,D$8) -> 0 | E40: =SUMIFS($J40:$V40,$J$5:$V$5,E$8) -> 0 | F40: =SUMIFS($J40:$V40,$J$5:$V$5,F$8) -> 0 | G40: =SUMIFS($J40:$V40,$J$5:$V$5,G$8) -> 0 | H40: =SUMIFS($J40:$V40,$J$5:$V$5,H$8) -> 0 | K40: 192 | L40: 1462 | N40: 0 | O40: 0 | P40: 0 | R40: 0
B41: Purchase of property and equipment | C41: =SUMIFS($J41:$V41,$J$5:$V$5,C$8) -> -134 | D41: =SUMIFS($J41:$V41,$J$5:$V$5,D$8) -> -2344 | E41: =SUMIFS($J41:$V41,$J$5:$V$5,E$8) -> -412 | F41: =SUMIFS($J41:$V41,$J$5:$V$5,F$8) -> 0 | G41: =SUMIFS($J41:$V41,$J$5:$V$5,G$8) -> 0 | H41: =SUMIFS($J41:$V41,$J$5:$V$5,H$8) -> 0 | K41: -42 | L41: -92 | N41: -196 | O41: -54 | P41: -2094 | R41: -412
B42: Proceeds on disposal of property and equipment | C42: =SUMIFS($J42:$V42,$J$5:$V$5,C$8) -> 0 | D42: =SUMIFS($J42:$V42,$J$5:$V$5,D$8) -> 0 | E42: =SUMIFS($J42:$V42,$J$5:$V$5,E$8) -> 20 | F42: =SUMIFS($J42:$V42,$J$5:$V$5,F$8) -> 0 | G42: =SUMIFS($J42:$V42,$J$5:$V$5,G$8) -> 0 | H42: =SUMIFS($J42:$V42,$J$5:$V$5,H$8) -> 0 | N42: 0 | R42: 20
B43: Purchase of digital assets held - intangible assets | C43: =SUMIFS($J43:$V43,$J$5:$V$5,C$8) -> -80 | D43: =SUMIFS($J43:$V43,$J$5:$V$5,D$8) -> -41666 | E43: =SUMIFS($J43:$V43,$J$5:$V$5,E$8) -> -907 | F43: =SUMIFS($J43:$V43,$J$5:$V$5,F$8) -> 0 | G43: =SUMIFS($J43:$V43,$J$5:$V$5,G$8) -> 0 | H43: =SUMIFS($J43:$V43,$J$5:$V$5,H$8) -> 0 | K43: 0 | L43: -80 | N43: -41491 | O43: -173 | P43: -2 | R43: -907
B44: Proceeds on disposal of digital assets held - intangible assets | C44: =SUMIFS($J44:$V44,$J$5:$V$5,C$8) -> 0 | D44: =SUMIFS($J44:$V44,$J$5:$V$5,D$8) -> 30549 | E44: =SUMIFS($J44:$V44,$J$5:$V$5,E$8) -> 4345 | F44: =SUMIFS($J44:$V44,$J$5:$V$5,F$8) -> 0 | G44: =SUMIFS($J44:$V44,$J$5:$V$5,G$8) -> 0 | H44: =SUMIFS($J44:$V44,$J$5:$V$5,H$8) -> 0 | K44: 0 | L44: 0 | N44: 30448 | O44: 0 | P44: 101 | R44: 4345
B45: Prepayment on intangible assets | C45: =SUMIFS($J45:$V45,$J$5:$V$5,C$8) -> -10001 | D45: =SUMIFS($J45:$V45,$J$5:$V$5,D$8) -> 0 | E45: =SUMIFS($J45:$V45,$J$5:$V$5,E$8) -> 0 | F45: =SUMIFS($J45:$V45,$J$5:$V$5,F$8) -> 0 | G45: =SUMIFS($J45:$V45,$J$5:$V$5,G$8) -> 0 | H45: =SUMIFS($J45:$V45,$J$5:$V$5,H$8) -> 0 | K45: -10001 | L45: 0 | N45: 0 | O45: 0 | P45: 0 | R45: 0
B46: Net cash provided by/(used in) investing activities | C46: =SUMIFS($J46:$V46,$J$5:$V$5,C$8) -> -8555 | D46: =SUMIFS($J46:$V46,$J$5:$V$5,D$8) -> 30132 | E46: =SUMIFS($J46:$V46,$J$5:$V$5,E$8) -> -3403 | F46: =SUMIFS($J46:$V46,$J$5:$V$5,F$8) -> 0 | G46: =SUMIFS($J46:$V46,$J$5:$V$5,G$8) -> 0 | H46: =SUMIFS($J46:$V46,$J$5:$V$5,H$8) -> 0 | J46: =J38+J39+J40+J41+J42+J43+J44+J45 -> 0 | K46: =K38+K39+K40+K41+K42+K43+K44+K45 -> -9851 | L46: =L38+L39+L40+L41+L42+L43+L44+L45 -> 1296 | M46: =M38+M39+M40+M41+M42+M43+M44+M45 -> 0 | N46: =N38+N39+N40+N41+N42+N43+N44+N45 -> -12514 | O46: =O38+O39+O40+O41+O42+O43+O44+O45 -> -227 | P46: =P38+P39+P40+P41+P42+P43+P44+P45 -> 42873 | Q46: =Q38+Q39+Q40+Q41+Q42+Q43+Q44+Q45 -> 0 | ... V46: =V38+V39+V40+V41+V42+V43+V44+V45 -> 0
B48: FINANCING ACTIVITIES
B49: Proceeds from issuance of ordinary shares | C49: =SUMIFS($J49:$V49,$J$5:$V$5,C$8) -> 0 | D49: =SUMIFS($J49:$V49,$J$5:$V$5,D$8) -> 59194 | E49: =SUMIFS($J49:$V49,$J$5:$V$5,E$8) -> 1349 | F49: =SUMIFS($J49:$V49,$J$5:$V$5,F$8) -> 0 | G49: =SUMIFS($J49:$V49,$J$5:$V$5,G$8) -> 0 | H49: =SUMIFS($J49:$V49,$J$5:$V$5,H$8) -> 0 | K49: 0 | L49: 0 | N49: 0 | O49: 0 | P49: 59194 | R49: 1349
B50: Interest paid | C50: =SUMIFS($J50:$V50,$J$5:$V$5,C$8) -> -18941 | D50: =SUMIFS($J50:$V50,$J$5:$V$5,D$8) -> -30554 | E50: =SUMIFS($J50:$V50,$J$5:$V$5,E$8) -> -13777 | F50: =SUMIFS($J50:$V50,$J$5:$V$5,F$8) -> 0 | G50: =SUMIFS($J50:$V50,$J$5:$V$5,G$8) -> 0 | H50: =SUMIFS($J50:$V50,$J$5:$V$5,H$8) -> 0 | K50: -9063 | L50: -9878 | N50: -10240 | O50: -10399 | P50: -9915 | R50: -13777
B51: Proceeds from borrowings | C51: =SUMIFS($J51:$V51,$J$5:$V$5,C$8) -> 25000 | D51: =SUMIFS($J51:$V51,$J$5:$V$5,D$8) -> 174300 | E51: =SUMIFS($J51:$V51,$J$5:$V$5,E$8) -> 0 | F51: =SUMIFS($J51:$V51,$J$5:$V$5,F$8) -> 0 | G51: =SUMIFS($J51:$V51,$J$5:$V$5,G$8) -> 0 | H51: =SUMIFS($J51:$V51,$J$5:$V$5,H$8) -> 0 | K51: 25000 | L51: 0 | N51: 74300 | O51: 100000 | P51: 0 | R51: 0
B52: Repayment of borrowings | C52: =SUMIFS($J52:$V52,$J$5:$V$5,C$8) -> 0 | D52: =SUMIFS($J52:$V52,$J$5:$V$5,D$8) -> -149300 | E52: =SUMIFS($J52:$V52,$J$5:$V$5,E$8) -> -50000 | F52: =SUMIFS($J52:$V52,$J$5:$V$5,F$8) -> 0 | G52: =SUMIFS($J52:$V52,$J$5:$V$5,G$8) -> 0 | H52: =SUMIFS($J52:$V52,$J$5:$V$5,H$8) -> 0 | K52: 0 | L52: 0 | N52: -49300 | O52: -100000 | P52: 0 | R52: -50000
B53: Repayment on lease liabilities | C53: =SUMIFS($J53:$V53,$J$5:$V$5,C$8) -> -2639 | D53: =SUMIFS($J53:$V53,$J$5:$V$5,D$8) -> -4064 | E53: =SUMIFS($J53:$V53,$J$5:$V$5,E$8) -> -1126 | F53: =SUMIFS($J53:$V53,$J$5:$V$5,F$8) -> 0 | G53: =SUMIFS($J53:$V53,$J$5:$V$5,G$8) -> 0 | H53: =SUMIFS($J53:$V53,$J$5:$V$5,H$8) -> 0 | K53: -1181 | L53: -1458 | N53: -1331 | O53: -1532 | P53: -1201 | R53: -1126
B54: Net cash provided by/(used in) financing activities | C54: =SUMIFS($J54:$V54,$J$5:$V$5,C$8) -> 3420 | D54: =SUMIFS($J54:$V54,$J$5:$V$5,D$8) -> 49576 | E54: =SUMIFS($J54:$V54,$J$5:$V$5,E$8) -> -63554 | F54: =SUMIFS($J54:$V54,$J$5:$V$5,F$8) -> 0 | G54: =SUMIFS($J54:$V54,$J$5:$V$5,G$8) -> 0 | H54: =SUMIFS($J54:$V54,$J$5:$V$5,H$8) -> 0 | J54: =J49+J50+J51+J52+J53 -> 0 | K54: =K49+K50+K51+K52+K53 -> 14756 | L54: =L49+L50+L51+L52+L53 -> -11336 | M54: =M49+M50+M51+M52+M53 -> 0 | N54: =N49+N50+N51+N52+N53 -> 13429 | O54: =O49+O50+O51+O52+O53 -> -11931 | P54: =P49+P50+P51+P52+P53 -> 48078 | Q54: =Q49+Q50+Q51+Q52+Q53 -> 0 | ... V54: =V49+V50+V51+V52+V53 -> 0
B56: Net increase/(decrease) in cash, customer segregated cash and restricted cash | C56: =SUMIFS($J56:$V56,$J$5:$V$5,C$8) -> -1448 | D56: =SUMIFS($J56:$V56,$J$5:$V$5,D$8) -> 46511 | E56: =SUMIFS($J56:$V56,$J$5:$V$5,E$8) -> 23966 | F56: =SUMIFS($J56:$V56,$J$5:$V$5,F$8) -> 0 | G56: =SUMIFS($J56:$V56,$J$5:$V$5,G$8) -> 0 | H56: =SUMIFS($J56:$V56,$J$5:$V$5,H$8) -> 0 | J56: =J35+J46+J54 -> -3275 | K56: =K35+K46+K54 -> 21642 | L56: =L35+L46+L54 -> -19815 | M56: =M35+M46+M54 -> 0 | N56: =N35+N46+N54 -> -2664 | O56: =O35+O46+O54 -> 4847 | P56: =P35+P46+P54 -> 44328 | Q56: =Q35+Q46+Q54 -> 0 | ... V56: =V35+V46+V54 -> 0
B57: Cash, customer segregated cash and restricted cash - beginning of period | C57: =SUMIFS($J57:$V57,$J$5:$V$5,C$8) -> 133125 | D57: =SUMIFS($J57:$V57,$J$5:$V$5,D$8) -> 166530 | E57: =SUMIFS($J57:$V57,$J$5:$V$5,E$8) -> 130502 | F57: =SUMIFS($J57:$V57,$J$5:$V$5,F$8) -> 0 | G57: =SUMIFS($J57:$V57,$J$5:$V$5,G$8) -> 0 | H57: =SUMIFS($J57:$V57,$J$5:$V$5,H$8) -> 0 | K57: 57379 | L57: 75746 | N57: 55783 | O57: 52888 | P57: 57859 | R57: 130502
B58: Effects of exchange rate changes | C58: =SUMIFS($J58:$V58,$J$5:$V$5,C$8) -> 0 | D58: =SUMIFS($J58:$V58,$J$5:$V$5,D$8) -> 208 | E58: =SUMIFS($J58:$V58,$J$5:$V$5,E$8) -> 67 | F58: =SUMIFS($J58:$V58,$J$5:$V$5,F$8) -> 0 | G58: =SUMIFS($J58:$V58,$J$5:$V$5,G$8) -> 0 | H58: =SUMIFS($J58:$V58,$J$5:$V$5,H$8) -> 0 | K58: 0 | L58: 0 | N58: -231 | O58: 124 | P58: 315 | R58: 67
B59: Cash, customer segregated cash and restricted cash - end of period | C59: =SUMIFS($J59:$V59,$J$5:$V$5,C$8) -> 131677 | D59: =SUMIFS($J59:$V59,$J$5:$V$5,D$8) -> 213249 | E59: =SUMIFS($J59:$V59,$J$5:$V$5,E$8) -> 154535 | F59: =SUMIFS($J59:$V59,$J$5:$V$5,F$8) -> 0 | G59: =SUMIFS($J59:$V59,$J$5:$V$5,G$8) -> 0 | H59: =SUMIFS($J59:$V59,$J$5:$V$5,H$8) -> 0 | J59: =J56+J57+J58 -> -3275 | K59: =K56+K57+K58 -> 79021 | L59: =L56+L57+L58 -> 55931 | M59: =M56+M57+M58 -> 0 | N59: =N56+N57+N58 -> 52888 | O59: =O56+O57+O58 -> 57859 | P59: =P56+P57+P58 -> 102502 | Q59: =Q56+Q57+Q58 -> 0 | ... V59: =V56+V57+V58 -> 0
B61: FREE CASH FLOW BRIDGE
B62: Net cash provided by/(used in) operating activities | C62: =C35 -> 3687 | D62: =D35 -> -33197 | E62: =E35 -> 90923 | F62: =F35 -> 0 | G62: =G35 -> 0 | H62: =H35 -> 0 | J62: =J35 -> -3275 | K62: =K35 -> 16737 | L62: =L35 -> -9775 | M62: =M35 -> 0 | N62: =N35 -> -3579 | O62: =O35 -> 17005 | P62: =P35 -> -46623 | Q62: =Q35 -> 0 | ... V62: =V35 -> 0
B63: Less: Capital expenditures (purchase of property & equipment) | C63: =SUMIFS($J63:$V63,$J$5:$V$5,C$8) -> -134 | D63: =SUMIFS($J63:$V63,$J$5:$V$5,D$8) -> -2344 | E63: =SUMIFS($J63:$V63,$J$5:$V$5,E$8) -> -412 | F63: =SUMIFS($J63:$V63,$J$5:$V$5,F$8) -> 0 | G63: =SUMIFS($J63:$V63,$J$5:$V$5,G$8) -> 0 | H63: =SUMIFS($J63:$V63,$J$5:$V$5,H$8) -> 0 | K63: -42 | L63: -92 | N63: -196 | O63: -54 | P63: -2094 | R63: -412
B64: Free cash flow | C64: =SUMIFS($J64:$V64,$J$5:$V$5,C$8) -> 3553 | D64: =SUMIFS($J64:$V64,$J$5:$V$5,D$8) -> -35541 | E64: =SUMIFS($J64:$V64,$J$5:$V$5,E$8) -> 90511 | F64: =SUMIFS($J64:$V64,$J$5:$V$5,F$8) -> 0 | G64: =SUMIFS($J64:$V64,$J$5:$V$5,G$8) -> 0 | H64: =SUMIFS($J64:$V64,$J$5:$V$5,H$8) -> 0 | J64: =J35+J63 -> -3275 | K64: =K35+K63 -> 16695 | L64: =L35+L63 -> -9867 | M64: =M35+M63 -> 0 | N64: =N35+N63 -> -3775 | O64: =O35+O63 -> 16951 | P64: =P35+P63 -> -48717 | Q64: =Q35+Q63 -> 0 | ... V64: =V35+V63 -> 0
B66: SOURCES
B67: 2Q24 and 2Q25 (3-month) actuals: Bullish 2Q'25 earnings release, "Condensed Consolidated Statements of Cash Flows (Unaudited) for the three and six months ended June 30, 2025 and 2024."
B68: 3Q24 and 3Q25 (3-month) actuals: Bullish 3Q'25 earnings release, "Condensed Consolidated Statements of Cash Flows (Unaudited) for the three and nine months ended September 30, 2025 and 2024."
B69: 1Q25 and 1Q26 (3-month) actuals: Bullish 1Q'26 earnings release (May 14, 2026), "Condensed Consolidated Statements of Cash Flows (Unaudited) for the three months ended March 31, 2026 and 2025."
B70: 1Q24 and 4Q24 (3-month) were not disclosed as standalone quarters in any sourced document. 4Q25 (3-month) was not disclosed either - the 4Q'25/FY2025 earnings release included the P&L and Balance Sheet but no Statement of Cash Flows. Pull all three from the FY2025 20-F (filed March 9, 2026) or the relevant Form 6-K.
B71: Because 4Q24 and 4Q25 are missing, FY2024A and FY2025A columns below are the SUM of only the three disclosed quarters each year (2Q24+3Q24 only for FY2024A; 1Q25+2Q25+3Q25 only for FY2025A) - both understate the true annual cash flow and should be treated as partial, not final, until the missing quarter is added.
B72: As a cross-check: quarter-end cash (this tab's "end of period" line, which includes customer segregated cash and restricted cash) ties to the sum of the three separately-disclosed Balance Sheet cash-related lines for the same date - e.g. Mar-26: $76,052 (cash) + $55,640 (customer segregated cash) + $22,843 (restricted cash, current+non-current) = $154,535, matching this tab's 1Q26 end-of-period figure.
B73: Capital expenditures proxy = "Purchase of property and equipment" line only (does not include digital-asset purchases, which Bullish does not treat as capex).
B74: FY2026E-FY2029E columns intentionally left blank pending the Week 3 model build - do not treat as zero.
B76: Legend: blue = actual reported figure (sourced). Yellow fill = forecast input cell, left blank pending Week 3/4 modeling. Grey/blank = not disclosed in source documents. Black = formula. Rows nested under a bold subtotal can be collapsed using the outline (+/-) controls to the left of the row numbers.

Sheet Rev Build Inputs >>

Sheet Monthly Metrics
B4: Monthly Metrics Report for June 2026
B5: (Unaudited)
C6: =+YEAR(C8) -> 2025 | D6: =+YEAR(D8) -> 2025 | E6: =+YEAR(E8) -> 2025 | F6: =+YEAR(F8) -> 2025 | G6: =+YEAR(G8) -> 2025 | H6: =+YEAR(H8) -> 2025 | I6: =+YEAR(I8) -> 2025 | J6: =+YEAR(J8) -> 2025 | ... BJ6: =+YEAR(BJ8) -> 2029
C7: ="Q"&ROUNDUP(MONTH(C8)/3,0) -> Q1 | D7: ="Q"&ROUNDUP(MONTH(D8)/3,0) -> Q1 | E7: ="Q"&ROUNDUP(MONTH(E8)/3,0) -> Q1 | F7: ="Q"&ROUNDUP(MONTH(F8)/3,0) -> Q2 | G7: ="Q"&ROUNDUP(MONTH(G8)/3,0) -> Q2 | H7: ="Q"&ROUNDUP(MONTH(H8)/3,0) -> Q2 | I7: ="Q"&ROUNDUP(MONTH(I8)/3,0) -> Q3 | J7: ="Q"&ROUNDUP(MONTH(J8)/3,0) -> Q3 | ... BJ7: ="Q"&ROUNDUP(MONTH(BJ8)/3,0) -> Q4
C8: 45688 | D8: =+EOMONTH(C8,1) -> 45716 | E8: =+EOMONTH(D8,1) -> 45747 | F8: =+EOMONTH(E8,1) -> 45777 | G8: =+EOMONTH(F8,1) -> 45808 | H8: =+EOMONTH(G8,1) -> 45838 | I8: =+EOMONTH(H8,1) -> 45869 | J8: =+EOMONTH(I8,1) -> 45900 | K8: =+EOMONTH(J8,1) -> 45930 | ... BJ8: =+EOMONTH(BI8,1) -> 47483
C9: 2025 | O9: 2026
C10: Jan | D10: Feb | E10: Mar | F10: Apr | G10: May | H10: Jun | I10: Jul | J10: Aug | K10: Sep | L10: Oct | M10: Nov | N10: Dec | O10: Jan | P10: Feb | Q10: Mar | R10: Apr | S10: May | T10: Jun | U10: Jul | V10: Aug | W10: Sep | X10: Oct | Y10: Nov | Z10: Dec | AA10: Jan | AB10: Feb | AC10: Mar | AD10: Apr | AE10: May | AF10: Jun | AG10: Jul | AH10: Aug | AI10: Sep | AJ10: Oct | AK10: Nov | AL10: Dec | AM10: Jan | AN10: Feb | AO10: Mar | AP10: Apr | AQ10: May | AR10: Jun | AS10: Jul | AT10: Aug | AU10: Sep | AV10: Oct | AW10: Nov | AX10: Dec | AY10: Jan | AZ10: Feb | BA10: Mar | BB10: Apr | BC10: May | BD10: Jun | BE10: Jul | BF10: Aug | BG10: Sep | BH10: Oct | BI10: Nov | BJ10: Dec
B11: (B - in billions)
B12: Trading Volume ($B)
B13: Spot - BTC | C13: 34.6 | D13: 30.9 | E13: 43.2 | F13: 39.2 | G13: 32.8 | H13: 19.9 | I13: 20.8 | J13: 18.2 | K13: 16.4 | L13: 38.2 | M13: 38.4 | N13: 25.9 | O13: 22.5 | P13: 41.8 | Q13: 29.1 | R13: 20.9 | S13: 16.8 | T13: 26.9
B14: Spot - ETH | C14: 18.3 | D14: 19.2 | E14: 14.9 | F14: 10.9 | G14: 12 | H14: 9.5 | I14: 11.1 | J14: 12.8 | K14: 8.8 | L14: 15.1 | M14: 14.1 | N14: 9.6 | O14: 8.4 | P14: 12.9 | Q14: 8 | R14: 5.4 | S14: 3.4 | T14: 4.9
B15: Spot - Stablecoin | C15: 19.4 | D15: 20.9 | E15: 17 | F15: 13.3 | G15: 10.3 | H15: 8.1 | I15: 12.9 | J15: 8.6 | K15: 8.1 | L15: 19.6 | M15: 18.4 | N15: 13.8 | O15: 11.2 | P15: 19 | Q15: 13.2 | R15: 9.6 | S15: 7.4 | T15: 10.8
B16: Spot - Other | C16: 4.8 | D16: 3.8 | E16: 2.7 | F16: 2.2 | G16: 2.6 | H16: 2.4 | I16: 4 | J16: 4.6 | K16: 4.1 | L16: 4.6 | M16: 4.4 | N16: 2.9 | O16: 3.4 | P16: 3.7 | Q16: 2.7 | R16: 2.1 | S16: 2.5 | T16: 2.9
B17: Total Spot | C17: 77.1 | D17: 74.8 | E17: 77.7 | F17: 65.5 | G17: 57.6 | H17: 39.9 | I17: 48.8 | J17: 44.3 | K17: 37.3 | L17: 77.5 | M17: 75.3 | N17: 52.2 | O17: 45.4 | P17: 77.4 | Q17: 52.9 | R17: 38 | S17: 30 | T17: 45.5 | U17: =T17 * (1+U23) + ((U34-T34)*C49) -> 51.405676 | V17: =U17 * (1+V23) + ((V34-U34)*D49) -> 53.172288 | W17: =V17 * (1+W23) + ((W34-V34)*E49) -> 54.999611 | X17: =W17 * (1+X23) + ((X34-W34)*F49) -> 56.889733 | Y17: =X17 * (1+Y23) + ((Y34-X34)*G49) -> 58.84481 | Z17: =Y17 * (1+Z23) + ((Z34-Y34)*H49) -> 60.867075 | AA17: =Z17 * (1+AA23) + ((AA34-Z34)*I49) -> 65.722756 | AB17: =AA17 * (1+AB23) + ((AB34-AA34)*J49) -> 70.9658 | ... BJ17: =BI17 * (1+BJ23) + ((BJ34-BI34)*AR49) -> 964.67813
B18: Options | J18: 0 | K18: 0 | L18: 0 | M18: 2.8 | N18: 6.2 | O18: 4.8 | P18: 3.6 | Q18: 3.2 | R18: 5.6 | S18: 0.9 | T18: 2.3 | U18: =T18 * (1+U23) + ((U34-T34)*C53) -> 2.3456909 | V18: =U18 * (1+V23) + ((V34-U34)*D53) -> 2.4263031 | W18: =V18 * (1+W23) + ((W34-V34)*E53) -> 2.5096857 | X18: =W18 * (1+X23) + ((X34-W34)*F53) -> 2.5959337 | Y18: =X18 * (1+Y23) + ((Y34-X34)*G53) -> 2.6851458 | Z18: =Y18 * (1+Z23) + ((Z34-Y34)*H53) -> 2.7774238 | AA18: =Z18 * (1+AA23) + ((AA34-Z34)*I53) -> 2.9989932 | AB18: =AA18 * (1+AB23) + ((AB34-AA34)*J53) -> 3.2382384 | ... BJ18: =BI18 * (1+BJ23) + ((BJ34-BI34)*AR53) -> 44.0192
B19: Perpetual | C19: 6.6 | D19: 7.8 | E19: 8 | F19: 6.8 | G19: 5.8 | H19: 4.1 | I19: 5 | J19: 4.6 | K19: 2.2 | L19: 3 | M19: 2.7 | N19: 2.6 | O19: 2 | P19: 3.1 | Q19: 4.4 | R19: 3.4 | S19: 2 | T19: 3.1 | U19: =T19 * (1+U23) + ((U34-T34)*C57) -> 3.5119883 | V19: =U19 * (1+V23) + ((V34-U34)*D57) -> 3.6326815 | W19: =V19 * (1+W23) + ((W34-V34)*E57) -> 3.7575226 | X19: =W19 * (1+X23) + ((X34-W34)*F57) -> 3.8866539 | Y19: =X19 * (1+Y23) + ((Y34-X34)*G57) -> 4.020223 | Z19: =Y19 * (1+Z23) + ((Z34-Y34)*H57) -> 4.1583823 | AA19: =Z19 * (1+AA23) + ((AA34-Z34)*I57) -> 4.4901179 | AB19: =AA19 * (1+AB23) + ((AB34-AA34)*J57) -> 4.8483178 | ... BJ19: =BI19 * (1+BJ23) + ((BJ34-BI34)*AR57) -> 65.905918
B20: Total Trading Volume | C20: 83.7 | D20: 82.5 | E20: 85.7 | F20: 72.3 | G20: 63.4 | H20: 44 | I20: 53.8 | J20: 48.8 | K20: 39.6 | L20: 80.5 | M20: 80.8 | N20: 61.1 | O20: 52.2 | P20: 84.1 | Q20: 60.4 | R20: 46.9 | S20: 32.9 | T20: 50.9 | U20: =SUM(U17:U19) -> 57.263355 | V20: =SUM(V17:V19) -> 59.231273 | W20: =SUM(W17:W19) -> 61.26682 | X20: =SUM(X17:X19) -> 63.37232 | Y20: =SUM(Y17:Y19) -> 65.550179 | Z20: =SUM(Z17:Z19) -> 67.802881 | AA20: =SUM(AA17:AA19) -> 73.211867 | AB20: =SUM(AB17:AB19) -> 79.052356 | ... BJ20: =SUM(BJ17:BJ19) -> 1074.6033
B22: Annual Growth Volume Growth Rate | U22: =INDEX('Scenario & Sensitivity'!$C$7:$F$9,MATCH(Summary!$C$18,'Scenario & Sensitivity'!$B$7:$B$9,0),MATCH('Monthly Metrics'!U$6,'Scenario & Sensitivity'!$C$6:$F$6,0)) -> 0.5 | V22: =INDEX('Scenario & Sensitivity'!$C$7:$F$9,MATCH(Summary!$C$18,'Scenario & Sensitivity'!$B$7:$B$9,0),MATCH('Monthly Metrics'!V$6,'Scenario & Sensitivity'!$C$6:$F$6,0)) -> 0.5 | W22: =INDEX('Scenario & Sensitivity'!$C$7:$F$9,MATCH(Summary!$C$18,'Scenario & Sensitivity'!$B$7:$B$9,0),MATCH('Monthly Metrics'!W$6,'Scenario & Sensitivity'!$C$6:$F$6,0)) -> 0.5 | X22: =INDEX('Scenario & Sensitivity'!$C$7:$F$9,MATCH(Summary!$C$18,'Scenario & Sensitivity'!$B$7:$B$9,0),MATCH('Monthly Metrics'!X$6,'Scenario & Sensitivity'!$C$6:$F$6,0)) -> 0.5 | Y22: =INDEX('Scenario & Sensitivity'!$C$7:$F$9,MATCH(Summary!$C$18,'Scenario & Sensitivity'!$B$7:$B$9,0),MATCH('Monthly Metrics'!Y$6,'Scenario & Sensitivity'!$C$6:$F$6,0)) -> 0.5 | Z22: =INDEX('Scenario & Sensitivity'!$C$7:$F$9,MATCH(Summary!$C$18,'Scenario & Sensitivity'!$B$7:$B$9,0),MATCH('Monthly Metrics'!Z$6,'Scenario & Sensitivity'!$C$6:$F$6,0)) -> 0.5 | AA22: =INDEX('Scenario & Sensitivity'!$C$7:$F$9,MATCH(Summary!$C$18,'Scenario & Sensitivity'!$B$7:$B$9,0),MATCH('Monthly Metrics'!AA$6,'Scenario & Sensitivity'!$C$6:$F$6,0)) -> 1.5118864 | AB22: =INDEX('Scenario & Sensitivity'!$C$7:$F$9,MATCH(Summary!$C$18,'Scenario & Sensitivity'!$B$7:$B$9,0),MATCH('Monthly Metrics'!AB$6,'Scenario & Sensitivity'!$C$6:$F$6,0)) -> 1.5118864 | ... BJ22: =INDEX('Scenario & Sensitivity'!$C$7:$F$9,MATCH(Summary!$C$18,'Scenario & Sensitivity'!$B$7:$B$9,0),MATCH('Monthly Metrics'!BJ$6,'Scenario & Sensitivity'!$C$6:$F$6,0)) -> 1.5118864
B23: Adjusted Monthly | U23: =+((1+U22)^(1/12)) -1 -> 0.034366083 | V23: =+((1+V22)^(1/12)) -1 -> 0.034366083 | W23: =+((1+W22)^(1/12)) -1 -> 0.034366083 | X23: =+((1+X22)^(1/12)) -1 -> 0.034366083 | Y23: =+((1+Y22)^(1/12)) -1 -> 0.034366083 | Z23: =+((1+Z22)^(1/12)) -1 -> 0.034366083 | AA23: =+((1+AA22)^(1/12)) -1 -> 0.079775162 | AB23: =+((1+AB22)^(1/12)) -1 -> 0.079775162 | ... BJ23: =+((1+BJ22)^(1/12)) -1 -> 0.079775162
B25: Average Trading Spread (bps)
B26: Spot | C26: 2.14 | D26: 1.97 | E26: 1.87 | F26: 1.65 | G26: 1.55 | H26: 1.58 | I26: 1.76 | J26: 2.55 | K26: 1.96 | L26: 1.75 | M26: 1.94 | N26: 1.82 | O26: 1.74 | P26: 2.22 | Q26: 2.01 | R26: 2.05 | S26: 2.4 | T26: 2.84
B27: Options | J27: 1 | K27: 0.93 | L27: 1.29 | M27: 1.34 | N27: 1.66 | O27: 1.95 | P27: 2.42 | Q27: 1.86 | R27: 2.5 | S27: 1.65 | T27: 0.59
B28: Perpetual | C28: -1.06 | D28: -1.41 | E28: -2.38 | F28: -1.47 | G28: -0.86 | H28: -1.22 | I28: -0.8 | J28: -0.65 | K28: 0.21 | L28: -2.67 | M28: -0.13 | N28: -0.3 | O28: -0.61 | P28: 0.37 | Q28: 0.09 | R28: -0.08 | S28: -0.12 | T28: -0.14
B29: Average Trading Spread | C29: 1.9 | D29: 1.65 | E29: 1.47 | F29: 1.36 | G29: 1.32 | H29: 1.32 | I29: 1.52 | J29: 2.25 | K29: 1.86 | L29: 1.59 | M29: 1.85 | N29: 1.71 | O29: 1.67 | P29: 2.16 | Q29: 1.86 | R29: 1.95 | S29: 2.23 | T29: 2.56
B31: Monthly Average Volatility
B32: BTC | C32: 0.48 | D32: 0.44 | E32: 0.5 | F32: 0.44 | G32: 0.33 | H32: 0.28 | I32: 0.27 | J32: 0.28 | K32: 0.23 | L32: 0.38 | M32: 0.45 | N32: 0.39 | O32: 0.33 | P32: 0.61 | Q32: 0.48 | R32: 0.35 | S32: 0.28 | T32: 0.47 | U32: =+'Volatility Cycle Timeline'!U12 -> 0.53 | V32: =+'Volatility Cycle Timeline'!V12 -> 0.54 | W32: =+'Volatility Cycle Timeline'!W12 -> 0.55 | X32: =+'Volatility Cycle Timeline'!X12 -> 0.567 | Y32: =+'Volatility Cycle Timeline'!Y12 -> 0.583 | Z32: =+'Volatility Cycle Timeline'!Z12 -> 0.6 | AA32: =+'Volatility Cycle Timeline'!AA12 -> 0.54 | AB32: =+'Volatility Cycle Timeline'!AB12 -> 0.48 | ... BJ32: =+'Volatility Cycle Timeline'!BJ12 -> 0.85
B33: ETH | C33: 0.6 | D33: 0.78 | E33: 0.69 | F33: 0.7 | G33: 0.67 | H33: 0.54 | I33: 0.54 | J33: 0.6 | K33: 0.42 | L33: 0.58 | M33: 0.68 | N33: 0.53 | O33: 0.46 | P33: 0.82 | Q33: 0.6 | R33: 0.44 | S33: 0.36 | T33: 0.67 | U33: =+'Volatility Cycle Timeline'!U13 -> 0.6784 | V33: =+'Volatility Cycle Timeline'!V13 -> 0.6912 | W33: =+'Volatility Cycle Timeline'!W13 -> 0.704 | X33: =+'Volatility Cycle Timeline'!X13 -> 0.72576 | Y33: =+'Volatility Cycle Timeline'!Y13 -> 0.74624 | Z33: =+'Volatility Cycle Timeline'!Z13 -> 0.768 | AA33: =+'Volatility Cycle Timeline'!AA13 -> 0.6912 | AB33: =+'Volatility Cycle Timeline'!AB13 -> 0.6144 | ... BJ33: =+'Volatility Cycle Timeline'!BJ13 -> 1.088
B34: Average | C34: =AVERAGE(C32:C33) -> 0.54 | D34: =AVERAGE(D32:D33) -> 0.61 | E34: =AVERAGE(E32:E33) -> 0.595 | F34: =AVERAGE(F32:F33) -> 0.57 | G34: =AVERAGE(G32:G33) -> 0.5 | H34: =AVERAGE(H32:H33) -> 0.41 | I34: =AVERAGE(I32:I33) -> 0.405 | J34: =AVERAGE(J32:J33) -> 0.44 | ... BJ34: =AVERAGE(BJ32:BJ33) -> 0.969
B36: Mothly Price
B37: BTC | C37: 102405.03 | D37: 84373.01 | E37: 82548.91 | F37: 94207.31 | G37: 104638.09 | H37: 107135.33 | I37: 115758.2 | J37: 108236.71 | K37: 114056.08 | L37: 109556.16 | M37: 90394.31 | N37: 87508.83 | O37: 78621.11 | P37: 66995.86 | Q37: 68233.32 | R37: 76304.32 | S37: 73579.69 | T37: 58558.86
B40: Correlation
B41: Spot Vol. to BTC Price | C41: =+CORREL(C17:N17,C37:N37) -> -0.58502631
B42: Total Vol. to BTC Price | C42: =+CORREL(C20:N20,C37:N37) -> -0.65219054
B43: Spot Vol. to Volatility BTC | C43: =+CORREL(C17:N17,C32:N32) -> 0.90330171
B44: Total Vol. to Volatility BTC | C44: =+CORREL(C20:N20,C32:N32) -> 0.93505323
B47: Regression
B48: Spot
B49: Slope | C49: =SLOPE(C17:T17,C34:T34) -> 126.95963
B50: Intercept | C50: =+INTERCEPT(C17:T17,C34:T34) -> -5.8049097
B51: Formula Check | C51: =+$C$50+($C$49*C34) -> 62.753293 | D51: =+$C$50+($C$49*D34) -> 71.640468 | E51: =+$C$50+($C$49*E34) -> 69.736073 | F51: =+$C$50+($C$49*F34) -> 66.562082 | G51: =+$C$50+($C$49*G34) -> 57.674908 | H51: =+$C$50+($C$49*H34) -> 46.248541 | I51: =+$C$50+($C$49*I34) -> 45.613742 | J51: =+$C$50+($C$49*J34) -> 50.05733 | ... T51: =+$C$50+($C$49*T34) -> 66.562082
B52: Options
B53: Slope | C53: =SLOPE(M18:T18,M34:T34) -> -0.9751773
B54: Intercept | C54: =+INTERCEPT(M18:T18,M34:T34) -> 4.1577128
B55: Formula Check | M55: =+$C$54+($C$53*M34) -> 3.6067376 | N55: =+$C$54+($C$53*N34) -> 3.7091312 | O55: =+$C$54+($C$53*O34) -> 3.7725177 | P55: =+$C$54+($C$53*P34) -> 3.460461 | Q55: =+$C$54+($C$53*Q34) -> 3.631117 | R55: =+$C$54+($C$53*R34) -> 3.7725177 | S55: =+$C$54+($C$53*S34) -> 3.845656 | T55: =+$C$54+($C$53*T34) -> 3.6018617
B56: Perps
B57: Slope | C57: =SLOPE(C19:T19,C34:T34) -> 8.931386
B58: Intercept | C58: =+INTERCEPT(C19:T19,C34:T34) -> -0.094933089
B59: Formula Check | C59: =+$C$58+($C$57*C34) -> 4.7280154 | D59: =+$C$58+($C$57*D34) -> 5.3532124 | E59: =+$C$58+($C$57*E34) -> 5.2192416 | F59: =+$C$58+($C$57*F34) -> 4.9959569 | G59: =+$C$58+($C$57*G34) -> 4.3707599 | H59: =+$C$58+($C$57*H34) -> 3.5669352 | I59: =+$C$58+($C$57*I34) -> 3.5222783 | J59: =+$C$58+($C$57*J34) -> 3.8348768 | ... T59: =+$C$58+($C$57*T34) -> 4.9959569
B61: Total Formula Check | C61: =+C59+C55+C51 -> 67.481309 | D61: =+D59+D55+D51 -> 76.99368 | E61: =+E59+E55+E51 -> 74.955315 | F61: =+F59+F55+F51 -> 71.558039 | G61: =+G59+G55+G51 -> 62.045668 | H61: =+H59+H55+H51 -> 49.815476 | I61: =+I59+I55+I51 -> 49.136021 | J61: =+J59+J55+J51 -> 53.892206 | ... T61: =+T59+T55+T51 -> 75.159901
B62: Delta | C62: =+C61-C20 -> -16.218691 | D62: =+D61-D20 -> -5.50632 | E62: =+E61-E20 -> -10.744685 | F62: =+F61-F20 -> -0.74196084 | G62: =+G61-G20 -> -1.3543323 | H62: =+H61-H20 -> 5.8154758 | I62: =+I61-I20 -> -4.6639793 | J62: =+J61-J20 -> 5.0922064 | ... T62: =+T61-T20 -> 24.259901
B63: Mean absolute percentage error (MAPE) | C63: {=AVERAGE(ABS(C62:T62)/C20:T20)} -> 0.12664262
B67: Trading Volume represents the notional value of trades, i.e. the product of the quantity of assets transacted and the trade price at the time the transaction was executed. The quantity represents the total U.S. dollar equivalent value of matched trades transacted between a buyer and seller through our platform during the period of measurement.
B69: Average Trading Spread represents total commissions earned from transactions on the Bullish Exchange for the period, expressed as a percentage of the trading volume for the period. Management reviews this metric, which reflects the cost of trading on the Bullish Exchange, changes in fair value of perpetual futures, and rebates, for insight into the average revenue generated per unit of trading volume on our platform.
B71: Volatility is calculated using 1-minute price intervals from Coindesk Data's Adaptive Diversified Liquidity Index for BTC and ETH. We determine the daily volatility by measuring the standard deviation of these minute-by-minute price changes, which provides a more granular view of price fluctuations. This daily figure is then converted to an annualized volatility by multiplying it by the square root of 365, a standard practice for making risk metrics comparable over a one-year period.

Sheet Volatility Cycle Timeline
B2: BLSH Volatility Cycle Timeline - Monthly, Jan 2025 - Dec 2029
B3: Actual BTC volatility (blue) = Bullish-disclosed quarterly average, held flat across the first quarter shown and linearly interpolated month-to-month between disclosed quarter-end anchors. Forecast (orange), starting 2Q26, = quarter-end anchors set from the cycle-phase narrative below, linearly interpolated monthly. ETH = BTC x 1.28 throughout (a fixed multiplier, not an independent forecast). This is a scenario for planning purposes, not a market call - see methodology below for the full reasoning and how to defend it.
C6: 2025 | D6: 2025 | E6: 2025 | F6: 2025 | G6: 2025 | H6: 2025 | I6: 2025 | J6: 2025 | K6: 2025 | L6: 2025 | M6: 2025 | N6: 2025 | O6: 2026 | P6: 2026 | Q6: 2026 | R6: 2026 | S6: 2026 | T6: 2026 | U6: 2026 | V6: 2026 | W6: 2026 | X6: 2026 | Y6: 2026 | Z6: 2026 | AA6: 2027 | AB6: 2027 | AC6: 2027 | AD6: 2027 | AE6: 2027 | AF6: 2027 | AG6: 2027 | AH6: 2027 | AI6: 2027 | AJ6: 2027 | AK6: 2027 | AL6: 2027 | AM6: 2028 | AN6: 2028 | AO6: 2028 | AP6: 2028 | AQ6: 2028 | AR6: 2028 | AS6: 2028 | AT6: 2028 | AU6: 2028 | AV6: 2028 | AW6: 2028 | AX6: 2028 | AY6: 2029 | AZ6: 2029 | BA6: 2029 | BB6: 2029 | BC6: 2029 | BD6: 2029 | BE6: 2029 | BF6: 2029 | BG6: 2029 | BH6: 2029 | BI6: 2029 | BJ6: 2029
C7: Q1 | D7: Q1 | E7: Q1 | F7: Q2 | G7: Q2 | H7: Q2 | I7: Q3 | J7: Q3 | K7: Q3 | L7: Q4 | M7: Q4 | N7: Q4 | O7: Q1 | P7: Q1 | Q7: Q1 | R7: Q2 | S7: Q2 | T7: Q2 | U7: Q3 | V7: Q3 | W7: Q3 | X7: Q4 | Y7: Q4 | Z7: Q4 | AA7: Q1 | AB7: Q1 | AC7: Q1 | AD7: Q2 | AE7: Q2 | AF7: Q2 | AG7: Q3 | AH7: Q3 | AI7: Q3 | AJ7: Q4 | AK7: Q4 | AL7: Q4 | AM7: Q1 | AN7: Q1 | AO7: Q1 | AP7: Q2 | AQ7: Q2 | AR7: Q2 | AS7: Q3 | AT7: Q3 | AU7: Q3 | AV7: Q4 | AW7: Q4 | AX7: Q4 | AY7: Q1 | AZ7: Q1 | BA7: Q1 | BB7: Q2 | BC7: Q2 | BD7: Q2 | BE7: Q3 | BF7: Q3 | BG7: Q3 | BH7: Q4 | BI7: Q4 | BJ7: Q4
C8: 45688 | D8: 45716 | E8: 45747 | F8: 45777 | G8: 45808 | H8: 45838 | I8: 45869 | J8: 45900 | K8: 45930 | L8: 45961 | M8: 45991 | N8: 46022 | O8: 46053 | P8: 46081 | Q8: 46112 | R8: 46142 | S8: 46173 | T8: 46203 | U8: 46234 | V8: 46265 | W8: 46295 | X8: 46326 | Y8: 46356 | Z8: 46387 | AA8: 46418 | AB8: 46446 | AC8: 46477 | AD8: 46507 | AE8: 46538 | AF8: 46568 | AG8: 46599 | AH8: 46630 | AI8: 46660 | AJ8: 46691 | AK8: 46721 | AL8: 46752 | AM8: 46783 | AN8: 46812 | AO8: 46843 | AP8: 46873 | AQ8: 46904 | AR8: 46934 | AS8: 46965 | AT8: 46996 | AU8: 47026 | AV8: 47057 | AW8: 47087 | AX8: 47118 | AY8: 47149 | AZ8: 47177 | BA8: 47208 | BB8: 47238 | BC8: 47269 | BD8: 47299 | BE8: 47330 | BF8: 47361 | BG8: 47391 | BH8: 47422 | BI8: 47452 | BJ8: 47483
C9: 2025 | O9: 2026 | AA9: 2027 | AM9: 2028 | AY9: 2029
C10: Jan | D10: Feb | E10: Mar | F10: Apr | G10: May | H10: Jun | I10: Jul | J10: Aug | K10: Sep | L10: Oct | M10: Nov | N10: Dec | O10: Jan | P10: Feb | Q10: Mar | R10: Apr | S10: May | T10: Jun | U10: Jul | V10: Aug | W10: Sep | X10: Oct | Y10: Nov | Z10: Dec | AA10: Jan | AB10: Feb | AC10: Mar | AD10: Apr | AE10: May | AF10: Jun | AG10: Jul | AH10: Aug | AI10: Sep | AJ10: Oct | AK10: Nov | AL10: Dec | AM10: Jan | AN10: Feb | AO10: Mar | AP10: Apr | AQ10: May | AR10: Jun | AS10: Jul | AT10: Aug | AU10: Sep | AV10: Oct | AW10: Nov | AX10: Dec | AY10: Jan | AZ10: Feb | BA10: Mar | BB10: Apr | BC10: May | BD10: Jun | BE10: Jul | BF10: Aug | BG10: Sep | BH10: Oct | BI10: Nov | BJ10: Dec
B12: BTC annualized volatility (spot, %) | C12: 0.474 | D12: 0.474 | E12: 0.474 | F12: 0.434 | G12: 0.393 | H12: 0.353 | I12: 0.322 | J12: 0.291 | K12: 0.26 | L12: 0.308 | M12: 0.357 | N12: 0.405 | O12: 0.427 | P12: 0.448 | Q12: 0.47 | R12: 0.487 | S12: 0.503 | T12: 0.52 | U12: 0.53 | V12: 0.54 | W12: 0.55 | X12: 0.567 | Y12: 0.583 | Z12: 0.6 | AA12: 0.54 | AB12: 0.48 | AC12: 0.42 | AD12: 0.39 | AE12: 0.36 | AF12: 0.33 | AG12: 0.32 | AH12: 0.31 | AI12: 0.3 | AJ12: 0.307 | AK12: 0.313 | AL12: 0.32 | AM12: 0.33 | AN12: 0.34 | AO12: 0.35 | AP12: 0.373 | AQ12: 0.397 | AR12: 0.42 | AS12: 0.447 | AT12: 0.473 | AU12: 0.5 | AV12: 0.527 | AW12: 0.553 | AX12: 0.58 | AY12: 0.603 | AZ12: 0.627 | BA12: 0.65 | BB12: 0.673 | BC12: 0.697 | BD12: 0.72 | BE12: 0.74 | BF12: 0.76 | BG12: 0.78 | BH12: 0.803 | BI12: 0.827 | BJ12: 0.85
B13: ETH annualized volatility (spot, %) = BTC x 1.28 | C13: =C12*1.28 -> 0.60672 | D13: =D12*1.28 -> 0.60672 | E13: =E12*1.28 -> 0.60672 | F13: =F12*1.28 -> 0.55552 | G13: =G12*1.28 -> 0.50304 | H13: =H12*1.28 -> 0.45184 | I13: =I12*1.28 -> 0.41216 | J13: =J12*1.28 -> 0.37248 | ... BJ13: =BJ12*1.28 -> 1.088
B15: Actual (A) / Forecast (F) | C15: A | D15: A | E15: A | F15: A | G15: A | H15: A | I15: A | J15: A | K15: A | L15: A | M15: A | N15: A | O15: A | P15: A | Q15: A | R15: F | S15: F | T15: F | U15: F | V15: F | W15: F | X15: F | Y15: F | Z15: F | AA15: F | AB15: F | AC15: F | AD15: F | AE15: F | AF15: F | AG15: F | AH15: F | AI15: F | AJ15: F | AK15: F | AL15: F | AM15: F | AN15: F | AO15: F | AP15: F | AQ15: F | AR15: F | AS15: F | AT15: F | AU15: F | AV15: F | AW15: F | AX15: F | AY15: F | AZ15: F | BA15: F | BB15: F | BC15: F | BD15: F | BE15: F | BF15: F | BG15: F | BH15: F | BI15: F | BJ15: F
B17: Cycle phase narrative | C17: Post-halving bull run continues (Apr'24 halving) | F17: Bull run continues, momentum building | I17: Bull run continues, approaching cycle top | L17: Cycle top: BTC ATH $126.3k reached Oct 6, 2025; initial rollover | O17: Bear decline continues | R17: Bear decline continues (FORECAST STARTS HERE) | U17: Capitulation / final flush expected | AA17: Transition into bottoming phase | AD17: Accumulation / bottoming | AG17: Accumulation / bottoming (trough) | AJ17: Late accumulation, base-building | AM17: Quiet base; pre-halving buildup begins | AP17: Pre-halving positioning (halving ~Apr 2028) | AS17: Post-halving: early rally | AV17: Rally continuing, vol building | AY17: Bull acceleration | BB17: Bull acceleration continues | BE17: Approaching new highs; elevated vol | BH17: Peak-approaching euphoria (capped below pre-ETF extremes)
B19: METHODOLOGY - HOW THIS WAS BUILT AND HOW TO DEFEND IT
B20: 1. Actual anchors (Jan'25-Mar'26)
B21: Quarterly BTC annualized volatility as disclosed by Bullish (Shareholder Update / earnings releases): 1Q25 47.4%, 2Q25 35.3%, 3Q25 26.0%, 4Q25 40.5%, 1Q26 47.0%. These are quarter-averages, not month-by-month, so the same quarterly figure is held flat for the first quarter shown and interpolated linearly toward the next disclosed quarter - a simplification, stated explicitly as such.
B22: 2. Forecast starts 2Q26
B23: No BLSH-disclosed data exists past 1Q26 at the time this was built (mid-2026). The forecast path uses a phase-based cycle framework rather than a single-variable extrapolation: (a) continuation of the post-October-2025-ATH decline through late 2026, (b) a bottoming/accumulation phase through 2027, (c) pre-halving positioning building into April 2028, and (d) a post-halving bull phase building through 2029.
B24: 3. Why these specific phase transitions
B25: BTC hit a new all-time high of ~$126.3k on October 6, 2025, then declined roughly 47% into early 2026 - consistent with the historical pattern of a roughly year-long peak-to-trough decline followed by a multi-month accumulation phase. The next halving is expected around April 2028 (four years after the April 20, 2024 halving), which is the standard trigger for the next bull leg under BTC's historical four-year cycle - anticipation typically builds 6-12 months ahead of the event itself.
B26: 4. Why the peaks are capped lower than pre-2024 history
B27: Pre-ETF-era BTC volatility often exceeded 150% annualized. Since spot ETFs launched in January 2024, institutional participation has structurally compressed realized volatility - spikes are milder and drawdowns shallower than in the 2018 or 2022 cycles. This forecast caps the 2029 peak around 80-85%, anchored to BLSH's own actual disclosed range (26%-47%) rather than to older, pre-institutionalization extremes.
B28: 5. Monthly interpolation method
B29: Quarterly anchor values are set at each quarter-END month. All other months are a straight-line interpolation between the two bracketing quarter-end anchors - not independently guessed month-by-month. This keeps the path smooth and makes the underlying assumption transparent and easy to challenge or adjust (change one anchor, the whole curve updates).
B30: 6. ETH treatment
... B35: This is a directional planning scenario, not a market-timing call. The actual cycle could shift by a year or more in either direction, the historical 4-year halving cycle could weaken further as institutional adoption matures (a live debate in the market right now), and any single macro shock (rate policy, regulatory action, a major exchange failure) could invalidate the whole path with no warning. Recommend pairing this with the volatility-to-volume regression built earlier (94% correlation, ~13% MAPE) as the actual revenue-driving mechanism, using this timeline only to set the volatility *input* to that model.

Sheet Valuation Inputs >>

Sheet Comps
B2: Comparable Companies
B3: Bucket comps by valuation logic, not just by industry label - conflating a high-growth peer with a mature one produces a misleading blended multiple. Keep buckets separate and state explicitly which bucket the market is using to price your name today.
B5: COMP SET
B6: Company Name | C6: Market Value | D6: Enterprise Value | E6: EV / Revenue | G6: EV / Gross Profit | I6: EV / EBITDA | K6: Revenue Growth | M6: Gross Profit Margin | O6: EBITDA Margin
E7: CY 26E | F7: CY 27E | G7: CY 26E | H7: CY 27E | I7: CY 26E | J7: CY 27E | K7: CY 26E | L7: CY 27E | M7: CY 26E | N7: CY 27E | O7: CY 26E | P7: CY 27E
B8: Legacy Market Infrastructure
B9: ICE | C9: 77626 | D9: 97832 | E9: 8.9 | F9: 8.5 | G9: 8.9 | H9: 8.5 | I9: 13.3 | J9: 12.7 | K9: 0.1 | L9: 0.05 | M9: 1 | N9: 1 | O9: 0.67 | P9: 0.67
B10: NASDAQ | C10: 50399 | D10: 59406 | E10: 10.3 | F10: 9.5 | G10: 10.3 | H10: 9.5 | I10: 17.4 | J10: 15.9 | K10: 0.1 | L10: 0.08 | M10: 1 | N10: 1 | O10: 0.59 | P10: 0.6
B11: CME Group | C11: 88488 | D11: 89715 | E11: 12.7 | F11: 12.3 | G11: 12.7 | H11: 12.3 | I11: 17.9 | J11: 17.3 | K11: 0.08 | L11: 0.04 | M11: 1 | N11: 1 | O11: 0.71 | P11: 0.71
B12: LSEG | C12: 58704 | D12: 71923 | E12: 5.4 | F12: 5.1 | G12: 6.2 | H12: 5.8 | I12: 10.8 | J12: 10 | K12: 0.06 | L12: 0.07 | M12: 0.88 | N12: 0.88 | O12: 0.5 | P12: 0.51
B13: Median | E13: =IFERROR(MEDIAN(E9:E12),"na") -> 9.6 | F13: =IFERROR(MEDIAN(F9:F12),"na") -> 9 | G13: =IFERROR(MEDIAN(G9:G12),"na") -> 9.6 | H13: =IFERROR(MEDIAN(H9:H12),"na") -> 9 | I13: =IFERROR(MEDIAN(I9:I12),"na") -> 15.35 | J13: =IFERROR(MEDIAN(J9:J12),"na") -> 14.3 | K13: =IFERROR(MEDIAN(K9:K12),"na") -> 0.09 | L13: =IFERROR(MEDIAN(L9:L12),"na") -> 0.06 | ... P13: =IFERROR(MEDIAN(P9:P12),"na") -> 0.635
B14: Mean | E14: =IFERROR(AVERAGE(E9:E12),"na") -> 9.325 | F14: =IFERROR(AVERAGE(F9:F12),"na") -> 8.85 | G14: =IFERROR(AVERAGE(G9:G12),"na") -> 9.525 | H14: =IFERROR(AVERAGE(H9:H12),"na") -> 9.025 | I14: =IFERROR(AVERAGE(I9:I12),"na") -> 14.85 | J14: =IFERROR(AVERAGE(J9:J12),"na") -> 13.975 | K14: =IFERROR(AVERAGE(K9:K12),"na") -> 0.085 | L14: =IFERROR(AVERAGE(L9:L12),"na") -> 0.06 | ... P14: =IFERROR(AVERAGE(P9:P12),"na") -> 0.6225
B16: Modern Trading Platforms
B17: Robinhood | C17: 100040 | D17: 105652 | E17: 20.8 | F17: 16.7 | G17: 22.5 | H17: 18.1 | I17: 40.2 | J17: 29.6 | K17: 0.14 | L17: 0.25 | M17: 0.92 | N17: 0.92 | O17: 0.52 | P17: 0.56
B18: Bullish | C18: 3478 | D18: 3696 | E18: 10 | F18: 8.7 | G18: 10 | H18: 8.7 | I18: 24.8 | J18: 19.5 | K18: 0.29 | L18: 0.15 | M18: 1 | N18: 1 | O18: 0.4 | P18: 0.45
B19: Coinbase | C19: 43444 | D19: 40970 | E19: 6.7 | F19: 5.3 | G19: 7.9 | H19: 6.3 | I19: 21.6 | J19: 12.9 | K19: -0.153 | L19: 0.26 | M19: 0.85 | N19: 0.85 | O19: 0.31 | P19: 0.42
B20: Gemini | C20: 500 | D20: 779 | E20: 3.9 | F20: 2.9 | G20: nm | H20: nm | I20: nm | J20: nm | K20: 0.12 | L20: 0.34 | M20: -0.288 | N20: -0.288 | O20: -0.942 | P20: -0.538
B21: WeBull | C21: 4031 | D21: 3456 | E21: 4.8 | F21: 3.9 | G21: 6.3 | H21: 5.1 | I21: 27.4 | J21: 14.9 | K21: 0.25 | L21: 0.23 | M21: 0.76 | N21: 0.76 | O21: 0.18 | P21: 0.26
B22: Interactive Brokers | C22: 41361 | D22: 63561 | E22: 8.8 | F22: 7.7 | G22: 9.5 | H22: 8.3 | I22: 11.3 | J22: 9.9 | K22: 0.17 | L22: 0.14 | M22: 0.93 | N22: 0.93 | O22: 0.78 | P22: 0.78
B23: eToro | C23: 3444 | D23: 2426 | E23: 2.5 | F23: 2.3 | G23: 76.6 | H23: 69.5 | I23: 6.7 | J23: 5.7 | K23: 0.11 | L23: 0.1 | M23: 0.03 | N23: 0.03 | O23: 0.37 | P23: 0.4
B24: Galaxy | C24: 4699 | D24: 8783 | E24: 0.1 | F24: 0.1 | G24: 0.1 | H24: 0.1 | I24: 10.3 | J24: na | K24: -0.244 | L24: 0.21 | M24: 1 | N24: 1 | O24: 0 | P24: 0.01
B25: Median | E25: =IFERROR(MEDIAN(E17:E24),"na") -> 5.75 | F25: =IFERROR(MEDIAN(F17:F24),"na") -> 4.6 | G25: =IFERROR(MEDIAN(G17:G24),"na") -> 9.5 | H25: =IFERROR(MEDIAN(H17:H24),"na") -> 8.3 | I25: =IFERROR(MEDIAN(I17:I24),"na") -> 21.6 | J25: =IFERROR(MEDIAN(J17:J24),"na") -> 13.9 | K25: =IFERROR(MEDIAN(K17:K24),"na") -> 0.13 | L25: =IFERROR(MEDIAN(L17:L24),"na") -> 0.22 | ... P25: =IFERROR(MEDIAN(P17:P24),"na") -> 0.41
B26: Mean | E26: =IFERROR(AVERAGE(E17:E24),"na") -> 7.2 | F26: =IFERROR(AVERAGE(F17:F24),"na") -> 5.95 | G26: =IFERROR(AVERAGE(G17:G24),"na") -> 18.985714 | H26: =IFERROR(AVERAGE(H17:H24),"na") -> 16.585714 | I26: =IFERROR(AVERAGE(I17:I24),"na") -> 20.328571 | J26: =IFERROR(AVERAGE(J17:J24),"na") -> 15.416667 | K26: =IFERROR(AVERAGE(K17:K24),"na") -> 0.085375 | L26: =IFERROR(AVERAGE(L17:L24),"na") -> 0.21 | ... P26: =IFERROR(AVERAGE(P17:P24),"na") -> 0.29275
B28: Register & Issuer Services
B29: Computer Share | C29: 15947 | D29: 16709 | E29: 5.2 | F29: 5.1 | G29: 18.6 | H29: 18 | I29: 13.1 | J29: 12.7 | K29: 0 | L29: 0.03 | M29: 0.28 | N29: 0.28 | O29: 0.4 | P29: 0.4
B30: Broadridge | C30: 17466 | D30: 20567 | E30: 2.7 | F30: 2.6 | G30: 8.7 | H30: 8.3 | I30: 11.3 | J30: 10.5 | K30: 0.05 | L30: 0.05 | M30: 0.31 | N30: 0.31 | O30: 0.24 | P30: 0.25
B31: SS&C | C31: 16470 | D31: 23737 | E31: 3.5 | F31: 3.4 | G31: 7.3 | H31: 7 | I31: 8.9 | J31: 8.3 | K31: 0.05 | L31: 0.08 | M31: 0.48 | N31: 0.48 | O31: 0.4 | P31: 0.4
B32: Equiniti (at announcement $38.48 BLSH share) | C32: 2350 | D32: 4200 | E32: 4.6 | F32: na | G32: na | H32: na | I32: 10.2 | J32: na | K32: na | L32: na | M32: na | N32: na | O32: 0.45 | P32: na
B33: Equiniti (today $22.75 BLSH share) | C33: 1389 | D33: 3239 | E33: 3.5 | F33: na | G33: na | H33: na | I33: 7.9 | J33: na | K33: na | L33: na | M33: na | N33: na | O33: 0.45 | P33: na
B34: Median (Excluding Equiniti) | E34: =IFERROR(MEDIAN(E29:E31),"na") -> 3.5 | F34: =IFERROR(MEDIAN(F29:F31),"na") -> 3.4 | G34: =IFERROR(MEDIAN(G29:G31),"na") -> 8.7 | H34: =IFERROR(MEDIAN(H29:H31),"na") -> 8.3 | I34: =IFERROR(MEDIAN(I29:I31),"na") -> 11.3 | J34: =IFERROR(MEDIAN(J29:J31),"na") -> 10.5 | K34: =IFERROR(MEDIAN(K29:K31),"na") -> 0.05 | L34: =IFERROR(MEDIAN(L29:L31),"na") -> 0.05 | ... P34: =IFERROR(MEDIAN(P29:P31),"na") -> 0.4
B35: Mean (Excluding Equiniti) | E35: =IFERROR(AVERAGE(E29:E31),"na") -> 3.8 | F35: =IFERROR(AVERAGE(F29:F31),"na") -> 3.7 | G35: =IFERROR(AVERAGE(G29:G31),"na") -> 11.533333 | H35: =IFERROR(AVERAGE(H29:H31),"na") -> 11.1 | I35: =IFERROR(AVERAGE(I29:I31),"na") -> 11.1 | J35: =IFERROR(AVERAGE(J29:J31),"na") -> 10.5 | K35: =IFERROR(AVERAGE(K29:K31),"na") -> 0.033333333 | L35: =IFERROR(AVERAGE(L29:L31),"na") -> 0.053333333 | ... P35: =IFERROR(AVERAGE(P29:P31),"na") -> 0.35
B37: Stablecoin Issuer
B38: Circle | C38: 16127 | D38: 14626 | E38: 4.8 | F38: 3.6 | G38: 59.2 | H38: 44.2 | I38: 23 | J38: 15.7 | K38: 0.11 | L38: 0.34 | M38: 0.08 | N38: 0.08 | O38: 0.21 | P38: 0.23
B39: Median | E39: =IFERROR(MEDIAN(E38:E38),"na") -> 4.8 | F39: =IFERROR(MEDIAN(F38:F38),"na") -> 3.6 | G39: =IFERROR(MEDIAN(G38:G38),"na") -> 59.2 | H39: =IFERROR(MEDIAN(H38:H38),"na") -> 44.2 | I39: =IFERROR(MEDIAN(I38:I38),"na") -> 23 | J39: =IFERROR(MEDIAN(J38:J38),"na") -> 15.7 | K39: =IFERROR(MEDIAN(K38:K38),"na") -> 0.11 | L39: =IFERROR(MEDIAN(L38:L38),"na") -> 0.34 | ... P39: =IFERROR(MEDIAN(P38:P38),"na") -> 0.23
B41: Tokenization Infrastructure
B42: Securitize | C42: 1382 | D42: 1382 | E42: na | F42: na | G42: na | H42: na | I42: na | J42: na | K42: na | L42: na | M42: na | N42: na | O42: na | P42: na
B43: Figure | C43: 7275 | D43: 7134 | E43: 8.6 | F43: 7.1 | G43: 8.6 | H43: 7.1 | I43: 17.2 | J43: 13 | K43: 0.64 | L43: 0.2 | M43: 1 | N43: 1 | O43: 0.5 | P43: 0.55
B44: Median | E44: =IFERROR(MEDIAN(E42:E43),"na") -> 8.6 | F44: =IFERROR(MEDIAN(F42:F43),"na") -> 7.1 | G44: =IFERROR(MEDIAN(G42:G43),"na") -> 8.6 | H44: =IFERROR(MEDIAN(H42:H43),"na") -> 7.1 | I44: =IFERROR(MEDIAN(I42:I43),"na") -> 17.2 | J44: =IFERROR(MEDIAN(J42:J43),"na") -> 13 | K44: =IFERROR(MEDIAN(K42:K43),"na") -> 0.64 | L44: =IFERROR(MEDIAN(L42:L43),"na") -> 0.2 | ... P44: =IFERROR(MEDIAN(P42:P43),"na") -> 0.55
B46: Data & Index Providers
B47: MSCI | C47: 45054 | D47: 51246 | E47: 14.6 | F47: 13.4 | G47: 17.6 | H47: 16.2 | I47: 23.5 | J47: 21.3 | K47: 0.12 | L47: 0.09 | M47: 0.83 | N47: 0.83 | O47: 0.62 | P47: 0.63
B48: Moody's | C48: 86761 | D48: 92803 | E48: 11.3 | F48: 10.5 | G48: 15.1 | H48: 14.1 | I48: 21.4 | J48: 19.7 | K48: 0.07 | L48: 0.07 | M48: 0.74 | N48: 0.74 | O48: 0.53 | P48: 0.53
B49: S&P Global | C49: 129753 | D49: 146875 | E49: 9.6 | F49: 9.3 | G49: 13.6 | H49: 13.3 | I49: 18 | J49: 17.6 | K49: 0 | L49: 0.02 | M49: 0.7 | N49: 0.7 | O49: 0.53 | P49: 0.53
B50: FactSet | C50: 9252 | D50: 10519 | E50: 4.2 | F50: 4 | G50: 8.2 | H50: 7.7 | I50: 11.5 | J50: 10.4 | K50: 0.06 | L50: 0.06 | M50: 0.51 | N50: 0.51 | O50: 0.37 | P50: 0.38
B51: Morningstar | C51: 6598 | D51: 7972 | E51: 3 | F51: 2.9 | G51: 4.9 | H51: 4.7 | I51: 9.9 | J51: 9 | K51: 0.07 | L51: 0.06 | M51: 0.62 | N51: 0.62 | O51: 0.31 | P51: 0.32
B52: Median | E52: =IFERROR(MEDIAN(E47:E51),"na") -> 9.6 | F52: =IFERROR(MEDIAN(F47:F51),"na") -> 9.3 | G52: =IFERROR(MEDIAN(G47:G51),"na") -> 13.6 | H52: =IFERROR(MEDIAN(H47:H51),"na") -> 13.3 | I52: =IFERROR(MEDIAN(I47:I51),"na") -> 18 | J52: =IFERROR(MEDIAN(J47:J51),"na") -> 17.6 | K52: =IFERROR(MEDIAN(K47:K51),"na") -> 0.07 | L52: =IFERROR(MEDIAN(L47:L51),"na") -> 0.06 | ... P52: =IFERROR(MEDIAN(P47:P51),"na") -> 0.53
B53: Mean | E53: =IFERROR(AVERAGE(E47:E51),"na") -> 8.54 | F53: =IFERROR(AVERAGE(F47:F51),"na") -> 8.02 | G53: =IFERROR(AVERAGE(G47:G51),"na") -> 11.88 | H53: =IFERROR(AVERAGE(H47:H51),"na") -> 11.2 | I53: =IFERROR(AVERAGE(I47:I51),"na") -> 16.86 | J53: =IFERROR(AVERAGE(J47:J51),"na") -> 15.6 | K53: =IFERROR(AVERAGE(K47:K51),"na") -> 0.064 | L53: =IFERROR(AVERAGE(L47:L51),"na") -> 0.06 | ... P53: =IFERROR(AVERAGE(P47:P51),"na") -> 0.478

Sheet DCF
B2: Pro Forma DCF
B4: UNLEVERED FREE CASH FLOW PROJECTION | I4: Notes
B5: ($mm) | C5: =+'Income Statement'!F6 -> 2027 | D5: =+C5+1 -> 2028 | E5: =+D5+1 -> 2029 | F5: =+E5+1 -> 2030 | G5: =+F5+1 -> 2031
B6: Adjusted EBITDA (D&A minimal) | C6: =+'P&L'!F45 -> 450.62827 | D6: =+'P&L'!G45 -> 577.38483 | E6: =+'P&L'!H45 -> 855.23759 | F6: =+E6 * (1+F7) -> 906.55184 | G6: =+F6 * (1+G7) -> 979.07599
B7: Growth | D7: =+D6/C6-1 -> 0.28128852 | E7: =+E6/D6-1 -> 0.48122628 | F7: 0.06 | G7: 0.08 | I7: 6-8%+ combined annual revenue growth, 2027E-2029; E2029E exit growth rate targeted at 8%+
B8: Less: taxes on EBIT | C8: =+-C6*$C$18 -> -90.125655 | D8: =+-D6*$C$18 -> -115.47697 | E8: =+-E6*$C$18 -> -171.04752 | F8: =+-F6*$C$18 -> -181.31037 | G8: =+-G6*$C$18 -> -195.8152
B9: NOPAT | C9: =+C6+C8 -> 360.50262 | D9: =+D6+D8 -> 461.90787 | E9: =+E6+E8 -> 684.19007 | F9: =+F6+F8 -> 725.24147 | G9: =+G6+G8 -> 783.26079
B10: + D&A | C10: 0 | D10: 0 | E10: 0 | F10: 0 | G10: 0
B11: - Capex | C11: 0 | D11: 0 | E11: 0 | F11: 0 | G11: 0
B12: - Change in net working capital | C12: 0 | D12: 0 | E12: 0 | F12: 0 | G12: 0
B13: Unlevered free cash flow | C13: =+SUM(C9:C12) -> 360.50262 | D13: =+SUM(D9:D12) -> 461.90787 | E13: =+SUM(E9:E12) -> 684.19007 | F13: =+SUM(F9:F12) -> 725.24147 | G13: =+SUM(G9:G12) -> 783.26079
B14: Discount factor | C14: =1 / ((1 + $C$19) ^ (C5-$C$5 +1)) -> 0.90909091 | D14: =1 / ((1 + $C$19) ^ (D5-$C$5 +1)) -> 0.82644628 | E14: =1 / ((1 + $C$19) ^ (E5-$C$5 +1)) -> 0.7513148 | F14: =1 / ((1 + $C$19) ^ (F5-$C$5 +1)) -> 0.68301346 | G14: =1 / ((1 + $C$19) ^ (G5-$C$5 +1)) -> 0.62092132
B15: PV of FCF | C15: =+C13*C14 -> 327.72965 | D15: =+D13*D14 -> 381.74204 | E15: =+E13*E14 -> 514.04213 | F15: =+F13*F14 -> 495.34969 | G15: =+G13*G14 -> 486.34333
B17: DCF ASSUMPTIONS & OUTPUT
B18: Tax rate | C18: 0.2 | I18: Equiniti Announcement: "Medium-term outlook net effective tax rate ~20%"
B19: WACC / discount rate | C19: 0.1
B20: Terminal growth rate | C20: 0.025
B21: Sum of PV of explicit FCFs ($mm) | C21: =+SUM(C15:G15) -> 2205.2068
B22: EBITDA Terminal Multiple | C22: 15
B23: Terminal value ($mm) | C23: =+G6*C22 -> 14686.14
B24: PV of terminal value ($mm) | C24: =+C23*G14 -> 9118.9374
B25: Implied enterprise value ($mm) | C25: =+C21+C24 -> 11324.144
B26: Less: net debt ($mm) | C26: =+-Summary!C26 -> -1553
B27: Implied equity value ($mm) | C27: =+C25+C26 -> 9771.1442
B28: Diluted shares (mm) | C28: =+Summary!C22 -> 212.71835
B29: Implied share price ($) | C29: =+C27/C28 -> 45.934657

Sheet 11. Model vs. Street
B2: Model vs. Street
B3: Where your near-term numbers differ from sell-side consensus is often the actual source of edge for the next print, distinct from the multi-year thesis. State it explicitly.
B5: NEXT QUARTER / NEXT PRINT
B6: Metric | C6: Your estimate | D6: Street consensus | E6: Variance | F6: Why you differ
B7: Revenue | E7: =IFERROR(C7/D7-1,"-") -> - | F7: [the specific data point or logic driving your delta from consensus]
B8: EBITDA | E8: =IFERROR(C8/D8-1,"-") -> - | F8: [the specific data point or logic driving your delta from consensus]
B9: EPS | E9: =IFERROR(C9/D9-1,"-") -> - | F9: [the specific data point or logic driving your delta from consensus]
B10: [Key KPI specific to this name] | E10: =IFERROR(C10/D10-1,"-") -> - | F10: [the specific data point or logic driving your delta from consensus]
B13: CONSENSUS SOURCE & DATE
B14: Source | C14: [Bloomberg / Visible Alpha / company-compiled, as-of date]
B17: Legend: grey italic = placeholder label, replace with your line item. Purple = illustrative EXAMPLE row (delete before use). Blue = input. Black = formula. Green = link to another tab. Yellow fill = key lever / fill-in cell.

Sheet 12. Historical Tracker
B2: Historical Tracker — Model vs. Actual
B3: Log your modeled estimate vs. actual reported results each quarter. This is what lets you show a PM you mark your own thesis to market rather than only ever looking forward.
B5: QUARTERLY TRACKING LOG
B6: Period | C6: Metric | D6: Your estimate (pre-print) | E6: Actual reported | F6: Variance | G6: Thesis status after print
B7: EXAMPLE ROW (illustrative - delete before use)
B8: Q[X] 20XX | C8: Revenue ($mm) | D8: 425 | E8: 441 | F8: =E8/D8-1 -> 0.037647059 | G8: Confirms — beat driven by [specific driver], consistent with thesis
B10: [ ]
B11: [ ]
B12: [ ]
B13: [ ]
B14: [ ]
B15: [ ]
B18: Legend: grey italic = placeholder label, replace with your line item. Purple = illustrative EXAMPLE row (delete before use). Blue = input. Black = formula. Green = link to another tab. Yellow fill = key lever / fill-in cell.
