Workbook

Sheet Guide
B1: PubMatic, Inc. (NASDAQ: PUBM) Financial Model
B2: Quarterly history Q1 2023 to Q2 2026, annual roll-up FY2023 to FY2025, forecast infrastructure Q3 2026 to Q4 2028. All figures in $ thousands unless noted.
B4: HOW TO USE
B5: 1. Go to Drivers | C5: Enter your assumptions in the yellow cells (columns P to Y, Q3 2026 to Q4 2028). They are placeholders today so the model runs; nothing is a recommendation.
B6: 2. Read the statements | C6: Income Statement, Balance Sheet and Cash Flow update automatically. Forecast columns have teal headers; actual columns have navy headers. Annual columns are on the right.
B7: 3. Check the Checks tab | C7: B8 should read ALL CHECKS PASS. The balance sheet balances by construction, and history ties to filings.
B8: 4. Use Summary | C8: One page of annual figures for FY2023A to FY2028E.
B10: COLOR LEGEND
B11: Blue text | C11: Hardcoded input (historical figures from filings, or your forecast assumptions)
B12: Black text | C12: Formula on the same sheet
B13: Green text | C13: Link to another sheet
B14: Yellow fill | C14: Forecast input cell for you to edit (Drivers tab)
B16: TABS
B17: Summary | C17: Annual snapshot FY2023A to FY2028E.
B18: Drivers | C18: All forecast assumptions in one place, with the same metric shown historically for context. Column AH explains how each driver is used.
B19: Income Statement | C19: Quarterly and annual P&L, growth and margin analysis, Adjusted EBITDA reconciliation, SBC and D&A memo lines.
B20: Balance Sheet | C20: Quarter-end balance sheet from Q4 2023, with working capital metrics. Annual columns show year-end balances.
B21: Cash Flow | C21: Full cash flow statement by quarter, derived from year-to-date filings for history, and free cash flow.
B22: CF YTD Inputs | C22: Cash flow statement as filed (year-to-date). Feeds the quarterly Cash Flow tab. Includes tie-out to reported totals.
B23: 10-K Data | C23: FY2023 to FY2025 as reported in the FY2025 10-K. Used to derive Q4 and to tie out annual totals.
B24: Checks | C24: Balance sheet, cash, net income, Adjusted EBITDA and annual tie-outs.
B25: Comps | C25: Q2 2026 and 6M 2026 benchmarking vs Magnite, The Trade Desk, Criteo and AppLovin, with infrastructure intensity and hosting model (owned vs cloud).
B27: FORECAST MECHANICS
B28: Revenue and expenses | C28: Each line = same quarter last year x (1 + YoY growth). This preserves the strong Q4 seasonality without a separate seasonal factor.
B29: Below the line | C29: Interest income = prior quarter cash and securities x yield / 4. Taxes = pretax income x effective rate. EPS = net income / diluted shares.
B30: Balance sheet | C30: AR = days sales outstanding x revenue; AP = days payable outstanding x revenue; accrued liabilities = accrued days x opex (all on days in the quarter). PP&E rolls forward with capex, capitalized software and D&A. Leases, goodwill, deferred taxes and other items are held flat.
B31: Cash flow | C31: Net income + D&A + SBC + working capital changes, less capex and capitalized software, less buybacks, plus option/ESPP proceeds. Cash is the plug that ties the balance sheet.
B32: Adjusted EBITDA | C32: Company definition: net income + SBC + D&A + litigation-related expenses - interest income + income taxes. Other income (expense), including FX, is not added back.
B34: SOURCES
B35: FY2025 Form 10-K | C35: Filed Feb 26, 2026. FY2023 to FY2025 income statement, cash flow, SBC by line, Adjusted EBITDA, 12/31/25 and 12/31/24 balance sheets, impressions processed.
B36: Form 10-Q | C36: Q2 2026 10-Q (filed Aug 6, 2026) also supplies the Q2 26 Adjusted EBITDA reconciliation and litigation add-back.
B37: 8-K earnings releases | C37: Q1, Q2, Q3 2024 (2023 and 2024 quarters and balance sheets), Q1, Q2, Q3 2025 (2025 quarters and balance sheets). Exhibit 99.1 on sec.gov.
B38: Form 10-Q | C38: Q1 2026 (filed May 2026) and Q2 2026 (filed Aug 6, 2026).
B39: Q4 figures | C39: Not filed separately. Q4 = full year (10-K) less the first three quarters, for every income statement, SBC and cash flow line.
B41: KNOWN LIMITATIONS AND FLAGS
B42: Balance sheet history | C42: Quarter-end balance sheets for Q1 to Q3 2023 are not included. History starts at Q4 2023.
B43: Q4 diluted shares | C43: Q4 2023, Q4 2024 and Q4 2025 diluted share counts come from a third-party data provider, not a filing. Q4 EPS is the only line affected. Q4 basic shares are approximated (4 x FY less Q1 to Q3).
B44: Q4 basic shares | C44: Q4 basic share counts are approximated as 4 x FY weighted average less Q1 to Q3, since quarterly figures are not reported separately in the 10-K.
B45: Placeholders | C45: Every yellow driver value is a placeholder, not a forecast recommendation.
B46: Operating items held at zero | C46: Deferred taxes, non-cash lease expense, accretion and lease liability changes are not forecast. Leases are held flat.

Sheet Summary
A1: PubMatic, Inc. (NASDAQ: PUBM): Annual Summary
A2: $ in thousands except per share. FY2026E combines two reported quarters (Q1, Q2) and two forecast quarters. Links to the annual roll-up columns on each statement.
A4: Fiscal year | B4: FY2023A | C4: FY2024A | D4: FY2025A | E4: FY2026E | F4: FY2027E | G4: FY2028E
A5: Status | B5: Actual | C5: Actual | D5: Actual | E5: 2A + 2E | F5: Forecast | G5: Forecast
A7: Income statement
A8: Revenue | B8: ='Income Statement'!AB9 -> 267014 | C8: ='Income Statement'!AC9 -> 291256 | D8: ='Income Statement'!AD9 -> 282926 | E8: ='Income Statement'!AE9 -> 330474.04 | F8: ='Income Statement'!AF9 -> 426616.98 | G8: ='Income Statement'!AG9 -> 529545.56
A9: Growth, YoY % | C9: ='Income Statement'!AC35 -> 0.090789247 | D9: ='Income Statement'!AD35 -> -0.028600269 | E9: ='Income Statement'!AE35 -> 0.16805821 | F9: ='Income Statement'!AF35 -> 0.29092434 | G9: ='Income Statement'!AG35 -> 0.24126696
A10: Gross profit | B10: ='Income Statement'!AB11 -> 167785 | C10: ='Income Statement'!AC11 -> 190229 | D10: ='Income Statement'!AD11 -> 179841 | E10: ='Income Statement'!AE11 -> 209309.37 | F10: ='Income Statement'!AF11 -> 275454.08 | G10: ='Income Statement'!AG11 -> 349301.05
A11: Gross margin % | B11: ='Income Statement'!AB12 -> 0.62837529 | C11: ='Income Statement'!AC12 -> 0.65313333 | D11: ='Income Statement'!AD12 -> 0.63564678 | E11: ='Income Statement'!AE12 -> 0.63336102 | F11: ='Income Statement'!AF12 -> 0.64567069 | G11: ='Income Statement'!AG12 -> 0.65962417
A12: Total operating expenses | B12: ='Income Statement'!AB17 -> 165749 | C12: ='Income Statement'!AC17 -> 186302 | D12: ='Income Statement'!AD17 -> 197100 | E12: ='Income Statement'!AE17 -> 204620.32 | F12: ='Income Statement'!AF17 -> 212469.69 | G12: ='Income Statement'!AG17 -> 220622.98
A13: Operating income (loss) | B13: ='Income Statement'!AB18 -> 2036 | C13: ='Income Statement'!AC18 -> 3927 | D13: ='Income Statement'!AD18 -> -17259 | E13: ='Income Statement'!AE18 -> 4689.0549 | F13: ='Income Statement'!AF18 -> 62984.386 | G13: ='Income Statement'!AG18 -> 128678.07
A14: Operating margin % | B14: ='Income Statement'!AB19 -> 0.0076250683 | C14: ='Income Statement'!AC19 -> 0.013482984 | D14: ='Income Statement'!AD19 -> -0.061001817 | E14: ='Income Statement'!AE19 -> 0.014188875 | F14: ='Income Statement'!AF19 -> 0.14763685 | G14: ='Income Statement'!AG19 -> 0.24299717
A15: Net income (loss) | B15: ='Income Statement'!AB27 -> 8881 | C15: ='Income Statement'!AC27 -> 12504 | D15: ='Income Statement'!AD27 -> -14462 | E15: ='Income Statement'!AE27 -> 3347.4791 | F15: ='Income Statement'!AF27 -> 54328.641 | G15: ='Income Statement'!AG27 -> 109146.42
A16: EPS, GAAP diluted ($) | B16: ='Income Statement'!AB32 -> 0.15851286 | C16: ='Income Statement'!AC32 -> 0.23030169 | D16: ='Income Statement'!AD32 -> -0.30764976 | E16: ='Income Statement'!AE32 -> 0.072206972 | F16: ='Income Statement'!AF32 -> 1.1783421 | G16: ='Income Statement'!AG32 -> 2.3672933
A17: Non-GAAP and cash flow
A18: Adjusted EBITDA | B18: ='Income Statement'!AB51 -> 75309 | C18: ='Income Statement'!AC51 -> 92325 | D18: ='Income Statement'!AD51 -> 61640 | E18: ='Income Statement'!AE51 -> 86075.854 | F18: ='Income Statement'!AF51 -> 163239.38 | G18: ='Income Statement'!AG51 -> 253121.28
A19: Adjusted EBITDA margin % | B19: ='Income Statement'!AB52 -> 0.28204139 | C19: ='Income Statement'!AC52 -> 0.31698918 | D19: ='Income Statement'!AD52 -> 0.21786616 | E19: ='Income Statement'!AE52 -> 0.26046177 | F19: ='Income Statement'!AF52 -> 0.38263685 | G19: ='Income Statement'!AG52 -> 0.47799717
A20: Stock-based compensation | B20: ='Income Statement'!AB59 -> 28862 | C20: ='Income Statement'!AC59 -> 37676 | D20: ='Income Statement'!AD59 -> 38378 | E20: ='Income Statement'!AE59 -> 37659.544 | F20: ='Income Statement'!AF59 -> 46927.868 | G20: ='Income Statement'!AG59 -> 58250.011
A21: Depreciation and amortization | B21: ='Income Statement'!AB62 -> 44770 | C21: ='Income Statement'!AC62 -> 45352 | D21: ='Income Statement'!AD62 -> 43769 | E21: ='Income Statement'!AE62 -> 43659.255 | F21: ='Income Statement'!AF62 -> 53327.122 | G21: ='Income Statement'!AG62 -> 66193.195
A22: Net cash from operating activities | B22: ='Cash Flow'!AA23 -> 81121 | C22: ='Cash Flow'!AB23 -> 73425 | D22: ='Cash Flow'!AC23 -> 81059 | E22: ='Cash Flow'!AD23 -> 76321.101 | F22: ='Cash Flow'!AE23 -> 151152.96 | G22: ='Cash Flow'!AF23 -> 229315.7
A23: Free cash flow | B23: ='Cash Flow'!AA50 -> 52833 | C23: ='Cash Flow'!AB50 -> 34897 | D23: ='Cash Flow'!AC50 -> 46203 | E23: ='Cash Flow'!AD50 -> 46184.101 | F23: ='Cash Flow'!AE50 -> 117152.96 | G23: ='Cash Flow'!AF50 -> 195315.7
A24: Free cash flow margin % | B24: ='Cash Flow'!AA51 -> 0.19786603 | C24: ='Cash Flow'!AB51 -> 0.11981556 | D24: ='Cash Flow'!AC51 -> 0.16330419 | E24: ='Cash Flow'!AD51 -> 0.13975107 | F24: ='Cash Flow'!AE51 -> 0.27460924 | G24: ='Cash Flow'!AF51 -> 0.36883645
A25: Share repurchases (cash outflow) | B25: ='Cash Flow'!AA40 -> -59268 | C25: ='Cash Flow'!AB40 -> -75332 | D25: ='Cash Flow'!AC40 -> -46498 | E25: ='Cash Flow'!AD40 -> -50500 | F25: ='Cash Flow'!AE40 -> -40000 | G25: ='Cash Flow'!AF40 -> -40000
A26: Balance sheet (year-end)
A27: Cash and marketable securities | B27: ='Balance Sheet'!AB45 -> 175344 | C27: ='Balance Sheet'!AC45 -> 140587 | D27: ='Balance Sheet'!AD45 -> 145518 | E27: ='Balance Sheet'!AE45 -> 141323.1 | F27: ='Balance Sheet'!AF45 -> 222476.06 | G27: ='Balance Sheet'!AG45 -> 381791.77
A28: Accounts receivable, net | B28: ='Balance Sheet'!AB11 -> 375468 | C28: ='Balance Sheet'!AC11 -> 424814 | D28: ='Balance Sheet'!AD11 -> 358240 | E28: ='Balance Sheet'!AE11 -> 448506.54 | F28: ='Balance Sheet'!AF11 -> 559598.03 | G28: ='Balance Sheet'!AG11 -> 692744.28
A29: Accounts payable | B29: ='Balance Sheet'!AB23 -> 347673 | C29: ='Balance Sheet'!AC23 -> 386602 | D29: ='Balance Sheet'!AD23 -> 343619 | E29: ='Balance Sheet'!AE23 -> 430553.23 | F29: ='Balance Sheet'!AF23 -> 537197.82 | G29: ='Balance Sheet'!AG23 -> 665014.34
A30: Total stockholders' equity | B30: ='Balance Sheet'!AB35 -> 296199 | C30: ='Balance Sheet'!AC35 -> 277263 | D30: ='Balance Sheet'!AD35 -> 262589 | E30: ='Balance Sheet'!AE35 -> 258612.02 | F30: ='Balance Sheet'!AF35 -> 323868.53 | G30: ='Balance Sheet'!AG35 -> 455264.97

Sheet Drivers
A1: Drivers: forecast assumptions
A2: Yellow cells with blue text are your forecast inputs (Q3 2026 to Q4 2028). All values are PLACEHOLDERS to keep the model running; replace them with your own view. History (black) shows the same metric for reference.
A4: Period | B4: Q1'23 | C4: Q2'23 | D4: Q3'23 | E4: Q4'23 | F4: Q1'24 | G4: Q2'24 | H4: Q3'24 | I4: Q4'24 | J4: Q1'25 | K4: Q2'25 | L4: Q3'25 | M4: Q4'25 | N4: Q1'26 | O4: Q2'26 | P4: Q3'26 | Q4: Q4'26 | R4: Q1'27 | S4: Q2'27 | T4: Q3'27 | U4: Q4'27 | V4: Q1'28 | W4: Q2'28 | X4: Q3'28 | Y4: Q4'28 | AA4: FY2023A | AB4: FY2024A | AC4: FY2025A | AD4: FY2026E | AE4: FY2027E | AF4: FY2028E | AH4: How this driver is used
A5: Period end | B5: 45016 | C5: 45107 | D5: 45199 | E5: 45291 | F5: 45382 | G5: 45473 | H5: 45565 | I5: 45657 | J5: 45747 | K5: 45838 | L5: 45930 | M5: 46022 | N5: 46112 | O5: 46203 | P5: 46295 | Q5: 46387 | R5: 46477 | S5: 46568 | T5: 46660 | U5: 46752 | V5: 46843 | W5: 46934 | X5: 47026 | Y5: 47118 | AA5: 45291 | AB5: 45657 | AC5: 46022 | AD5: 46387 | AE5: 46752 | AF5: 47118
A6: Status | B6: Actual | C6: Actual | D6: Actual | E6: Actual | F6: Actual | G6: Actual | H6: Actual | I6: Actual | J6: Actual | K6: Actual | L6: Actual | M6: Actual | N6: Actual | O6: Actual | P6: Forecast | Q6: Forecast | R6: Forecast | S6: Forecast | T6: Forecast | U6: Forecast | V6: Forecast | W6: Forecast | X6: Forecast | Y6: Forecast | AA6: Actual | AB6: Actual | AC6: Actual | AD6: 2A + 2E | AE6: Forecast | AF6: Forecast
A8: Revenue and expense growth (forecast: enter YoY growth vs the same quarter last year)
A9: Revenue growth, YoY % | F9: ='Income Statement'!G9/'Income Statement'!C9-1 -> 0.20383706 | G9: ='Income Statement'!H9/'Income Statement'!D9-1 -> 0.06216643 | H9: ='Income Statement'!I9/'Income Statement'!E9-1 -> 0.12734582 | I9: ='Income Statement'!J9/'Income Statement'!F9-1 -> 0.010661939 | J9: ='Income Statement'!K9/'Income Statement'!G9-1 -> -0.043117794 | K9: ='Income Statement'!L9/'Income Statement'!H9-1 -> 0.056907548 | L9: ='Income Statement'!M9/'Income Statement'!I9-1 -> -0.0532973 | M9: ='Income Statement'!N9/'Income Statement'!J9-1 -> -0.063811373 | ... O9: ='Income Statement'!P9/'Income Statement'!L9-1 -> 0.10546452 | P9: 0.1 | Q9: 0.1 | R9: 0.1 | S9: 0.1 | T9: 0.1 | U9: 0.1 | V9: 0.1 | W9: 0.1 | X9: 0.1 | Y9: 0.1 | AB9: ='Income Statement'!AC35 -> 0.090789247 | AC9: ='Income Statement'!AD35 -> -0.028600269 | AD9: ='Income Statement'!AE35 -> 0.16805821 | AE9: ='Income Statement'!AF35 -> 0.29092434 | AF9: ='Income Statement'!AG35 -> 0.24126696 | AH9: Forecast revenue = same quarter last year x (1 + growth). This keeps seasonality (Q4 is the peak quarter). Recent actuals: Q1 26 -2%, Q2 26 +11%. Placeholder 10%.
A10: Cost of revenue growth, YoY % | F10: ='Income Statement'!G10/'Income Statement'!C10-1 -> 0.065415078 | G10: ='Income Statement'!H10/'Income Statement'!D10-1 -> 0.003710057 | H10: ='Income Statement'!I10/'Income Statement'!E10-1 -> -0.02234487 | I10: ='Income Statement'!J10/'Income Statement'!F10-1 -> 0.030031395 | J10: ='Income Statement'!K10/'Income Statement'!G10-1 -> 0.0064505979 | K10: ='Income Statement'!L10/'Income Statement'!H10-1 -> 0.057710652 | L10: ='Income Statement'!M10/'Income Statement'!I10-1 -> -0.0041163557 | M10: ='Income Statement'!N10/'Income Statement'!J10-1 -> 0.021937036 | ... O10: ='Income Statement'!P10/'Income Statement'!L10-1 -> -0.027619119 | P10: 0.03 | Q10: 0.03 | R10: 0.03 | S10: 0.03 | T10: 0.03 | U10: 0.03 | V10: 0.03 | W10: 0.03 | X10: 0.03 | Y10: 0.03 | AB10: ='Income Statement'!AC10/'Income Statement'!AB10-1 -> 0.018119703 | AC10: ='Income Statement'!AD10/'Income Statement'!AC10-1 -> 0.020370792 | AD10: ='Income Statement'!AE10/'Income Statement'!AD10-1 -> 0.17538597 | AE10: ='Income Statement'!AF10/'Income Statement'!AE10-1 -> 0.24758238 | AF10: ='Income Statement'!AG10/'Income Statement'!AF10-1 -> 0.19238592 | AH10: Cost of revenue is largely fixed (data centers, D&A of platform). Modeled as YoY growth rather than % of revenue. Placeholder 3%.
A11: Technology and development growth, YoY % | F11: ='Income Statement'!G14/'Income Statement'!C14-1 -> 0.2214209 | G11: ='Income Statement'!H14/'Income Statement'!D14-1 -> 0.28662704 | H11: ='Income Statement'!I14/'Income Statement'!E14-1 -> 0.32845945 | I11: ='Income Statement'!J14/'Income Statement'!F14-1 -> 0.14387964 | J11: ='Income Statement'!K14/'Income Statement'!G14-1 -> 0.10201005 | K11: ='Income Statement'!L14/'Income Statement'!H14-1 -> 0.052777457 | L11: ='Income Statement'!M14/'Income Statement'!I14-1 -> 0.091115398 | M11: ='Income Statement'!N14/'Income Statement'!J14-1 -> -0.19346188 | ... O11: ='Income Statement'!P14/'Income Statement'!L14-1 -> 0.0035103115 | P11: 0.03 | Q11: 0.03 | R11: 0.03 | S11: 0.03 | T11: 0.03 | U11: 0.03 | V11: 0.03 | W11: 0.03 | X11: 0.03 | Y11: 0.03 | AB11: ='Income Statement'!AC14/'Income Statement'!AB14-1 -> 0.24454671 | AC11: ='Income Statement'!AD14/'Income Statement'!AC14-1 -> 0.016745333 | AD11: ='Income Statement'!AE14/'Income Statement'!AD14-1 -> -0.0081620343 | AE11: ='Income Statement'!AF14/'Income Statement'!AE14-1 -> 0.03 | AF11: ='Income Statement'!AG14/'Income Statement'!AF14-1 -> 0.03 | AH11: Same-quarter YoY growth. Placeholder 3%.
A12: Sales and marketing growth, YoY % | F12: ='Income Statement'!G15/'Income Statement'!C15-1 -> 0.072988282 | G12: ='Income Statement'!H15/'Income Statement'!D15-1 -> 0.16582534 | H12: ='Income Statement'!I15/'Income Statement'!E15-1 -> 0.21436991 | I12: ='Income Statement'!J15/'Income Statement'!F15-1 -> 0.16754287 | J12: ='Income Statement'!K15/'Income Statement'!G15-1 -> 0.079951642 | K12: ='Income Statement'!L15/'Income Statement'!H15-1 -> 0.09114527 | L12: ='Income Statement'!M15/'Income Statement'!I15-1 -> 0.085921675 | M12: ='Income Statement'!N15/'Income Statement'!J15-1 -> 0.060850903 | ... O12: ='Income Statement'!P15/'Income Statement'!L15-1 -> 0.036904762 | P12: 0.04 | Q12: 0.04 | R12: 0.04 | S12: 0.04 | T12: 0.04 | U12: 0.04 | V12: 0.04 | W12: 0.04 | X12: 0.04 | Y12: 0.04 | AB12: ='Income Statement'!AC15/'Income Statement'!AB15-1 -> 0.15175779 | AC12: ='Income Statement'!AD15/'Income Statement'!AC15-1 -> 0.079386383 | AD12: ='Income Statement'!AE15/'Income Statement'!AD15-1 -> 0.049870216 | AE12: ='Income Statement'!AF15/'Income Statement'!AE15-1 -> 0.04 | AF12: ='Income Statement'!AG15/'Income Statement'!AF15-1 -> 0.04 | AH12: Same-quarter YoY growth. Placeholder 4%.
A13: General and administrative growth, YoY % | F13: ='Income Statement'!G16/'Income Statement'!C16-1 -> 0.11573338 | G13: ='Income Statement'!H16/'Income Statement'!D16-1 -> -0.23964575 | H13: ='Income Statement'!I16/'Income Statement'!E16-1 -> 0.26011657 | I13: ='Income Statement'!J16/'Income Statement'!F16-1 -> 0.10884194 | J13: ='Income Statement'!K16/'Income Statement'!G16-1 -> 0.038639766 | K13: ='Income Statement'!L16/'Income Statement'!H16-1 -> 0.089970707 | L13: ='Income Statement'!M16/'Income Statement'!I16-1 -> 0.032641734 | M13: ='Income Statement'!N16/'Income Statement'!J16-1 -> 0.024274928 | ... O13: ='Income Statement'!P16/'Income Statement'!L16-1 -> 0.078768876 | P13: 0.04 | Q13: 0.04 | R13: 0.04 | S13: 0.04 | T13: 0.04 | U13: 0.04 | V13: 0.04 | W13: 0.04 | X13: 0.04 | Y13: 0.04 | AB13: ='Income Statement'!AC16/'Income Statement'!AB16-1 -> 0.02580978 | AC13: ='Income Statement'!AD16/'Income Statement'!AC16-1 -> 0.046297902 | AD13: ='Income Statement'!AE16/'Income Statement'!AD16-1 -> 0.044128605 | AE13: ='Income Statement'!AF16/'Income Statement'!AE16-1 -> 0.04 | AF13: ='Income Statement'!AG16/'Income Statement'!AF16-1 -> 0.04 | AH13: Same-quarter YoY growth. Placeholder 4%.
A15: Non-cash items, other income and taxes
A16: Depreciation and amortization, % of revenue | B16: ='Income Statement'!C62/'Income Statement'!C9 -> 0.20632772 | C16: ='Income Statement'!D62/'Income Statement'!D9 -> 0.17208274 | D16: ='Income Statement'!E62/'Income Statement'!E9 -> 0.17904424 | E16: ='Income Statement'!F62/'Income Statement'!F9 -> 0.13048463 | F16: ='Income Statement'!G62/'Income Statement'!G9 -> 0.16809343 | G16: ='Income Statement'!H62/'Income Statement'!H9 -> 0.16852246 | H16: ='Income Statement'!I62/'Income Statement'!I9 -> 0.15856852 | I16: ='Income Statement'!J62/'Income Statement'!J9 -> 0.13357582 | ... O16: ='Income Statement'!P62/'Income Statement'!P9 -> 0.12732686 | P16: 0.125 | Q16: 0.125 | R16: 0.125 | S16: 0.125 | T16: 0.125 | U16: 0.125 | V16: 0.125 | W16: 0.125 | X16: 0.125 | Y16: 0.125 | AA16: ='Income Statement'!AB62/'Income Statement'!AB9 -> 0.16766911 | AB16: ='Income Statement'!AC62/'Income Statement'!AC9 -> 0.15571181 | AC16: ='Income Statement'!AD62/'Income Statement'!AD9 -> 0.15470123 | AD16: ='Income Statement'!AE62/'Income Statement'!AE9 -> 0.132111 | AE16: ='Income Statement'!AF62/'Income Statement'!AF9 -> 0.125 | AF16: ='Income Statement'!AG62/'Income Statement'!AG9 -> 0.125 | AH16: Total D&A (embedded in cost of revenue and opex) as % of revenue. Feeds Adjusted EBITDA, cash flow and PP&E roll-forward. Q2 26 actual 12.7%. Placeholder 12.5%.
A17: Stock-based compensation, % of revenue | B17: ='Income Statement'!C59/'Income Statement'!C9 -> 0.12740267 | C17: ='Income Statement'!D59/'Income Statement'!D9 -> 0.11473235 | D17: ='Income Statement'!E59/'Income Statement'!E9 -> 0.11307065 | E17: ='Income Statement'!F59/'Income Statement'!F9 -> 0.086725768 | F17: ='Income Statement'!G59/'Income Statement'!G9 -> 0.13659465 | G17: ='Income Statement'!H59/'Income Statement'!H9 -> 0.1441866 | H17: ='Income Statement'!I59/'Income Statement'!I9 -> 0.13173878 | I17: ='Income Statement'!J59/'Income Statement'!J9 -> 0.11004421 | ... O17: ='Income Statement'!P59/'Income Statement'!P9 -> 0.10620539 | P17: 0.11 | Q17: 0.11 | R17: 0.11 | S17: 0.11 | T17: 0.11 | U17: 0.11 | V17: 0.11 | W17: 0.11 | X17: 0.11 | Y17: 0.11 | AA17: ='Income Statement'!AB59/'Income Statement'!AB9 -> 0.10809171 | AB17: ='Income Statement'!AC59/'Income Statement'!AC9 -> 0.12935699 | AC17: ='Income Statement'!AD59/'Income Statement'!AD9 -> 0.13564678 | AD17: ='Income Statement'!AE59/'Income Statement'!AE9 -> 0.11395614 | AE17: ='Income Statement'!AF59/'Income Statement'!AF9 -> 0.11 | AF17: ='Income Statement'!AG59/'Income Statement'!AG9 -> 0.11 | AH17: Total SBC as % of revenue. Feeds Adjusted EBITDA, cash flow and APIC. Q2 26 actual 10.6%. Placeholder 11%.
A18: Litigation-related add-back to Adjusted EBITDA ($000s) | B18: ='Income Statement'!C48 -> 0 | C18: ='Income Statement'!D48 -> 0 | D18: ='Income Statement'!E48 -> 0 | E18: ='Income Statement'!F48 -> 0 | F18: ='Income Statement'!G48 -> 0 | G18: ='Income Statement'!H48 -> 0 | H18: ='Income Statement'!I48 -> 0 | I18: ='Income Statement'!J48 -> 0 | ... O18: ='Income Statement'!P48 -> 594 | P18: 0 | Q18: 0 | R18: 0 | S18: 0 | T18: 0 | U18: 0 | V18: 0 | W18: 0 | X18: 0 | Y18: 0 | AA18: =SUM(B18:E18) -> 0 | AB18: =SUM(F18:I18) -> 0 | AC18: =SUM(J18:M18) -> 902 | AD18: =SUM(N18:Q18) -> 1032 | AE18: =SUM(R18:U18) -> 0 | AF18: =SUM(V18:Y18) -> 0 | AH18: Litigation-related expenses added back in company-defined Adjusted EBITDA. Placeholder 0.
A19: Interest yield on prior-quarter cash + securities (annualized %) | F19: ='Income Statement'!G21*4/('Balance Sheet'!F9+'Balance Sheet'!F10) -> 0.058490738 | G19: ='Income Statement'!H21*4/('Balance Sheet'!G9+'Balance Sheet'!G10) -> 0.053768073 | H19: ='Income Statement'!I21*4/('Balance Sheet'!H9+'Balance Sheet'!H10) -> 0.047561535 | I19: ='Income Statement'!J21*4/('Balance Sheet'!I9+'Balance Sheet'!I10) -> 0.045705493 | J19: ='Income Statement'!K21*4/('Balance Sheet'!J9+'Balance Sheet'!J10) -> 0.045324248 | K19: ='Income Statement'!L21*4/('Balance Sheet'!K9+'Balance Sheet'!K10) -> 0.038272067 | L19: ='Income Statement'!M21*4/('Balance Sheet'!L9+'Balance Sheet'!L10) -> 0.04076043 | M19: ='Income Statement'!N21*4/('Balance Sheet'!M9+'Balance Sheet'!M10) -> 0.037642441 | ... O19: ='Income Statement'!P21*4/('Balance Sheet'!O9+'Balance Sheet'!O10) -> 0.033490709 | P19: 0.033 | Q19: 0.033 | R19: 0.033 | S19: 0.033 | T19: 0.033 | U19: 0.033 | V19: 0.033 | W19: 0.033 | X19: 0.033 | Y19: 0.033 | AH19: Interest income = prior quarter-end (cash + marketable securities) x yield / 4. Uses prior period balance to avoid circularity. Q2 26 actual about 3.3%.
A20: Other income (expense), net ($000s) | B20: ='Income Statement'!C22 -> -465 | C20: ='Income Statement'!D22 -> -221 | D20: ='Income Statement'!E22 -> 210 | E20: ='Income Statement'!F22 -> 117 | F20: ='Income Statement'!G22 -> 258 | G20: ='Income Statement'!H22 -> 4028 | H20: ='Income Statement'!I22 -> -930 | I20: ='Income Statement'!J22 -> 2014 | ... O20: ='Income Statement'!P22 -> 89 | P20: 0 | Q20: 0 | R20: 0 | S20: 0 | T20: 0 | U20: 0 | V20: 0 | W20: 0 | X20: 0 | Y20: 0 | AA20: =SUM(B20:E20) -> -359 | AB20: =SUM(F20:I20) -> 5370 | AC20: =SUM(J20:M20) -> -4150 | AD20: =SUM(N20:Q20) -> -964 | AE20: =SUM(R20:U20) -> 0 | AF20: =SUM(V20:Y20) -> 0 | AH20: Other income (expense), mainly FX. Placeholder 0.
A21: Effective tax rate % | B21: ='Income Statement'!C26 -> 0.36502271 | C21: ='Income Statement'!D26 -> -0.10523267 | D21: ='Income Statement'!E26 -> 0.058885942 | E21: ='Income Statement'!F26 -> 0.18845737 | F21: ='Income Statement'!G26 -> 0.092119867 | G21: ='Income Statement'!H26 -> 0.17289131 | H21: ='Income Statement'!I26 -> -1.797546 | I21: ='Income Statement'!J26 -> 0.24543974 | ... O21: ='Income Statement'!P26 -> 1.6390218 | P21: 0.21 | Q21: 0.21 | R21: 0.21 | S21: 0.21 | T21: 0.21 | U21: 0.21 | V21: 0.21 | W21: 0.21 | X21: 0.21 | Y21: 0.21 | AA21: ='Income Statement'!AB26 -> 0.15459305 | AB21: ='Income Statement'!AC26 -> 0.29650051 | AC21: ='Income Statement'!AD26 -> 0.093518867 | AD21: ='Income Statement'!AE26 -> 0.5997886 | AE21: ='Income Statement'!AF26 -> 0.21 | AF21: ='Income Statement'!AG26 -> 0.21 | AH21: Tax provision = pretax income x rate. Reported quarterly rates are volatile (Q2 26 was 164% on small pretax income). Placeholder 21%.
A22: Weighted-average diluted shares (000s) | B22: ='Income Statement'!C31 -> 52740 | C22: ='Income Statement'!D31 -> 52029 | D22: ='Income Statement'!E31 -> 55979 | E22: ='Income Statement'!F31 -> 54940 | F22: ='Income Statement'!G31 -> 50039 | G22: ='Income Statement'!H31 -> 55577 | H22: ='Income Statement'!I31 -> 49056 | I22: ='Income Statement'!J31 -> 52620 | ... O22: ='Income Statement'!P31 -> 46106 | P22: 46106 | Q22: 46106 | R22: 46106 | S22: 46106 | T22: 46106 | U22: 46106 | V22: 46106 | W22: 46106 | X22: 46106 | Y22: 46106 | AH22: Weighted-average diluted shares used for forecast EPS. Placeholder holds Q2 26 flat; lower it to reflect buybacks.
A24: Working capital and balance sheet
A25: Days sales outstanding (AR / quarterly revenue x days) | E25: ='Balance Sheet'!F41 -> 408.31035 | F25: ='Balance Sheet'!G41 -> 413.76957 | G25: ='Balance Sheet'!H41 -> 475.63318 | H25: ='Balance Sheet'!I41 -> 482.88914 | I25: ='Balance Sheet'!J41 -> 457.09911 | J25: ='Balance Sheet'!K41 -> 492.30035 | K25: ='Balance Sheet'!L41 -> 490.74721 | L25: ='Balance Sheet'!M41 -> 490.85303 | ... O25: ='Balance Sheet'!P41 -> 443.68999 | P25: 491.3 | Q25: 412.2 | R25: 484.2 | S25: 444.1 | T25: 491.3 | U25: 412.2 | V25: 489.6 | W25: 444.1 | X25: 491.3 | Y25: 412.2 | AH25: Accounts receivable = DSO / days in quarter x quarterly revenue. AR reflects gross billings while revenue is net, so DSO is well above a typical 30-90 days. Placeholder = same quarter last year (seasonal).
A26: Days payable outstanding (AP / quarterly revenue x days) | E26: ='Balance Sheet'!F42 -> 378.08411 | F26: ='Balance Sheet'!G42 -> 394.52206 | G26: ='Balance Sheet'!H42 -> 461.03086 | H26: ='Balance Sheet'!I42 -> 462.26328 | I26: ='Balance Sheet'!J42 -> 415.98306 | J26: ='Balance Sheet'!K42 -> 456.32573 | K26: ='Balance Sheet'!L42 -> 462.54419 | L26: ='Balance Sheet'!M42 -> 482.56545 | ... O26: ='Balance Sheet'!P42 -> 451.6202 | P26: 481.5 | Q26: 395.7 | R26: 493.9 | S26: 453 | T26: 481.5 | U26: 395.7 | V26: 499.4 | W26: 453 | X26: 481.5 | Y26: 395.7 | AH26: Accounts payable (mostly publisher payables) = DPO / days in quarter x quarterly revenue. Measured on net revenue so it is directly comparable to DSO (DSO less DPO = net float). Placeholder = same quarter last year.
A27: Prepaid expenses and other current assets ($000s) | E27: ='Balance Sheet'!F12 -> 11143 | F27: ='Balance Sheet'!G12 -> 11540 | G27: ='Balance Sheet'!H12 -> 14788 | H27: ='Balance Sheet'!I12 -> 12640 | I27: ='Balance Sheet'!J12 -> 10145 | J27: ='Balance Sheet'!K12 -> 12018 | K27: ='Balance Sheet'!L12 -> 11994 | L27: ='Balance Sheet'!M12 -> 21307 | ... O27: ='Balance Sheet'!P12 -> 17162 | P27: 17162 | Q27: 17162 | R27: 17162 | S27: 17162 | T27: 17162 | U27: 17162 | V27: 17162 | W27: 17162 | X27: 17162 | Y27: 17162 | AH27: Balance held flat at Q2 26 level. Overwrite with your own balance.
A28: Accrued liabilities days (accrued / quarterly opex x days) | E28: ='Balance Sheet'!F44 -> 59.10423 | F28: ='Balance Sheet'!G44 -> 38.426413 | G28: ='Balance Sheet'!H44 -> 44.520741 | H28: ='Balance Sheet'!I44 -> 49.621644 | I28: ='Balance Sheet'!J44 -> 53.000765 | J28: ='Balance Sheet'!K44 -> 36.454128 | K28: ='Balance Sheet'!L44 -> 38.23188 | L28: ='Balance Sheet'!M44 -> 46.232815 | ... O28: ='Balance Sheet'!P44 -> 42.291079 | P28: 46 | Q28: 50.6 | R28: 32.4 | S28: 41.9 | T28: 46 | U28: 50.6 | V28: 32.8 | W28: 41.9 | X28: 46 | Y28: 50.6 | AH28: Accrued liabilities = accrued days / days in quarter x quarterly operating expenses (includes seasonal bonus accruals). Placeholder = same quarter last year.
A29: Marketable securities balance ($000s) | E29: ='Balance Sheet'!F10 -> 96835 | F29: ='Balance Sheet'!G10 -> 93887 | G29: ='Balance Sheet'!H10 -> 92075 | H29: ='Balance Sheet'!I10 -> 61463 | I29: ='Balance Sheet'!J10 -> 40135 | J29: ='Balance Sheet'!K10 -> 42315 | K29: ='Balance Sheet'!L10 -> 27089 | L29: ='Balance Sheet'!M10 -> 0 | ... O29: ='Balance Sheet'!P10 -> 17536 | P29: 17536 | Q29: 17536 | R29: 17536 | S29: 17536 | T29: 17536 | U29: 17536 | V29: 17536 | W29: 17536 | X29: 17536 | Y29: 17536 | AH29: Marketable securities balance held flat. Changes flow through investing cash flow.
A31: Capital expenditures and capital allocation ($000s, enter as positive numbers)
A32: Purchases of property and equipment | B32: =-'Cash Flow'!B26 -> 1417 | C32: =-'Cash Flow'!C26 -> 1135 | D32: =-'Cash Flow'!D26 -> 2872 | E32: =-'Cash Flow'!E26 -> 5177 | F32: =-'Cash Flow'!F26 -> 801 | G32: =-'Cash Flow'!G26 -> 736 | H32: =-'Cash Flow'!H26 -> 11731 | I32: =-'Cash Flow'!I26 -> 4324 | ... O32: =-'Cash Flow'!O26 -> 2955 | P32: 3500 | Q32: 3500 | R32: 3500 | S32: 3500 | T32: 3500 | U32: 3500 | V32: 3500 | W32: 3500 | X32: 3500 | Y32: 3500 | AA32: =SUM(B32:E32) -> 10601 | AB32: =SUM(F32:I32) -> 17592 | AC32: =SUM(J32:M32) -> 14345 | AD32: =SUM(N32:Q32) -> 9966 | AE32: =SUM(R32:U32) -> 14000 | AF32: =SUM(V32:Y32) -> 14000 | AH32: Cash purchases of PP&E. Q1 26 and Q2 26 actuals were $0.0M and $3.0M. Placeholder $3.5M per quarter.
A33: Capitalized software development costs | B33: =-'Cash Flow'!B27 -> 6001 | C33: =-'Cash Flow'!C27 -> 3918 | D33: =-'Cash Flow'!D27 -> 3806 | E33: =-'Cash Flow'!E27 -> 3962 | F33: =-'Cash Flow'!F27 -> 7231 | G33: =-'Cash Flow'!G27 -> 4295 | H33: =-'Cash Flow'!H27 -> 4542 | I33: =-'Cash Flow'!I27 -> 4868 | ... O33: =-'Cash Flow'!O27 -> 3592 | P33: 5000 | Q33: 5000 | R33: 5000 | S33: 5000 | T33: 5000 | U33: 5000 | V33: 5000 | W33: 5000 | X33: 5000 | Y33: 5000 | AA33: =SUM(B33:E33) -> 17687 | AB33: =SUM(F33:I33) -> 20936 | AC33: =SUM(J33:M33) -> 20511 | AD33: =SUM(N33:Q33) -> 20171 | AE33: =SUM(R33:U33) -> 20000 | AF33: =SUM(V33:Y33) -> 20000 | AH33: Cash capitalized internal-use software. Recent run rate about $5M per quarter. Placeholder $5.0M.
A34: Amortization of acquisition-related intangibles (included in D&A) | P34: 395 | Q34: 395 | R34: 281 | S34: 281 | T34: 281 | U34: 281 | V34: 0 | W34: 0 | X34: 0 | Y34: 0 | AD34: =SUM(N34:Q34) -> 790 | AE34: =SUM(R34:U34) -> 1124 | AF34: =SUM(V34:Y34) -> 0 | AH34: Intangible amortization per the Q2 26 10-Q schedule: $790K for the rest of 2026, $1,124K in 2027, then nil. Included in total D&A.
A35: Share repurchases | B35: =-'Cash Flow'!B40 -> 7898 | C35: =-'Cash Flow'!C40 -> 15582 | D35: =-'Cash Flow'!D40 -> 17999 | E35: =-'Cash Flow'!E40 -> 17789 | F35: =-'Cash Flow'!F40 -> 17500 | G35: =-'Cash Flow'!G40 -> 18368 | H35: =-'Cash Flow'!H40 -> 29532 | I35: =-'Cash Flow'!I40 -> 9932 | ... O35: =-'Cash Flow'!O40 -> 22000 | P35: 10000 | Q35: 10000 | R35: 10000 | S35: 10000 | T35: 10000 | U35: 10000 | V35: 10000 | W35: 10000 | X35: 10000 | Y35: 10000 | AA35: =SUM(B35:E35) -> 59268 | AB35: =SUM(F35:I35) -> 75332 | AC35: =SUM(J35:M35) -> 46498 | AD35: =SUM(N35:Q35) -> 50500 | AE35: =SUM(R35:U35) -> 40000 | AF35: =SUM(V35:Y35) -> 40000 | AH35: Cash spent on repurchases. $63.6M of authorization remained at 6/30/26 and the program expires 12/31/26 unless extended. Placeholder $10M per quarter assumes an extension.
A36: Proceeds from option exercises and ESPP | B36: ='Cash Flow'!B38+'Cash Flow'!B37 -> 314 | C36: ='Cash Flow'!C38+'Cash Flow'!C37 -> 1594 | D36: ='Cash Flow'!D38+'Cash Flow'!D37 -> 273 | E36: ='Cash Flow'!E38+'Cash Flow'!E37 -> 1237 | F36: ='Cash Flow'!F38+'Cash Flow'!F37 -> 939 | G36: ='Cash Flow'!G38+'Cash Flow'!G37 -> 1786 | H36: ='Cash Flow'!H38+'Cash Flow'!H37 -> 304 | I36: ='Cash Flow'!I38+'Cash Flow'!I37 -> 1104 | ... O36: ='Cash Flow'!O38+'Cash Flow'!O37 -> 1461 | P36: 1000 | Q36: 1000 | R36: 1000 | S36: 1000 | T36: 1000 | U36: 1000 | V36: 1000 | W36: 1000 | X36: 1000 | Y36: 1000 | AA36: =SUM(B36:E36) -> 3418 | AB36: =SUM(F36:I36) -> 4133 | AC36: =SUM(J36:M36) -> 3907 | AD36: =SUM(N36:Q36) -> 3938 | AE36: =SUM(R36:U36) -> 4000 | AF36: =SUM(V36:Y36) -> 4000 | AH36: Proceeds from option exercises and ESPP. H1 26 actual about $1.9M. Placeholder $1M per quarter.
A38: Revenue Drivers
A39: Impressions processed (trillions) | F39: 57.9 | G39: 60.7 | H39: 69.8 | I39: 74.7 | J39: 74.7 | K39: 77.7 | L39: 86.8 | M39: 97.6 | N39: 94 | O39: 92 | P39: =+L39*(1+P40) -> 109.40767 | Q39: =+M39*(1+Q40) -> 122.7664 | R39: =+N39*(1+R40) -> 117.99575 | S39: =+O39*(1+S40) -> 115.25035 | T39: =+P39*(1+T40) -> 136.7808 | U39: =+Q39*(1+U40) -> 153.17465 | V39: =+R39*(1+V40) -> 146.93008 | W39: =+S39*(1+W40) -> 143.22886 | ... Y39: =+U39*(1+Y40) -> 189.61979 | AB39: =SUM(F39:I39) -> 263.1 | AC39: =SUM(J39:M39) -> 336.8 | AH39: From the FY2025 10-K. 2023 and 2026 quarters not disclosed in the documents reviewed; enter if you have them.
A40: YoY Growth (%) | J40: =+J39/F39 -1 -> 0.29015544 | K40: =+K39/G39 -1 -> 0.2800659 | L40: =+L39/H39 -1 -> 0.24355301 | M40: =+M39/I39 -1 -> 0.30655957 | N40: =+N39/J39 -1 -> 0.2583668 | O40: =+O39/K39 -1 -> 0.18404118 | P40: =+AVERAGE(J40:O40) -> 0.26045698 | Q40: =+P40*0.99 -> 0.25785241 | R40: =+Q40*0.99 -> 0.25527389 | S40: =+R40*0.99 -> 0.25272115 | T40: =+S40*0.99 -> 0.25019394 | U40: =+T40*0.99 -> 0.247692 | V40: =+U40*0.99 -> 0.24521508 | W40: =+V40*0.99 -> 0.24276293 | X40: =+W40*0.99 -> 0.2403353 | Y40: =+X40*0.99 -> 0.23793195
A41: Revenue per million impressions ($) | F41: ='Income Statement'!G9/(F39*1000) -> 1.1520035 | G41: ='Income Statement'!H9/(G39*1000) -> 1.1081878 | H41: ='Income Statement'!I9/(H39*1000) -> 1.0284527 | I41: ='Income Statement'!J9/(I39*1000) -> 1.1446051 | J41: ='Income Statement'!K9/(J39*1000) -> 0.85441767 | K41: ='Income Statement'!L9/(K39*1000) -> 0.91499356 | L41: ='Income Statement'!M9/(L39*1000) -> 0.78294931 | M41: ='Income Statement'!N9/(M39*1000) -> 0.82014344 | N41: ='Income Statement'!O9 / (N39*1000) -> 0.66560638 | O41: ='Income Statement'!P9 / (O39*1000) -> 0.85427174 | P41: =+AVERAGE(J41:O41) -> 0.81539702 | Q41: =+P41 -> 0.81539702 | R41: =+Q41 -> 0.81539702 | S41: =+R41 -> 0.81539702 | T41: =+S41 -> 0.81539702 | U41: =+T41 -> 0.81539702 | V41: =+U41 -> 0.81539702 | W41: =+V41 -> 0.81539702 | X41: =+W41 -> 0.81539702 | Y41: =+X41 -> 0.81539702 | AH41: Revenue divided by impressions processed.
A42: Cost of revenue per million impressions ($) | F42: ='Income Statement'!G10/(F39*1000) -> 0.4391019 | G42: ='Income Statement'!H10/(G39*1000) -> 0.41449753 | H42: ='Income Statement'!I10/(H39*1000) -> 0.36544413 | I42: ='Income Statement'!J10/(I39*1000) -> 0.33380187 | J42: ='Income Statement'!K10/(J39*1000) -> 0.34254351 | K42: ='Income Statement'!L10/(K39*1000) -> 0.34249678 | L42: ='Income Statement'!M10/(L39*1000) -> 0.29266129 | M42: ='Income Statement'!N10/(M39*1000) -> 0.26108607 | ... O42: ='Income Statement'!P10/(O39*1000) -> 0.28127174 | P42: =+AVERAGE(J42:O42) -> 0.29960919 | Q42: =+P42*0.99 -> 0.2966131 | R42: =+Q42*0.99 -> 0.29364697 | S42: =+R42*0.99 -> 0.2907105 | T42: =+S42*0.99 -> 0.28780339 | U42: =+T42*0.99 -> 0.28492536 | V42: =+U42*0.99 -> 0.2820761 | W42: =+V42*0.99 -> 0.27925534 | X42: =+W42*0.99 -> 0.27646279 | Y42: =+X42*0.99 -> 0.27369816 | AH42: Cost of revenue divided by impressions processed.

Sheet Income Statement
B1: PubMatic, Inc. (NASDAQ: PUBM): Income Statement
B2: $ in thousands except per share. Fiscal year ends Dec 31. Actuals through Q2 2026; forecast from Q3 2026. Q4 actuals = full year (10-K) less Q1 to Q3.
B4: Period | C4: Q1'23 | D4: Q2'23 | E4: Q3'23 | F4: Q4'23 | G4: Q1'24 | H4: Q2'24 | I4: Q3'24 | J4: Q4'24 | K4: Q1'25 | L4: Q2'25 | M4: Q3'25 | N4: Q4'25 | O4: Q1'26 | P4: Q2'26 | Q4: Q3'26 | R4: Q4'26 | S4: Q1'27 | T4: Q2'27 | U4: Q3'27 | V4: Q4'27 | W4: Q1'28 | X4: Q2'28 | Y4: Q3'28 | Z4: Q4'28 | AB4: FY2023A | AC4: FY2024A | AD4: FY2025A | AE4: FY2026E | AF4: FY2027E | AG4: FY2028E
B5: Period end | C5: 45016 | D5: 45107 | E5: 45199 | F5: 45291 | G5: 45382 | H5: 45473 | I5: 45565 | J5: 45657 | K5: 45747 | L5: 45838 | M5: 45930 | N5: 46022 | O5: 46112 | P5: 46203 | Q5: 46295 | R5: 46387 | S5: 46477 | T5: 46568 | U5: 46660 | V5: 46752 | W5: 46843 | X5: 46934 | Y5: 47026 | Z5: 47118 | AB5: 45291 | AC5: 45657 | AD5: 46022 | AE5: 46387 | AF5: 46752 | AG5: 47118
B6: Status | C6: Actual | D6: Actual | E6: Actual | F6: Actual | G6: Actual | H6: Actual | I6: Actual | J6: Actual | K6: Actual | L6: Actual | M6: Actual | N6: Actual | O6: Actual | P6: Actual | Q6: Forecast | R6: Forecast | S6: Forecast | T6: Forecast | U6: Forecast | V6: Forecast | W6: Forecast | X6: Forecast | Y6: Forecast | Z6: Forecast | AB6: Actual | AC6: Actual | AD6: Actual | AE6: 2A + 2E | AF6: Forecast | AG6: Forecast
A8: x | B8: Income statement ($ in thousands, except per share)
B9: Revenue | C9: 55407 | D9: 63330 | E9: 63677 | F9: ='10-K Data'!B9-SUM(C9:E9) -> 84600 | G9: 66701 | H9: 67267 | I9: 71786 | J9: ='10-K Data'!C9-SUM(G9:I9) -> 85502 | K9: 63825 | L9: 71095 | M9: 67960 | N9: ='10-K Data'!D9-SUM(K9:M9) -> 80046 | O9: 62567 | P9: 78593 | Q9: =+(Drivers!P$39*1000)*Drivers!P41 -> 89210.685 | R9: =+(Drivers!Q$39*1000)*Drivers!Q41 -> 100103.35 | S9: =+(Drivers!R$39*1000)*Drivers!R41 -> 96213.379 | T9: =+(Drivers!S$39*1000)*Drivers!S41 -> 93974.788 | U9: =+(Drivers!T$39*1000)*Drivers!T41 -> 111530.66 | V9: =+(Drivers!U$39*1000)*Drivers!U41 -> 124898.15 | W9: =+(Drivers!V$39*1000)*Drivers!V41 -> 119806.35 | X9: =+(Drivers!W$39*1000)*Drivers!W41 -> 116788.38 | ... Z9: =+(Drivers!Y$39*1000)*Drivers!Y41 -> 154615.41 | AB9: =SUM(C9:F9) -> 267014 | AC9: =SUM(G9:J9) -> 291256 | AD9: =SUM(K9:N9) -> 282926 | AE9: =SUM(O9:R9) -> 330474.04 | AF9: =SUM(S9:V9) -> 426616.98 | AG9: =SUM(W9:Z9) -> 529545.56
B10: Cost of revenue | C10: 23863 | D10: 25067 | E10: 26091 | F10: ='10-K Data'!B10-SUM(C10:E10) -> 24208 | G10: 25424 | H10: 25160 | I10: 25508 | J10: ='10-K Data'!C10-SUM(G10:I10) -> 24935 | K10: 25588 | L10: 26612 | M10: 25403 | N10: ='10-K Data'!D10-SUM(K10:M10) -> 25482 | O10: 26094 | P10: 25877 | Q10: =+(Drivers!P$39*1000)*Drivers!P42 -> 32779.542 | R10: =+(Drivers!Q$39*1000)*Drivers!Q42 -> 36414.121 | S10: =+(Drivers!R$39*1000)*Drivers!R42 -> 34649.093 | T10: =+(Drivers!S$39*1000)*Drivers!S42 -> 33504.485 | U10: =+(Drivers!T$39*1000)*Drivers!T42 -> 39365.978 | V10: =+(Drivers!U$39*1000)*Drivers!U42 -> 43643.342 | W10: =+(Drivers!V$39*1000)*Drivers!V42 -> 41445.465 | X10: =+(Drivers!W$39*1000)*Drivers!W42 -> 39997.424 | ... Z10: =+(Drivers!Y$39*1000)*Drivers!Y42 -> 51898.588 | AB10: =SUM(C10:F10) -> 99229 | AC10: =SUM(G10:J10) -> 101027 | AD10: =SUM(K10:N10) -> 103085 | AE10: =SUM(O10:R10) -> 121164.66 | AF10: =SUM(S10:V10) -> 151162.9 | AG10: =SUM(W10:Z10) -> 180244.51
B11: Gross profit | C11: =C9-C10 -> 31544 | D11: =D9-D10 -> 38263 | E11: =E9-E10 -> 37586 | F11: =F9-F10 -> 60392 | G11: =G9-G10 -> 41277 | H11: =H9-H10 -> 42107 | I11: =I9-I10 -> 46278 | J11: =J9-J10 -> 60567 | ... Z11: =Z9-Z10 -> 102716.82 | AB11: =AB9-AB10 -> 167785 | AC11: =AC9-AC10 -> 190229 | AD11: =AD9-AD10 -> 179841 | AE11: =AE9-AE10 -> 209309.37 | AF11: =AF9-AF10 -> 275454.08 | AG11: =AG9-AG10 -> 349301.05
B12: Gross margin % | C12: =IF(C9=0,0,C11/C9) -> 0.56931435 | D12: =IF(D9=0,0,D11/D9) -> 0.60418443 | E12: =IF(E9=0,0,E11/E9) -> 0.59026022 | F12: =IF(F9=0,0,F11/F9) -> 0.71385343 | G12: =IF(G9=0,0,G11/G9) -> 0.6188363 | H12: =IF(H9=0,0,H11/H9) -> 0.62596816 | I12: =IF(I9=0,0,I11/I9) -> 0.64466609 | J12: =IF(J9=0,0,J11/J9) -> 0.70836939 | ... Z12: =IF(Z9=0,0,Z11/Z9) -> 0.66433755 | AB12: =IF(AB9=0,0,AB11/AB9) -> 0.62837529 | AC12: =IF(AC9=0,0,AC11/AC9) -> 0.65313333 | AD12: =IF(AD9=0,0,AD11/AD9) -> 0.63564678 | AE12: =IF(AE9=0,0,AE11/AE9) -> 0.63336102 | AF12: =IF(AF9=0,0,AF11/AF9) -> 0.64567069 | AG12: =IF(AG9=0,0,AG11/AG9) -> 0.65962417
B14: Technology and development | C14: 6517 | D14: 6730 | E14: 6634 | F14: ='10-K Data'!B11-SUM(C14:E14) -> 6846 | G14: 7960 | H14: 8659 | I14: 8813 | J14: ='10-K Data'!C11-SUM(G14:I14) -> 7831 | K14: 8772 | L14: 9116 | M14: 9616 | N14: ='10-K Data'!D11-SUM(K14:M14) -> 6316 | O14: 7986 | P14: 9148 | Q14: =M14*(1+Drivers!P11) -> 9904.48 | R14: =N14*(1+Drivers!Q11) -> 6505.48 | S14: =O14*(1+Drivers!R11) -> 8225.58 | T14: =P14*(1+Drivers!S11) -> 9422.44 | U14: =Q14*(1+Drivers!T11) -> 10201.614 | V14: =R14*(1+Drivers!U11) -> 6700.6444 | W14: =S14*(1+Drivers!V11) -> 8472.3474 | X14: =T14*(1+Drivers!W11) -> 9705.1132 | ... Z14: =V14*(1+Drivers!Y11) -> 6901.6637 | AB14: =SUM(C14:F14) -> 26727 | AC14: =SUM(G14:J14) -> 33263 | AD14: =SUM(K14:N14) -> 33820 | AE14: =SUM(O14:R14) -> 33543.96 | AF14: =SUM(S14:V14) -> 34550.279 | AG14: =SUM(W14:Z14) -> 35586.787
B15: Sales and marketing | C15: 23127 | D15: 19810 | E15: 19513 | F15: ='10-K Data'!B12-SUM(C15:E15) -> 20353 | G15: 24815 | H15: 23095 | I15: 23696 | J15: ='10-K Data'!C12-SUM(G15:I15) -> 23763 | K15: 26799 | L15: 25200 | M15: 25732 | N15: ='10-K Data'!D12-SUM(K15:M15) -> 25209 | O15: 28965 | P15: 26130 | Q15: =M15*(1+Drivers!P12) -> 26761.28 | R15: =N15*(1+Drivers!Q12) -> 26217.36 | S15: =O15*(1+Drivers!R12) -> 30123.6 | T15: =P15*(1+Drivers!S12) -> 27175.2 | U15: =Q15*(1+Drivers!T12) -> 27831.731 | V15: =R15*(1+Drivers!U12) -> 27266.054 | W15: =S15*(1+Drivers!V12) -> 31328.544 | X15: =T15*(1+Drivers!W12) -> 28262.208 | ... Z15: =V15*(1+Drivers!Y12) -> 28356.697 | AB15: =SUM(C15:F15) -> 82803 | AC15: =SUM(G15:J15) -> 95369 | AD15: =SUM(K15:N15) -> 102940 | AE15: =SUM(O15:R15) -> 108073.64 | AF15: =SUM(S15:V15) -> 112396.59 | AG15: =SUM(W15:Z15) -> 116892.45
B16: General and administrative | C16: 12572 | D16: 18857 | E16: 12010 | F16: ='10-K Data'!B13-SUM(C16:E16) -> 12780 | G16: 14027 | H16: 14338 | I16: 15134 | J16: ='10-K Data'!C13-SUM(G16:I16) -> 14171 | K16: 14569 | L16: 15628 | M16: 15628 | N16: ='10-K Data'!D13-SUM(K16:M16) -> 14515 | O16: 14795 | P16: 16859 | Q16: =M16*(1+Drivers!P13) -> 16253.12 | R16: =N16*(1+Drivers!Q13) -> 15095.6 | S16: =O16*(1+Drivers!R13) -> 15386.8 | T16: =P16*(1+Drivers!S13) -> 17533.36 | U16: =Q16*(1+Drivers!T13) -> 16903.245 | V16: =R16*(1+Drivers!U13) -> 15699.424 | W16: =S16*(1+Drivers!V13) -> 16002.272 | X16: =T16*(1+Drivers!W13) -> 18234.694 | ... Z16: =V16*(1+Drivers!Y13) -> 16327.401 | AB16: =SUM(C16:F16) -> 56219 | AC16: =SUM(G16:J16) -> 57670 | AD16: =SUM(K16:N16) -> 60340 | AE16: =SUM(O16:R16) -> 63002.72 | AF16: =SUM(S16:V16) -> 65522.829 | AG16: =SUM(W16:Z16) -> 68143.742
B17: Total operating expenses | C17: =C14+C15+C16 -> 42216 | D17: =D14+D15+D16 -> 45397 | E17: =E14+E15+E16 -> 38157 | F17: =F14+F15+F16 -> 39979 | G17: =G14+G15+G16 -> 46802 | H17: =H14+H15+H16 -> 46092 | I17: =I14+I15+I16 -> 47643 | J17: =J14+J15+J16 -> 45765 | ... Z17: =Z14+Z15+Z16 -> 51585.761 | AB17: =AB14+AB15+AB16 -> 165749 | AC17: =AC14+AC15+AC16 -> 186302 | AD17: =AD14+AD15+AD16 -> 197100 | AE17: =AE14+AE15+AE16 -> 204620.32 | AF17: =AF14+AF15+AF16 -> 212469.69 | AG17: =AG14+AG15+AG16 -> 220622.98
B18: Operating income (loss) | C18: =C11-C17 -> -10672 | D18: =D11-D17 -> -7134 | E18: =E11-E17 -> -571 | F18: =F11-F17 -> 20413 | G18: =G11-G17 -> -5525 | H18: =H11-H17 -> -3985 | I18: =I11-I17 -> -1365 | J18: =J11-J17 -> 14802 | ... Z18: =Z11-Z17 -> 51131.064 | AB18: =AB11-AB17 -> 2036 | AC18: =AC11-AC17 -> 3927 | AD18: =AD11-AD17 -> -17259 | AE18: =AE11-AE17 -> 4689.0549 | AF18: =AF11-AF17 -> 62984.386 | AG18: =AG11-AG17 -> 128678.07
B19: Operating margin % | C19: =IF(C9=0,0,C18/C9) -> -0.19261104 | D19: =IF(D9=0,0,D18/D9) -> -0.11264803 | E19: =IF(E9=0,0,E18/E9) -> -0.008967131 | F19: =IF(F9=0,0,F18/F9) -> 0.24128842 | G19: =IF(G9=0,0,G18/G9) -> -0.082832341 | H19: =IF(H9=0,0,H18/H9) -> -0.05924153 | I19: =IF(I9=0,0,I18/I9) -> -0.01901485 | J19: =IF(J9=0,0,J18/J9) -> 0.17311876 | ... Z19: =IF(Z9=0,0,Z18/Z9) -> 0.33069836 | AB19: =IF(AB9=0,0,AB18/AB9) -> 0.0076250683 | AC19: =IF(AC9=0,0,AC18/AC9) -> 0.013482984 | AD19: =IF(AD9=0,0,AD18/AD9) -> -0.061001817 | AE19: =IF(AE9=0,0,AE18/AE9) -> 0.014188875 | AF19: =IF(AF9=0,0,AF18/AF9) -> 0.14763685 | AG19: =IF(AG9=0,0,AG18/AG9) -> 0.24299717
B21: Interest income | C21: 1891 | D21: 2176 | E21: 2246 | F21: ='10-K Data'!B15-SUM(C21:E21) -> 2515 | G21: 2564 | H21: 2340 | I21: 1969 | J21: ='10-K Data'!C15-SUM(G21:I21) -> 1604 | K21: 1593 | L21: 1379 | M21: 1198 | N21: ='10-K Data'!D15-SUM(K21:M21) -> 1285 | O21: 1215 | P21: 1213 | Q21: =('Balance Sheet'!P9+'Balance Sheet'!P10)*Drivers!P19/4 -> 1134.4327 | R21: =('Balance Sheet'!Q9+'Balance Sheet'!Q10)*Drivers!Q19/4 -> 1076.7897 | S21: =('Balance Sheet'!R9+'Balance Sheet'!R10)*Drivers!R19/4 -> 1165.9156 | T21: =('Balance Sheet'!S9+'Balance Sheet'!S10)*Drivers!S19/4 -> 1442.9784 | U21: =('Balance Sheet'!T9+'Balance Sheet'!T10)*Drivers!T19/4 -> 1567.8212 | V21: =('Balance Sheet'!U9+'Balance Sheet'!U10)*Drivers!U19/4 -> 1609.3297 | W21: =('Balance Sheet'!V9+'Balance Sheet'!V10)*Drivers!V19/4 -> 1835.4275 | X21: =('Balance Sheet'!W9+'Balance Sheet'!W10)*Drivers!W19/4 -> 2314.1323 | ... Z21: =('Balance Sheet'!Y9+'Balance Sheet'!Y10)*Drivers!Y19/4 -> 2751.6052 | AB21: =SUM(C21:F21) -> 8828 | AC21: =SUM(G21:J21) -> 8477 | AD21: =SUM(K21:N21) -> 5455 | AE21: =SUM(O21:R21) -> 4639.2224 | AF21: =SUM(S21:V21) -> 5786.0449 | AG21: =SUM(W21:Z21) -> 9481.9587
B22: Other income (expense), net | C22: -465 | D22: -221 | E22: 210 | F22: ='10-K Data'!B16-SUM(C22:E22) -> 117 | G22: 258 | H22: 4028 | I22: -930 | J22: ='10-K Data'!C16-SUM(G22:I22) -> 2014 | K22: -1014 | L22: -1988 | M22: -937 | N22: ='10-K Data'!D16-SUM(K22:M22) -> -211 | O22: -1053 | P22: 89 | Q22: =Drivers!P20 -> 0 | R22: =Drivers!Q20 -> 0 | S22: =Drivers!R20 -> 0 | T22: =Drivers!S20 -> 0 | U22: =Drivers!T20 -> 0 | V22: =Drivers!U20 -> 0 | W22: =Drivers!V20 -> 0 | X22: =Drivers!W20 -> 0 | ... Z22: =Drivers!Y20 -> 0 | AB22: =SUM(C22:F22) -> -359 | AC22: =SUM(G22:J22) -> 5370 | AD22: =SUM(K22:N22) -> -4150 | AE22: =SUM(O22:R22) -> -964 | AF22: =SUM(S22:V22) -> 0 | AG22: =SUM(W22:Z22) -> 0
B23: Total other income, net | C23: =C21+C22 -> 1426 | D23: =D21+D22 -> 1955 | E23: =E21+E22 -> 2456 | F23: =F21+F22 -> 2632 | G23: =G21+G22 -> 2822 | H23: =H21+H22 -> 6368 | I23: =I21+I22 -> 1039 | J23: =J21+J22 -> 3618 | ... Z23: =Z21+Z22 -> 2751.6052 | AB23: =AB21+AB22 -> 8469 | AC23: =AC21+AC22 -> 13847 | AD23: =AD21+AD22 -> 1305 | AE23: =AE21+AE22 -> 3675.2224 | AF23: =AF21+AF22 -> 5786.0449 | AG23: =AG21+AG22 -> 9481.9587
B24: Income (loss) before income taxes | C24: =C18+C23 -> -9246 | D24: =D18+D23 -> -5179 | E24: =E18+E23 -> 1885 | F24: =F18+F23 -> 23045 | G24: =G18+G23 -> -2703 | H24: =H18+H23 -> 2383 | I24: =I18+I23 -> -326 | J24: =J18+J23 -> 18420 | ... Z24: =Z18+Z23 -> 53882.669 | AB24: =AB18+AB23 -> 10505 | AC24: =AC18+AC23 -> 17774 | AD24: =AD18+AD23 -> -15954 | AE24: =AE18+AE23 -> 8364.2774 | AF24: =AF18+AF23 -> 68770.431 | AG24: =AG18+AG23 -> 138160.03
B25: Provision for (benefit from) income taxes | C25: -3375 | D25: 545 | E25: 111 | F25: ='10-K Data'!B17-SUM(C25:E25) -> 4343 | G25: -249 | H25: 412 | I25: 586 | J25: ='10-K Data'!C17-SUM(G25:I25) -> 4521 | K25: -1838 | L25: -862 | M25: -1706 | N25: ='10-K Data'!D17-SUM(K25:M25) -> 2914 | O25: -2601 | P25: 3083 | Q25: =Q24*Drivers!P21 -> 975.80605 | R25: =R24*Drivers!Q21 -> 3558.9922 | S25: =S24*Drivers!R21 -> 1888.7866 | T25: =T24*Drivers!S21 -> 1634.2791 | U25: =U24*Drivers!T21 -> 3947.1411 | V25: =V24*Drivers!U21 -> 6971.5837 | W25: =W24*Drivers!V21 -> 5122.5615 | X25: =X24*Drivers!W21 -> 4809.646 | ... Z25: =Z24*Drivers!Y21 -> 11315.36 | AB25: =SUM(C25:F25) -> 1624 | AC25: =SUM(G25:J25) -> 5270 | AD25: =SUM(K25:N25) -> -1492 | AE25: =SUM(O25:R25) -> 5016.7982 | AF25: =SUM(S25:V25) -> 14441.791 | AG25: =SUM(W25:Z25) -> 29013.606
B26: Effective tax rate % | C26: =IF(C24=0,0,C25/C24) -> 0.36502271 | D26: =IF(D24=0,0,D25/D24) -> -0.10523267 | E26: =IF(E24=0,0,E25/E24) -> 0.058885942 | F26: =IF(F24=0,0,F25/F24) -> 0.18845737 | G26: =IF(G24=0,0,G25/G24) -> 0.092119867 | H26: =IF(H24=0,0,H25/H24) -> 0.17289131 | I26: =IF(I24=0,0,I25/I24) -> -1.797546 | J26: =IF(J24=0,0,J25/J24) -> 0.24543974 | ... Z26: =IF(Z24=0,0,Z25/Z24) -> 0.21 | AB26: =IF(AB24=0,0,AB25/AB24) -> 0.15459305 | AC26: =IF(AC24=0,0,AC25/AC24) -> 0.29650051 | AD26: =IF(AD24=0,0,AD25/AD24) -> 0.093518867 | AE26: =IF(AE24=0,0,AE25/AE24) -> 0.5997886 | AF26: =IF(AF24=0,0,AF25/AF24) -> 0.21 | AG26: =IF(AG24=0,0,AG25/AG24) -> 0.21
B27: Net income (loss) | C27: =C24-C25 -> -5871 | D27: =D24-D25 -> -5724 | E27: =E24-E25 -> 1774 | F27: =F24-F25 -> 18702 | G27: =G24-G25 -> -2454 | H27: =H24-H25 -> 1971 | I27: =I24-I25 -> -912 | J27: =J24-J25 -> 13899 | ... Z27: =Z24-Z25 -> 42567.308 | AB27: =AB24-AB25 -> 8881 | AC27: =AC24-AC25 -> 12504 | AD27: =AD24-AD25 -> -14462 | AE27: =AE24-AE25 -> 3347.4791 | AF27: =AF24-AF25 -> 54328.641 | AG27: =AG24-AG25 -> 109146.42
B28: Net margin % | C28: =IF(C9=0,0,C27/C9) -> -0.10596134 | D28: =IF(D9=0,0,D27/D9) -> -0.090383704 | E28: =IF(E9=0,0,E27/E9) -> 0.027859353 | F28: =IF(F9=0,0,F27/F9) -> 0.22106383 | G28: =IF(G9=0,0,G27/G9) -> -0.036791053 | H28: =IF(H9=0,0,H27/H9) -> 0.029301143 | I28: =IF(I9=0,0,I27/I9) -> -0.012704427 | J28: =IF(J9=0,0,J27/J9) -> 0.1625576 | ... Z28: =IF(Z9=0,0,Z27/Z9) -> 0.2753109 | AB28: =IF(AB9=0,0,AB27/AB9) -> 0.033260428 | AC28: =IF(AC9=0,0,AC27/AC9) -> 0.042931304 | AD28: =IF(AD9=0,0,AD27/AD9) -> -0.051115839 | AE28: =IF(AE9=0,0,AE27/AE9) -> 0.010129326 | AF28: =IF(AF9=0,0,AF27/AF9) -> 0.12734758 | AG28: =IF(AG9=0,0,AG27/AG9) -> 0.20611338
B30: Weighted-average shares, basic (000s) | C30: 52740 | D30: 52029 | E30: 51638 | F30: =4*'10-K Data'!B19-SUM(C30:E30) -> 50633 | G30: 50039 | H30: 49780 | I30: 49056 | J30: =4*'10-K Data'!C19-SUM(G30:I30) -> 47977 | K30: 48346 | L30: 47185 | M30: 45933 | N30: =4*'10-K Data'!D19-SUM(K30:M30) -> 46568 | O30: 47120 | P30: 46106 | Q30: =Q31 -> 46106 | R30: =R31 -> 46106 | S30: =S31 -> 46106 | T30: =T31 -> 46106 | U30: =U31 -> 46106 | V30: =V31 -> 46106 | W30: =W31 -> 46106 | X30: =X31 -> 46106 | ... Z30: =Z31 -> 46106 | AB30: ='10-K Data'!B19 -> 51760 | AC30: ='10-K Data'!C19 -> 49213 | AD30: ='10-K Data'!D19 -> 47008 | AE30: =AVERAGE(O30:R30) -> 46359.5 | AF30: =AVERAGE(S30:V30) -> 46106 | AG30: =AVERAGE(W30:Z30) -> 46106
B31: Weighted-average shares, diluted (000s) | C31: 52740 | D31: 52029 | E31: 55979 | F31: 54940 | G31: 50039 | H31: 55577 | I31: 49056 | J31: 52620 | K31: 48346 | L31: 47185 | M31: 45933 | N31: 49320 | O31: 47120 | P31: 46106 | Q31: =Drivers!P22 -> 46106 | R31: =Drivers!Q22 -> 46106 | S31: =Drivers!R22 -> 46106 | T31: =Drivers!S22 -> 46106 | U31: =Drivers!T22 -> 46106 | V31: =Drivers!U22 -> 46106 | W31: =Drivers!V22 -> 46106 | X31: =Drivers!W22 -> 46106 | ... Z31: =Drivers!Y22 -> 46106 | AB31: ='10-K Data'!B20 -> 56027 | AC31: ='10-K Data'!C20 -> 54294 | AD31: ='10-K Data'!D20 -> 47008 | AE31: =AVERAGE(O31:R31) -> 46359.5 | AF31: =AVERAGE(S31:V31) -> 46106 | AG31: =AVERAGE(W31:Z31) -> 46106
B32: EPS, GAAP diluted ($) | C32: =IF(C27>0,C27/C31,C27/C30) -> -0.11131968 | D32: =IF(D27>0,D27/D31,D27/D30) -> -0.11001557 | E32: =IF(E27>0,E27/E31,E27/E30) -> 0.031690455 | F32: =IF(F27>0,F27/F31,F27/F30) -> 0.34040772 | G32: =IF(G27>0,G27/G31,G27/G30) -> -0.049041747 | H32: =IF(H27>0,H27/H31,H27/H30) -> 0.035464311 | I32: =IF(I27>0,I27/I31,I27/I30) -> -0.018590998 | J32: =IF(J27>0,J27/J31,J27/J30) -> 0.26413911 | ... P32: =IF(P27>0,P27/P31,P27/P30) -> -0.02607036 | Q32: =Q27/Q31 -> 0.079618475 | R32: =R27/R31 -> 0.29038714 | S32: =S27/S31 -> 0.15411086 | T32: =T27/T31 -> 0.13334495 | U32: =U27/U31 -> 0.32205719 | V32: =V27/V31 -> 0.56882909 | W32: =W27/W31 -> 0.4179627 | X32: =X27/X31 -> 0.39243114 | ... Z32: =Z27/Z31 -> 0.92324878 | AB32: =IF(AB27>0,AB27/AB31,AB27/AB30) -> 0.15851286 | AC32: =IF(AC27>0,AC27/AC31,AC27/AC30) -> 0.23030169 | AD32: =IF(AD27>0,AD27/AD31,AD27/AD30) -> -0.30764976 | AE32: =IF(AE27>0,AE27/AE31,AE27/AE30) -> 0.072206972 | AF32: =IF(AF27>0,AF27/AF31,AF27/AF30) -> 1.1783421 | AG32: =IF(AG27>0,AG27/AG31,AG27/AG30) -> 2.3672933
A34: x | B34: Growth and margin analysis
B35: Revenue growth, YoY % | G35: =G9/C9-1 -> 0.20383706 | H35: =H9/D9-1 -> 0.06216643 | I35: =I9/E9-1 -> 0.12734582 | J35: =J9/F9-1 -> 0.010661939 | K35: =K9/G9-1 -> -0.043117794 | L35: =L9/H9-1 -> 0.056907548 | M35: =M9/I9-1 -> -0.0532973 | N35: =N9/J9-1 -> -0.063811373 | ... Z35: =Z9/V9-1 -> 0.23793195 | AC35: =AC9/AB9-1 -> 0.090789247 | AD35: =AD9/AC9-1 -> -0.028600269 | AE35: =AE9/AD9-1 -> 0.16805821 | AF35: =AF9/AE9-1 -> 0.29092434 | AG35: =AG9/AF9-1 -> 0.24126696
B36: Revenue growth, QoQ % | D36: =D9/C9-1 -> 0.14299637 | E36: =E9/D9-1 -> 0.0054792357 | F36: =F9/E9-1 -> 0.32858018 | G36: =G9/F9-1 -> -0.2115721 | H36: =H9/G9-1 -> 0.0084856299 | I36: =I9/H9-1 -> 0.067180044 | J36: =J9/I9-1 -> 0.1910679 | K36: =K9/J9-1 -> -0.25352623 | ... Z36: =Z9/Y9-1 -> 0.11768499
B37: Gross profit growth, YoY % | G37: =G11/C11-1 -> 0.30855313 | H37: =H11/D11-1 -> 0.10046259 | I37: =I11/E11-1 -> 0.23125632 | J37: =J11/F11-1 -> 0.0028977348 | K37: =K11/G11-1 -> -0.073648763 | L37: =L11/H11-1 -> 0.056427672 | M37: =M11/I11-1 -> -0.080405376 | N37: =N11/J11-1 -> -0.099113379 | ... Z37: =Z11/V11-1 -> 0.26413222 | AC37: =AC11/AB11-1 -> 0.13376643 | AD37: =AD11/AC11-1 -> -0.054607867 | AE37: =AE11/AD11-1 -> 0.16385794 | AF37: =AF11/AE11-1 -> 0.31601406 | AG37: =AG11/AF11-1 -> 0.26809176
B38: Cost of revenue, % of revenue | C38: =IF(C9=0,0,C10/C9) -> 0.43068565 | D38: =IF(D9=0,0,D10/D9) -> 0.39581557 | E38: =IF(E9=0,0,E10/E9) -> 0.40973978 | F38: =IF(F9=0,0,F10/F9) -> 0.28614657 | G38: =IF(G9=0,0,G10/G9) -> 0.3811637 | H38: =IF(H9=0,0,H10/H9) -> 0.37403184 | I38: =IF(I9=0,0,I10/I9) -> 0.35533391 | J38: =IF(J9=0,0,J10/J9) -> 0.29163061 | ... Z38: =IF(Z9=0,0,Z10/Z9) -> 0.33566245 | AB38: =IF(AB9=0,0,AB10/AB9) -> 0.37162471 | AC38: =IF(AC9=0,0,AC10/AC9) -> 0.34686667 | AD38: =IF(AD9=0,0,AD10/AD9) -> 0.36435322 | AE38: =IF(AE9=0,0,AE10/AE9) -> 0.36663898 | AF38: =IF(AF9=0,0,AF10/AF9) -> 0.35432931 | AG38: =IF(AG9=0,0,AG10/AG9) -> 0.34037583
B39: Technology and development, % of revenue | C39: =IF(C9=0,0,C14/C9) -> 0.11762052 | D39: =IF(D9=0,0,D14/D9) -> 0.10626875 | E39: =IF(E9=0,0,E14/E9) -> 0.10418204 | F39: =IF(F9=0,0,F14/F9) -> 0.080921986 | G39: =IF(G9=0,0,G14/G9) -> 0.11933854 | H39: =IF(H9=0,0,H14/H9) -> 0.12872582 | I39: =IF(I9=0,0,I14/I9) -> 0.12276767 | J39: =IF(J9=0,0,J14/J9) -> 0.091588501 | ... Z39: =IF(Z9=0,0,Z14/Z9) -> 0.044637618 | AB39: =IF(AB9=0,0,AB14/AB9) -> 0.10009588 | AC39: =IF(AC9=0,0,AC14/AC9) -> 0.11420537 | AD39: =IF(AD9=0,0,AD14/AD9) -> 0.11953656 | AE39: =IF(AE9=0,0,AE14/AE9) -> 0.10150256 | AF39: =IF(AF9=0,0,AF14/AF9) -> 0.080986648 | AG39: =IF(AG9=0,0,AG14/AG9) -> 0.067202503
B40: Sales and marketing, % of revenue | C40: =IF(C9=0,0,C15/C9) -> 0.41740213 | D40: =IF(D9=0,0,D15/D9) -> 0.31280594 | E40: =IF(E9=0,0,E15/E9) -> 0.30643718 | F40: =IF(F9=0,0,F15/F9) -> 0.2405792 | G40: =IF(G9=0,0,G15/G9) -> 0.3720334 | H40: =IF(H9=0,0,H15/H9) -> 0.34333328 | I40: =IF(I9=0,0,I15/I9) -> 0.33009222 | J40: =IF(J9=0,0,J15/J9) -> 0.27792332 | ... Z40: =IF(Z9=0,0,Z15/Z9) -> 0.18340149 | AB40: =IF(AB9=0,0,AB15/AB9) -> 0.31010734 | AC40: =IF(AC9=0,0,AC15/AC9) -> 0.32744046 | AD40: =IF(AD9=0,0,AD15/AD9) -> 0.36384072 | AE40: =IF(AE9=0,0,AE15/AE9) -> 0.32702611 | AF40: =IF(AF9=0,0,AF15/AF9) -> 0.26346018 | AG40: =IF(AG9=0,0,AG15/AG9) -> 0.22074106
B41: General and administrative, % of revenue | C41: =IF(C9=0,0,C16/C9) -> 0.22690274 | D41: =IF(D9=0,0,D16/D9) -> 0.29775778 | E41: =IF(E9=0,0,E16/E9) -> 0.18860813 | F41: =IF(F9=0,0,F16/F9) -> 0.15106383 | G41: =IF(G9=0,0,G16/G9) -> 0.2102967 | H41: =IF(H9=0,0,H16/H9) -> 0.21315058 | I41: =IF(I9=0,0,I16/I9) -> 0.21082105 | J41: =IF(J9=0,0,J16/J9) -> 0.16573881 | ... Z41: =IF(Z9=0,0,Z16/Z9) -> 0.10560009 | AB41: =IF(AB9=0,0,AB16/AB9) -> 0.21054701 | AC41: =IF(AC9=0,0,AC16/AC9) -> 0.1980045 | AD41: =IF(AD9=0,0,AD16/AD9) -> 0.21327131 | AE41: =IF(AE9=0,0,AE16/AE9) -> 0.19064348 | AF41: =IF(AF9=0,0,AF16/AF9) -> 0.15358702 | AG41: =IF(AG9=0,0,AG16/AG9) -> 0.12868344
B42: Total operating expenses, % of revenue | C42: =IF(C9=0,0,C17/C9) -> 0.76192539 | D42: =IF(D9=0,0,D17/D9) -> 0.71683246 | E42: =IF(E9=0,0,E17/E9) -> 0.59922735 | F42: =IF(F9=0,0,F17/F9) -> 0.47256501 | G42: =IF(G9=0,0,G17/G9) -> 0.70166864 | H42: =IF(H9=0,0,H17/H9) -> 0.68520969 | I42: =IF(I9=0,0,I17/I9) -> 0.66368094 | J42: =IF(J9=0,0,J17/J9) -> 0.53525064 | ... Z42: =IF(Z9=0,0,Z17/Z9) -> 0.33363919 | AB42: =IF(AB9=0,0,AB17/AB9) -> 0.62075022 | AC42: =IF(AC9=0,0,AC17/AC9) -> 0.63965034 | AD42: =IF(AD9=0,0,AD17/AD9) -> 0.69664859 | AE42: =IF(AE9=0,0,AE17/AE9) -> 0.61917215 | AF42: =IF(AF9=0,0,AF17/AF9) -> 0.49803384 | AG42: =IF(AG9=0,0,AG17/AG9) -> 0.416627
A44: x | B44: Adjusted EBITDA reconciliation (company definition)
B45: Net income (loss) | C45: =C27 -> -5871 | D45: =D27 -> -5724 | E45: =E27 -> 1774 | F45: =F27 -> 18702 | G45: =G27 -> -2454 | H45: =H27 -> 1971 | I45: =I27 -> -912 | J45: =J27 -> 13899 | ... Z45: =Z27 -> 42567.308 | AB45: =AB27 -> 8881 | AC45: =AC27 -> 12504 | AD45: =AD27 -> -14462 | AE45: =AE27 -> 3347.4791 | AF45: =AF27 -> 54328.641 | AG45: =AG27 -> 109146.42
B46: Plus: stock-based compensation | C46: =C59 -> 7059 | D46: =D59 -> 7266 | E46: =E59 -> 7200 | F46: =F59 -> 7337 | G46: =G59 -> 9111 | H46: =H59 -> 9699 | I46: =I59 -> 9457 | J46: =J59 -> 9409 | ... Z46: =Z59 -> 17007.695 | AB46: =AB59 -> 28862 | AC46: =AC59 -> 37676 | AD46: =AD59 -> 38378 | AE46: =AE59 -> 37659.544 | AF46: =AF59 -> 46927.868 | AG46: =AG59 -> 58250.011
B47: Plus: depreciation and amortization | C47: =C62 -> 11432 | D47: =D62 -> 10898 | E47: =E62 -> 11401 | F47: =F62 -> 11039 | G47: =G62 -> 11212 | H47: =H62 -> 11336 | I47: =I62 -> 11383 | J47: =J62 -> 11421 | ... Z47: =Z62 -> 19326.927 | AB47: =AB62 -> 44770 | AC47: =AC62 -> 45352 | AD47: =AD62 -> 43769 | AE47: =AE62 -> 43659.255 | AF47: =AF62 -> 53327.122 | AG47: =AG62 -> 66193.195
B48: Plus: litigation-related expenses | C48: 0 | D48: 0 | E48: 0 | F48: 0 | G48: 0 | H48: 0 | I48: 0 | J48: 0 | K48: 0 | L48: 0 | M48: 538 | N48: ='10-K Data'!D31-SUM(K48:M48) -> 364 | O48: 438 | P48: 594 | Q48: =Drivers!P18 -> 0 | R48: =Drivers!Q18 -> 0 | S48: =Drivers!R18 -> 0 | T48: =Drivers!S18 -> 0 | U48: =Drivers!T18 -> 0 | V48: =Drivers!U18 -> 0 | W48: =Drivers!V18 -> 0 | X48: =Drivers!W18 -> 0 | ... Z48: =Drivers!Y18 -> 0 | AB48: =SUM(C48:F48) -> 0 | AC48: =SUM(G48:J48) -> 0 | AD48: =SUM(K48:N48) -> 902 | AE48: =SUM(O48:R48) -> 1032 | AF48: =SUM(S48:V48) -> 0 | AG48: =SUM(W48:Z48) -> 0
B49: Less: interest income | C49: =-C21 -> -1891 | D49: =-D21 -> -2176 | E49: =-E21 -> -2246 | F49: =-F21 -> -2515 | G49: =-G21 -> -2564 | H49: =-H21 -> -2340 | I49: =-I21 -> -1969 | J49: =-J21 -> -1604 | ... Z49: =-Z21 -> -2751.6052 | AB49: =-AB21 -> -8828 | AC49: =-AC21 -> -8477 | AD49: =-AD21 -> -5455 | AE49: =-AE21 -> -4639.2224 | AF49: =-AF21 -> -5786.0449 | AG49: =-AG21 -> -9481.9587
B50: Plus: provision for (benefit from) income taxes | C50: =C25 -> -3375 | D50: =D25 -> 545 | E50: =E25 -> 111 | F50: =F25 -> 4343 | G50: =G25 -> -249 | H50: =H25 -> 412 | I50: =I25 -> 586 | J50: =J25 -> 4521 | ... Z50: =Z25 -> 11315.36 | AB50: =AB25 -> 1624 | AC50: =AC25 -> 5270 | AD50: =AD25 -> -1492 | AE50: =AE25 -> 5016.7982 | AF50: =AF25 -> 14441.791 | AG50: =AG25 -> 29013.606
B51: Adjusted EBITDA | C51: =SUM(C45:C50) -> 7354 | D51: =SUM(D45:D50) -> 10809 | E51: =SUM(E45:E50) -> 18240 | F51: =SUM(F45:F50) -> 38906 | G51: =SUM(G45:G50) -> 15056 | H51: =SUM(H45:H50) -> 21078 | I51: =SUM(I45:I50) -> 18545 | J51: =SUM(J45:J50) -> 37646 | ... Z51: =SUM(Z45:Z50) -> 87465.686 | AB51: =SUM(AB45:AB50) -> 75309 | AC51: =SUM(AC45:AC50) -> 92325 | AD51: =SUM(AD45:AD50) -> 61640 | AE51: =SUM(AE45:AE50) -> 86075.854 | AF51: =SUM(AF45:AF50) -> 163239.38 | AG51: =SUM(AG45:AG50) -> 253121.28
B52: Adjusted EBITDA margin % | C52: =IF(C9=0,0,C51/C9) -> 0.13272691 | D52: =IF(D9=0,0,D51/D9) -> 0.1706774 | E52: =IF(E9=0,0,E51/E9) -> 0.28644566 | F52: =IF(F9=0,0,F51/F9) -> 0.4598818 | G52: =IF(G9=0,0,G51/G9) -> 0.22572375 | H52: =IF(H9=0,0,H51/H9) -> 0.3133483 | I52: =IF(I9=0,0,I51/I9) -> 0.25833728 | J52: =IF(J9=0,0,J51/J9) -> 0.44029379 | ... Z52: =IF(Z9=0,0,Z51/Z9) -> 0.56569836 | AB52: =IF(AB9=0,0,AB51/AB9) -> 0.28204139 | AC52: =IF(AC9=0,0,AC51/AC9) -> 0.31698918 | AD52: =IF(AD9=0,0,AD51/AD9) -> 0.21786616 | AE52: =IF(AE9=0,0,AE51/AE9) -> 0.26046177 | AF52: =IF(AF9=0,0,AF51/AF9) -> 0.38263685 | AG52: =IF(AG9=0,0,AG51/AG9) -> 0.47799717
A54: x | B54: Memo: stock-based compensation by line item
B55: Cost of revenue | C55: 316 | D55: 387 | E55: 387 | F55: ='10-K Data'!B23-SUM(C55:E55) -> 382 | G55: 437 | H55: 494 | I55: 486 | J55: ='10-K Data'!C23-SUM(G55:I55) -> 438 | K55: 474 | L55: 474 | M55: 474 | N55: ='10-K Data'!D23-SUM(K55:M55) -> 432 | O55: 384 | P55: 357 | AB55: =SUM(C55:F55) -> 1472 | AC55: =SUM(G55:J55) -> 1855 | AD55: =SUM(K55:N55) -> 1854
B56: Technology and development | C56: 1008 | D56: 1089 | E56: 1112 | F56: ='10-K Data'!B24-SUM(C56:E56) -> 1137 | G56: 1441 | H56: 1644 | I56: 1603 | J56: ='10-K Data'!C24-SUM(G56:I56) -> 1625 | K56: 1585 | L56: 1628 | M56: 1471 | N56: ='10-K Data'!D24-SUM(K56:M56) -> 1404 | O56: 1029 | P56: 1055 | AB56: =SUM(C56:F56) -> 4346 | AC56: =SUM(G56:J56) -> 6313 | AD56: =SUM(K56:N56) -> 6088
B57: Sales and marketing | C57: 2709 | D57: 2614 | E57: 2550 | F57: ='10-K Data'!B25-SUM(C57:E57) -> 2589 | G57: 3238 | H57: 3472 | I57: 3450 | J57: ='10-K Data'!C25-SUM(G57:I57) -> 3247 | K57: 3463 | L57: 3465 | M57: 3423 | N57: ='10-K Data'!D25-SUM(K57:M57) -> 3352 | O57: 3057 | P57: 2605 | AB57: =SUM(C57:F57) -> 10462 | AC57: =SUM(G57:J57) -> 13407 | AD57: =SUM(K57:N57) -> 13703
B58: General and administrative | C58: 3026 | D58: 3176 | E58: 3151 | F58: ='10-K Data'!B26-SUM(C58:E58) -> 3229 | G58: 3995 | H58: 4089 | I58: 3918 | J58: ='10-K Data'!C26-SUM(G58:I58) -> 4099 | K58: 4176 | L58: 4234 | M58: 4143 | N58: ='10-K Data'!D26-SUM(K58:M58) -> 4180 | O58: 4018 | P58: 4330 | AB58: =SUM(C58:F58) -> 12582 | AC58: =SUM(G58:J58) -> 16101 | AD58: =SUM(K58:N58) -> 16733
B59: Total stock-based compensation | C59: =SUM(C55:C58) -> 7059 | D59: =SUM(D55:D58) -> 7266 | E59: =SUM(E55:E58) -> 7200 | F59: =SUM(F55:F58) -> 7337 | G59: =SUM(G55:G58) -> 9111 | H59: =SUM(H55:H58) -> 9699 | I59: =SUM(I55:I58) -> 9457 | J59: =SUM(J55:J58) -> 9409 | ... P59: =SUM(P55:P58) -> 8347 | Q59: =Q9*Drivers!P17 -> 9813.1753 | R59: =R9*Drivers!Q17 -> 11011.369 | S59: =S9*Drivers!R17 -> 10583.472 | T59: =T9*Drivers!S17 -> 10337.227 | U59: =U9*Drivers!T17 -> 12268.372 | V59: =V9*Drivers!U17 -> 13738.797 | W59: =W9*Drivers!V17 -> 13178.699 | X59: =X9*Drivers!W17 -> 12846.722 | ... Z59: =Z9*Drivers!Y17 -> 17007.695 | AB59: =SUM(C59:F59) -> 28862 | AC59: =SUM(G59:J59) -> 37676 | AD59: =SUM(K59:N59) -> 38378 | AE59: =SUM(O59:R59) -> 37659.544 | AF59: =SUM(S59:V59) -> 46927.868 | AG59: =SUM(W59:Z59) -> 58250.011
A61: x | B61: Memo: depreciation and amortization
B62: Total depreciation and amortization | C62: ='Cash Flow'!B10 -> 11432 | D62: ='Cash Flow'!C10 -> 10898 | E62: ='Cash Flow'!D10 -> 11401 | F62: ='Cash Flow'!E10 -> 11039 | G62: ='Cash Flow'!F10 -> 11212 | H62: ='Cash Flow'!G10 -> 11336 | I62: ='Cash Flow'!H10 -> 11383 | J62: ='Cash Flow'!I10 -> 11421 | ... P62: ='Cash Flow'!O10 -> 10007 | Q62: =Q9*Drivers!P16 -> 11151.336 | R62: =R9*Drivers!Q16 -> 12512.919 | S62: =S9*Drivers!R16 -> 12026.672 | T62: =T9*Drivers!S16 -> 11746.849 | U62: =U9*Drivers!T16 -> 13941.332 | V62: =V9*Drivers!U16 -> 15612.269 | W62: =W9*Drivers!V16 -> 14975.794 | X62: =X9*Drivers!W16 -> 14598.548 | ... Z62: =Z9*Drivers!Y16 -> 19326.927 | AB62: =SUM(C62:F62) -> 44770 | AC62: =SUM(G62:J62) -> 45352 | AD62: =SUM(K62:N62) -> 43769 | AE62: =SUM(O62:R62) -> 43659.255 | AF62: =SUM(S62:V62) -> 53327.122 | AG62: =SUM(W62:Z62) -> 66193.195

Sheet Balance Sheet
B1: PubMatic, Inc. (NASDAQ: PUBM): Balance Sheet
B2: $ in thousands. Quarter-end balances. History begins Q4 2023; forecast balances are driven by the Drivers tab and the cash flow statement. Annual columns show year-end balances.
B4: Period | C4: Q1'23 | D4: Q2'23 | E4: Q3'23 | F4: Q4'23 | G4: Q1'24 | H4: Q2'24 | I4: Q3'24 | J4: Q4'24 | K4: Q1'25 | L4: Q2'25 | M4: Q3'25 | N4: Q4'25 | O4: Q1'26 | P4: Q2'26 | Q4: Q3'26 | R4: Q4'26 | S4: Q1'27 | T4: Q2'27 | U4: Q3'27 | V4: Q4'27 | W4: Q1'28 | X4: Q2'28 | Y4: Q3'28 | Z4: Q4'28 | AB4: FY2023A | AC4: FY2024A | AD4: FY2025A | AE4: FY2026E | AF4: FY2027E | AG4: FY2028E
B5: Period end | C5: 45016 | D5: 45107 | E5: 45199 | F5: 45291 | G5: 45382 | H5: 45473 | I5: 45565 | J5: 45657 | K5: 45747 | L5: 45838 | M5: 45930 | N5: 46022 | O5: 46112 | P5: 46203 | Q5: 46295 | R5: 46387 | S5: 46477 | T5: 46568 | U5: 46660 | V5: 46752 | W5: 46843 | X5: 46934 | Y5: 47026 | Z5: 47118 | AB5: 45291 | AC5: 45657 | AD5: 46022 | AE5: 46387 | AF5: 46752 | AG5: 47118
B6: Status | C6: Actual | D6: Actual | E6: Actual | F6: Actual | G6: Actual | H6: Actual | I6: Actual | J6: Actual | K6: Actual | L6: Actual | M6: Actual | N6: Actual | O6: Actual | P6: Actual | Q6: Forecast | R6: Forecast | S6: Forecast | T6: Forecast | U6: Forecast | V6: Forecast | W6: Forecast | X6: Forecast | Y6: Forecast | Z6: Forecast | AB6: Actual | AC6: Actual | AD6: Actual | AE6: 2A + 2E | AF6: Forecast | AG6: Forecast
A8: x | B8: Assets ($ in thousands, quarter-end)
B9: Cash and cash equivalents | C9: n/a | F9: 78509 | G9: 80194 | H9: 73521 | I9: 78914 | J9: 100452 | K9: 101811 | L9: 90476 | M9: 136548 | N9: 145518 | O9: 144876 | P9: 119971 | Q9: ='Cash Flow'!P47 -> 112983.96 | R9: ='Cash Flow'!Q47 -> 123787.1 | S9: ='Cash Flow'!R47 -> 157370.47 | T9: ='Cash Flow'!S47 -> 172502.93 | U9: ='Cash Flow'!T47 -> 177534.26 | V9: ='Cash Flow'!U47 -> 204940.06 | W9: ='Cash Flow'!V47 -> 262964.88 | X9: ='Cash Flow'!W47 -> 295287.48 | ... Z9: ='Cash Flow'!Y47 -> 364255.77 | AB9: =F9 -> 78509 | AC9: =J9 -> 100452 | AD9: =N9 -> 145518 | AE9: =R9 -> 123787.1 | AF9: =V9 -> 204940.06 | AG9: =Z9 -> 364255.77
B10: Marketable securities | F10: 96835 | G10: 93887 | H10: 92075 | I10: 61463 | J10: 40135 | K10: 42315 | L10: 27089 | M10: 0 | N10: 0 | O10: 0 | P10: 17536 | Q10: =Drivers!P29 -> 17536 | R10: =Drivers!Q29 -> 17536 | S10: =Drivers!R29 -> 17536 | T10: =Drivers!S29 -> 17536 | U10: =Drivers!T29 -> 17536 | V10: =Drivers!U29 -> 17536 | W10: =Drivers!V29 -> 17536 | X10: =Drivers!W29 -> 17536 | ... Z10: =Drivers!Y29 -> 17536 | AB10: =F10 -> 96835 | AC10: =J10 -> 40135 | AD10: =N10 -> 0 | AE10: =R10 -> 17536 | AF10: =V10 -> 17536 | AG10: =Z10 -> 17536
B11: Accounts receivable, net | F11: 375468 | G11: 303284 | H11: 351587 | I11: 376790 | J11: 424814 | K11: 349123 | L11: 383403 | M11: 362591 | N11: 358240 | O11: 336904 | P11: 383197 | Q11: =Drivers!P25/Q$40*'Income Statement'!Q9 -> 476404.45 | R11: =Drivers!Q25/R$40*'Income Statement'!R9 -> 448506.54 | S11: =Drivers!R25/S$40*'Income Statement'!S9 -> 517627.98 | T11: =Drivers!S25/T$40*'Income Statement'!T9 -> 458617.62 | U11: =Drivers!T25/U$40*'Income Statement'!U9 -> 595597.96 | V11: =Drivers!U25/V$40*'Income Statement'!V9 -> 559598.03 | W11: =Drivers!V25/W$40*'Income Statement'!W9 -> 644584.5 | X11: =Drivers!W25/X$40*'Income Statement'!X9 -> 569952.98 | ... Z11: =Drivers!Y25/Z$40*'Income Statement'!Z9 -> 692744.28 | AB11: =F11 -> 375468 | AC11: =J11 -> 424814 | AD11: =N11 -> 358240 | AE11: =R11 -> 448506.54 | AF11: =V11 -> 559598.03 | AG11: =Z11 -> 692744.28
B12: Prepaid expenses and other current assets | F12: 11143 | G12: 11540 | H12: 14788 | I12: 12640 | J12: 10145 | K12: 12018 | L12: 11994 | M12: 21307 | N12: 18889 | O12: 22397 | P12: 17162 | Q12: =Drivers!P27 -> 17162 | R12: =Drivers!Q27 -> 17162 | S12: =Drivers!R27 -> 17162 | T12: =Drivers!S27 -> 17162 | U12: =Drivers!T27 -> 17162 | V12: =Drivers!U27 -> 17162 | W12: =Drivers!V27 -> 17162 | X12: =Drivers!W27 -> 17162 | ... Z12: =Drivers!Y27 -> 17162 | AB12: =F12 -> 11143 | AC12: =J12 -> 10145 | AD12: =N12 -> 18889 | AE12: =R12 -> 17162 | AF12: =V12 -> 17162 | AG12: =Z12 -> 17162
B13: Total current assets | F13: =SUM(F9:F12) -> 561955 | G13: =SUM(G9:G12) -> 488905 | H13: =SUM(H9:H12) -> 531971 | I13: =SUM(I9:I12) -> 529807 | J13: =SUM(J9:J12) -> 575546 | K13: =SUM(K9:K12) -> 505267 | L13: =SUM(L9:L12) -> 512962 | M13: =SUM(M9:M12) -> 520446 | ... Z13: =SUM(Z9:Z12) -> 1091698 | AB13: =F13 -> 561955 | AC13: =J13 -> 575546 | AD13: =N13 -> 522647 | AE13: =R13 -> 606991.65 | AF13: =V13 -> 799236.09 | AG13: =Z13 -> 1091698
B14: Property, equipment and software, net | F14: 60729 | G14: 56550 | H14: 60137 | I14: 63247 | J14: 58522 | K14: 54386 | L14: 51584 | M14: 51396 | N14: 52657 | O14: 50139 | P14: 58528 | Q14: =P14-'Cash Flow'!P26-'Cash Flow'!P27-('Income Statement'!Q62-Drivers!P34) -> 56271.664 | R14: =Q14-'Cash Flow'!Q26-'Cash Flow'!Q27-('Income Statement'!R62-Drivers!Q34) -> 52653.745 | S14: =R14-'Cash Flow'!R26-'Cash Flow'!R27-('Income Statement'!S62-Drivers!R34) -> 49408.073 | T14: =S14-'Cash Flow'!S26-'Cash Flow'!S27-('Income Statement'!T62-Drivers!S34) -> 46442.224 | U14: =T14-'Cash Flow'!T26-'Cash Flow'!T27-('Income Statement'!U62-Drivers!T34) -> 41281.892 | V14: =U14-'Cash Flow'!U26-'Cash Flow'!U27-('Income Statement'!V62-Drivers!U34) -> 34450.623 | W14: =V14-'Cash Flow'!V26-'Cash Flow'!V27-('Income Statement'!W62-Drivers!V34) -> 27974.829 | X14: =W14-'Cash Flow'!W26-'Cash Flow'!W27-('Income Statement'!X62-Drivers!W34) -> 21876.281 | ... Z14: =Y14-'Cash Flow'!Y26-'Cash Flow'!Y27-('Income Statement'!Z62-Drivers!Y34) -> 2257.4283 | AB14: =F14 -> 60729 | AC14: =J14 -> 58522 | AD14: =N14 -> 52657 | AE14: =R14 -> 52653.745 | AF14: =V14 -> 34450.623 | AG14: =Z14 -> 2257.4283
B15: Operating lease right-of-use assets | F15: 21102 | G15: 23473 | H15: 21915 | I15: 34440 | J15: 44402 | K15: 42575 | L15: 41888 | M15: 39993 | N15: 38149 | O15: 36267 | P15: 34518 | Q15: =P15 -> 34518 | R15: =Q15 -> 34518 | S15: =R15 -> 34518 | T15: =S15 -> 34518 | U15: =T15 -> 34518 | V15: =U15 -> 34518 | W15: =V15 -> 34518 | X15: =W15 -> 34518 | ... Z15: =Y15 -> 34518 | AB15: =F15 -> 21102 | AC15: =J15 -> 44402 | AD15: =N15 -> 38149 | AE15: =R15 -> 34518 | AF15: =V15 -> 34518 | AG15: =Z15 -> 34518
B16: Acquisition-related intangible assets, net | F16: 5864 | G16: 5469 | H16: 5074 | I16: 4679 | J16: 4284 | K16: 3889 | L16: 3494 | M16: 3099 | N16: 2704 | O16: 2309 | P16: 1914 | Q16: =P16-Drivers!P34 -> 1519 | R16: =Q16-Drivers!Q34 -> 1124 | S16: =R16-Drivers!R34 -> 843 | T16: =S16-Drivers!S34 -> 562 | U16: =T16-Drivers!T34 -> 281 | V16: =U16-Drivers!U34 -> 0 | W16: =V16-Drivers!V34 -> 0 | X16: =W16-Drivers!W34 -> 0 | ... Z16: =Y16-Drivers!Y34 -> 0 | AB16: =F16 -> 5864 | AC16: =J16 -> 4284 | AD16: =N16 -> 2704 | AE16: =R16 -> 1124 | AF16: =V16 -> 0 | AG16: =Z16 -> 0
B17: Goodwill | F17: 29577 | G17: 29577 | H17: 29577 | I17: 29577 | J17: 29577 | K17: 29577 | L17: 29577 | M17: 29577 | N17: 29577 | O17: 29577 | P17: 29577 | Q17: =P17 -> 29577 | R17: =Q17 -> 29577 | S17: =R17 -> 29577 | T17: =S17 -> 29577 | U17: =T17 -> 29577 | V17: =U17 -> 29577 | W17: =V17 -> 29577 | X17: =W17 -> 29577 | ... Z17: =Y17 -> 29577 | AB17: =F17 -> 29577 | AC17: =J17 -> 29577 | AD17: =N17 -> 29577 | AE17: =R17 -> 29577 | AF17: =V17 -> 29577 | AG17: =Z17 -> 29577
B18: Deferred income tax asset | F18: 13880 | G18: 18547 | H18: 22612 | I18: 24711 | J18: 24864 | K18: 29619 | L18: 33889 | M18: 28269 | N18: 30986 | O18: 32409 | P18: 32128 | Q18: =P18 -> 32128 | R18: =Q18 -> 32128 | S18: =R18 -> 32128 | T18: =S18 -> 32128 | U18: =T18 -> 32128 | V18: =U18 -> 32128 | W18: =V18 -> 32128 | X18: =W18 -> 32128 | ... Z18: =Y18 -> 32128 | AB18: =F18 -> 13880 | AC18: =J18 -> 24864 | AD18: =N18 -> 30986 | AE18: =R18 -> 32128 | AF18: =V18 -> 32128 | AG18: =Z18 -> 32128
B19: Other assets, non-current | F19: 2136 | G19: 3669 | H19: 1817 | I19: 2683 | J19: 2324 | K19: 3289 | L19: 1826 | M19: 3408 | N19: 3475 | O19: 4563 | P19: 5511 | Q19: =P19 -> 5511 | R19: =Q19 -> 5511 | S19: =R19 -> 5511 | T19: =S19 -> 5511 | U19: =T19 -> 5511 | V19: =U19 -> 5511 | W19: =V19 -> 5511 | X19: =W19 -> 5511 | ... Z19: =Y19 -> 5511 | AB19: =F19 -> 2136 | AC19: =J19 -> 2324 | AD19: =N19 -> 3475 | AE19: =R19 -> 5511 | AF19: =V19 -> 5511 | AG19: =Z19 -> 5511
B20: TOTAL ASSETS | F20: =F13+SUM(F14:F19) -> 695243 | G20: =G13+SUM(G14:G19) -> 626190 | H20: =H13+SUM(H14:H19) -> 673103 | I20: =I13+SUM(I14:I19) -> 689144 | J20: =J13+SUM(J14:J19) -> 739519 | K20: =K13+SUM(K14:K19) -> 668602 | L20: =L13+SUM(L14:L19) -> 675220 | M20: =M13+SUM(M14:M19) -> 676188 | ... Z20: =Z13+SUM(Z14:Z19) -> 1195689.5 | AB20: =F20 -> 695243 | AC20: =J20 -> 739519 | AD20: =N20 -> 680195 | AE20: =R20 -> 762503.39 | AF20: =V20 -> 935420.71 | AG20: =Z20 -> 1195689.5
A22: x | B22: Liabilities and stockholders equity
B23: Accounts payable | F23: 347673 | G23: 289176 | H23: 340793 | I23: 360696 | J23: 386602 | K23: 323611 | L23: 361369 | M23: 356469 | N23: 343619 | O23: 342644 | P23: 390046 | Q23: =Drivers!P26/Q$40*'Income Statement'!Q9 -> 466901.57 | R23: =Drivers!Q26/R$40*'Income Statement'!R9 -> 430553.23 | S23: =Drivers!R26/S$40*'Income Statement'!S9 -> 527997.64 | T23: =Drivers!S26/T$40*'Income Statement'!T9 -> 467808.56 | U23: =Drivers!T26/U$40*'Income Statement'!U9 -> 583717.52 | V23: =Drivers!U26/V$40*'Income Statement'!V9 -> 537197.82 | W23: =Drivers!V26/W$40*'Income Statement'!W9 -> 657486.72 | X23: =Drivers!W26/X$40*'Income Statement'!X9 -> 581375.14 | ... Z23: =Drivers!Y26/Z$40*'Income Statement'!Z9 -> 665014.34 | AB23: =F23 -> 347673 | AC23: =J23 -> 386602 | AD23: =N23 -> 343619 | AE23: =R23 -> 430553.23 | AF23: =V23 -> 537197.82 | AG23: =Z23 -> 665014.34
B24: Accrued liabilities | F24: 25684 | G24: 19763 | H24: 22550 | I24: 25697 | J24: 26365 | K24: 20309 | L24: 20983 | M24: 25617 | N24: 25278 | O24: 18616 | P24: 24230 | Q24: =Drivers!P28/Q$40*'Income Statement'!Q17 -> 26459.44 | R24: =Drivers!Q28/R$40*'Income Statement'!R17 -> 26300.142 | S24: =Drivers!R28/S$40*'Income Statement'!S17 -> 19344.953 | T24: =Drivers!S28/T$40*'Income Statement'!T17 -> 24924.054 | U24: =Drivers!T28/U$40*'Income Statement'!U17 -> 27468.295 | V24: =Drivers!U28/V$40*'Income Statement'!V17 -> 27316.368 | W24: =Drivers!V28/W$40*'Income Statement'!W17 -> 20113.668 | X24: =Drivers!W28/X$40*'Income Statement'!X17 -> 25877.631 | ... Z24: =Drivers!Y28/Z$40*'Income Statement'!Z17 -> 28372.169 | AB24: =F24 -> 25684 | AC24: =J24 -> 26365 | AD24: =N24 -> 25278 | AE24: =R24 -> 26300.142 | AF24: =V24 -> 27316.368 | AG24: =Z24 -> 28372.169
B25: Operating lease liabilities, current | F25: 6236 | G25: 6841 | H25: 6780 | I25: 6376 | J25: 5843 | K25: 6241 | L25: 6391 | M25: 6333 | N25: 6953 | O25: 7601 | P25: 7842 | Q25: =P25 -> 7842 | R25: =Q25 -> 7842 | S25: =R25 -> 7842 | T25: =S25 -> 7842 | U25: =T25 -> 7842 | V25: =U25 -> 7842 | W25: =V25 -> 7842 | X25: =W25 -> 7842 | ... Z25: =Y25 -> 7842 | AB25: =F25 -> 6236 | AC25: =J25 -> 5843 | AD25: =N25 -> 6953 | AE25: =R25 -> 7842 | AF25: =V25 -> 7842 | AG25: =Z25 -> 7842
B26: Total current liabilities | F26: =SUM(F23:F25) -> 379593 | G26: =SUM(G23:G25) -> 315780 | H26: =SUM(H23:H25) -> 370123 | I26: =SUM(I23:I25) -> 392769 | J26: =SUM(J23:J25) -> 418810 | K26: =SUM(K23:K25) -> 350161 | L26: =SUM(L23:L25) -> 388743 | M26: =SUM(M23:M25) -> 388419 | ... Z26: =SUM(Z23:Z25) -> 701228.51 | AB26: =F26 -> 379593 | AC26: =J26 -> 418810 | AD26: =N26 -> 375850 | AE26: =R26 -> 464695.37 | AF26: =V26 -> 572356.18 | AG26: =Z26 -> 701228.51
B27: Operating lease liabilities, non-current | F27: 15607 | G27: 17613 | H27: 16199 | I27: 28978 | J27: 39538 | K27: 38649 | L27: 38857 | M27: 38255 | N27: 36910 | O27: 34779 | P27: 32795 | Q27: =P27 -> 32795 | R27: =Q27 -> 32795 | S27: =R27 -> 32795 | T27: =S27 -> 32795 | U27: =T27 -> 32795 | V27: =U27 -> 32795 | W27: =V27 -> 32795 | X27: =W27 -> 32795 | ... Z27: =Y27 -> 32795 | AB27: =F27 -> 15607 | AC27: =J27 -> 39538 | AD27: =N27 -> 36910 | AE27: =R27 -> 32795 | AF27: =V27 -> 32795 | AG27: =Z27 -> 32795
B28: Other liabilities, non-current | F28: 3844 | G28: 4067 | H28: 4052 | I28: 4196 | J28: 3908 | K28: 4191 | L28: 4336 | M28: 4454 | N28: 4846 | O28: 4801 | P28: 6401 | Q28: =P28 -> 6401 | R28: =Q28 -> 6401 | S28: =R28 -> 6401 | T28: =S28 -> 6401 | U28: =T28 -> 6401 | V28: =U28 -> 6401 | W28: =V28 -> 6401 | X28: =W28 -> 6401 | ... Z28: =Y28 -> 6401 | AB28: =F28 -> 3844 | AC28: =J28 -> 3908 | AD28: =N28 -> 4846 | AE28: =R28 -> 6401 | AF28: =V28 -> 6401 | AG28: =Z28 -> 6401
B29: TOTAL LIABILITIES | F29: =F26+F27+F28 -> 399044 | G29: =G26+G27+G28 -> 337460 | H29: =H26+H27+H28 -> 390374 | I29: =I26+I27+I28 -> 425943 | J29: =J26+J27+J28 -> 462256 | K29: =K26+K27+K28 -> 393001 | L29: =L26+L27+L28 -> 431936 | M29: =M26+M27+M28 -> 431128 | ... Z29: =Z26+Z27+Z28 -> 740424.51 | AB29: =F29 -> 399044 | AC29: =J29 -> 462256 | AD29: =N29 -> 417606 | AE29: =R29 -> 503891.37 | AF29: =V29 -> 611552.18 | AG29: =Z29 -> 740424.51
B30: Common stock | F30: 6 | G30: 6 | H30: 6 | I30: 6 | J30: 6 | K30: 6 | L30: 6 | M30: 6 | N30: 7 | O30: 7 | P30: 7 | Q30: =P30 -> 7 | R30: =Q30 -> 7 | S30: =R30 -> 7 | T30: =S30 -> 7 | U30: =T30 -> 7 | V30: =U30 -> 7 | W30: =V30 -> 7 | X30: =W30 -> 7 | ... Z30: =Y30 -> 7 | AB30: =F30 -> 6 | AC30: =J30 -> 6 | AD30: =N30 -> 7 | AE30: =R30 -> 7 | AF30: =V30 -> 7 | AG30: =Z30 -> 7
B31: Treasury stock, at cost | F31: -71103 | G31: -86857 | H31: -107097 | I31: -136275 | J31: -146796 | K31: -150409 | L31: -190687 | M31: -193041 | N31: -193471 | O31: -202296 | P31: -223977 | Q31: =P31+'Cash Flow'!P40 -> -233977 | R31: =Q31+'Cash Flow'!Q40 -> -243977 | S31: =R31+'Cash Flow'!R40 -> -253977 | T31: =S31+'Cash Flow'!S40 -> -263977 | U31: =T31+'Cash Flow'!T40 -> -273977 | V31: =U31+'Cash Flow'!U40 -> -283977 | W31: =V31+'Cash Flow'!V40 -> -293977 | X31: =W31+'Cash Flow'!W40 -> -303977 | ... Z31: =Y31+'Cash Flow'!Y40 -> -323977 | AB31: =F31 -> -71103 | AC31: =J31 -> -146796 | AD31: =N31 -> -193471 | AE31: =R31 -> -243977 | AF31: =V31 -> -283977 | AG31: =Z31 -> -323977
B32: Additional paid-in capital | F32: 230419 | G32: 241179 | H32: 253455 | I32: 264013 | J32: 275304 | K32: 286471 | L32: 299113 | M32: 309789 | N32: 321062 | O32: 330962 | P32: 341643 | Q32: =P32+'Income Statement'!Q59+'Cash Flow'!P38+'Cash Flow'!P37 -> 352456.18 | R32: =Q32+'Income Statement'!R59+'Cash Flow'!Q38+'Cash Flow'!Q37 -> 364467.54 | S32: =R32+'Income Statement'!S59+'Cash Flow'!R38+'Cash Flow'!R37 -> 376051.02 | T32: =S32+'Income Statement'!T59+'Cash Flow'!S38+'Cash Flow'!S37 -> 387388.24 | U32: =T32+'Income Statement'!U59+'Cash Flow'!T38+'Cash Flow'!T37 -> 400656.61 | V32: =U32+'Income Statement'!V59+'Cash Flow'!U38+'Cash Flow'!U37 -> 415395.41 | W32: =V32+'Income Statement'!W59+'Cash Flow'!V38+'Cash Flow'!V37 -> 429574.11 | X32: =W32+'Income Statement'!X59+'Cash Flow'!W38+'Cash Flow'!W37 -> 443420.83 | ... Z32: =Y32+'Income Statement'!Z59+'Cash Flow'!Y38+'Cash Flow'!Y37 -> 477645.42 | AB32: =F32 -> 230419 | AC32: =J32 -> 275304 | AD32: =N32 -> 321062 | AE32: =R32 -> 364467.54 | AF32: =V32 -> 415395.41 | AG32: =Z32 -> 477645.42
B33: Accumulated other comprehensive income (loss) | F33: -4 | G33: -25 | H33: -33 | I33: -29 | J33: -636 | K33: -366 | L33: 161 | M33: 67 | N33: 68 | O33: -86 | P33: -156 | Q33: =P33 -> -156 | R33: =Q33 -> -156 | S33: =R33 -> -156 | T33: =S33 -> -156 | U33: =T33 -> -156 | V33: =U33 -> -156 | W33: =V33 -> -156 | X33: =W33 -> -156 | ... Z33: =Y33 -> -156 | AB33: =F33 -> -4 | AC33: =J33 -> -636 | AD33: =N33 -> 68 | AE33: =R33 -> -156 | AF33: =V33 -> -156 | AG33: =Z33 -> -156
B34: Retained earnings | F34: 136881 | G34: 134427 | H34: 136398 | I34: 135486 | J34: 149385 | K34: 139899 | L34: 134691 | M34: 128239 | N34: 134923 | O34: 122413 | P34: 121211 | Q34: =P34+'Income Statement'!Q27 -> 124881.89 | R34: =Q34+'Income Statement'!R27 -> 138270.48 | S34: =R34+'Income Statement'!S27 -> 145375.91 | T34: =S34+'Income Statement'!T27 -> 151523.92 | U34: =T34+'Income Statement'!U27 -> 166372.69 | V34: =U34+'Income Statement'!V27 -> 192599.12 | W34: =V34+'Income Statement'!W27 -> 211869.71 | X34: =W34+'Income Statement'!X27 -> 229963.14 | ... Z34: =Y34+'Income Statement'!Z27 -> 301745.54 | AB34: =F34 -> 136881 | AC34: =J34 -> 149385 | AD34: =N34 -> 134923 | AE34: =R34 -> 138270.48 | AF34: =V34 -> 192599.12 | AG34: =Z34 -> 301745.54
B35: TOTAL STOCKHOLDERS' EQUITY | F35: =SUM(F30:F34) -> 296199 | G35: =SUM(G30:G34) -> 288730 | H35: =SUM(H30:H34) -> 282729 | I35: =SUM(I30:I34) -> 263201 | J35: =SUM(J30:J34) -> 277263 | K35: =SUM(K30:K34) -> 275601 | L35: =SUM(L30:L34) -> 243284 | M35: =SUM(M30:M34) -> 245060 | ... Z35: =SUM(Z30:Z34) -> 455264.97 | AB35: =F35 -> 296199 | AC35: =J35 -> 277263 | AD35: =N35 -> 262589 | AE35: =R35 -> 258612.02 | AF35: =V35 -> 323868.53 | AG35: =Z35 -> 455264.97
B36: TOTAL LIABILITIES AND STOCKHOLDERS' EQUITY | F36: =F29+F35 -> 695243 | G36: =G29+G35 -> 626190 | H36: =H29+H35 -> 673103 | I36: =I29+I35 -> 689144 | J36: =J29+J35 -> 739519 | K36: =K29+K35 -> 668602 | L36: =L29+L35 -> 675220 | M36: =M29+M35 -> 676188 | ... Z36: =Z29+Z35 -> 1195689.5 | AB36: =F36 -> 695243 | AC36: =J36 -> 739519 | AD36: =N36 -> 680195 | AE36: =R36 -> 762503.39 | AF36: =V36 -> 935420.71 | AG36: =Z36 -> 1195689.5
B37: Balance check (assets less liabilities and equity) | F37: =F20-F36 -> 0 | G37: =G20-G36 -> 0 | H37: =H20-H36 -> 0 | I37: =I20-I36 -> 0 | J37: =J20-J36 -> 0 | K37: =K20-K36 -> 0 | L37: =L20-L36 -> 0 | M37: =M20-M36 -> 0 | ... Z37: =Z20-Z36 -> 0 | AB37: =F37 -> 0 | AC37: =J37 -> 0 | AD37: =N37 -> 0 | AE37: =R37 -> 0 | AF37: =V37 -> 0 | AG37: =Z37 -> 0
A39: x | B39: Working capital and liquidity metrics
B40: Days in quarter (period end less prior period end) | F40: =F5-E5 -> 92 | G40: =G5-F5 -> 91 | H40: =H5-G5 -> 91 | I40: =I5-H5 -> 92 | J40: =J5-I5 -> 92 | K40: =K5-J5 -> 90 | L40: =L5-K5 -> 91 | M40: =M5-L5 -> 92 | ... Z40: =Z5-Y5 -> 92 | AB40: =F40 -> 92 | AC40: =J40 -> 92 | AD40: =N40 -> 92 | AE40: =R40 -> 92 | AF40: =V40 -> 92 | AG40: =Z40 -> 92
B41: Days sales outstanding (AR / quarterly revenue x days) | F41: =IF('Income Statement'!F9=0,0,F11/'Income Statement'!F9*F$40) -> 408.31035 | G41: =IF('Income Statement'!G9=0,0,G11/'Income Statement'!G9*G$40) -> 413.76957 | H41: =IF('Income Statement'!H9=0,0,H11/'Income Statement'!H9*H$40) -> 475.63318 | I41: =IF('Income Statement'!I9=0,0,I11/'Income Statement'!I9*I$40) -> 482.88914 | J41: =IF('Income Statement'!J9=0,0,J11/'Income Statement'!J9*J$40) -> 457.09911 | K41: =IF('Income Statement'!K9=0,0,K11/'Income Statement'!K9*K$40) -> 492.30035 | L41: =IF('Income Statement'!L9=0,0,L11/'Income Statement'!L9*L$40) -> 490.74721 | M41: =IF('Income Statement'!M9=0,0,M11/'Income Statement'!M9*M$40) -> 490.85303 | ... Z41: =IF('Income Statement'!Z9=0,0,Z11/'Income Statement'!Z9*Z$40) -> 412.2 | AB41: =F41 -> 408.31035 | AC41: =J41 -> 457.09911 | AD41: =N41 -> 411.73925 | AE41: =R41 -> 412.2 | AF41: =V41 -> 412.2 | AG41: =Z41 -> 412.2
B42: Days payable outstanding (AP / quarterly revenue x days) | F42: =IF('Income Statement'!F9=0,0,F23/'Income Statement'!F9*F$40) -> 378.08411 | G42: =IF('Income Statement'!G9=0,0,G23/'Income Statement'!G9*G$40) -> 394.52206 | H42: =IF('Income Statement'!H9=0,0,H23/'Income Statement'!H9*H$40) -> 461.03086 | I42: =IF('Income Statement'!I9=0,0,I23/'Income Statement'!I9*I$40) -> 462.26328 | J42: =IF('Income Statement'!J9=0,0,J23/'Income Statement'!J9*J$40) -> 415.98306 | K42: =IF('Income Statement'!K9=0,0,K23/'Income Statement'!K9*K$40) -> 456.32573 | L42: =IF('Income Statement'!L9=0,0,L23/'Income Statement'!L9*L$40) -> 462.54419 | M42: =IF('Income Statement'!M9=0,0,M23/'Income Statement'!M9*M$40) -> 482.56545 | ... Z42: =IF('Income Statement'!Z9=0,0,Z23/'Income Statement'!Z9*Z$40) -> 395.7 | AB42: =F42 -> 378.08411 | AC42: =J42 -> 415.98306 | AD42: =N42 -> 394.93476 | AE42: =R42 -> 395.7 | AF42: =V42 -> 395.7 | AG42: =Z42 -> 395.7
B43: Cash Conversion cycle | F43: =+F41-F42 -> 30.226241 | G43: =+G41-G42 -> 19.247508 | H43: =+H41-H42 -> 14.602316 | I43: =+I41-I42 -> 20.62586 | J43: =+J41-J42 -> 41.116044 | K43: =+K41-K42 -> 35.974618 | L43: =+L41-L42 -> 28.203024 | M43: =+M41-M42 -> 8.2875809 | ... Z43: =+Z41-Z42 -> 16.5
B44: Accrued liabilities days (accrued / quarterly opex x days) | F44: =IF('Income Statement'!F17=0,0,F24/'Income Statement'!F17*F$40) -> 59.10423 | G44: =IF('Income Statement'!G17=0,0,G24/'Income Statement'!G17*G$40) -> 38.426413 | H44: =IF('Income Statement'!H17=0,0,H24/'Income Statement'!H17*H$40) -> 44.520741 | I44: =IF('Income Statement'!I17=0,0,I24/'Income Statement'!I17*I$40) -> 49.621644 | J44: =IF('Income Statement'!J17=0,0,J24/'Income Statement'!J17*J$40) -> 53.000765 | K44: =IF('Income Statement'!K17=0,0,K24/'Income Statement'!K17*K$40) -> 36.454128 | L44: =IF('Income Statement'!L17=0,0,L24/'Income Statement'!L17*L$40) -> 38.23188 | M44: =IF('Income Statement'!M17=0,0,M24/'Income Statement'!M17*M$40) -> 46.232815 | ... Z44: =IF('Income Statement'!Z17=0,0,Z24/'Income Statement'!Z17*Z$40) -> 50.6 | AB44: =F44 -> 59.10423 | AC44: =J44 -> 53.000765 | AD44: =N44 -> 50.512076 | AE44: =R44 -> 50.6 | AF44: =V44 -> 50.6 | AG44: =Z44 -> 50.6
B45: Cash and marketable securities | F45: =F9+F10 -> 175344 | G45: =G9+G10 -> 174081 | H45: =H9+H10 -> 165596 | I45: =I9+I10 -> 140377 | J45: =J9+J10 -> 140587 | K45: =K9+K10 -> 144126 | L45: =L9+L10 -> 117565 | M45: =M9+M10 -> 136548 | ... Z45: =Z9+Z10 -> 381791.77 | AB45: =F45 -> 175344 | AC45: =J45 -> 140587 | AD45: =N45 -> 145518 | AE45: =R45 -> 141323.1 | AF45: =V45 -> 222476.06 | AG45: =Z45 -> 381791.77
B46: Net working capital (current assets less current liabilities) | F46: =F13-F26 -> 182362 | G46: =G13-G26 -> 173125 | H46: =H13-H26 -> 161848 | I46: =I13-I26 -> 137038 | J46: =J13-J26 -> 156736 | K46: =K13-K26 -> 155106 | L46: =L13-L26 -> 124219 | M46: =M13-M26 -> 132027 | ... Z46: =Z13-Z26 -> 390469.54 | AB46: =F46 -> 182362 | AC46: =J46 -> 156736 | AD46: =N46 -> 146797 | AE46: =R46 -> 142296.28 | AF46: =V46 -> 226879.91 | AG46: =Z46 -> 390469.54
A54: x

Sheet Cash Flow
A1: PubMatic, Inc. (NASDAQ: PUBM): Cash Flow Statement
A2: $ in thousands. Actual quarters are derived from year-to-date filings (see CF YTD Inputs). Forecast cash flow is built from the income statement, balance sheet drivers and capital allocation inputs.
A4: Period | B4: Q1'23 | C4: Q2'23 | D4: Q3'23 | E4: Q4'23 | F4: Q1'24 | G4: Q2'24 | H4: Q3'24 | I4: Q4'24 | J4: Q1'25 | K4: Q2'25 | L4: Q3'25 | M4: Q4'25 | N4: Q1'26 | O4: Q2'26 | P4: Q3'26 | Q4: Q4'26 | R4: Q1'27 | S4: Q2'27 | T4: Q3'27 | U4: Q4'27 | V4: Q1'28 | W4: Q2'28 | X4: Q3'28 | Y4: Q4'28 | AA4: FY2023A | AB4: FY2024A | AC4: FY2025A | AD4: FY2026E | AE4: FY2027E | AF4: FY2028E
A5: Period end | B5: 45016 | C5: 45107 | D5: 45199 | E5: 45291 | F5: 45382 | G5: 45473 | H5: 45565 | I5: 45657 | J5: 45747 | K5: 45838 | L5: 45930 | M5: 46022 | N5: 46112 | O5: 46203 | P5: 46295 | Q5: 46387 | R5: 46477 | S5: 46568 | T5: 46660 | U5: 46752 | V5: 46843 | W5: 46934 | X5: 47026 | Y5: 47118 | AA5: 45291 | AB5: 45657 | AC5: 46022 | AD5: 46387 | AE5: 46752 | AF5: 47118
A6: Status | B6: Actual | C6: Actual | D6: Actual | E6: Actual | F6: Actual | G6: Actual | H6: Actual | I6: Actual | J6: Actual | K6: Actual | L6: Actual | M6: Actual | N6: Actual | O6: Actual | P6: Forecast | Q6: Forecast | R6: Forecast | S6: Forecast | T6: Forecast | U6: Forecast | V6: Forecast | W6: Forecast | X6: Forecast | Y6: Forecast | AA6: Actual | AB6: Actual | AC6: Actual | AD6: 2A + 2E | AE6: Forecast | AF6: Forecast
A8: Cash flow from operating activities ($ in thousands)
A9: Net income (loss) | B9: ='CF YTD Inputs'!B9 -> -5871 | C9: ='CF YTD Inputs'!C9-'CF YTD Inputs'!B9 -> -5724 | D9: ='CF YTD Inputs'!D9-'CF YTD Inputs'!C9 -> 1774 | E9: ='CF YTD Inputs'!E9-'CF YTD Inputs'!D9 -> 18702 | F9: ='CF YTD Inputs'!F9 -> -2454 | G9: ='CF YTD Inputs'!G9-'CF YTD Inputs'!F9 -> 1971 | H9: ='CF YTD Inputs'!H9-'CF YTD Inputs'!G9 -> -912 | I9: ='CF YTD Inputs'!I9-'CF YTD Inputs'!H9 -> 13899 | J9: ='CF YTD Inputs'!J9 -> -9486 | K9: ='CF YTD Inputs'!K9-'CF YTD Inputs'!J9 -> -5208 | L9: ='CF YTD Inputs'!L9-'CF YTD Inputs'!K9 -> -6452 | M9: ='CF YTD Inputs'!M9-'CF YTD Inputs'!L9 -> 6684 | N9: ='CF YTD Inputs'!N9 -> -12510 | O9: ='CF YTD Inputs'!O9-'CF YTD Inputs'!N9 -> -1202 | P9: ='Income Statement'!Q27 -> 3670.8894 | Q9: ='Income Statement'!R27 -> 13388.59 | R9: ='Income Statement'!S27 -> 7105.4355 | S9: ='Income Statement'!T27 -> 6148.0025 | T9: ='Income Statement'!U27 -> 14848.769 | U9: ='Income Statement'!V27 -> 26226.434 | V9: ='Income Statement'!W27 -> 19270.588 | W9: ='Income Statement'!X27 -> 18093.43 | ... Y9: ='Income Statement'!Z27 -> 42567.308 | AA9: =SUM(B9:E9) -> 8881 | AB9: =SUM(F9:I9) -> 12504 | AC9: =SUM(J9:M9) -> -14462 | AD9: =SUM(N9:Q9) -> 3347.4791 | AE9: =SUM(R9:U9) -> 54328.641 | AF9: =SUM(V9:Y9) -> 109146.42
A10: Depreciation and amortization | B10: ='CF YTD Inputs'!B10 -> 11432 | C10: ='CF YTD Inputs'!C10-'CF YTD Inputs'!B10 -> 10898 | D10: ='CF YTD Inputs'!D10-'CF YTD Inputs'!C10 -> 11401 | E10: ='CF YTD Inputs'!E10-'CF YTD Inputs'!D10 -> 11039 | F10: ='CF YTD Inputs'!F10 -> 11212 | G10: ='CF YTD Inputs'!G10-'CF YTD Inputs'!F10 -> 11336 | H10: ='CF YTD Inputs'!H10-'CF YTD Inputs'!G10 -> 11383 | I10: ='CF YTD Inputs'!I10-'CF YTD Inputs'!H10 -> 11421 | J10: ='CF YTD Inputs'!J10 -> 11676 | K10: ='CF YTD Inputs'!K10-'CF YTD Inputs'!J10 -> 11861 | L10: ='CF YTD Inputs'!L10-'CF YTD Inputs'!K10 -> 10459 | M10: ='CF YTD Inputs'!M10-'CF YTD Inputs'!L10 -> 9773 | N10: ='CF YTD Inputs'!N10 -> 9988 | O10: ='CF YTD Inputs'!O10-'CF YTD Inputs'!N10 -> 10007 | P10: ='Income Statement'!Q62 -> 11151.336 | Q10: ='Income Statement'!R62 -> 12512.919 | R10: ='Income Statement'!S62 -> 12026.672 | S10: ='Income Statement'!T62 -> 11746.849 | T10: ='Income Statement'!U62 -> 13941.332 | U10: ='Income Statement'!V62 -> 15612.269 | V10: ='Income Statement'!W62 -> 14975.794 | W10: ='Income Statement'!X62 -> 14598.548 | ... Y10: ='Income Statement'!Z62 -> 19326.927 | AA10: =SUM(B10:E10) -> 44770 | AB10: =SUM(F10:I10) -> 45352 | AC10: =SUM(J10:M10) -> 43769 | AD10: =SUM(N10:Q10) -> 43659.255 | AE10: =SUM(R10:U10) -> 53327.122 | AF10: =SUM(V10:Y10) -> 66193.195
A11: Stock-based compensation | B11: ='CF YTD Inputs'!B11 -> 7059 | C11: ='CF YTD Inputs'!C11-'CF YTD Inputs'!B11 -> 7266 | D11: ='CF YTD Inputs'!D11-'CF YTD Inputs'!C11 -> 7200 | E11: ='CF YTD Inputs'!E11-'CF YTD Inputs'!D11 -> 7337 | F11: ='CF YTD Inputs'!F11 -> 9111 | G11: ='CF YTD Inputs'!G11-'CF YTD Inputs'!F11 -> 9699 | H11: ='CF YTD Inputs'!H11-'CF YTD Inputs'!G11 -> 9457 | I11: ='CF YTD Inputs'!I11-'CF YTD Inputs'!H11 -> 9409 | J11: ='CF YTD Inputs'!J11 -> 9698 | K11: ='CF YTD Inputs'!K11-'CF YTD Inputs'!J11 -> 9801 | L11: ='CF YTD Inputs'!L11-'CF YTD Inputs'!K11 -> 9511 | M11: ='CF YTD Inputs'!M11-'CF YTD Inputs'!L11 -> 9368 | N11: ='CF YTD Inputs'!N11 -> 8488 | O11: ='CF YTD Inputs'!O11-'CF YTD Inputs'!N11 -> 8347 | P11: ='Income Statement'!Q59 -> 9813.1753 | Q11: ='Income Statement'!R59 -> 11011.369 | R11: ='Income Statement'!S59 -> 10583.472 | S11: ='Income Statement'!T59 -> 10337.227 | T11: ='Income Statement'!U59 -> 12268.372 | U11: ='Income Statement'!V59 -> 13738.797 | V11: ='Income Statement'!W59 -> 13178.699 | W11: ='Income Statement'!X59 -> 12846.722 | ... Y11: ='Income Statement'!Z59 -> 17007.695 | AA11: =SUM(B11:E11) -> 28862 | AB11: =SUM(F11:I11) -> 37676 | AC11: =SUM(J11:M11) -> 38378 | AD11: =SUM(N11:Q11) -> 37659.544 | AE11: =SUM(R11:U11) -> 46927.868 | AF11: =SUM(V11:Y11) -> 58250.011
A12: Provision for doubtful accounts | B12: ='CF YTD Inputs'!B12 -> 0 | C12: ='CF YTD Inputs'!C12-'CF YTD Inputs'!B12 -> 5675 | D12: ='CF YTD Inputs'!D12-'CF YTD Inputs'!C12 -> 0 | E12: ='CF YTD Inputs'!E12-'CF YTD Inputs'!D12 -> 0 | F12: ='CF YTD Inputs'!F12 -> 0 | G12: ='CF YTD Inputs'!G12-'CF YTD Inputs'!F12 -> 0 | H12: ='CF YTD Inputs'!H12-'CF YTD Inputs'!G12 -> 0 | I12: ='CF YTD Inputs'!I12-'CF YTD Inputs'!H12 -> 0 | J12: ='CF YTD Inputs'!J12 -> 0 | K12: ='CF YTD Inputs'!K12-'CF YTD Inputs'!J12 -> 0 | L12: ='CF YTD Inputs'!L12-'CF YTD Inputs'!K12 -> 0 | M12: ='CF YTD Inputs'!M12-'CF YTD Inputs'!L12 -> 0 | N12: ='CF YTD Inputs'!N12 -> 0 | O12: ='CF YTD Inputs'!O12-'CF YTD Inputs'!N12 -> 0 | AA12: =SUM(B12:E12) -> 5675 | AB12: =SUM(F12:I12) -> 0 | AC12: =SUM(J12:M12) -> 0 | AD12: =SUM(N12:Q12) -> 0 | AE12: =SUM(R12:U12) -> 0 | AF12: =SUM(V12:Y12) -> 0
A13: Deferred income taxes | B13: ='CF YTD Inputs'!B13 -> -4327 | C13: ='CF YTD Inputs'!C13-'CF YTD Inputs'!B13 -> -9228 | D13: ='CF YTD Inputs'!D13-'CF YTD Inputs'!C13 -> -630 | E13: ='CF YTD Inputs'!E13-'CF YTD Inputs'!D13 -> 779 | F13: ='CF YTD Inputs'!F13 -> -4667 | G13: ='CF YTD Inputs'!G13-'CF YTD Inputs'!F13 -> -4065 | H13: ='CF YTD Inputs'!H13-'CF YTD Inputs'!G13 -> -2099 | I13: ='CF YTD Inputs'!I13-'CF YTD Inputs'!H13 -> -153 | J13: ='CF YTD Inputs'!J13 -> -4754 | K13: ='CF YTD Inputs'!K13-'CF YTD Inputs'!J13 -> -4270 | L13: ='CF YTD Inputs'!L13-'CF YTD Inputs'!K13 -> -2748 | M13: ='CF YTD Inputs'!M13-'CF YTD Inputs'!L13 -> -2717 | N13: ='CF YTD Inputs'!N13 -> -1423 | O13: ='CF YTD Inputs'!O13-'CF YTD Inputs'!N13 -> 280 | AA13: =SUM(B13:E13) -> -13406 | AB13: =SUM(F13:I13) -> -10984 | AC13: =SUM(J13:M13) -> -14489 | AD13: =SUM(N13:Q13) -> -1143 | AE13: =SUM(R13:U13) -> 0 | AF13: =SUM(V13:Y13) -> 0
A14: Accretion of discount on marketable securities | B14: ='CF YTD Inputs'!B14 -> -1057 | C14: ='CF YTD Inputs'!C14-'CF YTD Inputs'!B14 -> -985 | D14: ='CF YTD Inputs'!D14-'CF YTD Inputs'!C14 -> -1019 | E14: ='CF YTD Inputs'!E14-'CF YTD Inputs'!D14 -> -1032 | F14: ='CF YTD Inputs'!F14 -> -1234 | G14: ='CF YTD Inputs'!G14-'CF YTD Inputs'!F14 -> -1226 | H14: ='CF YTD Inputs'!H14-'CF YTD Inputs'!G14 -> -1092 | I14: ='CF YTD Inputs'!I14-'CF YTD Inputs'!H14 -> -565 | J14: ='CF YTD Inputs'!J14 -> -454 | K14: ='CF YTD Inputs'!K14-'CF YTD Inputs'!J14 -> -365 | L14: ='CF YTD Inputs'!L14-'CF YTD Inputs'!K14 -> -3 | M14: ='CF YTD Inputs'!M14-'CF YTD Inputs'!L14 -> 0 | N14: ='CF YTD Inputs'!N14 -> 0 | O14: ='CF YTD Inputs'!O14-'CF YTD Inputs'!N14 -> -110 | AA14: =SUM(B14:E14) -> -4093 | AB14: =SUM(F14:I14) -> -4117 | AC14: =SUM(J14:M14) -> -822 | AD14: =SUM(N14:Q14) -> -110 | AE14: =SUM(R14:U14) -> 0 | AF14: =SUM(V14:Y14) -> 0
A15: Non-cash operating lease expense | B15: ='CF YTD Inputs'!B15 -> 1532 | C15: ='CF YTD Inputs'!C15-'CF YTD Inputs'!B15 -> 1535 | D15: ='CF YTD Inputs'!D15-'CF YTD Inputs'!C15 -> 1538 | E15: ='CF YTD Inputs'!E15-'CF YTD Inputs'!D15 -> 1540 | F15: ='CF YTD Inputs'!F15 -> 1690 | G15: ='CF YTD Inputs'!G15-'CF YTD Inputs'!F15 -> 1785 | H15: ='CF YTD Inputs'!H15-'CF YTD Inputs'!G15 -> 1623 | I15: ='CF YTD Inputs'!I15-'CF YTD Inputs'!H15 -> 1703 | J15: ='CF YTD Inputs'!J15 -> 1928 | K15: ='CF YTD Inputs'!K15-'CF YTD Inputs'!J15 -> 1782 | L15: ='CF YTD Inputs'!L15-'CF YTD Inputs'!K15 -> 1818 | M15: ='CF YTD Inputs'!M15-'CF YTD Inputs'!L15 -> 1823 | N15: ='CF YTD Inputs'!N15 -> 1840 | O15: ='CF YTD Inputs'!O15-'CF YTD Inputs'!N15 -> 1751 | AA15: =SUM(B15:E15) -> 6145 | AB15: =SUM(F15:I15) -> 6801 | AC15: =SUM(J15:M15) -> 7351 | AD15: =SUM(N15:Q15) -> 3591 | AE15: =SUM(R15:U15) -> 0 | AF15: =SUM(V15:Y15) -> 0
A16: Other non-cash items | B16: ='CF YTD Inputs'!B16 -> -3 | C16: ='CF YTD Inputs'!C16-'CF YTD Inputs'!B16 -> 7 | D16: ='CF YTD Inputs'!D16-'CF YTD Inputs'!C16 -> -1 | E16: ='CF YTD Inputs'!E16-'CF YTD Inputs'!D16 -> 42 | F16: ='CF YTD Inputs'!F16 -> -1 | G16: ='CF YTD Inputs'!G16-'CF YTD Inputs'!F16 -> 2 | H16: ='CF YTD Inputs'!H16-'CF YTD Inputs'!G16 -> -79 | I16: ='CF YTD Inputs'!I16-'CF YTD Inputs'!H16 -> 53 | J16: ='CF YTD Inputs'!J16 -> -223 | K16: ='CF YTD Inputs'!K16-'CF YTD Inputs'!J16 -> -55 | L16: ='CF YTD Inputs'!L16-'CF YTD Inputs'!K16 -> -586 | M16: ='CF YTD Inputs'!M16-'CF YTD Inputs'!L16 -> -183 | N16: ='CF YTD Inputs'!N16 -> -676 | O16: ='CF YTD Inputs'!O16-'CF YTD Inputs'!N16 -> 371 | AA16: =SUM(B16:E16) -> 45 | AB16: =SUM(F16:I16) -> -25 | AC16: =SUM(J16:M16) -> -1047 | AD16: =SUM(N16:Q16) -> -305 | AE16: =SUM(R16:U16) -> 0 | AF16: =SUM(V16:Y16) -> 0
A17: Change in accounts receivable | B17: ='CF YTD Inputs'!B17 -> 61292 | C17: ='CF YTD Inputs'!C17-'CF YTD Inputs'!B17 -> -19549 | D17: ='CF YTD Inputs'!D17-'CF YTD Inputs'!C17 -> -33376 | E17: ='CF YTD Inputs'!E17-'CF YTD Inputs'!D17 -> -84083 | F17: ='CF YTD Inputs'!F17 -> 72184 | G17: ='CF YTD Inputs'!G17-'CF YTD Inputs'!F17 -> -48303 | H17: ='CF YTD Inputs'!H17-'CF YTD Inputs'!G17 -> -25203 | I17: ='CF YTD Inputs'!I17-'CF YTD Inputs'!H17 -> -48023 | J17: ='CF YTD Inputs'!J17 -> 75691 | K17: ='CF YTD Inputs'!K17-'CF YTD Inputs'!J17 -> -34279 | L17: ='CF YTD Inputs'!L17-'CF YTD Inputs'!K17 -> 20811 | M17: ='CF YTD Inputs'!M17-'CF YTD Inputs'!L17 -> 4351 | N17: ='CF YTD Inputs'!N17 -> 21335 | O17: ='CF YTD Inputs'!O17-'CF YTD Inputs'!N17 -> -46292 | P17: =-('Balance Sheet'!Q11-'Balance Sheet'!P11) -> -93207.45 | Q17: =-('Balance Sheet'!R11-'Balance Sheet'!Q11) -> 27897.906 | R17: =-('Balance Sheet'!S11-'Balance Sheet'!R11) -> -69121.436 | S17: =-('Balance Sheet'!T11-'Balance Sheet'!S11) -> 59010.359 | T17: =-('Balance Sheet'!U11-'Balance Sheet'!T11) -> -136980.34 | U17: =-('Balance Sheet'!V11-'Balance Sheet'!U11) -> 35999.929 | V17: =-('Balance Sheet'!W11-'Balance Sheet'!V11) -> -84986.47 | W17: =-('Balance Sheet'!X11-'Balance Sheet'!W11) -> 74631.519 | ... Y17: =-('Balance Sheet'!Z11-'Balance Sheet'!Y11) -> 45996.895 | AA17: =SUM(B17:E17) -> -75716 | AB17: =SUM(F17:I17) -> -49345 | AC17: =SUM(J17:M17) -> 66574 | AD17: =SUM(N17:Q17) -> -90266.544 | AE17: =SUM(R17:U17) -> -111091.48 | AF17: =SUM(V17:Y17) -> -133146.25
A18: Change in prepaid expenses and other assets | B18: ='CF YTD Inputs'!B18 -> 894 | C18: ='CF YTD Inputs'!C18-'CF YTD Inputs'!B18 -> 13 | D18: ='CF YTD Inputs'!D18-'CF YTD Inputs'!C18 -> 2594 | E18: ='CF YTD Inputs'!E18-'CF YTD Inputs'!D18 -> 417 | F18: ='CF YTD Inputs'!F18 -> -196 | G18: ='CF YTD Inputs'!G18-'CF YTD Inputs'!F18 -> -3201 | H18: ='CF YTD Inputs'!H18-'CF YTD Inputs'!G18 -> 1843 | I18: ='CF YTD Inputs'!I18-'CF YTD Inputs'!H18 -> -4272 | J18: ='CF YTD Inputs'!J18 -> 5681 | K18: ='CF YTD Inputs'!K18-'CF YTD Inputs'!J18 -> -6021 | L18: ='CF YTD Inputs'!L18-'CF YTD Inputs'!K18 -> -1881 | M18: ='CF YTD Inputs'!M18-'CF YTD Inputs'!L18 -> -13999 | N18: ='CF YTD Inputs'!N18 -> 4082 | O18: ='CF YTD Inputs'!O18-'CF YTD Inputs'!N18 -> -36 | P18: =-('Balance Sheet'!Q12-'Balance Sheet'!P12) -> 0 | Q18: =-('Balance Sheet'!R12-'Balance Sheet'!Q12) -> 0 | R18: =-('Balance Sheet'!S12-'Balance Sheet'!R12) -> 0 | S18: =-('Balance Sheet'!T12-'Balance Sheet'!S12) -> 0 | T18: =-('Balance Sheet'!U12-'Balance Sheet'!T12) -> 0 | U18: =-('Balance Sheet'!V12-'Balance Sheet'!U12) -> 0 | V18: =-('Balance Sheet'!W12-'Balance Sheet'!V12) -> 0 | W18: =-('Balance Sheet'!X12-'Balance Sheet'!W12) -> 0 | ... Y18: =-('Balance Sheet'!Z12-'Balance Sheet'!Y12) -> 0 | AA18: =SUM(B18:E18) -> 3918 | AB18: =SUM(F18:I18) -> -5826 | AC18: =SUM(J18:M18) -> -16220 | AD18: =SUM(N18:Q18) -> 4046 | AE18: =SUM(R18:U18) -> 0 | AF18: =SUM(V18:Y18) -> 0
A19: Change in accounts payable | B19: ='CF YTD Inputs'!B19 -> -55387 | C19: ='CF YTD Inputs'!C19-'CF YTD Inputs'!B19 -> 25309 | D19: ='CF YTD Inputs'!D19-'CF YTD Inputs'!C19 -> 34219 | E19: ='CF YTD Inputs'!E19-'CF YTD Inputs'!D19 -> 75546 | F19: ='CF YTD Inputs'!F19 -> -58444 | G19: ='CF YTD Inputs'!G19-'CF YTD Inputs'!F19 -> 43676 | H19: ='CF YTD Inputs'!H19-'CF YTD Inputs'!G19 -> 23609 | I19: ='CF YTD Inputs'!I19-'CF YTD Inputs'!H19 -> 29255 | J19: ='CF YTD Inputs'!J19 -> -62578 | K19: ='CF YTD Inputs'!K19-'CF YTD Inputs'!J19 -> 36713 | L19: ='CF YTD Inputs'!L19-'CF YTD Inputs'!K19 -> -4116 | M19: ='CF YTD Inputs'!M19-'CF YTD Inputs'!L19 -> -12416 | N19: ='CF YTD Inputs'!N19 -> -997 | O19: ='CF YTD Inputs'!O19-'CF YTD Inputs'!N19 -> 37555 | P19: ='Balance Sheet'!Q23-'Balance Sheet'!P23 -> 76855.573 | Q19: ='Balance Sheet'!R23-'Balance Sheet'!Q23 -> -36348.348 | R19: ='Balance Sheet'!S23-'Balance Sheet'!R23 -> 97444.419 | S19: ='Balance Sheet'!T23-'Balance Sheet'!S23 -> -60189.082 | T19: ='Balance Sheet'!U23-'Balance Sheet'!T23 -> 115908.96 | U19: ='Balance Sheet'!V23-'Balance Sheet'!U23 -> -46519.702 | V19: ='Balance Sheet'!W23-'Balance Sheet'!V23 -> 120288.9 | W19: ='Balance Sheet'!X23-'Balance Sheet'!W23 -> -76111.581 | ... Y19: ='Balance Sheet'!Z23-'Balance Sheet'!Y23 -> -58991.104 | AA19: =SUM(B19:E19) -> 79687 | AB19: =SUM(F19:I19) -> 38096 | AC19: =SUM(J19:M19) -> -42397 | AD19: =SUM(N19:Q19) -> 77065.226 | AE19: =SUM(R19:U19) -> 106644.59 | AF19: =SUM(V19:Y19) -> 127816.52
A20: Change in accrued liabilities | B20: ='CF YTD Inputs'!B20 -> -833 | C20: ='CF YTD Inputs'!C20-'CF YTD Inputs'!B20 -> 2708 | D20: ='CF YTD Inputs'!D20-'CF YTD Inputs'!C20 -> 1339 | E20: ='CF YTD Inputs'!E20-'CF YTD Inputs'!D20 -> -179 | F20: ='CF YTD Inputs'!F20 -> -1784 | G20: ='CF YTD Inputs'!G20-'CF YTD Inputs'!F20 -> 1840 | H20: ='CF YTD Inputs'!H20-'CF YTD Inputs'!G20 -> 2203 | I20: ='CF YTD Inputs'!I20-'CF YTD Inputs'!H20 -> 7368 | J20: ='CF YTD Inputs'!J20 -> -11287 | K20: ='CF YTD Inputs'!K20-'CF YTD Inputs'!J20 -> 5728 | L20: ='CF YTD Inputs'!L20-'CF YTD Inputs'!K20 -> 5988 | M20: ='CF YTD Inputs'!M20-'CF YTD Inputs'!L20 -> 15750 | N20: ='CF YTD Inputs'!N20 -> -11382 | O20: ='CF YTD Inputs'!O20-'CF YTD Inputs'!N20 -> 9644 | P20: ='Balance Sheet'!Q24-'Balance Sheet'!P24 -> 2229.44 | Q20: ='Balance Sheet'!R24-'Balance Sheet'!Q24 -> -159.298 | R20: ='Balance Sheet'!S24-'Balance Sheet'!R24 -> -6955.1892 | S20: ='Balance Sheet'!T24-'Balance Sheet'!S24 -> 5579.101 | T20: ='Balance Sheet'!U24-'Balance Sheet'!T24 -> 2544.2414 | U20: ='Balance Sheet'!V24-'Balance Sheet'!U24 -> -151.92766 | V20: ='Balance Sheet'!W24-'Balance Sheet'!V24 -> -7202.6999 | W20: ='Balance Sheet'!X24-'Balance Sheet'!W24 -> 5763.9637 | ... Y20: ='Balance Sheet'!Z24-'Balance Sheet'!Y24 -> -143.85024 | AA20: =SUM(B20:E20) -> 3035 | AB20: =SUM(F20:I20) -> 9627 | AC20: =SUM(J20:M20) -> 16179 | AD20: =SUM(N20:Q20) -> 332.142 | AE20: =SUM(R20:U20) -> 1016.2255 | AF20: =SUM(V20:Y20) -> 1055.8012
A21: Change in operating lease liabilities | B21: ='CF YTD Inputs'!B21 -> -1265 | C21: ='CF YTD Inputs'!C21-'CF YTD Inputs'!B21 -> -1475 | D21: ='CF YTD Inputs'!D21-'CF YTD Inputs'!C21 -> -1542 | E21: ='CF YTD Inputs'!E21-'CF YTD Inputs'!D21 -> -1507 | F21: ='CF YTD Inputs'!F21 -> -1380 | G21: ='CF YTD Inputs'!G21-'CF YTD Inputs'!F21 -> -1590 | H21: ='CF YTD Inputs'!H21-'CF YTD Inputs'!G21 -> -1771 | I21: ='CF YTD Inputs'!I21-'CF YTD Inputs'!H21 -> -1790 | J21: ='CF YTD Inputs'!J21 -> -590 | K21: ='CF YTD Inputs'!K21-'CF YTD Inputs'!J21 -> -738 | L21: ='CF YTD Inputs'!L21-'CF YTD Inputs'!K21 -> -584 | M21: ='CF YTD Inputs'!M21-'CF YTD Inputs'!L21 -> -704 | N21: ='CF YTD Inputs'!N21 -> -1444 | O21: ='CF YTD Inputs'!O21-'CF YTD Inputs'!N21 -> -1744 | AA21: =SUM(B21:E21) -> -5789 | AB21: =SUM(F21:I21) -> -6531 | AC21: =SUM(J21:M21) -> -2616 | AD21: =SUM(N21:Q21) -> -3188 | AE21: =SUM(R21:U21) -> 0 | AF21: =SUM(V21:Y21) -> 0
A22: Change in other liabilities, non-current | B22: ='CF YTD Inputs'!B22 -> -712 | C22: ='CF YTD Inputs'!C22-'CF YTD Inputs'!B22 -> -602 | D22: ='CF YTD Inputs'!D22-'CF YTD Inputs'!C22 -> 348 | E22: ='CF YTD Inputs'!E22-'CF YTD Inputs'!D22 -> 73 | F22: ='CF YTD Inputs'!F22 -> 257 | G22: ='CF YTD Inputs'!G22-'CF YTD Inputs'!F22 -> 20 | H22: ='CF YTD Inputs'!H22-'CF YTD Inputs'!G22 -> 177 | I22: ='CF YTD Inputs'!I22-'CF YTD Inputs'!H22 -> -257 | J22: ='CF YTD Inputs'!J22 -> 319 | K22: ='CF YTD Inputs'!K22-'CF YTD Inputs'!J22 -> -44 | L22: ='CF YTD Inputs'!L22-'CF YTD Inputs'!K22 -> 157 | M22: ='CF YTD Inputs'!M22-'CF YTD Inputs'!L22 -> 429 | N22: ='CF YTD Inputs'!N22 -> -6 | O22: ='CF YTD Inputs'!O22-'CF YTD Inputs'!N22 -> 1639 | AA22: =SUM(B22:E22) -> -893 | AB22: =SUM(F22:I22) -> 197 | AC22: =SUM(J22:M22) -> 861 | AD22: =SUM(N22:Q22) -> 1633 | AE22: =SUM(R22:U22) -> 0 | AF22: =SUM(V22:Y22) -> 0
A23: Net cash provided by operating activities | B23: =SUM(B9:B22) -> 12754 | C23: =SUM(C9:C22) -> 15848 | D23: =SUM(D9:D22) -> 23845 | E23: =SUM(E9:E22) -> 28674 | F23: =SUM(F9:F22) -> 24294 | G23: =SUM(G9:G22) -> 11944 | H23: =SUM(H9:H22) -> 19139 | I23: =SUM(I9:I22) -> 18048 | ... Y23: =SUM(Y9:Y22) -> 65763.87 | AA23: =SUM(AA9:AA22) -> 81121 | AB23: =SUM(AB9:AB22) -> 73425 | AC23: =SUM(AC9:AC22) -> 81059 | AD23: =SUM(AD9:AD22) -> 76321.101 | AE23: =SUM(AE9:AE22) -> 151152.96 | AF23: =SUM(AF9:AF22) -> 229315.7
A25: Cash flow from investing activities
A26: Purchases of property and equipment | B26: ='CF YTD Inputs'!B26 -> -1417 | C26: ='CF YTD Inputs'!C26-'CF YTD Inputs'!B26 -> -1135 | D26: ='CF YTD Inputs'!D26-'CF YTD Inputs'!C26 -> -2872 | E26: ='CF YTD Inputs'!E26-'CF YTD Inputs'!D26 -> -5177 | F26: ='CF YTD Inputs'!F26 -> -801 | G26: ='CF YTD Inputs'!G26-'CF YTD Inputs'!F26 -> -736 | H26: ='CF YTD Inputs'!H26-'CF YTD Inputs'!G26 -> -11731 | I26: ='CF YTD Inputs'!I26-'CF YTD Inputs'!H26 -> -4324 | J26: ='CF YTD Inputs'!J26 -> -1441 | K26: ='CF YTD Inputs'!K26-'CF YTD Inputs'!J26 -> -1340 | L26: ='CF YTD Inputs'!L26-'CF YTD Inputs'!K26 -> -4674 | M26: ='CF YTD Inputs'!M26-'CF YTD Inputs'!L26 -> -6890 | N26: ='CF YTD Inputs'!N26 -> -11 | O26: ='CF YTD Inputs'!O26-'CF YTD Inputs'!N26 -> -2955 | P26: =-Drivers!P32 -> -3500 | Q26: =-Drivers!Q32 -> -3500 | R26: =-Drivers!R32 -> -3500 | S26: =-Drivers!S32 -> -3500 | T26: =-Drivers!T32 -> -3500 | U26: =-Drivers!U32 -> -3500 | V26: =-Drivers!V32 -> -3500 | W26: =-Drivers!W32 -> -3500 | ... Y26: =-Drivers!Y32 -> -3500 | AA26: =SUM(B26:E26) -> -10601 | AB26: =SUM(F26:I26) -> -17592 | AC26: =SUM(J26:M26) -> -14345 | AD26: =SUM(N26:Q26) -> -9966 | AE26: =SUM(R26:U26) -> -14000 | AF26: =SUM(V26:Y26) -> -14000
A27: Capitalized software development costs | B27: ='CF YTD Inputs'!B27 -> -6001 | C27: ='CF YTD Inputs'!C27-'CF YTD Inputs'!B27 -> -3918 | D27: ='CF YTD Inputs'!D27-'CF YTD Inputs'!C27 -> -3806 | E27: ='CF YTD Inputs'!E27-'CF YTD Inputs'!D27 -> -3962 | F27: ='CF YTD Inputs'!F27 -> -7231 | G27: ='CF YTD Inputs'!G27-'CF YTD Inputs'!F27 -> -4295 | H27: ='CF YTD Inputs'!H27-'CF YTD Inputs'!G27 -> -4542 | I27: ='CF YTD Inputs'!I27-'CF YTD Inputs'!H27 -> -4868 | J27: ='CF YTD Inputs'!J27 -> -6880 | K27: ='CF YTD Inputs'!K27-'CF YTD Inputs'!J27 -> -4300 | L27: ='CF YTD Inputs'!L27-'CF YTD Inputs'!K27 -> -4914 | M27: ='CF YTD Inputs'!M27-'CF YTD Inputs'!L27 -> -4417 | N27: ='CF YTD Inputs'!N27 -> -6579 | O27: ='CF YTD Inputs'!O27-'CF YTD Inputs'!N27 -> -3592 | P27: =-Drivers!P33 -> -5000 | Q27: =-Drivers!Q33 -> -5000 | R27: =-Drivers!R33 -> -5000 | S27: =-Drivers!S33 -> -5000 | T27: =-Drivers!T33 -> -5000 | U27: =-Drivers!U33 -> -5000 | V27: =-Drivers!V33 -> -5000 | W27: =-Drivers!W33 -> -5000 | ... Y27: =-Drivers!Y33 -> -5000 | AA27: =SUM(B27:E27) -> -17687 | AB27: =SUM(F27:I27) -> -20936 | AC27: =SUM(J27:M27) -> -20511 | AD27: =SUM(N27:Q27) -> -20171 | AE27: =SUM(R27:U27) -> -20000 | AF27: =SUM(V27:Y27) -> -20000
A28: Purchases of marketable securities | B28: ='CF YTD Inputs'!B28 -> -40343 | C28: ='CF YTD Inputs'!C28-'CF YTD Inputs'!B28 -> -6372 | D28: ='CF YTD Inputs'!D28-'CF YTD Inputs'!C28 -> -30217 | E28: ='CF YTD Inputs'!E28-'CF YTD Inputs'!D28 -> -63671 | F28: ='CF YTD Inputs'!F28 -> -34336 | G28: ='CF YTD Inputs'!G28-'CF YTD Inputs'!F28 -> -62229 | H28: ='CF YTD Inputs'!H28-'CF YTD Inputs'!G28 -> -21412 | I28: ='CF YTD Inputs'!I28-'CF YTD Inputs'!H28 -> -24039 | J28: ='CF YTD Inputs'!J28 -> -15307 | K28: ='CF YTD Inputs'!K28-'CF YTD Inputs'!J28 -> -10719 | L28: ='CF YTD Inputs'!L28-'CF YTD Inputs'!K28 -> 0 | M28: ='CF YTD Inputs'!M28-'CF YTD Inputs'!L28 -> 0 | N28: ='CF YTD Inputs'!N28 -> 0 | O28: ='CF YTD Inputs'!O28-'CF YTD Inputs'!N28 -> -17429 | AA28: =SUM(B28:E28) -> -140603 | AB28: =SUM(F28:I28) -> -142016 | AC28: =SUM(J28:M28) -> -26026 | AD28: =SUM(N28:Q28) -> -17429 | AE28: =SUM(R28:U28) -> 0 | AF28: =SUM(V28:Y28) -> 0
A29: Proceeds from sales of marketable securities | B29: ='CF YTD Inputs'!B29 -> 0 | C29: ='CF YTD Inputs'!C29-'CF YTD Inputs'!B29 -> 18873 | D29: ='CF YTD Inputs'!D29-'CF YTD Inputs'!C29 -> 0 | E29: ='CF YTD Inputs'!E29-'CF YTD Inputs'!D29 -> 0 | F29: ='CF YTD Inputs'!F29 -> 0 | G29: ='CF YTD Inputs'!G29-'CF YTD Inputs'!F29 -> 0 | H29: ='CF YTD Inputs'!H29-'CF YTD Inputs'!G29 -> 0 | I29: ='CF YTD Inputs'!I29-'CF YTD Inputs'!H29 -> 0 | J29: ='CF YTD Inputs'!J29 -> 0 | K29: ='CF YTD Inputs'!K29-'CF YTD Inputs'!J29 -> 0 | L29: ='CF YTD Inputs'!L29-'CF YTD Inputs'!K29 -> 27095 | M29: ='CF YTD Inputs'!M29-'CF YTD Inputs'!L29 -> 0 | N29: ='CF YTD Inputs'!N29 -> 0 | O29: ='CF YTD Inputs'!O29-'CF YTD Inputs'!N29 -> 0 | AA29: =SUM(B29:E29) -> 18873 | AB29: =SUM(F29:I29) -> 0 | AC29: =SUM(J29:M29) -> 27095 | AD29: =SUM(N29:Q29) -> 0 | AE29: =SUM(R29:U29) -> 0 | AF29: =SUM(V29:Y29) -> 0
A30: Proceeds from maturities of marketable securities | B30: ='CF YTD Inputs'!B30 -> 29500 | C30: ='CF YTD Inputs'!C30-'CF YTD Inputs'!B30 -> 17000 | D30: ='CF YTD Inputs'!D30-'CF YTD Inputs'!C30 -> 23000 | E30: ='CF YTD Inputs'!E30-'CF YTD Inputs'!D30 -> 41500 | F30: ='CF YTD Inputs'!F30 -> 38500 | G30: ='CF YTD Inputs'!G30-'CF YTD Inputs'!F30 -> 65258 | H30: ='CF YTD Inputs'!H30-'CF YTD Inputs'!G30 -> 53200 | I30: ='CF YTD Inputs'!I30-'CF YTD Inputs'!H30 -> 45900 | J30: ='CF YTD Inputs'!J30 -> 13559 | K30: ='CF YTD Inputs'!K30-'CF YTD Inputs'!J30 -> 26300 | L30: ='CF YTD Inputs'!L30-'CF YTD Inputs'!K30 -> 0 | M30: ='CF YTD Inputs'!M30-'CF YTD Inputs'!L30 -> 0 | N30: ='CF YTD Inputs'!N30 -> 0 | O30: ='CF YTD Inputs'!O30-'CF YTD Inputs'!N30 -> 0 | AA30: =SUM(B30:E30) -> 111000 | AB30: =SUM(F30:I30) -> 202858 | AC30: =SUM(J30:M30) -> 39859 | AD30: =SUM(N30:Q30) -> 0 | AE30: =SUM(R30:U30) -> 0 | AF30: =SUM(V30:Y30) -> 0
A31: Net marketable securities activity | B31: =SUM(B28:B30) -> -10843 | C31: =SUM(C28:C30) -> 29501 | D31: =SUM(D28:D30) -> -7217 | E31: =SUM(E28:E30) -> -22171 | F31: =SUM(F28:F30) -> 4164 | G31: =SUM(G28:G30) -> 3029 | H31: =SUM(H28:H30) -> 31788 | I31: =SUM(I28:I30) -> 21861 | ... O31: =SUM(O28:O30) -> -17429 | P31: =-('Balance Sheet'!Q10-'Balance Sheet'!P10) -> 0 | Q31: =-('Balance Sheet'!R10-'Balance Sheet'!Q10) -> 0 | R31: =-('Balance Sheet'!S10-'Balance Sheet'!R10) -> 0 | S31: =-('Balance Sheet'!T10-'Balance Sheet'!S10) -> 0 | T31: =-('Balance Sheet'!U10-'Balance Sheet'!T10) -> 0 | U31: =-('Balance Sheet'!V10-'Balance Sheet'!U10) -> 0 | V31: =-('Balance Sheet'!W10-'Balance Sheet'!V10) -> 0 | W31: =-('Balance Sheet'!X10-'Balance Sheet'!W10) -> 0 | ... Y31: =-('Balance Sheet'!Z10-'Balance Sheet'!Y10) -> 0 | AA31: =SUM(B31:E31) -> -10730 | AB31: =SUM(F31:I31) -> 60842 | AC31: =SUM(J31:M31) -> 40928 | AD31: =SUM(N31:Q31) -> -17429 | AE31: =SUM(R31:U31) -> 0 | AF31: =SUM(V31:Y31) -> 0
A32: Purchase of equity investments | B32: ='CF YTD Inputs'!B31 -> 0 | C32: ='CF YTD Inputs'!C31-'CF YTD Inputs'!B31 -> 0 | D32: ='CF YTD Inputs'!D31-'CF YTD Inputs'!C31 -> 0 | E32: ='CF YTD Inputs'!E31-'CF YTD Inputs'!D31 -> 0 | F32: ='CF YTD Inputs'!F31 -> 0 | G32: ='CF YTD Inputs'!G31-'CF YTD Inputs'!F31 -> 0 | H32: ='CF YTD Inputs'!H31-'CF YTD Inputs'!G31 -> 0 | I32: ='CF YTD Inputs'!I31-'CF YTD Inputs'!H31 -> 0 | J32: ='CF YTD Inputs'!J31 -> 0 | K32: ='CF YTD Inputs'!K31-'CF YTD Inputs'!J31 -> 0 | L32: ='CF YTD Inputs'!L31-'CF YTD Inputs'!K31 -> 0 | M32: ='CF YTD Inputs'!M31-'CF YTD Inputs'!L31 -> 0 | N32: ='CF YTD Inputs'!N31 -> -3000 | O32: ='CF YTD Inputs'!O31-'CF YTD Inputs'!N31 -> -500 | AA32: =SUM(B32:E32) -> 0 | AB32: =SUM(F32:I32) -> 0 | AC32: =SUM(J32:M32) -> 0 | AD32: =SUM(N32:Q32) -> -3500 | AE32: =SUM(R32:U32) -> 0 | AF32: =SUM(V32:Y32) -> 0
A33: Net cash provided by (used in) investing activities | B33: =B26+B27+B31+B32 -> -18261 | C33: =C26+C27+C31+C32 -> 24448 | D33: =D26+D27+D31+D32 -> -13895 | E33: =E26+E27+E31+E32 -> -31310 | F33: =F26+F27+F31+F32 -> -3868 | G33: =G26+G27+G31+G32 -> -2002 | H33: =H26+H27+H31+H32 -> 15515 | I33: =I26+I27+I31+I32 -> 12669 | ... Y33: =Y26+Y27+Y31+Y32 -> -8500 | AA33: =AA26+AA27+AA31+AA32 -> -39018 | AB33: =AB26+AB27+AB31+AB32 -> 22314 | AC33: =AC26+AC27+AC31+AC32 -> 6072 | AD33: =AD26+AD27+AD31+AD32 -> -51066 | AE33: =AE26+AE27+AE31+AE32 -> -34000 | AF33: =AF26+AF27+AF31+AF32 -> -34000
A35: Cash flow from financing activities
A36: Payment of acquisition indemnification holdback | B36: ='CF YTD Inputs'!B35 -> 0 | C36: ='CF YTD Inputs'!C35-'CF YTD Inputs'!B35 -> 0 | D36: ='CF YTD Inputs'!D35-'CF YTD Inputs'!C35 -> 0 | E36: ='CF YTD Inputs'!E35-'CF YTD Inputs'!D35 -> 0 | F36: ='CF YTD Inputs'!F35 -> -2148 | G36: ='CF YTD Inputs'!G35-'CF YTD Inputs'!F35 -> 0 | H36: ='CF YTD Inputs'!H35-'CF YTD Inputs'!G35 -> 0 | I36: ='CF YTD Inputs'!I35-'CF YTD Inputs'!H35 -> 0 | J36: ='CF YTD Inputs'!J35 -> 0 | K36: ='CF YTD Inputs'!K35-'CF YTD Inputs'!J35 -> 0 | L36: ='CF YTD Inputs'!L35-'CF YTD Inputs'!K35 -> 0 | M36: ='CF YTD Inputs'!M35-'CF YTD Inputs'!L35 -> 0 | N36: ='CF YTD Inputs'!N35 -> 0 | O36: ='CF YTD Inputs'!O35-'CF YTD Inputs'!N35 -> 0 | AA36: =SUM(B36:E36) -> 0 | AB36: =SUM(F36:I36) -> -2148 | AC36: =SUM(J36:M36) -> 0 | AD36: =SUM(N36:Q36) -> 0 | AE36: =SUM(R36:U36) -> 0 | AF36: =SUM(V36:Y36) -> 0
A37: Proceeds from employee stock purchase plan | B37: ='CF YTD Inputs'!B36 -> 0 | C37: ='CF YTD Inputs'!C36-'CF YTD Inputs'!B36 -> 971 | D37: ='CF YTD Inputs'!D36-'CF YTD Inputs'!C36 -> 0 | E37: ='CF YTD Inputs'!E36-'CF YTD Inputs'!D36 -> 898 | F37: ='CF YTD Inputs'!F36 -> 0 | G37: ='CF YTD Inputs'!G36-'CF YTD Inputs'!F36 -> 1451 | H37: ='CF YTD Inputs'!H36-'CF YTD Inputs'!G36 -> 0 | I37: ='CF YTD Inputs'!I36-'CF YTD Inputs'!H36 -> 917 | J37: ='CF YTD Inputs'!J36 -> 0 | K37: ='CF YTD Inputs'!K36-'CF YTD Inputs'!J36 -> 1357 | L37: ='CF YTD Inputs'!L36-'CF YTD Inputs'!K36 -> 0 | M37: ='CF YTD Inputs'!M36-'CF YTD Inputs'!L36 -> 791 | N37: ='CF YTD Inputs'!N36 -> 0 | O37: ='CF YTD Inputs'!O36-'CF YTD Inputs'!N36 -> 1054 | AA37: =SUM(B37:E37) -> 1869 | AB37: =SUM(F37:I37) -> 2368 | AC37: =SUM(J37:M37) -> 2148 | AD37: =SUM(N37:Q37) -> 1054 | AE37: =SUM(R37:U37) -> 0 | AF37: =SUM(V37:Y37) -> 0
A38: Proceeds from exercise of stock options | B38: ='CF YTD Inputs'!B37 -> 314 | C38: ='CF YTD Inputs'!C37-'CF YTD Inputs'!B37 -> 623 | D38: ='CF YTD Inputs'!D37-'CF YTD Inputs'!C37 -> 273 | E38: ='CF YTD Inputs'!E37-'CF YTD Inputs'!D37 -> 339 | F38: ='CF YTD Inputs'!F37 -> 939 | G38: ='CF YTD Inputs'!G37-'CF YTD Inputs'!F37 -> 335 | H38: ='CF YTD Inputs'!H37-'CF YTD Inputs'!G37 -> 304 | I38: ='CF YTD Inputs'!I37-'CF YTD Inputs'!H37 -> 187 | J38: ='CF YTD Inputs'!J37 -> 563 | K38: ='CF YTD Inputs'!K37-'CF YTD Inputs'!J37 -> 611 | L38: ='CF YTD Inputs'!L37-'CF YTD Inputs'!K37 -> 321 | M38: ='CF YTD Inputs'!M37-'CF YTD Inputs'!L37 -> 264 | N38: ='CF YTD Inputs'!N37 -> 477 | O38: ='CF YTD Inputs'!O37-'CF YTD Inputs'!N37 -> 407 | P38: =Drivers!P36 -> 1000 | Q38: =Drivers!Q36 -> 1000 | R38: =Drivers!R36 -> 1000 | S38: =Drivers!S36 -> 1000 | T38: =Drivers!T36 -> 1000 | U38: =Drivers!U36 -> 1000 | V38: =Drivers!V36 -> 1000 | W38: =Drivers!W36 -> 1000 | ... Y38: =Drivers!Y36 -> 1000 | AA38: =SUM(B38:E38) -> 1549 | AB38: =SUM(F38:I38) -> 1765 | AC38: =SUM(J38:M38) -> 1759 | AD38: =SUM(N38:Q38) -> 2884 | AE38: =SUM(R38:U38) -> 4000 | AF38: =SUM(V38:Y38) -> 4000
A39: Principal payments on finance leases | B39: ='CF YTD Inputs'!B38 -> -31 | C39: ='CF YTD Inputs'!C38-'CF YTD Inputs'!B38 -> -31 | D39: ='CF YTD Inputs'!D38-'CF YTD Inputs'!C38 -> -31 | E39: ='CF YTD Inputs'!E38-'CF YTD Inputs'!D38 -> -33 | F39: ='CF YTD Inputs'!F38 -> -32 | G39: ='CF YTD Inputs'!G38-'CF YTD Inputs'!F38 -> -33 | H39: ='CF YTD Inputs'!H38-'CF YTD Inputs'!G38 -> -33 | I39: ='CF YTD Inputs'!I38-'CF YTD Inputs'!H38 -> -33 | J39: ='CF YTD Inputs'!J38 -> -35 | K39: ='CF YTD Inputs'!K38-'CF YTD Inputs'!J38 -> -35 | L39: ='CF YTD Inputs'!L38-'CF YTD Inputs'!K38 -> -35 | M39: ='CF YTD Inputs'!M38-'CF YTD Inputs'!L38 -> -35 | N39: ='CF YTD Inputs'!N38 -> -36 | O39: ='CF YTD Inputs'!O38-'CF YTD Inputs'!N38 -> -39 | AA39: =SUM(B39:E39) -> -126 | AB39: =SUM(F39:I39) -> -131 | AC39: =SUM(J39:M39) -> -140 | AD39: =SUM(N39:Q39) -> -75 | AE39: =SUM(R39:U39) -> 0 | AF39: =SUM(V39:Y39) -> 0
A40: Payments to acquire treasury stock (buybacks) | B40: ='CF YTD Inputs'!B39 -> -7898 | C40: ='CF YTD Inputs'!C39-'CF YTD Inputs'!B39 -> -15582 | D40: ='CF YTD Inputs'!D39-'CF YTD Inputs'!C39 -> -17999 | E40: ='CF YTD Inputs'!E39-'CF YTD Inputs'!D39 -> -17789 | F40: ='CF YTD Inputs'!F39 -> -17500 | G40: ='CF YTD Inputs'!G39-'CF YTD Inputs'!F39 -> -18368 | H40: ='CF YTD Inputs'!H39-'CF YTD Inputs'!G39 -> -29532 | I40: ='CF YTD Inputs'!I39-'CF YTD Inputs'!H39 -> -9932 | J40: ='CF YTD Inputs'!J39 -> -5000 | K40: ='CF YTD Inputs'!K39-'CF YTD Inputs'!J39 -> -38649 | L40: ='CF YTD Inputs'!L39-'CF YTD Inputs'!K39 -> -4001 | M40: ='CF YTD Inputs'!M39-'CF YTD Inputs'!L39 -> 1152 | N40: ='CF YTD Inputs'!N39 -> -8500 | O40: ='CF YTD Inputs'!O39-'CF YTD Inputs'!N39 -> -22000 | P40: =-Drivers!P35 -> -10000 | Q40: =-Drivers!Q35 -> -10000 | R40: =-Drivers!R35 -> -10000 | S40: =-Drivers!S35 -> -10000 | T40: =-Drivers!T35 -> -10000 | U40: =-Drivers!U35 -> -10000 | V40: =-Drivers!V35 -> -10000 | W40: =-Drivers!W35 -> -10000 | ... Y40: =-Drivers!Y35 -> -10000 | AA40: =SUM(B40:E40) -> -59268 | AB40: =SUM(F40:I40) -> -75332 | AC40: =SUM(J40:M40) -> -46498 | AD40: =SUM(N40:Q40) -> -50500 | AE40: =SUM(R40:U40) -> -40000 | AF40: =SUM(V40:Y40) -> -40000
A41: Net cash used in financing activities | B41: =SUM(B36:B40) -> -7615 | C41: =SUM(C36:C40) -> -14019 | D41: =SUM(D36:D40) -> -17757 | E41: =SUM(E36:E40) -> -16585 | F41: =SUM(F36:F40) -> -18741 | G41: =SUM(G36:G40) -> -16615 | H41: =SUM(H36:H40) -> -29261 | I41: =SUM(I36:I40) -> -8861 | ... Y41: =SUM(Y36:Y40) -> -9000 | AA41: =SUM(AA36:AA40) -> -55976 | AB41: =SUM(AB36:AB40) -> -73478 | AC41: =SUM(AC36:AC40) -> -42731 | AD41: =SUM(AD36:AD40) -> -46637 | AE41: =SUM(AE36:AE40) -> -36000 | AF41: =SUM(AF36:AF40) -> -36000
A43: Cash reconciliation
A44: Net increase (decrease) in cash | B44: =B23+B33+B41 -> -13122 | C44: =C23+C33+C41 -> 26277 | D44: =D23+D33+D41 -> -7807 | E44: =E23+E33+E41 -> -19221 | F44: =F23+F33+F41 -> 1685 | G44: =G23+G33+G41 -> -6673 | H44: =H23+H33+H41 -> 5393 | I44: =I23+I33+I41 -> 21856 | ... Y44: =Y23+Y33+Y41 -> 48263.87 | AA44: =AA23+AA33+AA41 -> -13873 | AB44: =AB23+AB33+AB41 -> 22261 | AC44: =AC23+AC33+AC41 -> 44400 | AD44: =AD23+AD33+AD41 -> -21381.899 | AE44: =AE23+AE33+AE41 -> 81152.963 | AF44: =AF23+AF33+AF41 -> 159315.7
A45: Effect of foreign currency on cash | B45: ='CF YTD Inputs'!B44 -> 0 | C45: ='CF YTD Inputs'!C44-'CF YTD Inputs'!B44 -> 0 | D45: ='CF YTD Inputs'!D44-'CF YTD Inputs'!C44 -> 0 | E45: ='CF YTD Inputs'!E44-'CF YTD Inputs'!D44 -> 0 | F45: ='CF YTD Inputs'!F44 -> 0 | G45: ='CF YTD Inputs'!G44-'CF YTD Inputs'!F44 -> 0 | H45: ='CF YTD Inputs'!H44-'CF YTD Inputs'!G44 -> 0 | I45: ='CF YTD Inputs'!I44-'CF YTD Inputs'!H44 -> -318 | J45: ='CF YTD Inputs'!J44 -> 279 | K45: ='CF YTD Inputs'!K44-'CF YTD Inputs'!J44 -> 535 | L45: ='CF YTD Inputs'!L44-'CF YTD Inputs'!K44 -> -94 | M45: ='CF YTD Inputs'!M44-'CF YTD Inputs'!L44 -> -54 | N45: ='CF YTD Inputs'!N44 -> -288 | O45: ='CF YTD Inputs'!O44-'CF YTD Inputs'!N44 -> -61 | AA45: =SUM(B45:E45) -> 0 | AB45: =SUM(F45:I45) -> -318 | AC45: =SUM(J45:M45) -> 666 | AD45: =SUM(N45:Q45) -> -349 | AE45: =SUM(R45:U45) -> 0 | AF45: =SUM(V45:Y45) -> 0
A46: Cash, beginning of period | B46: ='CF YTD Inputs'!B45 -> 92382 | C46: =B47 -> 79260 | D46: =C47 -> 105537 | E46: =D47 -> 97730 | F46: ='CF YTD Inputs'!F45 -> 78509 | G46: =F47 -> 80194 | H46: =G47 -> 73521 | I46: =H47 -> 78914 | J46: ='CF YTD Inputs'!J45 -> 100452 | K46: =J47 -> 101811 | L46: =K47 -> 90476 | M46: =L47 -> 136548 | N46: ='CF YTD Inputs'!N45 -> 145518 | O46: =N47 -> 144876 | P46: =O47 -> 119971 | Q46: =P47 -> 112983.96 | R46: =Q47 -> 123787.1 | S46: =R47 -> 157370.47 | T46: =S47 -> 172502.93 | U46: =T47 -> 177534.26 | V46: =U47 -> 204940.06 | ... Y46: =X47 -> 315991.9 | AA46: =B46 -> 92382 | AB46: =F46 -> 78509 | AC46: =J46 -> 100452 | AD46: =N46 -> 145518 | AE46: =R46 -> 123787.1 | AF46: =V46 -> 204940.06
A47: Cash, end of period | B47: =B46+B44+B45 -> 79260 | C47: =C46+C44+C45 -> 105537 | D47: =D46+D44+D45 -> 97730 | E47: =E46+E44+E45 -> 78509 | F47: =F46+F44+F45 -> 80194 | G47: =G46+G44+G45 -> 73521 | H47: =H46+H44+H45 -> 78914 | I47: =I46+I44+I45 -> 100452 | ... Y47: =Y46+Y44+Y45 -> 364255.77 | AA47: =AA46+AA44+AA45 -> 78509 | AB47: =AB46+AB44+AB45 -> 100452 | AC47: =AC46+AC44+AC45 -> 145518 | AD47: =AD46+AD44+AD45 -> 123787.1 | AE47: =AE46+AE44+AE45 -> 204940.06 | AF47: =AF46+AF44+AF45 -> 364255.77
A49: Free cash flow (company definition: CFO less PP&E purchases and capitalized software)
A50: Free cash flow | B50: =B23+B26+B27 -> 5336 | C50: =C23+C26+C27 -> 10795 | D50: =D23+D26+D27 -> 17167 | E50: =E23+E26+E27 -> 19535 | F50: =F23+F26+F27 -> 16262 | G50: =G23+G26+G27 -> 6913 | H50: =H23+H26+H27 -> 2866 | I50: =I23+I26+I27 -> 8856 | ... Y50: =Y23+Y26+Y27 -> 57263.87 | AA50: =AA23+AA26+AA27 -> 52833 | AB50: =AB23+AB26+AB27 -> 34897 | AC50: =AC23+AC26+AC27 -> 46203 | AD50: =AD23+AD26+AD27 -> 46184.101 | AE50: =AE23+AE26+AE27 -> 117152.96 | AF50: =AF23+AF26+AF27 -> 195315.7
A51: Free cash flow margin % | B51: =IF('Income Statement'!C9=0,0,B50/'Income Statement'!C9) -> 0.096305521 | C51: =IF('Income Statement'!D9=0,0,C50/'Income Statement'!D9) -> 0.17045634 | D51: =IF('Income Statement'!E9=0,0,D50/'Income Statement'!E9) -> 0.26959499 | E51: =IF('Income Statement'!F9=0,0,E50/'Income Statement'!F9) -> 0.23091017 | F51: =IF('Income Statement'!G9=0,0,F50/'Income Statement'!G9) -> 0.24380444 | G51: =IF('Income Statement'!H9=0,0,G50/'Income Statement'!H9) -> 0.10276956 | H51: =IF('Income Statement'!I9=0,0,H50/'Income Statement'!I9) -> 0.039924219 | I51: =IF('Income Statement'!J9=0,0,I50/'Income Statement'!J9) -> 0.10357652 | ... Y51: =IF('Income Statement'!Z9=0,0,Y50/'Income Statement'!Z9) -> 0.37036327 | AA51: =IF('Income Statement'!AB9=0,0,AA50/'Income Statement'!AB9) -> 0.19786603 | AB51: =IF('Income Statement'!AC9=0,0,AB50/'Income Statement'!AC9) -> 0.11981556 | AC51: =IF('Income Statement'!AD9=0,0,AC50/'Income Statement'!AD9) -> 0.16330419 | AD51: =IF('Income Statement'!AE9=0,0,AD50/'Income Statement'!AE9) -> 0.13975107 | AE51: =IF('Income Statement'!AF9=0,0,AE50/'Income Statement'!AF9) -> 0.27460924 | AF51: =IF('Income Statement'!AG9=0,0,AF50/'Income Statement'!AG9) -> 0.36883645
A52: Free cash flow / Adjusted EBITDA | B52: =IF('Income Statement'!C51=0,0,B50/'Income Statement'!C51) -> 0.72559151 | C52: =IF('Income Statement'!D51=0,0,C50/'Income Statement'!D51) -> 0.99870478 | D52: =IF('Income Statement'!E51=0,0,D50/'Income Statement'!E51) -> 0.94117325 | E52: =IF('Income Statement'!F51=0,0,E50/'Income Statement'!F51) -> 0.50210764 | F52: =IF('Income Statement'!G51=0,0,F50/'Income Statement'!G51) -> 1.080101 | G52: =IF('Income Statement'!H51=0,0,G50/'Income Statement'!H51) -> 0.32797229 | H52: =IF('Income Statement'!I51=0,0,H50/'Income Statement'!I51) -> 0.154543 | I52: =IF('Income Statement'!J51=0,0,I50/'Income Statement'!J51) -> 0.23524412 | ... Y52: =IF('Income Statement'!Z51=0,0,Y50/'Income Statement'!Z51) -> 0.65470098 | AA52: =IF('Income Statement'!AB51=0,0,AA50/'Income Statement'!AB51) -> 0.70154962 | AB52: =IF('Income Statement'!AC51=0,0,AB50/'Income Statement'!AC51) -> 0.37797996 | AC52: =IF('Income Statement'!AD51=0,0,AC50/'Income Statement'!AD51) -> 0.74956197 | AD52: =IF('Income Statement'!AE51=0,0,AD50/'Income Statement'!AE51) -> 0.53655118 | AE52: =IF('Income Statement'!AF51=0,0,AE50/'Income Statement'!AF51) -> 0.71767588 | AF52: =IF('Income Statement'!AG51=0,0,AF50/'Income Statement'!AG51) -> 0.77162895

Sheet CF YTD Inputs
A1: CF YTD Inputs: cash flow statement as reported, year-to-date
A2: Sources: 8-K earnings releases (Q1 to Q3), 10-K (FY), 10-Q (2026). Inflows positive. The Cash Flow tab derives each quarter as YTD less prior YTD.
A4: Period (YTD) | B4: 3M'23 | C4: 6M'23 | D4: 9M'23 | E4: FY'23 | F4: 3M'24 | G4: 6M'24 | H4: 9M'24 | I4: FY'24 | J4: 3M'25 | K4: 6M'25 | L4: 9M'25 | M4: FY'25 | N4: 3M'26 | O4: 6M'26
A5: Period end | B5: 45016 | C5: 45107 | D5: 45199 | E5: 45291 | F5: 45382 | G5: 45473 | H5: 45565 | I5: 45657 | J5: 45747 | K5: 45838 | L5: 45930 | M5: 46022 | N5: 46112 | O5: 46203
A8: Operating activities (year-to-date, as reported; $ in thousands)
A9: Net income (loss) | B9: -5871 | C9: -11595 | D9: -9821 | E9: 8881 | F9: -2454 | G9: -483 | H9: -1395 | I9: 12504 | J9: -9486 | K9: -14694 | L9: -21146 | M9: -14462 | N9: -12510 | O9: -13712
A10: Depreciation and amortization | B10: 11432 | C10: 22330 | D10: 33731 | E10: 44770 | F10: 11212 | G10: 22548 | H10: 33931 | I10: 45352 | J10: 11676 | K10: 23537 | L10: 33996 | M10: 43769 | N10: 9988 | O10: 19995
A11: Stock-based compensation | B11: 7059 | C11: 14325 | D11: 21525 | E11: 28862 | F11: 9111 | G11: 18810 | H11: 28267 | I11: 37676 | J11: 9698 | K11: 19499 | L11: 29010 | M11: 38378 | N11: 8488 | O11: 16835
A12: Provision for doubtful accounts | B12: 0 | C12: 5675 | D12: 5675 | E12: 5675 | F12: 0 | G12: 0 | H12: 0 | I12: 0 | J12: 0 | K12: 0 | L12: 0 | M12: 0 | N12: 0 | O12: 0
A13: Deferred income taxes | B13: -4327 | C13: -13555 | D13: -14185 | E13: -13406 | F13: -4667 | G13: -8732 | H13: -10831 | I13: -10984 | J13: -4754 | K13: -9024 | L13: -11772 | M13: -14489 | N13: -1423 | O13: -1143
A14: Accretion of discount on marketable securities | B14: -1057 | C14: -2042 | D14: -3061 | E14: -4093 | F14: -1234 | G14: -2460 | H14: -3552 | I14: -4117 | J14: -454 | K14: -819 | L14: -822 | M14: -822 | N14: 0 | O14: -110
A15: Non-cash operating lease expense | B15: 1532 | C15: 3067 | D15: 4605 | E15: 6145 | F15: 1690 | G15: 3475 | H15: 5098 | I15: 6801 | J15: 1928 | K15: 3710 | L15: 5528 | M15: 7351 | N15: 1840 | O15: 3591
A16: Other non-cash items | B16: -3 | C16: 4 | D16: 3 | E16: 45 | F16: -1 | G16: 1 | H16: -78 | I16: -25 | J16: -223 | K16: -278 | L16: -864 | M16: -1047 | N16: -676 | O16: -305
A17: Change in accounts receivable | B17: 61292 | C17: 41743 | D17: 8367 | E17: -75716 | F17: 72184 | G17: 23881 | H17: -1322 | I17: -49345 | J17: 75691 | K17: 41412 | L17: 62223 | M17: 66574 | N17: 21335 | O17: -24957
A18: Change in prepaid expenses and other assets | B18: 894 | C18: 907 | D18: 3501 | E18: 3918 | F18: -196 | G18: -3397 | H18: -1554 | I18: -5826 | J18: 5681 | K18: -340 | L18: -2221 | M18: -16220 | N18: 4082 | O18: 4046
A19: Change in accounts payable | B19: -55387 | C19: -30078 | D19: 4141 | E19: 79687 | F19: -58444 | G19: -14768 | H19: 8841 | I19: 38096 | J19: -62578 | K19: -25865 | L19: -29981 | M19: -42397 | N19: -997 | O19: 36558
A20: Change in accrued liabilities | B20: -833 | C20: 1875 | D20: 3214 | E20: 3035 | F20: -1784 | G20: 56 | H20: 2259 | I20: 9627 | J20: -11287 | K20: -5559 | L20: 429 | M20: 16179 | N20: -11382 | O20: -1738
... A22: Change in other liabilities, non-current | B22: -712 | C22: -1314 | D22: -966 | E22: -893 | F22: 257 | G22: 277 | H22: 454 | I22: 197 | J22: 319 | K22: 275 | L22: 432 | M22: 861 | N22: -6 | O22: 1633
A23: Net cash provided by operating activities | B23: =SUM(B9:B22) -> 12754 | C23: =SUM(C9:C22) -> 28602 | D23: =SUM(D9:D22) -> 52447 | E23: =SUM(E9:E22) -> 81121 | F23: =SUM(F9:F22) -> 24294 | G23: =SUM(G9:G22) -> 36238 | H23: =SUM(H9:H22) -> 55377 | I23: =SUM(I9:I22) -> 73425 | ... O23: =SUM(O9:O22) -> 37505
A25: Investing activities (year-to-date)
A26: Purchases of property and equipment | B26: -1417 | C26: -2552 | D26: -5424 | E26: -10601 | F26: -801 | G26: -1537 | H26: -13268 | I26: -17592 | J26: -1441 | K26: -2781 | L26: -7455 | M26: -14345 | N26: -11 | O26: -2966
A27: Capitalized software development costs | B27: -6001 | C27: -9919 | D27: -13725 | E27: -17687 | F27: -7231 | G27: -11526 | H27: -16068 | I27: -20936 | J27: -6880 | K27: -11180 | L27: -16094 | M27: -20511 | N27: -6579 | O27: -10171
A28: Purchases of marketable securities | B28: -40343 | C28: -46715 | D28: -76932 | E28: -140603 | F28: -34336 | G28: -96565 | H28: -117977 | I28: -142016 | J28: -15307 | K28: -26026 | L28: -26026 | M28: -26026 | N28: 0 | O28: -17429
A29: Proceeds from sales of marketable securities | B29: 0 | C29: 18873 | D29: 18873 | E29: 18873 | F29: 0 | G29: 0 | H29: 0 | I29: 0 | J29: 0 | K29: 0 | L29: 27095 | M29: 27095 | N29: 0 | O29: 0
A30: Proceeds from maturities of marketable securities | B30: 29500 | C30: 46500 | D30: 69500 | E30: 111000 | F30: 38500 | G30: 103758 | H30: 156958 | I30: 202858 | J30: 13559 | K30: 39859 | L30: 39859 | M30: 39859 | N30: 0 | O30: 0
A31: Purchase of equity investments | B31: 0 | C31: 0 | D31: 0 | E31: 0 | F31: 0 | G31: 0 | H31: 0 | I31: 0 | J31: 0 | K31: 0 | L31: 0 | M31: 0 | N31: -3000 | O31: -3500
A32: Net cash provided by (used in) investing activities | B32: =SUM(B26:B31) -> -18261 | C32: =SUM(C26:C31) -> 6187 | D32: =SUM(D26:D31) -> -7708 | E32: =SUM(E26:E31) -> -39018 | F32: =SUM(F26:F31) -> -3868 | G32: =SUM(G26:G31) -> -5870 | H32: =SUM(H26:H31) -> 9645 | I32: =SUM(I26:I31) -> 22314 | ... O32: =SUM(O26:O31) -> -34066
A34: Financing activities (year-to-date)
A35: Payment of acquisition indemnification holdback | B35: 0 | C35: 0 | D35: 0 | E35: 0 | F35: -2148 | G35: -2148 | H35: -2148 | I35: -2148 | J35: 0 | K35: 0 | L35: 0 | M35: 0 | N35: 0 | O35: 0
A36: Proceeds from employee stock purchase plan | B36: 0 | C36: 971 | D36: 971 | E36: 1869 | F36: 0 | G36: 1451 | H36: 1451 | I36: 2368 | J36: 0 | K36: 1357 | L36: 1357 | M36: 2148 | N36: 0 | O36: 1054
A37: Proceeds from exercise of stock options | B37: 314 | C37: 937 | D37: 1210 | E37: 1549 | F37: 939 | G37: 1274 | H37: 1578 | I37: 1765 | J37: 563 | K37: 1174 | L37: 1495 | M37: 1759 | N37: 477 | O37: 884
A38: Principal payments on finance leases | B38: -31 | C38: -62 | D38: -93 | E38: -126 | F38: -32 | G38: -65 | H38: -98 | I38: -131 | J38: -35 | K38: -70 | L38: -105 | M38: -140 | N38: -36 | O38: -75
A39: Payments to acquire treasury stock | B39: -7898 | C39: -23480 | D39: -41479 | E39: -59268 | F39: -17500 | G39: -35868 | H39: -65400 | I39: -75332 | J39: -5000 | K39: -43649 | L39: -47650 | M39: -46498 | N39: -8500 | O39: -30500
A40: Net cash used in financing activities | B40: =SUM(B35:B39) -> -7615 | C40: =SUM(C35:C39) -> -21634 | D40: =SUM(D35:D39) -> -39391 | E40: =SUM(E35:E39) -> -55976 | F40: =SUM(F35:F39) -> -18741 | G40: =SUM(G35:G39) -> -35356 | H40: =SUM(H35:H39) -> -64617 | I40: =SUM(I35:I39) -> -73478 | ... O40: =SUM(O35:O39) -> -28637
A42: Cash reconciliation (year-to-date)
A43: Net increase (decrease) in cash | B43: =B23+B32+B40 -> -13122 | C43: =C23+C32+C40 -> 13155 | D43: =D23+D32+D40 -> 5348 | E43: =E23+E32+E40 -> -13873 | F43: =F23+F32+F40 -> 1685 | G43: =G23+G32+G40 -> -4988 | H43: =H23+H32+H40 -> 405 | I43: =I23+I32+I40 -> 22261 | ... O43: =O23+O32+O40 -> -25198
A44: Effect of foreign currency on cash | B44: 0 | C44: 0 | D44: 0 | E44: 0 | F44: 0 | G44: 0 | H44: 0 | I44: -318 | J44: 279 | K44: 814 | L44: 720 | M44: 666 | N44: -288 | O44: -349
A45: Cash, beginning of year | B45: 92382 | C45: 92382 | D45: 92382 | E45: 92382 | F45: 78509 | G45: 78509 | H45: 78509 | I45: 78509 | J45: 100452 | K45: 100452 | L45: 100452 | M45: 100452 | N45: 145518 | O45: 145518
A46: Cash, end of period | B46: =B45+B43+B44 -> 79260 | C46: =C45+C43+C44 -> 105537 | D46: =D45+D43+D44 -> 97730 | E46: =E45+E43+E44 -> 78509 | F46: =F45+F43+F44 -> 80194 | G46: =G45+G43+G44 -> 73521 | H46: =H45+H43+H44 -> 78914 | I46: =I45+I43+I44 -> 100452 | ... O46: =O45+O43+O44 -> 119971
A48: Tie-out to reported totals (inputs from filings)
A49: Reported net cash from operating activities | B49: 12754 | C49: 28602 | D49: 52447 | E49: 81121 | F49: 24294 | G49: 36238 | H49: 55377 | I49: 73425 | J49: 15621 | K49: 30526 | L49: 62900 | M49: 81059 | N49: 17295 | O49: 37505
A50: Reported net cash from investing activities | B50: -18261 | C50: 6187 | D50: -7708 | E50: -39018 | F50: -3868 | G50: -5870 | H50: 9645 | I50: 22314 | J50: -10069 | K50: -128 | L50: 17379 | M50: 6072 | N50: -9590 | O50: -34066
A51: Reported net cash from financing activities | B51: -7615 | C51: -21634 | D51: -39391 | E51: -55976 | F51: -18741 | G51: -35356 | H51: -64617 | I51: -73478 | J51: -4472 | K51: -41188 | L51: -44903 | M51: -42731 | N51: -8059 | O51: -28637
A52: Reported ending cash | B52: 79260 | C52: 105537 | D52: 97730 | E52: 78509 | F52: 80194 | G52: 73521 | H52: 78914 | I52: 100452 | J52: 101811 | K52: 90476 | L52: 136548 | M52: 145518 | N52: 144876 | O52: 119971
A53: Difference (should be zero) | B53: =ABS(B23-B49)+ABS(B32-B50)+ABS(B40-B51)+ABS(B46-B52) -> 0 | C53: =ABS(C23-C49)+ABS(C32-C50)+ABS(C40-C51)+ABS(C46-C52) -> 0 | D53: =ABS(D23-D49)+ABS(D32-D50)+ABS(D40-D51)+ABS(D46-D52) -> 0 | E53: =ABS(E23-E49)+ABS(E32-E50)+ABS(E40-E51)+ABS(E46-E52) -> 0 | F53: =ABS(F23-F49)+ABS(F32-F50)+ABS(F40-F51)+ABS(F46-F52) -> 0 | G53: =ABS(G23-G49)+ABS(G32-G50)+ABS(G40-G51)+ABS(G46-G52) -> 0 | H53: =ABS(H23-H49)+ABS(H32-H50)+ABS(H40-H51)+ABS(H46-H52) -> 0 | I53: =ABS(I23-I49)+ABS(I32-I50)+ABS(I40-I51)+ABS(I46-I52) -> 0 | ... O53: =ABS(O23-O49)+ABS(O32-O50)+ABS(O40-O51)+ABS(O46-O52) -> 0

Sheet 10-K Data
A1: 10-K Data: FY2023 to FY2025 as reported
A2: Source: PubMatic FY2025 Form 10-K (filed Feb 26, 2026). Used to derive Q4 as full year less first nine months, and to tie out annual totals.
A4: Fiscal year | B4: FY2023 | C4: FY2024 | D4: FY2025
A5: Status | B5: Reported | C5: Reported | D5: Reported
A8: Income statement, FY per 10-K ($ in thousands)
A9: Revenue | B9: 267014 | C9: 291256 | D9: 282926
A10: Cost of revenue | B10: 99229 | C10: 101027 | D10: 103085
A11: Technology and development | B11: 26727 | C11: 33263 | D11: 33820
A12: Sales and marketing | B12: 82803 | C12: 95369 | D12: 102940
A13: General and administrative | B13: 56219 | C13: 57670 | D13: 60340
A14: Operating income (loss) | B14: 2036 | C14: 3927 | D14: -17259
A15: Interest income | B15: 8828 | C15: 8477 | D15: 5455
A16: Other income (expense), net | B16: -359 | C16: 5370 | D16: -4150
A17: Provision for (benefit from) income taxes | B17: 1624 | C17: 5270 | D17: -1492
A18: Net income (loss) | B18: 8881 | C18: 12504 | D18: -14462
A19: Weighted-average shares, basic (000s) | B19: 51760 | C19: 49213 | D19: 47008
A20: Weighted-average shares, diluted (000s) | B20: 56027 | C20: 54294 | D20: 47008
A22: Stock-based compensation, FY per 10-K
A23: Cost of revenue | B23: 1472 | C23: 1855 | D23: 1854
A24: Technology and development | B24: 4346 | C24: 6313 | D24: 6088
A25: Sales and marketing | B25: 10462 | C25: 13407 | D25: 13703
A26: General and administrative | B26: 12582 | C26: 16101 | D26: 16733
A27: Total stock-based compensation | B27: 28862 | C27: 37676 | D27: 38378
A29: Non-GAAP, FY per 10-K
A30: Depreciation and amortization | B30: 44770 | C30: 45352 | D30: 43769
A31: Litigation-related expenses | B31: 0 | C31: 0 | D31: 902
A32: Adjusted EBITDA (reported) | B32: 75309 | C32: 92325 | D32: 61640

Sheet Checks
A1: Checks: model integrity and tie-outs
A2: Differences should be zero (within $2K of rounding). Column groups match the other tabs.
A4: Period | B4: Q1'23 | C4: Q2'23 | D4: Q3'23 | E4: Q4'23 | F4: Q1'24 | G4: Q2'24 | H4: Q3'24 | I4: Q4'24 | J4: Q1'25 | K4: Q2'25 | L4: Q3'25 | M4: Q4'25 | N4: Q1'26 | O4: Q2'26 | P4: Q3'26 | Q4: Q4'26 | R4: Q1'27 | S4: Q2'27 | T4: Q3'27 | U4: Q4'27 | V4: Q1'28 | W4: Q2'28 | X4: Q3'28 | Y4: Q4'28 | AA4: FY2023A | AB4: FY2024A | AC4: FY2025A | AD4: FY2026E | AE4: FY2027E | AF4: FY2028E
A5: Period end | B5: 45016 | C5: 45107 | D5: 45199 | E5: 45291 | F5: 45382 | G5: 45473 | H5: 45565 | I5: 45657 | J5: 45747 | K5: 45838 | L5: 45930 | M5: 46022 | N5: 46112 | O5: 46203 | P5: 46295 | Q5: 46387 | R5: 46477 | S5: 46568 | T5: 46660 | U5: 46752 | V5: 46843 | W5: 46934 | X5: 47026 | Y5: 47118 | AA5: 45291 | AB5: 45657 | AC5: 46022 | AD5: 46387 | AE5: 46752 | AF5: 47118
A6: Status | B6: Actual | C6: Actual | D6: Actual | E6: Actual | F6: Actual | G6: Actual | H6: Actual | I6: Actual | J6: Actual | K6: Actual | L6: Actual | M6: Actual | N6: Actual | O6: Actual | P6: Forecast | Q6: Forecast | R6: Forecast | S6: Forecast | T6: Forecast | U6: Forecast | V6: Forecast | W6: Forecast | X6: Forecast | Y6: Forecast | AA6: Actual | AB6: Actual | AC6: Actual | AD6: 2A + 2E | AE6: Forecast | AF6: Forecast
A8: OVERALL STATUS | B8: =IF((SUMPRODUCT(ABS(B11:AF11))+SUMPRODUCT(ABS(B12:AF12))+SUMPRODUCT(ABS(B15:AF15))+SUMPRODUCT(ABS(B18:AF18))+SUMPRODUCT(ABS(B19:AF19))+SUMPRODUCT(ABS(B24:AF24))+SUMPRODUCT(ABS(B27:AF27))+SUMPRODUCT(ABS(B30:AF30))+SUMPRODUCT(ABS(B33:AF33))+SUMPRODUCT(ABS(B34:AF34))+SUMPRODUCT(ABS(B35:AF35))+SUMPRODUCT(ABS(B36:AF36))+SUMPRODUCT(ABS(B37:AF37))+SUMPRODUCT(ABS(B38:AF38))+SUMPRODUCT(ABS(B39:AF39))+SUMPRODUCT(ABS(B40:AF40)))<=25,"ALL CHECKS PASS","REVIEW CHECKS") -> ALL CHECKS PASS
B9: Rounding tolerance: source figures are in $000s and a few 10-Q line items differ by $1K between filings.
A10: Time-series checks
A11: Balance sheet balances (assets less liabilities and equity) | E11: ='Balance Sheet'!F37 -> 0 | F11: ='Balance Sheet'!G37 -> 0 | G11: ='Balance Sheet'!H37 -> 0 | H11: ='Balance Sheet'!I37 -> 0 | I11: ='Balance Sheet'!J37 -> 0 | J11: ='Balance Sheet'!K37 -> 0 | K11: ='Balance Sheet'!L37 -> 0 | L11: ='Balance Sheet'!M37 -> 0 | ... Y11: ='Balance Sheet'!Z37 -> 0
A12: Cash flow ending cash less balance sheet cash | E12: ='Cash Flow'!E47-'Balance Sheet'!F9 -> 0 | F12: ='Cash Flow'!F47-'Balance Sheet'!G9 -> 0 | G12: ='Cash Flow'!G47-'Balance Sheet'!H9 -> 0 | H12: ='Cash Flow'!H47-'Balance Sheet'!I9 -> 0 | I12: ='Cash Flow'!I47-'Balance Sheet'!J9 -> 0 | J12: ='Cash Flow'!J47-'Balance Sheet'!K9 -> 0 | K12: ='Cash Flow'!K47-'Balance Sheet'!L9 -> 0 | L12: ='Cash Flow'!L47-'Balance Sheet'!M9 -> 0 | ... Y12: ='Cash Flow'!Y47-'Balance Sheet'!Z9 -> 0
A13: Net income: model | B13: ='Income Statement'!C27 -> -5871 | C13: ='Income Statement'!D27 -> -5724 | D13: ='Income Statement'!E27 -> 1774 | F13: ='Income Statement'!G27 -> -2454 | G13: ='Income Statement'!H27 -> 1971 | H13: ='Income Statement'!I27 -> -912 | J13: ='Income Statement'!K27 -> -9486 | K13: ='Income Statement'!L27 -> -5208 | L13: ='Income Statement'!M27 -> -6452 | N13: ='Income Statement'!O27 -> -12510 | O13: ='Income Statement'!P27 -> -1202
A14: Net income: reported (10-Q / 8-K) | B14: -5871 | C14: -5724 | D14: 1774 | F14: -2454 | G14: 1971 | H14: -912 | J14: -9486 | K14: -5208 | L14: -6452 | N14: -12510 | O14: -1202
A15: Difference | B15: =B13-B14 -> 0 | C15: =C13-C14 -> 0 | D15: =D13-D14 -> 0 | F15: =F13-F14 -> 0 | G15: =G13-G14 -> 0 | H15: =H13-H14 -> 0 | J15: =J13-J14 -> 0 | K15: =K13-K14 -> 0 | L15: =L13-L14 -> 0 | N15: =N13-N14 -> 0 | O15: =O13-O14 -> 0
A16: Adjusted EBITDA: model | B16: ='Income Statement'!C51 -> 7354 | C16: ='Income Statement'!D51 -> 10809 | D16: ='Income Statement'!E51 -> 18240 | E16: ='Income Statement'!F51 -> 38906 | F16: ='Income Statement'!G51 -> 15056 | G16: ='Income Statement'!H51 -> 21078 | H16: ='Income Statement'!I51 -> 18545 | I16: ='Income Statement'!J51 -> 37646 | ... O16: ='Income Statement'!P51 -> 19616
A17: Adjusted EBITDA: reported (Q4 = FY less Q1 to Q3) | B17: 7354 | C17: 10809 | D17: 18240 | E17: ='10-K Data'!B32-SUM(B17:D17) -> 38906 | F17: 15056 | G17: 21078 | H17: 18546 | I17: ='10-K Data'!C32-SUM(F17:H17) -> 37645 | J17: 8457 | K17: 14213 | L17: 11152 | M17: ='10-K Data'!D32-SUM(J17:L17) -> 27818 | N17: 2588 | O17: 19616
A18: Difference | B18: =B16-B17 -> 0 | C18: =C16-C17 -> 0 | D18: =D16-D17 -> 0 | E18: =E16-E17 -> 0 | F18: =F16-F17 -> 0 | G18: =G16-G17 -> 0 | H18: =H16-H17 -> -1 | I18: =I16-I17 -> 1 | ... O18: =O16-O17 -> 0
A19: Cash flow YTD tie-out to reported CFO, CFI, CFF, ending cash | B19: ='CF YTD Inputs'!B53 -> 0 | C19: ='CF YTD Inputs'!C53 -> 0 | D19: ='CF YTD Inputs'!D53 -> 0 | E19: ='CF YTD Inputs'!E53 -> 0 | F19: ='CF YTD Inputs'!F53 -> 0 | G19: ='CF YTD Inputs'!G53 -> 0 | H19: ='CF YTD Inputs'!H53 -> 0 | I19: ='CF YTD Inputs'!I53 -> 0 | ... O19: ='CF YTD Inputs'!O53 -> 0
A21: Nine-month tie-out (sum of Q1 to Q3 in model vs reported nine-month figures), shown in Q3 columns
A22: Revenue: model Q1 to Q3 | D22: =SUM('Income Statement'!C9:E9) -> 182414 | H22: =SUM('Income Statement'!G9:I9) -> 205754 | L22: =SUM('Income Statement'!K9:M9) -> 202880
A23: Revenue: reported 9M | D23: 182414 | H23: 205754 | L23: 202880
A24: Difference | D24: =D22-D23 -> 0 | H24: =H22-H23 -> 0 | L24: =L22-L23 -> 0
A25: Operating income: model Q1 to Q3 | D25: =SUM('Income Statement'!C18:E18) -> -18377 | H25: =SUM('Income Statement'!G18:I18) -> -10875 | L25: =SUM('Income Statement'!K18:M18) -> -25783
A26: Operating income: reported 9M | D26: -18377 | H26: -10875 | L26: -25783
A27: Difference | D27: =D25-D26 -> 0 | H27: =H25-H26 -> 0 | L27: =L25-L26 -> 0
A28: SBC: model Q1 to Q3 | D28: =SUM('Income Statement'!C59:E59) -> 21525 | H28: =SUM('Income Statement'!G59:I59) -> 28267 | L28: =SUM('Income Statement'!K59:M59) -> 29010
A29: SBC: reported 9M | D29: 21525 | H29: 28267 | L29: 29010
A30: Difference | D30: =D28-D29 -> 0 | H30: =H28-H29 -> 0 | L30: =L28-L29 -> 0
A32: Annual tie-out to 10-K (shown in FY23 to FY25 columns)
A33: Revenue: model less 10-K | AA33: ='Income Statement'!AB9-'10-K Data'!B9 -> 0 | AB33: ='Income Statement'!AC9-'10-K Data'!C9 -> 0 | AC33: ='Income Statement'!AD9-'10-K Data'!D9 -> 0
A34: Cost of revenue: model less 10-K | AA34: ='Income Statement'!AB10-'10-K Data'!B10 -> 0 | AB34: ='Income Statement'!AC10-'10-K Data'!C10 -> 0 | AC34: ='Income Statement'!AD10-'10-K Data'!D10 -> 0
A35: Operating expenses: model less 10-K (T&D + S&M + G&A) | AA35: ='Income Statement'!AB17-('10-K Data'!B11+'10-K Data'!B12+'10-K Data'!B13) -> 0 | AB35: ='Income Statement'!AC17-('10-K Data'!C11+'10-K Data'!C12+'10-K Data'!C13) -> 0 | AC35: ='Income Statement'!AD17-('10-K Data'!D11+'10-K Data'!D12+'10-K Data'!D13) -> 0
A36: Operating income: model less 10-K | AA36: ='Income Statement'!AB18-'10-K Data'!B14 -> 0 | AB36: ='Income Statement'!AC18-'10-K Data'!C14 -> 0 | AC36: ='Income Statement'!AD18-'10-K Data'!D14 -> 0
A37: Net income: model less 10-K | AA37: ='Income Statement'!AB27-'10-K Data'!B18 -> 0 | AB37: ='Income Statement'!AC27-'10-K Data'!C18 -> 0 | AC37: ='Income Statement'!AD27-'10-K Data'!D18 -> 0
A38: Adjusted EBITDA: model less 10-K | AA38: ='Income Statement'!AB51-'10-K Data'!B32 -> 0 | AB38: ='Income Statement'!AC51-'10-K Data'!C32 -> 0 | AC38: ='Income Statement'!AD51-'10-K Data'!D32 -> 0
A39: Cash flow from operations: model less 10-K reported | AA39: ='Cash Flow'!AA23-'CF YTD Inputs'!E49 -> 0 | AB39: ='Cash Flow'!AB23-'CF YTD Inputs'!I49 -> 0 | AC39: ='Cash Flow'!AC23-'CF YTD Inputs'!M49 -> 0
A40: Year-end cash: model less 10-K reported | AA40: ='Cash Flow'!AA47-'CF YTD Inputs'!E52 -> 0 | AB40: ='Cash Flow'!AB47-'CF YTD Inputs'!I52 -> 0 | AC40: ='Cash Flow'!AC47-'CF YTD Inputs'!M52 -> 0

Sheet Comps
A1: Competitive Analysis: Ad-Tech Peer Benchmarking
A2: $ in millions. Q2 2026 (quarter ended June 30, 2026) and six months ended June 30, 2026. Blue = hard-coded from filings; black = formula.
A4: 1. Q2 2026 RESULTS | B4: PUBM | C4: MGNI | D4: TTD | E4: CRTO | F4: APP | G4: Notes
A5: Reported revenue | B5: 78.593 | C5: 192.823 | D5: 715.057 | E5: 428.018 | F5: 1923.686 | G5: GAAP revenue. Criteo reports revenue gross of traffic acquisition cost (TAC); see net revenue below.
A6: Reported revenue, Q2 2025 | B6: 71.095 | C6: 173.332 | D6: 694.039 | E6: 482.671 | F6: 1258.754
A7: YoY growth | B7: =B5/B6-1 -> 0.10546452 | C7: =C5/C6-1 -> 0.11244894 | D7: =D5/D6-1 -> 0.030283601 | E7: =E5/E6-1 -> -0.11323034 | F7: =F5/F6-1 -> 0.52824619
A8: Net revenue (revenue less TAC) | B8: 78.593 | C8: 189.595 | D8: 715.057 | E8: 255.473 | F8: 1923.686 | G8: Magnite and Criteo "Contribution ex-TAC"; PUBM, TTD and AppLovin report net, so equals revenue. Best like-for-like top line.
A9: Net revenue, Q2 2025 | B9: 71.095 | C9: 161.956 | D9: 694.039 | E9: 292.069 | F9: 1258.754
A10: YoY growth | B10: =B8/B9-1 -> 0.10546452 | C10: =C8/C9-1 -> 0.17065746 | D10: =D8/D9-1 -> 0.030283601 | E10: =E8/E9-1 -> -0.12529916 | F10: =F8/F9-1 -> 0.52824619
A11: Cost of revenue excl. TAC | B11: 25.877 | C11: 58.81 | D11: 184.333 | E11: 33.259 | F11: 225.801 | G11: TTD "platform operations" (includes personnel and data costs, so not a pure hosting line). AppLovin: mostly third-party cloud, finance-lease servers and acquired-tech amortization. Magnite CoR is $62.0M incl. TAC.
A12: % of net revenue | B12: =B11/B8 -> 0.32925324 | C12: =C11/C8 -> 0.3101875 | D12: =D11/D8 -> 0.25778784 | E12: =E11/E8 -> 0.13018597 | F12: =F11/F8 -> 0.11737934
A13: Gross profit on net revenue basis | B13: =B8-B11 -> 52.716 | C13: =C8-C11 -> 130.785 | D13: =D8-D11 -> 530.724 | E13: =E8-E11 -> 222.214 | F13: =F8-F11 -> 1697.885
A14: Gross margin on net revenue | B14: =B13/B8 -> 0.67074676 | C14: =C13/C8 -> 0.6898125 | D14: =D13/D8 -> 0.74221216 | E14: =E13/E8 -> 0.86981403 | F14: =F13/F8 -> 0.88262066 | G14: Reported GAAP gross margin differs for Criteo (52%) and Magnite (68%) because TAC sits in their cost of revenue.
A15: Adjusted EBITDA | B15: 19.616 | C15: 70.6 | D15: 241.279 | E15: 73.299 | F15: 1613.823 | G15: Company-defined. Each company adds back SBC and D&A; definitions differ in other items (PUBM and MGNI add back litigation, Criteo adds back restructuring).
A16: Adjusted EBITDA, Q2 2025 | B16: 14.213 | C16: 54.391 | D16: 270.755 | E16: 89.38 | F16: 1018.347
A17: YoY growth | B17: =B15/B16-1 -> 0.38014494 | C17: =C15/C16-1 -> 0.29800886 | D17: =D15/D16-1 -> -0.10886595 | E17: =E15/E16-1 -> -0.17991721 | F17: =F15/F16-1 -> 0.58474764
A18: Adj. EBITDA margin on net revenue | B18: =B15/B8 -> 0.24958966 | C18: =C15/C8 -> 0.37237269 | D18: =D15/D8 -> 0.33742625 | E18: =E15/E8 -> 0.28691486 | F18: =F15/F8 -> 0.83892226 | G18: Criteo and Magnite headline margins (29%, 37%) are on Contribution ex-TAC, same basis as here.
A19: Net income (GAAP) | B19: -1.202 | C19: 19.369 | D19: 64.394 | E19: 11.751 | F19: 1266.538 | G19: AppLovin shown from continuing operations.
A20: Net income, Q2 2025 | B20: -5.208 | C20: 11.139 | D20: 90.129 | E20: 22.92 | F20: 771.856 | G20: AppLovin Q2 2025 from continuing operations ($819.5M including discontinued).
A21: Net margin on net revenue | B21: =B19/B8 -> -0.015293983 | C21: =C19/C8 -> 0.10215987 | D21: =D19/D8 -> 0.090054359 | E21: =E19/E8 -> 0.045997033 | F21: =F19/F8 -> 0.65839123
A22: Source: Q2 2026 earnings releases (MGNI 8/5/26, TTD 8/6/26, CRTO 8/5/26, APP 8/5/26) and PUBM Q2 2026 10-Q.
A24: 2. INFRASTRUCTURE INTENSITY, SIX MONTHS 2026 | B24: PUBM | C24: MGNI | D24: TTD | E24: CRTO | F24: APP | G24: Notes
A25: Net revenue, 6M | B25: 141.16 | C25: 350.499 | D25: 1403.914 | E25: 505.841 | F25: 3766.135
A26: Cost of revenue excl. TAC, 6M | B26: 51.971 | C26: 115.751 | D26: 366.303 | E26: 60.885 | F26: 429.433
A27: % of net revenue | B27: =B26/B25 -> 0.36817087 | C27: =C26/C25 -> 0.33024631 | D27: =D26/D25 -> 0.26091555 | E27: =E26/E25 -> 0.12036391 | F27: =F26/F25 -> 0.11402486 | G27: Lower = cheaper to serve a dollar of net revenue. Criteo and AppLovin are lowest, but for different reasons (see section 3).
A28: Depreciation and amortization, 6M | B28: 19.995 | C28: 28.922 | D28: 61.571 | E28: 59.948 | F28: 66.228 | G28: Includes acquired-intangible amortization (Magnite $5.1M, Criteo $13.3M, AppLovin most of its balance).
A29: % of net revenue | B29: =B28/B25 -> 0.14164778 | C29: =C28/C25 -> 0.082516641 | D29: =D28/D25 -> 0.043856675 | E29: =E28/E25 -> 0.11851155 | F29: =F28/F25 -> 0.017585137 | G29: Proxy for how much of the cost base is owned, depreciating hardware and capitalized software.
A30: Capex incl. capitalized software, 6M | B30: 13.137 | C30: 29.595 | D30: 133.365 | E30: 91.088 | F30: n.a. | G30: PP&E purchases plus capitalized software. AppLovin does not report 6M capex in its release: Q2 PP&E was $1.4M plus $4.3M of finance-lease principal.
A31: % of net revenue | B31: =IFERROR(B30/B25,"n.a.") -> 0.093064608 | C31: =IFERROR(C30/C25,"n.a.") -> 0.08443676 | D31: =IFERROR(D30/D25,"n.a.") -> 0.094995135 | E31: =IFERROR(E30/E25,"n.a.") -> 0.18007239 | F31: =IFERROR(F30/F25,"n.a.") -> n.a. | G31: Criteo 2026 capex guided around $190M, mainly data center renewals (per third-party Q2 call summary).
A32: Adjusted EBITDA, 6M | B32: 22.204 | C32: 113.461 | D32: 447.345 | E32: 138.198 | F32: 3170.742
A33: % of net revenue | B33: =B32/B25 -> 0.15729668 | C33: =C32/C25 -> 0.32371276 | D33: =D32/D25 -> 0.31864131 | E33: =E32/E25 -> 0.27320443 | F33: =F32/F25 -> 0.84190875
A34: Adj. EBITDA less capex | B34: =IFERROR(B32-B30,"n.a.") -> 9.067 | C34: =IFERROR(C32-C30,"n.a.") -> 83.866 | D34: =IFERROR(D32-D30,"n.a.") -> 313.98 | E34: =IFERROR(E32-E30,"n.a.") -> 47.11 | F34: =IFERROR(F32-F30,"n.a.") -> n.a.
A35: % of net revenue | B35: =IFERROR(B34/B25,"n.a.") -> 0.064232077 | C35: =IFERROR(C34/C25,"n.a.") -> 0.239276 | D35: =IFERROR(D34/D25,"n.a.") -> 0.22364618 | E35: =IFERROR(E34/E25,"n.a.") -> 0.093132032 | F35: =IFERROR(F34/F25,"n.a.") -> n.a. | G35: Cash-style margin after reinvestment. Penalizes owners of hardware, which is the point of the comparison.
A36: Sources: same earnings releases; cash flow statements for capex and D&A.
A38: 3. HOSTING MODEL AND EVIDENCE | B38: Model | G38: Evidence
A39: PubMatic | B39: Owned hardware | G39: Owns and operates its own hardware and software infrastructure (Q2 26 10-Q). Q2 26 cost of revenue per million impressions down ~18% YoY; data center costs +$1.4M, D&A -$1.7M YoY.
A40: Magnite | B40: Hybrid, shifting to owned | G40: On-prem data centers (US, Europe, Asia) for most non-CTV traffic; CTV runs mostly on cloud, with additional on-prem build-out to cut cost (FY25 10-K). FY26 capex guided ~ $60M.
A41: The Trade Desk | B41: Owned / hosted data centers | G41: Platform hosted in global data centers; FY22 10-K cites hosting cost growth from new data centers. Capex $133M in 6M 2026 (9.5% of revenue). Not re-verified against the FY25 10-K.
A42: Criteo | B42: Owned data centers | G42: Q2 26 capex $57.8M, +66% YoY (earnings release supplement). Other cost of revenue only ~12% of net revenue, but capex is the heaviest in the set.
A43: AppLovin | B43: Mostly third-party cloud | G43: Cost of revenue is mainly third-party cloud, finance-leased servers and amortization (FY25 10-K). Capex near zero. Business model differs (owns demand and ML ranking), so margins are not a clean cloud-vs-own read.
A45: 4. OBSERVATIONS (analyst judgment, not model output)
A46: - Ownership shows up in D&A and capex, not in gross margin. PubMatic carries the heaviest D&A load (about 14% of net revenue) yet its Q2 gross margin on net revenue (67%) is within about 2 points of Magnite (69%).
A47: - Most of the PubMatic vs Magnite EBITDA gap (25% vs 37% in Q2) sits in operating expenses, not infrastructure: PubMatic opex was about 66% of revenue vs roughly 52% of net revenue at Magnite. That points to scale, not hosting choice.
A48: - The peer set is mostly not "own vs AWS". Magnite, TTD and Criteo all own substantial infrastructure; Magnite is actively moving CTV from cloud to on-prem for cost reasons, which is the closest direct evidence for the thesis.
A49: - AppLovin is the only cloud-heavy comp and has the best margins (88% gross, 84% EBITDA), but its edge comes from owning demand and ML-driven pricing, so it should not be read as proof that cloud wins.
A50: - Cash view matters: after capex, PubMatic converts about 6% of net revenue (6M) vs about 24% at Magnite and 22% at TTD. Ownership only pays if per-impression cost savings outrun the capex and D&A burden.
A51: - A cleaner test needs unit economics: cost per million impressions or per billion auctions. PubMatic discloses a YoY change only; Magnite and TTD do not disclose it. Worth asking in expert calls.
A53: Comparability: revenue definitions (net vs gross of TAC) and Adjusted EBITDA definitions differ by company. TTD cost of revenue ("platform operations") mixes personnel and data costs with hosting.
A55: 5. MARKET DATA AND ENTERPRISE VALUE ($M) | B55: PUBM | C55: MGNI | D55: TTD | E55: CRTO | F55: APP | G55: Notes
A56: Share price ($), approx. 9/29-9/30/26 | B56: 18.8 | C56: 24.8 | D56: 12.05 | E56: 15.8 | F56: 305.66 | G56: INPUT, refresh before use. PUBM, TTD, APP = 9/29 close; MGNI and CRTO from web quotes dated 9/28-9/30 that disagreed by a few %. Pull from Bloomberg/FactSet.
A57: Shares outstanding (M) | B57: 45.55 | C57: 143.42 | D57: 472.8 | E57: 48.55 | F57: 334.65 | G57: PUBM: Class A 37.304M + Class B 8.246M (10-Q cover, 7/30/26). CRTO: 6/30/26 release. Others: latest quote-page counts. Basic only, no option/RSU dilution (TSM) applied.
A58: Equity value (market cap) | B58: =B56*B57 -> 856.34 | C58: =C56*C57 -> 3556.816 | D58: =D56*D57 -> 5697.24 | E58: =E56*E57 -> 767.09 | F58: =F56*F57 -> 102289.12 | G58: Basic. PUBM fully diluted would be roughly $1.0B (7.3M options at $12.58 plus 5.6M RSUs), about 17% above basic; peers not run.
A59: Plus: debt | B59: 0 | C59: 350.4 | D59: 0 | E59: 9.645 | F59: 3515.072 | G59: Balance sheets 6/30/26. MGNI term loan (current + non-current, net of costs). CRTO "financial liabilities - current". APP long-term debt. PUBM revolver undrawn. Leases excluded for all.
A60: Plus: noncontrolling interest | B60: 0 | C60: 0 | D60: 0 | E60: 36.616 | F60: 0 | G60: Criteo only.
A61: Less: cash and marketable securities | B61: 137.507 | C61: 332.615 | D61: 1485.333 | E61: 303.076 | F61: 3053.306 | G61: 6/30/26. TTD cash + ST investments; CRTO cash + current and noncurrent securities; PUBM cash + marketable securities.
A62: Enterprise value | B62: =B58+B59+B60-B61 -> 718.833 | C62: =C58+C59+C60-C61 -> 3574.601 | D62: =D58+D59+D60-D61 -> 4211.907 | E62: =E58+E59+E60-E61 -> 510.275 | F62: =F58+F59+F60-F61 -> 102750.89 | G62: Cash is not adjusted for customer/publisher float: all five hold large receivables and payables, so treat net cash cautiously.
A64: 6. LTM FINANCIALS (FY2025 + 6M 2026 - 6M 2025, $M) | B64: PUBM | C64: MGNI | D64: TTD | E64: CRTO | F64: APP | G64: Notes
A65: Net revenue, FY2025 | B65: 282.926 | C65: 669.633 | D65: 2896.284 | E65: 1174.6 | F65: 5480.717 | G65: Contribution ex-TAC for MGNI and CRTO. APP continuing operations. Sources: FY25 10-K / Q4 releases.
A66: Net revenue, 6M 2026 | B66: =B25 -> 141.16 | C66: =C25 -> 350.499 | D66: =D25 -> 1403.914 | E66: =E25 -> 505.841 | F66: =F25 -> 3766.135 | G66: Linked to section 2.
A67: Net revenue, 6M 2025 | B67: 134.92 | C67: 307.804 | D67: 1310.06 | E67: 556.441 | F67: 2417.728
A68: LTM net revenue | B68: =B65+B66-B67 -> 289.166 | C68: =C65+C66-C67 -> 712.328 | D68: =D65+D66-D67 -> 2990.138 | E68: =E65+E66-E67 -> 1124 | F68: =F65+F66-F67 -> 6829.124
A69: Adjusted EBITDA, FY2025 | B69: 61.64 | C69: 232.1 | D69: 1196.449 | E69: 406.7 | F69: 4512.452 | G69: MGNI and CRTO FY figures are rounded in their releases.
A70: Adjusted EBITDA, 6M 2026 | B70: =B32 -> 22.204 | C70: =C32 -> 113.461 | D70: =D32 -> 447.345 | E70: =E32 -> 138.198 | F70: =F32 -> 3170.742 | G70: Linked to section 2.
A71: Adjusted EBITDA, 6M 2025 | B71: 22.67 | C71: 91.191 | D71: 478.63 | E71: 181.528 | F71: 1956.119
A72: LTM Adjusted EBITDA | B72: =B69+B70-B71 -> 61.174 | C72: =C69+C70-C71 -> 254.37 | D72: =D69+D70-D71 -> 1165.164 | E72: =E69+E70-E71 -> 363.37 | F72: =F69+F70-F71 -> 5727.075
A73: LTM margin on net revenue | B73: =B72/B68 -> 0.21155323 | C73: =C72/C68 -> 0.35709673 | D73: =D72/D68 -> 0.38966897 | E73: =E72/E68 -> 0.32328292 | F73: =F72/F68 -> 0.83862513
A74: Net income, FY2025 | B74: -14.462 | C74: 144.6 | D74: 443.304 | E74: 149.4 | F74: 3433.195 | G74: MGNI includes a ~$90M one-time tax benefit (valuation allowance release). APP continuing operations.
A75: Net income, 6M 2026 | B75: -13.712 | C75: 23.781 | D75: 104.391 | E75: 20.331 | F75: 2472.151
A76: Net income, 6M 2025 | B76: -14.694 | C76: 1.505 | D76: 140.807 | E76: 62.931 | F76: 1495.394 | G76: APP continuing operations.
A77: LTM net income | B77: =B74+B75-B76 -> -13.48 | C77: =C74+C75-C76 -> 166.876 | D77: =D74+D75-D76 -> 406.888 | E77: =E74+E75-E76 -> 106.8 | F77: =F74+F75-F76 -> 4409.952
A78: Gross profit on net revenue (continuation of section 6)
A79: Gross profit, FY2025 | B79: =B65-'Infra Trend'!D6 -> 179.841 | C79: =C65-'Infra Trend'!D20 -> 447.334 | D79: =D65-'Infra Trend'!D34 -> 2277.217 | E79: =E65-'Infra Trend'!D48 -> 1049.363 | F79: =F65-'Infra Trend'!D62 -> 4815.577 | G79: Net revenue less cost of revenue excl. TAC (links to Infra Trend). Ties to reported gross profit for MGNI and CRTO. TTD has no cost of revenue line, so this is revenue less platform operations (includes personnel and data costs), which understates TTD gross margin vs peers.
A80: Gross profit, 6M 2026 | B80: =B25-B26 -> 89.189 | C80: =C25-C26 -> 234.748 | D80: =D25-D26 -> 1037.611 | E80: =E25-E26 -> 444.956 | F80: =F25-F26 -> 3336.702 | G80: Linked to section 2.
A81: Cost of revenue excl. TAC, 6M 2025 | B81: =('Income Statement'!K10+'Income Statement'!L10)/1000 -> 52.2 | C81: 106.453 | D81: 293.819 | E81: 60.9 | F81: 306.756 | G81: PUBM from model. MGNI, TTD, CRTO, APP from Q2 2026 releases (prior-year six months). CRTO rounded in release.
A82: Gross profit, 6M 2025 | B82: =B67-B81 -> 82.72 | C82: =C67-C81 -> 201.351 | D82: =D67-D81 -> 1016.241 | E82: =E67-E81 -> 495.541 | F82: =F67-F81 -> 2110.972
A83: LTM gross profit | B83: =B79+B80-B82 -> 186.31 | C83: =C79+C80-C82 -> 480.731 | D83: =D79+D80-D82 -> 2298.587 | E83: =E79+E80-E82 -> 998.778 | F83: =F79+F80-F82 -> 6041.307
A84: LTM gross margin on net revenue | B84: =B83/B68 -> 0.6443012 | C84: =C83/C68 -> 0.67487309 | D84: =D83/D68 -> 0.76872271 | E84: =E83/E68 -> 0.88859253 | F84: =F83/F68 -> 0.88463864
A86: 7. TRADING MULTIPLES (with related operating metric under each) | B86: PUBM | C86: MGNI | D86: TTD | E86: CRTO | F86: APP | G86: Notes
A87: EV / LTM net revenue | B87: =B62/B68 -> 2.4858835 | C87: =C62/C68 -> 5.0181953 | D87: =D62/D68 -> 1.4085995 | E87: =E62/E68 -> 0.45398132 | F87: =F62/F68 -> 15.045983
A88: Net revenue growth, 6M 2026 YoY | B88: =B66/B67-1 -> 0.046249629 | C88: =C66/C67-1 -> 0.1387084 | D88: =D66/D67-1 -> 0.071640994 | E88: =E66/E67-1 -> -0.090935068 | F88: =F66/F67-1 -> 0.55771658 | G88: Growth under the revenue multiple. Latest six months vs prior-year six months.
A89: EV / LTM gross profit | B89: =B62/B83 -> 3.8582631 | C89: =C62/C83 -> 7.4357614 | D89: =D62/D83 -> 1.8323896 | E89: =E62/E83 -> 0.51089932 | F89: =F62/F83 -> 17.008056 | G89: Gross profit on net revenue basis. See note in row 79 on TTD.
A90: LTM gross margin on net revenue | B90: =B84 -> 0.6443012 | C90: =C84 -> 0.67487309 | D90: =D84 -> 0.76872271 | E90: =E84 -> 0.88859253 | F90: =F84 -> 0.88463864
A91: EV / LTM Adjusted EBITDA | B91: =B62/B72 -> 11.750629 | C91: =C62/C72 -> 14.052762 | D91: =D62/D72 -> 3.6148619 | E91: =E62/E72 -> 1.4042849 | F91: =F62/F72 -> 17.94125 | G91: Adjusted EBITDA excludes SBC, which is about 12% of 6M net revenue at PUBM, 11% at MGNI and 16% at TTD, so SBC-burdened multiples are higher for all.
A92: LTM Adjusted EBITDA margin | B92: =B73 -> 0.21155323 | C92: =C73 -> 0.35709673 | D92: =D73 -> 0.38966897 | E92: =E73 -> 0.32328292 | F92: =F73 -> 0.83862513
A93: EV / (LTM Adj. EBITDA less 6M capex x2) | B93: =IFERROR(B62/(B72-2*B30),"n.a.") -> 20.596934 | C93: =IFERROR(C62/(C72-2*C30),"n.a.") -> 18.314382 | D93: =IFERROR(D62/(D72-2*D30),"n.a.") -> 4.6880539 | E93: =IFERROR(E62/(E72-2*E30),"n.a.") -> 2.8161804 | F93: =IFERROR(F62/(F72-2*F30),"n.a.") -> n.a. | G93: Rough capex-burdened view: LTM EBITDA less 6M capex annualized. APP n.a. (capex not in release).
A94: Margin after capex (same basis) | B94: =IFERROR((B72-2*B30)/B68,"n.a.") -> 0.12069192 | C94: =IFERROR((C72-2*C30)/C68,"n.a.") -> 0.27400299 | D94: =IFERROR((D72-2*D30)/D68,"n.a.") -> 0.30046573 | E94: =IFERROR((E72-2*E30)/E68,"n.a.") -> 0.16120463 | F94: =IFERROR((F72-2*F30)/F68,"n.a.") -> n.a.
A95: Price / LTM earnings | B95: =IF(B77>0,B58/B77,"NM") -> NM | C95: =IF(C77>0,C58/C77,"NM") -> 21.314125 | D95: =IF(D77>0,D58/D77,"NM") -> 14.001986 | E95: =IF(E77>0,E58/E77,"NM") -> 7.1824906 | F95: =IF(F77>0,F58/F77,"NM") -> 23.195064 | G95: NM where LTM net income is negative. MGNI P/E flattered by the one-time tax benefit.
A96: LTM net income margin on net revenue | B96: =B77/B68 -> -0.046616822 | C96: =C77/C68 -> 0.23426848 | D96: =D77/D68 -> 0.13607666 | E96: =E77/E68 -> 0.095017794 | F96: =F77/F68 -> 0.64575662
A97: LTM net income yield on equity value | B97: =B77/B58 -> -0.015741411 | C97: =C77/C58 -> 0.046917243 | D97: =D77/D58 -> 0.071418441 | E97: =E77/E58 -> 0.13922747 | F97: =F77/F58 -> 0.043112621
A98: Sources: company filings and earnings releases for financials; web quote pages for prices and share counts (inputs in blue, verify before external use).

Sheet Valuation Comps
A1: ($ in mm)
A2: Ad-Tech Valuation Comps
A3: Market data and consensus estimates as of late Sep / early Oct 2026. Multiples are formulas off the Inputs block below (row 36+). Blue = hard-coded input; green = link to another tab; black = formula.
A4: Company | B4: Ticker | C4: Market Value | D4: Enterprise Value | E4: EV / Revenue | G4: EV / Gross Profit | I4: EV / Adj. EBITDA | K4: Revenue Growth | M4: Gross Profit Margin | O4: Adj. EBITDA Margin
E5: CY 26E | F5: CY 27E | G5: CY 26E | H5: CY 27E | I5: CY 26E | J5: CY 27E | K5: CY 26E | L5: CY 27E | M5: CY 26E | N5: CY 27E | O5: CY 26E | P5: CY 27E
A6: Target: PubMatic (excluded from statistics)
A7: =A37 -> PubMatic (Street) | B7: =B37 -> PUBM | C7: =C37 -> 856.34 | D7: =G37 -> 718.833 | E7: =$D7/I37 -> 2.3298642 | F7: =$D7/J37 -> 2.1508423 | G7: =$D7/O37 -> 3.5205848 | H7: =$D7/P37 -> 3.2500704 | I7: =IF(Q37<=0,"NM",$D7/Q37) -> 11.013135 | J7: =IF(R37<=0,"NM",$D7/R37) -> 10.166908 | K7: =I37/H37-1 -> 0.090481745 | L7: =J37/I37-1 -> 0.083233397 | M7: =K37 -> 0.66178329 | N7: =L37 -> 0.66178329 | O7: =M37 -> 0.21155323 | P7: =N37 -> 0.21155323
A8: =A38 -> PubMatic (Model case) | B8: =B38 -> PUBM (Model) | C8: =+DCF!B51 -> 512.3205 | D8: =+DCF!B49 -> 374.8135 | E8: =$D8/I38 -> 1.1341693 | F8: =$D8/J38 -> 0.87857146 | G8: =$D8/O38 -> 1.7907153 | H8: =$D8/P38 -> 1.3607114 | I8: =IF(Q38<=0,"NM",$D8/Q38) -> 4.3544558 | J8: =IF(R38<=0,"NM",$D8/R38) -> 2.2960974 | K8: =I38/H38-1 -> 0.16805821 | L8: =J38/I38-1 -> 0.29092434 | M8: =K38 -> 0.63336102 | N8: =L38 -> 0.64567069 | O8: =M38 -> 0.26046177 | P8: =N38 -> 0.38263685
A10: Supply & Demand-Side Platforms
A11: =A39 -> Magnite | B11: =B39 -> MGNI | C11: =C39 -> 3556.816 | D11: =G39 -> 3574.601 | E11: =$D11/I39 -> 4.6945275 | F11: =$D11/J39 -> 4.2742536 | G11: =$D11/O39 -> 7.2468779 | H11: =$D11/P39 -> 6.5981068 | I11: =IF(Q39<=0,"NM",$D11/Q39) -> 13.146375 | J11: =IF(R39<=0,"NM",$D11/R39) -> 11.969456 | K11: =I39/H39-1 -> 0.066517263 | L11: =J39/I39-1 -> 0.098326854 | M11: =K39 -> 0.6478 | N11: =L39 -> 0.6478 | O11: =M39 -> 0.35709673 | P11: =N39 -> 0.35709673
A12: =A40 -> The Trade Desk | B12: =B40 -> TTD | C12: =C40 -> 5697.24 | D12: =G40 -> 4211.907 | E12: =$D12/I40 -> 1.5316025 | F12: =$D12/J40 -> 1.6075981 | G12: =$D12/O40 -> 2.090925 | H12: =$D12/P40 -> 2.1946732 | I12: =IF(Q40<=0,"NM",$D12/Q40) -> 3.9305222 | J12: =IF(R40<=0,"NM",$D12/R40) -> 4.1255481 | K12: =I40/H40-1 -> -0.050507478 | L12: =J40/I40-1 -> -0.047272727 | M12: =K40 -> 0.7325 | N12: =L40 -> 0.7325 | O12: =M40 -> 0.38966897 | P12: =N40 -> 0.38966897
A13: =A41 -> Criteo | B13: =B41 -> CRTO | C13: =C41 -> 767.09 | D13: =G41 -> 510.275 | E13: =$D13/I41 -> 0.48597619 | F13: =$D13/J41 -> 0.47247685 | G13: =$D13/O41 -> 0.54690556 | H13: =$D13/P41 -> 0.53171374 | I13: =IF(Q41<=0,"NM",$D13/Q41) -> 1.5032535 | J13: =IF(R41<=0,"NM",$D13/R41) -> 1.4614965 | K13: =I41/H41-1 -> -0.10607867 | L13: =J41/I41-1 -> 0.028571429 | M13: =K41 -> 0.88859253 | N13: =L41 -> 0.88859253 | O13: =M41 -> 0.32328292 | P13: =N41 -> 0.32328292
A14: =A42 -> Viant Technology | B14: =B42 -> DSP | C14: =C42 -> 789.72 | D14: =G42 -> 618.81 | E14: =$D14/I42 -> 1.3981563 | F14: =$D14/J42 -> 1.160929 | G14: =$D14/O42 -> 3.138398 | H14: =$D14/P42 -> 2.6059013 | I14: =IF(Q42<=0,"NM",$D14/Q42) -> 10.280561 | J14: =IF(R42<=0,"NM",$D14/R42) -> 8.5362429 | K14: =I42/H42-1 -> 0.28585125 | L14: =J42/I42-1 -> 0.20434262 | M14: =K42 -> 0.4455 | N14: =L42 -> 0.4455 | O14: =M42 -> 0.136 | P14: =N42 -> 0.136
A15: Median | E15: =MEDIAN(E11:E14) -> 1.4648794 | F15: =MEDIAN(F11:F14) -> 1.3842636 | G15: =MEDIAN(G11:G14) -> 2.6146615 | H15: =MEDIAN(H11:H14) -> 2.4002872 | I15: =MEDIAN(I11:I14) -> 7.1055416 | J15: =MEDIAN(J11:J14) -> 6.3308955 | K15: =MEDIAN(K11:K14) -> 0.0080048926 | L15: =MEDIAN(L11:L14) -> 0.063449141 | ... P15: =MEDIAN(P11:P14) -> 0.34018982
A16: Mean | E16: =AVERAGE(E11:E14) -> 2.0275656 | F16: =AVERAGE(F11:F14) -> 1.8788144 | G16: =AVERAGE(G11:G14) -> 3.2557766 | H16: =AVERAGE(H11:H14) -> 2.9825987 | I16: =AVERAGE(I11:I14) -> 7.2151779 | J16: =AVERAGE(J11:J14) -> 6.5231858 | K16: =AVERAGE(K11:K14) -> 0.048945592 | L16: =AVERAGE(L11:L14) -> 0.070992044 | ... P16: =AVERAGE(P11:P14) -> 0.30151216
A18: Mobile & Performance
A19: =A43 -> AppLovin | B19: =B43 -> APP | C19: =C43 -> 102289.12 | D19: =G43 -> 102750.89 | E19: =$D19/I43 -> 12.685294 | F19: =$D19/J43 -> 10.024477 | G19: =$D19/O43 -> 14.374271 | H19: =$D19/P43 -> 11.35918 | I19: =IF(Q43<=0,"NM",$D19/Q43) -> 15.126299 | J19: =IF(R43<=0,"NM",$D19/R43) -> 11.953466 | K19: =I43/H43-1 -> 0.47790882 | L19: =J43/I43-1 -> 0.2654321 | M19: =K43 -> 0.8825 | N19: =L43 -> 0.8825 | O19: =M43 -> 0.83862513 | P19: =N43 -> 0.83862513
A20: =A44 -> Digital Turbine | B20: =B44 -> APPS | C20: =C44 -> 1410 | D20: =G44 -> 1723.16 | E20: =$D20/I44 -> 2.5955505 | F20: =$D20/J44 -> 2.3372804 | G20: =$D20/O44 -> 5.2382451 | H20: =$D20/P44 -> 4.717014 | I20: =IF(Q44<=0,"NM",$D20/Q44) -> 11.487733 | J20: =IF(R44<=0,"NM",$D20/R44) -> 10.344647 | K20: =I44/H44-1 -> 0.17450686 | L20: =J44/I44-1 -> 0.11050023 | M20: =K44 -> 0.4955 | N20: =L44 -> 0.4955 | O20: =M44 -> 0.22594104 | P20: =N44 -> 0.22594104
A21: =A45 -> Perion Network | B21: =B45 -> PERI | C21: =C45 -> 337.85 | D21: =G45 -> 92.12 | E21: =$D21/I45 -> 0.1980181 | F21: =$D21/J45 -> 0.17948368 | G21: =$D21/O45 -> 0.58257752 | H21: =$D21/P45 -> 0.52804849 | I21: =IF(Q45<=0,"NM",$D21/Q45) -> 1.7715385 | J21: =IF(R45<=0,"NM",$D21/R45) -> 1.6057232 | K21: =I45/H45-1 -> 0.057463687 | L21: =J45/I45-1 -> 0.10326519 | M21: =K45 -> 0.3399 | N21: =L45 -> 0.3399 | O21: =M45 -> 0.11177748 | P21: =N45 -> 0.11177748
A22: Median | E22: =MEDIAN(E19:E21) -> 2.5955505 | F22: =MEDIAN(F19:F21) -> 2.3372804 | G22: =MEDIAN(G19:G21) -> 5.2382451 | H22: =MEDIAN(H19:H21) -> 4.717014 | I22: =MEDIAN(I19:I21) -> 11.487733 | J22: =MEDIAN(J19:J21) -> 10.344647 | K22: =MEDIAN(K19:K21) -> 0.17450686 | L22: =MEDIAN(L19:L21) -> 0.11050023 | ... P22: =MEDIAN(P19:P21) -> 0.22594104
A23: Mean | E23: =AVERAGE(E19:E21) -> 5.159621 | F23: =AVERAGE(F19:F21) -> 4.1804136 | G23: =AVERAGE(G19:G21) -> 6.731698 | H23: =AVERAGE(H19:H21) -> 5.5347476 | I23: =AVERAGE(I19:I21) -> 9.4618569 | J23: =AVERAGE(J19:J21) -> 7.9679454 | K23: =AVERAGE(K19:K21) -> 0.23662645 | L23: =AVERAGE(L19:L21) -> 0.15973251 | ... P23: =AVERAGE(P19:P21) -> 0.39211455
A25: All Peers (excl. PubMatic and DV)
A26: Median | E26: =MEDIAN(E11:E14,E19:E21) -> 1.5316025 | F26: =MEDIAN(F11:F14,F19:F21) -> 1.6075981 | G26: =MEDIAN(G11:G14,G19:G21) -> 3.138398 | H26: =MEDIAN(H11:H14,H19:H21) -> 2.6059013 | I26: =MEDIAN(I11:I14,I19:I21) -> 10.280561 | J26: =MEDIAN(J11:J14,J19:J21) -> 8.5362429 | K26: =MEDIAN(K11:K14,K19:K21) -> 0.066517263 | L26: =MEDIAN(L11:L14,L19:L21) -> 0.10326519 | ... P26: =MEDIAN(P11:P14,P19:P21) -> 0.32328292
A27: Mean | E27: =AVERAGE(E11:E14,E19:E21) -> 3.3698751 | F27: =AVERAGE(F11:F14,F19:F21) -> 2.865214 | G27: =AVERAGE(G11:G14,G19:G21) -> 4.7454572 | H27: =AVERAGE(H11:H14,H19:H21) -> 4.0763768 | I27: =AVERAGE(I11:I14,I19:I21) -> 8.1780403 | J27: =AVERAGE(J11:J14,J19:J21) -> 7.1423685 | K27: =AVERAGE(K11:K14,K19:K21) -> 0.12938025 | L27: =AVERAGE(L11:L14,L19:L21) -> 0.10902367 | ... P27: =AVERAGE(P11:P14,P19:P21) -> 0.34034175
A29: Memo: excluded from statistics
A30: =A46 -> DoubleVerify (memo) | B30: =B46 -> DV | C30: =C46 -> 2090 | D30: =G46 -> 1991.66 | E30: =$D30/I46 -> 2.469449 | F30: =$D30/J46 -> 2.2794131 | G30: =$D30/O46 -> 3.0082215 | H30: =$D30/P46 -> 2.7767245 | I30: =IF(Q46<=0,"NM",$D30/Q46) -> 7.2630853 | J30: =IF(R46<=0,"NM",$D30/R46) -> 6.7041562 | K30: =I46/H46-1 -> 0.077817424 | L30: =J46/I46-1 -> 0.08337053 | M30: =K46 -> 0.8209 | N30: =L46 -> 0.8209 | O30: =M46 -> 0.34 | P30: =N46 -> 0.34
A32: Notes: Peer revenue and gross profit are analyst consensus from StockAnalysis.com (unofficial, see cell notes on Inputs). Adj. EBITDA uses company guidance where available (APPS, PERI, DV), otherwise LTM / latest-quarter margin held flat into CY27E. Replace with your own estimates or FactSet/CapIQ consensus.
A33: Basis differences: MGNI, DSP, PERI revenue is gross; CRTO is Contribution ex-TAC; PUBM, TTD, APP report net. APPS fiscal year ends March. Market data for PUBM/MGNI/TTD/CRTO/APP links to the Comps tab (refresh prices there). IAS excluded (taken private Dec 2025).
A35: INPUTS ($ in mm)
A36: Company | B36: Ticker | C36: Market value | D36: Debt | E36: Noncontrolling interest | F36: Cash & securities | G36: Enterprise value | H36: Revenue CY25A | I36: Revenue CY26E | J36: Revenue CY27E | K36: Gross margin CY26E | L36: Gross margin CY27E | M36: Adj. EBITDA margin CY26E | N36: Adj. EBITDA margin CY27E | O36: Gross profit CY26E | P36: Gross profit CY27E | Q36: Adj. EBITDA CY26E | R36: Adj. EBITDA CY27E | S36: Basis / notes
A37: PubMatic (Street) | B37: PUBM | C37: =Comps!B58 -> 856.34 | D37: =Comps!B59 -> 0 | E37: =Comps!B60 -> 0 | F37: =Comps!B61 -> 137.507 | G37: =C37+D37+E37-F37 -> 718.833 | H37: 282.93 | I37: 308.53 | J37: 334.21 | K37: =204.18/I37 -> 0.66178329 | L37: =K37 -> 0.66178329 | M37: =Comps!B73 -> 0.21155323 | N37: =M37 -> 0.21155323 | O37: =I37*K37 -> 204.18 | P37: =J37*L37 -> 221.1746 | Q37: =I37*M37 -> 65.270517 | R37: =J37*N37 -> 70.703203 | S37: Market data from Comps tab (9/29-9/30/26). Revenue/GP = consensus. EBITDA margin = LTM actual held flat.
A38: PubMatic (Model case) | B38: PUBM (Model) | C38: =C37 -> 856.34 | D38: =D37 -> 0 | E38: =E37 -> 0 | F38: =F37 -> 137.507 | G38: =C38+D38+E38-F38 -> 718.833 | H38: ='Income Statement'!AD9/1000 -> 282.926 | I38: ='Income Statement'!AE9/1000 -> 330.47404 | J38: ='Income Statement'!AF9/1000 -> 426.61698 | K38: ='Income Statement'!AE11/'Income Statement'!AE9 -> 0.63336102 | L38: ='Income Statement'!AF11/'Income Statement'!AF9 -> 0.64567069 | M38: ='Income Statement'!AE51/'Income Statement'!AE9 -> 0.26046177 | N38: ='Income Statement'!AF51/'Income Statement'!AF9 -> 0.38263685 | O38: =I38*K38 -> 209.30937 | P38: =J38*L38 -> 275.45408 | Q38: =I38*M38 -> 86.075854 | R38: =J38*N38 -> 163.23938 | S38: Your model's FY2026E / FY2027E (Income Statement tab). CY27E margins use model FY2027E.
A39: Magnite | B39: MGNI | C39: =Comps!C58 -> 3556.816 | D39: =Comps!C59 -> 350.4 | E39: =Comps!C60 -> 0 | F39: =Comps!C61 -> 332.615 | G39: =C39+D39+E39-F39 -> 3574.601 | H39: 713.95 | I39: 761.44 | J39: 836.31 | K39: 0.6478 | L39: =K39 -> 0.6478 | M39: =Comps!C73 -> 0.35709673 | N39: =M39 -> 0.35709673 | O39: =I39*K39 -> 493.26083 | P39: =J39*L39 -> 541.76162 | Q39: =I39*M39 -> 271.90773 | R39: =J39*N39 -> 298.64357 | S39: Revenue on reported (gross) basis per consensus; EBITDA margin = LTM on ex-TAC basis (close to gross for MGNI).
A40: The Trade Desk | B40: TTD | C40: =Comps!D58 -> 5697.24 | D40: =Comps!D59 -> 0 | E40: =Comps!D60 -> 0 | F40: =Comps!D61 -> 1485.333 | G40: =C40+D40+E40-F40 -> 4211.907 | H40: =Comps!D65 -> 2896.284 | I40: 2750 | J40: 2620 | K40: 0.7325 | L40: =K40 -> 0.7325 | M40: =Comps!D73 -> 0.38966897 | N40: =M40 -> 0.38966897 | O40: =I40*K40 -> 2014.375 | P40: =J40*L40 -> 1919.15 | Q40: =I40*M40 -> 1071.5897 | R40: =J40*N40 -> 1020.9327 | S40: CY25A from Comps tab (FY2025 10-K). EBITDA margin = LTM actual held flat.
A41: Criteo | B41: CRTO | C41: =Comps!E58 -> 767.09 | D41: =Comps!E59 -> 9.645 | E41: =Comps!E60 -> 36.616 | F41: =Comps!E61 -> 303.076 | G41: =C41+D41+E41-F41 -> 510.275 | H41: =Comps!E65 -> 1174.6 | I41: 1050 | J41: 1080 | K41: =Comps!E84 -> 0.88859253 | L41: =K41 -> 0.88859253 | M41: =Comps!E73 -> 0.32328292 | N41: =M41 -> 0.32328292 | O41: =I41*K41 -> 933.02215 | P41: =J41*L41 -> 959.67993 | Q41: =I41*M41 -> 339.44706 | R41: =J41*N41 -> 349.14555 | S41: All on Contribution ex-TAC basis (consensus switched to ex-TAC in 2026). GM and EBITDA margin = LTM ex-TAC from Comps tab.
A42: Viant Technology | B42: DSP | C42: 789.72 | D42: 22.14 | E42: 0 | F42: 193.05 | G42: =C42+D42+E42-F42 -> 618.81 | H42: 344.2 | I42: 442.59 | J42: 533.03 | K42: 0.4455 | L42: =K42 -> 0.4455 | M42: 0.136 | N42: =M42 -> 0.136 | O42: =I42*K42 -> 197.17385 | P42: =J42*L42 -> 237.46487 | Q42: =I42*M42 -> 60.19224 | R42: =J42*N42 -> 72.49208 | S42: Gross revenue basis. EBITDA margin = Q2'26 adj. EBITDA / revenue (no FY guidance given).
A43: AppLovin | B43: APP | C43: =Comps!F58 -> 102289.12 | D43: =Comps!F59 -> 3515.072 | E43: =Comps!F60 -> 0 | F43: =Comps!F61 -> 3053.306 | G43: =C43+D43+E43-F43 -> 102750.89 | H43: =Comps!F65 -> 5480.717 | I43: 8100 | J43: 10250 | K43: 0.8825 | L43: =K43 -> 0.8825 | M43: =Comps!F73 -> 0.83862513 | N43: =M43 -> 0.83862513 | O43: =I43*K43 -> 7148.25 | P43: =J43*L43 -> 9045.625 | Q43: =I43*M43 -> 6792.8636 | R43: =J43*N43 -> 8595.9076 | S43: Continuing operations. EBITDA margin = LTM actual held flat.
A44: Digital Turbine | B44: APPS | C44: 1410 | D44: 356.09 | E44: 0 | F44: 42.93 | G44: =C44+D44+E44-F44 -> 1723.16 | H44: 565.25 | I44: 663.89 | J44: 737.25 | K44: 0.4955 | L44: =K44 -> 0.4955 | M44: =150/I44 -> 0.22594104 | N44: =M44 -> 0.22594104 | O44: =I44*K44 -> 328.95749 | P44: =J44*L44 -> 365.30737 | Q44: =I44*M44 -> 150 | R44: =J44*N44 -> 166.57504 | S44: Fiscal year ends March: FY Mar-26 / Mar-27 / Mar-28 shown as CY25A / CY26E / CY27E.
A45: Perion Network | B45: PERI | C45: 337.85 | D45: 22.1 | E45: 0 | F45: 267.83 | G45: =C45+D45+E45-F45 -> 92.12 | H45: 439.93 | I45: 465.21 | J45: 513.25 | K45: 0.3399 | L45: =K45 -> 0.3399 | M45: =52/I45 -> 0.11177748 | N45: =M45 -> 0.11177748 | O45: =I45*K45 -> 158.12488 | P45: =J45*L45 -> 174.45367 | Q45: =I45*M45 -> 52 | R45: =J45*N45 -> 57.36979 | S45: Gross revenue basis. EBITDA = FY26 guidance midpoint.
A46: DoubleVerify (memo) | B46: DV | C46: 2090 | D46: 111.83 | E46: 0 | F46: 210.17 | G46: =C46+D46+E46-F46 -> 1991.66 | H46: 748.29 | I46: 806.52 | J46: 873.76 | K46: 0.8209 | L46: =K46 -> 0.8209 | M46: 0.34 | N46: =M46 -> 0.34 | O46: =I46*K46 -> 662.07227 | P46: =J46*L46 -> 717.26958 | Q46: =I46*M46 -> 274.2168 | R46: =J46*N46 -> 297.0784 | S46: Pending acquisition by Nielsen (announced 8/6/26); trades on deal terms. Excluded from medians/means.

Sheet Infra Trend
A1: Infrastructure cost breakdown and trend: own vs cloud
A2: $ in millions. FY2024/FY2025 from Q4 2025 earnings releases (blue = hard-coded). 6M 2026 links to Comps. PUBM links to the model. Net revenue = revenue for PUBM, TTD, APP; contribution ex-TAC for MGNI and CRTO.
A4: PUBM (owns hardware, colocated data centers) | B4: FY2023 | C4: FY2024 | D4: FY2025 | E4: 6M'26 | F4: FY25 YoY | G4: Notes
A5: Net revenue | B5: ='Income Statement'!AB9/1000 -> 267.014 | C5: ='Income Statement'!AC9/1000 -> 291.256 | D5: ='Income Statement'!AD9/1000 -> 282.926 | E5: =Comps!B25 -> 141.16 | F5: =IFERROR(D5/C5-1,"n.a.") -> -0.028600269 | G5: Cost of revenue is almost all infrastructure: data center, bandwidth, depreciation of owned servers, amortization of capitalized software.
A6: Cost of revenue excl. TAC | B6: ='Income Statement'!AB10/1000 -> 99.229 | C6: ='Income Statement'!AC10/1000 -> 101.027 | D6: ='Income Statement'!AD10/1000 -> 103.085 | E6: =Comps!B26 -> 51.971 | F6: =IFERROR(D6/C6-1,"n.a.") -> 0.020370792
A7: % of net revenue | B7: =IFERROR(B6/B5,"n.a.") -> 0.37162471 | C7: =IFERROR(C6/C5,"n.a.") -> 0.34686667 | D7: =IFERROR(D6/D5,"n.a.") -> 0.36435322 | E7: =IFERROR(E6/E5,"n.a.") -> 0.36817087
A8: Depreciation and amortization | B8: ='Income Statement'!AB47/1000 -> 44.77 | C8: ='Income Statement'!AC47/1000 -> 45.352 | D8: ='Income Statement'!AD47/1000 -> 43.769 | E8: =Comps!B28 -> 19.995 | F8: =IFERROR(D8/C8-1,"n.a.") -> -0.034904745
A9: % of net revenue | B9: =IFERROR(B8/B5,"n.a.") -> 0.16766911 | C9: =IFERROR(C8/C5,"n.a.") -> 0.15571181 | D9: =IFERROR(D8/D5,"n.a.") -> 0.15470123 | E9: =IFERROR(E8/E5,"n.a.") -> 0.14164778
A10: Capex incl. capitalized software | B10: =-('Cash Flow'!AA26+'Cash Flow'!AA27)/1000 -> 28.288 | C10: =-('Cash Flow'!AB26+'Cash Flow'!AB27)/1000 -> 38.528 | D10: =-('Cash Flow'!AC26+'Cash Flow'!AC27)/1000 -> 34.856 | E10: =Comps!B30 -> 13.137 | F10: =IFERROR(D10/C10-1,"n.a.") -> -0.095307309
A11: % of net revenue | B11: =IFERROR(B10/B5,"n.a.") -> 0.10594201 | C11: =IFERROR(C10/C5,"n.a.") -> 0.13228225 | D11: =IFERROR(D10/D5,"n.a.") -> 0.12319829 | E11: =IFERROR(E10/E5,"n.a.") -> 0.093064608
A12: Finance lease principal | B12: =-'Cash Flow'!AA39/1000 -> 0.126 | C12: =-'Cash Flow'!AB39/1000 -> 0.131 | D12: =-'Cash Flow'!AC39/1000 -> 0.14 | E12: =-('Cash Flow'!N39+'Cash Flow'!O39)/1000 -> 0.075 | F12: =IFERROR(D12/C12-1,"n.a.") -> 0.06870229
A13: Adjusted EBITDA | B13: ='Income Statement'!AB51/1000 -> 75.309 | C13: ='Income Statement'!AC51/1000 -> 92.325 | D13: ='Income Statement'!AD51/1000 -> 61.64 | E13: =Comps!B32 -> 22.204 | F13: =IFERROR(D13/C13-1,"n.a.") -> -0.33235852
A14: % of net revenue | B14: =IFERROR(B13/B5,"n.a.") -> 0.28204139 | C14: =IFERROR(C13/C5,"n.a.") -> 0.31698918 | D14: =IFERROR(D13/D5,"n.a.") -> 0.21786616 | E14: =IFERROR(E13/E5,"n.a.") -> 0.15729668
A15: Adj. EBITDA less capex and lease principal | B15: =IFERROR(B13-B10-B12,"n.a.") -> 46.895 | C15: =IFERROR(C13-C10-C12,"n.a.") -> 53.666 | D15: =IFERROR(D13-D10-D12,"n.a.") -> 26.644 | E15: =IFERROR(E13-E10-E12,"n.a.") -> 8.992
A16: % of net revenue | B16: =IFERROR(B15/B5,"n.a.") -> 0.1756275 | C16: =IFERROR(C15/C5,"n.a.") -> 0.18425715 | D16: =IFERROR(D15/D5,"n.a.") -> 0.094173035 | E16: =IFERROR(E15/E5,"n.a.") -> 0.063700765
A18: MGNI (hybrid: on-prem plus cloud, CTV shifting on-prem) | B18: FY2023 | C18: FY2024 | D18: FY2025 | E18: 6M'26 | F18: FY25 YoY | G18: Notes
A19: Net revenue | B19: n.a. | C19: 606.942 | D19: 669.633 | E19: =Comps!C25 -> 350.499 | F19: =IFERROR(D19/C19-1,"n.a.") -> 0.10328994 | G19: FY25 PP&E purchases jumped to $70.5M from $32.8M (about 2.1x), consistent with the on-prem build. Finance lease principal not pulled, set to 0 (verify in 10-K).
A20: Cost of revenue excl. TAC | B20: n.a. | C20: 197.61 | D20: 222.299 | E20: =Comps!C26 -> 115.751 | F20: =IFERROR(D20/C20-1,"n.a.") -> 0.12493801
A21: % of net revenue | B21: =IFERROR(B20/B19,"n.a.") -> n.a. | C21: =IFERROR(C20/C19,"n.a.") -> 0.325583 | D21: =IFERROR(D20/D19,"n.a.") -> 0.33197139 | E21: =IFERROR(E20/E19,"n.a.") -> 0.33024631
A22: Depreciation and amortization | B22: n.a. | C22: 58.51 | D22: 53.674 | E22: =Comps!C28 -> 28.922 | F22: =IFERROR(D22/C22-1,"n.a.") -> -0.082652538
A23: % of net revenue | B23: =IFERROR(B22/B19,"n.a.") -> n.a. | C23: =IFERROR(C22/C19,"n.a.") -> 0.096401304 | D23: =IFERROR(D22/D19,"n.a.") -> 0.080154353 | E23: =IFERROR(E22/E19,"n.a.") -> 0.082516641
A24: Capex incl. capitalized software | B24: n.a. | C24: =32.81+14.26 -> 47.07 | D24: =70.535+13.768 -> 84.303 | E24: =Comps!C30 -> 29.595 | F24: =IFERROR(D24/C24-1,"n.a.") -> 0.79101338
A25: % of net revenue | B25: =IFERROR(B24/B19,"n.a.") -> n.a. | C25: =IFERROR(C24/C19,"n.a.") -> 0.077552715 | D25: =IFERROR(D24/D19,"n.a.") -> 0.12589433 | E25: =IFERROR(E24/E19,"n.a.") -> 0.08443676
A26: Finance lease principal | B26: n.a. | C26: 0 | D26: 0 | E26: 0 | F26: =IFERROR(D26/C26-1,"n.a.") -> n.a.
A27: Adjusted EBITDA | B27: n.a. | C27: 196.85 | D27: 232.131 | E27: =Comps!C32 -> 113.461 | F27: =IFERROR(D27/C27-1,"n.a.") -> 0.17922784
A28: % of net revenue | B28: =IFERROR(B27/B19,"n.a.") -> n.a. | C28: =IFERROR(C27/C19,"n.a.") -> 0.32433083 | D28: =IFERROR(D27/D19,"n.a.") -> 0.34665406 | E28: =IFERROR(E27/E19,"n.a.") -> 0.32371276
A29: Adj. EBITDA less capex and lease principal | B29: =IFERROR(B27-B24-B26,"n.a.") -> n.a. | C29: =IFERROR(C27-C24-C26,"n.a.") -> 149.78 | D29: =IFERROR(D27-D24-D26,"n.a.") -> 147.828 | E29: =IFERROR(E27-E24-E26,"n.a.") -> 83.866
A30: % of net revenue | B30: =IFERROR(B29/B19,"n.a.") -> n.a. | C30: =IFERROR(C29/C19,"n.a.") -> 0.24677811 | D30: =IFERROR(D29/D19,"n.a.") -> 0.22075973 | E30: =IFERROR(E29/E19,"n.a.") -> 0.239276
A32: TTD (owned or hosted data centers, Kokai build) | B32: FY2023 | C32: FY2024 | D32: FY2025 | E32: 6M'26 | F32: FY25 YoY | G32: Notes
A33: Net revenue | B33: n.a. | C33: 2444.831 | D33: 2896.284 | E33: =Comps!D25 -> 1403.914 | F33: =IFERROR(D33/C33-1,"n.a.") -> 0.18465612 | G33: Cost line is platform operations, which also includes people and data costs, so it overstates pure infrastructure. Capex roughly doubled in FY25. Finance leases not pulled, set to 0.
A34: Cost of revenue excl. TAC | B34: n.a. | C34: 472.012 | D34: 619.067 | E34: =Comps!D26 -> 366.303 | F34: =IFERROR(D34/C34-1,"n.a.") -> 0.31154928
A35: % of net revenue | B35: =IFERROR(B34/B33,"n.a.") -> n.a. | C35: =IFERROR(C34/C33,"n.a.") -> 0.19306529 | D35: =IFERROR(D34/D33,"n.a.") -> 0.21374527 | E35: =IFERROR(E34/E33,"n.a.") -> 0.26091555
A36: Depreciation and amortization | B36: n.a. | C36: 87.49 | D36: 115.784 | E36: =Comps!D28 -> 61.571 | F36: =IFERROR(D36/C36-1,"n.a.") -> 0.32339696
A37: % of net revenue | B37: =IFERROR(B36/B33,"n.a.") -> n.a. | C37: =IFERROR(C36/C33,"n.a.") -> 0.035785705 | D37: =IFERROR(D36/D33,"n.a.") -> 0.039976743 | E37: =IFERROR(E36/E33,"n.a.") -> 0.043856675
A38: Capex incl. capitalized software | B38: n.a. | C38: =98.238+8.824 -> 107.062 | D38: =197.011+12.752 -> 209.763 | E38: =Comps!D30 -> 133.365 | F38: =IFERROR(D38/C38-1,"n.a.") -> 0.95926659
A39: % of net revenue | B39: =IFERROR(B38/B33,"n.a.") -> n.a. | C39: =IFERROR(C38/C33,"n.a.") -> 0.043791166 | D39: =IFERROR(D38/D33,"n.a.") -> 0.072424873 | E39: =IFERROR(E38/E33,"n.a.") -> 0.094995135
A40: Finance lease principal | B40: n.a. | C40: 0 | D40: 0 | E40: 0 | F40: =IFERROR(D40/C40-1,"n.a.") -> n.a.
A41: Adjusted EBITDA | B41: n.a. | C41: 1010.649 | D41: 1196.449 | E41: =Comps!D32 -> 447.345 | F41: =IFERROR(D41/C41-1,"n.a.") -> 0.18384226
A42: % of net revenue | B42: =IFERROR(B41/B33,"n.a.") -> n.a. | C42: =IFERROR(C41/C33,"n.a.") -> 0.41338195 | D42: =IFERROR(D41/D33,"n.a.") -> 0.41309796 | E42: =IFERROR(E41/E33,"n.a.") -> 0.31864131
A43: Adj. EBITDA less capex and lease principal | B43: =IFERROR(B41-B38-B40,"n.a.") -> n.a. | C43: =IFERROR(C41-C38-C40,"n.a.") -> 903.587 | D43: =IFERROR(D41-D38-D40,"n.a.") -> 986.686 | E43: =IFERROR(E41-E38-E40,"n.a.") -> 313.98
A44: % of net revenue | B44: =IFERROR(B43/B33,"n.a.") -> n.a. | C44: =IFERROR(C43/C33,"n.a.") -> 0.36959078 | D44: =IFERROR(D43/D33,"n.a.") -> 0.34067308 | E44: =IFERROR(E43/E33,"n.a.") -> 0.22364618
A46: CRTO (owns data centers) | B46: FY2023 | C46: FY2024 | D46: FY2025 | E46: 6M'26 | F46: FY25 YoY | G46: Notes
A47: Net revenue | B47: n.a. | C47: 1121.483 | D47: 1174.617 | E47: =Comps!E25 -> 505.841 | F47: =IFERROR(D47/C47-1,"n.a.") -> 0.047378337 | G47: Other cost of revenue fell while D&A and capex rose: classic owner profile, cost moves from COGS into depreciation. Capex per release (PP&E plus intangibles). Leases not pulled, set to 0.
A48: Cost of revenue excl. TAC | B48: n.a. | C48: 138.512 | D48: 125.237 | E48: =Comps!E26 -> 60.885 | F48: =IFERROR(D48/C48-1,"n.a.") -> -0.095840072
A49: % of net revenue | B49: =IFERROR(B48/B47,"n.a.") -> n.a. | C49: =IFERROR(C48/C47,"n.a.") -> 0.12350789 | D49: =IFERROR(D48/D47,"n.a.") -> 0.10661943 | E49: =IFERROR(E48/E47,"n.a.") -> 0.12036391
A50: Depreciation and amortization | B50: n.a. | C50: 101.193 | D50: 122.32 | E50: =Comps!E28 -> 59.948 | F50: =IFERROR(D50/C50-1,"n.a.") -> 0.20877926
A51: % of net revenue | B51: =IFERROR(B50/B47,"n.a.") -> n.a. | C51: =IFERROR(C50/C47,"n.a.") -> 0.090231417 | D51: =IFERROR(D50/D47,"n.a.") -> 0.10413607 | E51: =IFERROR(E50/E47,"n.a.") -> 0.11851155
A52: Capex incl. capitalized software | B52: n.a. | C52: 78.112 | D52: 102.739 | E52: =Comps!E30 -> 91.088 | F52: =IFERROR(D52/C52-1,"n.a.") -> 0.31527806
A53: % of net revenue | B53: =IFERROR(B52/B47,"n.a.") -> n.a. | C53: =IFERROR(C52/C47,"n.a.") -> 0.069650632 | D53: =IFERROR(D52/D47,"n.a.") -> 0.087465957 | E53: =IFERROR(E52/E47,"n.a.") -> 0.18007239
A54: Finance lease principal | B54: n.a. | C54: 0 | D54: 0 | E54: 0 | F54: =IFERROR(D54/C54-1,"n.a.") -> n.a.
A55: Adjusted EBITDA | B55: n.a. | C55: 390.118 | D55: 406.696 | E55: =Comps!E32 -> 138.198 | F55: =IFERROR(D55/C55-1,"n.a.") -> 0.042494835
A56: % of net revenue | B56: =IFERROR(B55/B47,"n.a.") -> n.a. | C56: =IFERROR(C55/C47,"n.a.") -> 0.34785904 | D56: =IFERROR(D55/D47,"n.a.") -> 0.34623711 | E56: =IFERROR(E55/E47,"n.a.") -> 0.27320443
A57: Adj. EBITDA less capex and lease principal | B57: =IFERROR(B55-B52-B54,"n.a.") -> n.a. | C57: =IFERROR(C55-C52-C54,"n.a.") -> 312.006 | D57: =IFERROR(D55-D52-D54,"n.a.") -> 303.957 | E57: =IFERROR(E55-E52-E54,"n.a.") -> 47.11
A58: % of net revenue | B58: =IFERROR(B57/B47,"n.a.") -> n.a. | C58: =IFERROR(C57/C47,"n.a.") -> 0.27820841 | D58: =IFERROR(D57/D47,"n.a.") -> 0.25877116 | E58: =IFERROR(E57/E47,"n.a.") -> 0.093132032
A60: APP (mostly third-party cloud plus finance-leased servers) | B60: FY2023 | C60: FY2024 | D60: FY2025 | E60: 6M'26 | F60: FY25 YoY | G60: Notes
A61: Net revenue | B61: n.a. | C61: 3224.058 | D61: 5480.717 | E61: =Comps!F25 -> 3766.135 | F61: =IFERROR(D61/C61-1,"n.a.") -> 0.69994367 | G61: Cost of revenue is largely hosting and payment processing. Capex near zero: the cloud-renter profile, so the cost sits in COGS and EBITDA. Not a clean comp (different business).
A62: Cost of revenue excl. TAC | B62: n.a. | C62: 520.613 | D62: 665.14 | E62: =Comps!F26 -> 429.433 | F62: =IFERROR(D62/C62-1,"n.a.") -> 0.27760928
A63: % of net revenue | B63: =IFERROR(B62/B61,"n.a.") -> n.a. | C63: =IFERROR(C62/C61,"n.a.") -> 0.16147755 | D63: =IFERROR(D62/D61,"n.a.") -> 0.12136003 | E63: =IFERROR(E62/E61,"n.a.") -> 0.11402486
A64: Depreciation and amortization | B64: n.a. | C64: 128.791 | D64: 130.724 | E64: =Comps!F28 -> 66.228 | F64: =IFERROR(D64/C64-1,"n.a.") -> 0.015008813
A65: % of net revenue | B65: =IFERROR(B64/B61,"n.a.") -> n.a. | C65: =IFERROR(C64/C61,"n.a.") -> 0.039946862 | D65: =IFERROR(D64/D61,"n.a.") -> 0.023851624 | E65: =IFERROR(E64/E61,"n.a.") -> 0.017585137
A66: Capex incl. capitalized software | B66: n.a. | C66: =4.776 -> 4.776 | D66: =0.473 -> 0.473 | E66: =Comps!F30 -> n.a. | F66: =IFERROR(D66/C66-1,"n.a.") -> -0.90096315
A67: % of net revenue | B67: =IFERROR(B66/B61,"n.a.") -> n.a. | C67: =IFERROR(C66/C61,"n.a.") -> 0.0014813629 | D67: =IFERROR(D66/D61,"n.a.") -> 8.6302577e-05 | E67: =IFERROR(E66/E61,"n.a.") -> n.a.
A68: Finance lease principal | B68: n.a. | C68: 20.875 | D68: 18.669 | E68: n.a. | F68: =IFERROR(D68/C68-1,"n.a.") -> -0.10567665
A69: Adjusted EBITDA | B69: n.a. | C69: 2411.764 | D69: 4512.452 | E69: =Comps!F32 -> 3170.742 | F69: =IFERROR(D69/C69-1,"n.a.") -> 0.87101723
A70: % of net revenue | B70: =IFERROR(B69/B61,"n.a.") -> n.a. | C70: =IFERROR(C69/C61,"n.a.") -> 0.7480523 | D70: =IFERROR(D69/D61,"n.a.") -> 0.82333242 | E70: =IFERROR(E69/E61,"n.a.") -> 0.84190875
A71: Adj. EBITDA less capex and lease principal | B71: =IFERROR(B69-B66-B68,"n.a.") -> n.a. | C71: =IFERROR(C69-C66-C68,"n.a.") -> 2386.113 | D71: =IFERROR(D69-D66-D68,"n.a.") -> 4493.31 | E71: =IFERROR(E69-E66-E68,"n.a.") -> n.a.
A72: % of net revenue | B72: =IFERROR(B71/B61,"n.a.") -> n.a. | C72: =IFERROR(C71/C61,"n.a.") -> 0.74009618 | D72: =IFERROR(D71/D61,"n.a.") -> 0.81983981 | E72: =IFERROR(E71/E61,"n.a.") -> n.a.
A74: SUMMARY TREND (% of net revenue) | B74: FY2023 | C74: FY2024 | D74: FY2025 | E74: 6M'26 | F74: Chg FY24-25 | G74: Notes
A75: Cost of revenue excl. TAC
A76: PUBM | B76: =B7 -> 0.37162471 | C76: =C7 -> 0.34686667 | D76: =D7 -> 0.36435322 | E76: =E7 -> 0.36817087 | F76: =IFERROR(D7-C7,"n.a.") -> 0.017486549
A77: MGNI | B77: =B21 -> n.a. | C77: =C21 -> 0.325583 | D77: =D21 -> 0.33197139 | E77: =E21 -> 0.33024631 | F77: =IFERROR(D21-C21,"n.a.") -> 0.0063883886
A78: TTD | B78: =B35 -> n.a. | C78: =C35 -> 0.19306529 | D78: =D35 -> 0.21374527 | E78: =E35 -> 0.26091555 | F78: =IFERROR(D35-C35,"n.a.") -> 0.020679981
A79: CRTO | B79: =B49 -> n.a. | C79: =C49 -> 0.12350789 | D79: =D49 -> 0.10661943 | E79: =E49 -> 0.12036391 | F79: =IFERROR(D49-C49,"n.a.") -> -0.016888457
A80: APP | B80: =B63 -> n.a. | C80: =C63 -> 0.16147755 | D80: =D63 -> 0.12136003 | E80: =E63 -> 0.11402486 | F80: =IFERROR(D63-C63,"n.a.") -> -0.04011752
A81: D&A
A82: PUBM | B82: =B9 -> 0.16766911 | C82: =C9 -> 0.15571181 | D82: =D9 -> 0.15470123 | E82: =E9 -> 0.14164778 | F82: =IFERROR(D9-C9,"n.a.") -> -0.0010105844
A83: MGNI | B83: =B23 -> n.a. | C83: =C23 -> 0.096401304 | D83: =D23 -> 0.080154353 | E83: =E23 -> 0.082516641 | F83: =IFERROR(D23-C23,"n.a.") -> -0.01624695
A84: TTD | B84: =B37 -> n.a. | C84: =C37 -> 0.035785705 | D84: =D37 -> 0.039976743 | E84: =E37 -> 0.043856675 | F84: =IFERROR(D37-C37,"n.a.") -> 0.004191038
A85: CRTO | B85: =B51 -> n.a. | C85: =C51 -> 0.090231417 | D85: =D51 -> 0.10413607 | E85: =E51 -> 0.11851155 | F85: =IFERROR(D51-C51,"n.a.") -> 0.013904655
A86: APP | B86: =B65 -> n.a. | C86: =C65 -> 0.039946862 | D86: =D65 -> 0.023851624 | E86: =E65 -> 0.017585137 | F86: =IFERROR(D65-C65,"n.a.") -> -0.016095238
A87: Capex incl. capitalized software
A88: PUBM | B88: =B11 -> 0.10594201 | C88: =C11 -> 0.13228225 | D88: =D11 -> 0.12319829 | E88: =E11 -> 0.093064608 | F88: =IFERROR(D11-C11,"n.a.") -> -0.0090839613
A89: MGNI | B89: =B25 -> n.a. | C89: =C25 -> 0.077552715 | D89: =D25 -> 0.12589433 | E89: =E25 -> 0.08443676 | F89: =IFERROR(D25-C25,"n.a.") -> 0.048341618
A90: TTD | B90: =B39 -> n.a. | C90: =C39 -> 0.043791166 | D90: =D39 -> 0.072424873 | E90: =E39 -> 0.094995135 | F90: =IFERROR(D39-C39,"n.a.") -> 0.028633707
A91: CRTO | B91: =B53 -> n.a. | C91: =C53 -> 0.069650632 | D91: =D53 -> 0.087465957 | E91: =E53 -> 0.18007239 | F91: =IFERROR(D53-C53,"n.a.") -> 0.017815325
A92: APP | B92: =B67 -> n.a. | C92: =C67 -> 0.0014813629 | D92: =D67 -> 8.6302577e-05 | E92: =E67 -> n.a. | F92: =IFERROR(D67-C67,"n.a.") -> -0.0013950604
A93: Adj. EBITDA
A94: PUBM | B94: =B14 -> 0.28204139 | C94: =C14 -> 0.31698918 | D94: =D14 -> 0.21786616 | E94: =E14 -> 0.15729668 | F94: =IFERROR(D14-C14,"n.a.") -> -0.099123022
A95: MGNI | B95: =B28 -> n.a. | C95: =C28 -> 0.32433083 | D95: =D28 -> 0.34665406 | E95: =E28 -> 0.32371276 | F95: =IFERROR(D28-C28,"n.a.") -> 0.022323237
A96: TTD | B96: =B42 -> n.a. | C96: =C42 -> 0.41338195 | D96: =D42 -> 0.41309796 | E96: =E42 -> 0.31864131 | F96: =IFERROR(D42-C42,"n.a.") -> -0.0002839916
A97: CRTO | B97: =B56 -> n.a. | C97: =C56 -> 0.34785904 | D97: =D56 -> 0.34623711 | E97: =E56 -> 0.27320443 | F97: =IFERROR(D56-C56,"n.a.") -> -0.0016219263
A98: APP | B98: =B70 -> n.a. | C98: =C70 -> 0.7480523 | D98: =D70 -> 0.82333242 | E98: =E70 -> 0.84190875 | F98: =IFERROR(D70-C70,"n.a.") -> 0.075280122
A99: Adj. EBITDA less capex and leases
A100: PUBM | B100: =B16 -> 0.1756275 | C100: =C16 -> 0.18425715 | D100: =D16 -> 0.094173035 | E100: =E16 -> 0.063700765 | F100: =IFERROR(D16-C16,"n.a.") -> -0.090084114
A101: MGNI | B101: =B30 -> n.a. | C101: =C30 -> 0.24677811 | D101: =D30 -> 0.22075973 | E101: =E30 -> 0.239276 | F101: =IFERROR(D30-C30,"n.a.") -> -0.026018381
A102: TTD | B102: =B44 -> n.a. | C102: =C44 -> 0.36959078 | D102: =D44 -> 0.34067308 | E102: =E44 -> 0.22364618 | F102: =IFERROR(D44-C44,"n.a.") -> -0.028917698
A103: CRTO | B103: =B58 -> n.a. | C103: =C58 -> 0.27820841 | D103: =D58 -> 0.25877116 | E103: =E58 -> 0.093132032 | F103: =IFERROR(D58-C58,"n.a.") -> -0.019437251
A104: APP | B104: =B72 -> n.a. | C104: =C72 -> 0.74009618 | D104: =D72 -> 0.81983981 | E104: =E72 -> n.a. | F104: =IFERROR(D72-C72,"n.a.") -> 0.079743636
A106: Own vs cloud reading
A107: Owners (PUBM, CRTO, MGNI) carry 8% to 16% of net revenue in D&A and 8% to 18% in capex; the renter (APP) carries about 2% D&A and near-zero capex but 12% cost of revenue, mostly hosting.
...

Sheet DCF
A1: PubMatic (PUBM): discounted cash flow
A2: $ in millions except per share. Yellow cells are adjustable assumptions (blue text = input). Defaults are illustrative placeholders, not a view: set your own. Base year links to the model.
A4: GLOBAL ASSUMPTIONS | B4: Input
A5: Valuation date | B5: 46295 | H5: Cash flows before this date are excluded; 2026E is prorated for the remaining stub.
A6: WACC | B6: 0.11 | H6: Placeholder. Small-cap ad-tech, high beta: 10% to 13% is a typical range to test.
A7: Terminal growth rate | B7: 0.03 | H7: Used when terminal method = 1.
A8: Terminal method (1 = perpetuity growth, 2 = exit multiple) | B8: 1
A9: Exit multiple, EV / Adj. EBITDA | B9: 10 | H9: Used when terminal method = 2. Compare with Comps section 7 (PUBM trades near 11.7x LTM).
A10: Cash tax rate | B10: 0.25 | H10: Applied to EBIT after SBC and D&A. Ignores NOLs and the valuation allowance.
A11: Treat SBC as a cash cost (1 = yes, 0 = no) | B11: 1 | H11: 1 is the conservative and generally preferred treatment: SBC is a real cost to shareholders. 0 adds it back like Adjusted EBITDA does.
A12: Mid-year convention (1 = yes, 0 = no) | B12: 1
A14: CAPITAL STRUCTURE (linked to Comps) | B14: Value
A15: Basic shares outstanding (M) | B15: =Comps!B57 -> 45.55 | H15: Class A + Class B.
A16: Options outstanding (M) | B16: 7.3 | H16: From 10-Q, per Comps note. Treasury stock method at the DCF price (closed form, no circularity).
A17: Weighted-average option strike ($) | B17: 12.58
A18: RSUs outstanding (M) | B18: 5.6
A19: Cash and marketable securities | B19: =Comps!B61 -> 137.507 | H19: 6/30/26.
A20: Debt | B20: =Comps!B59 -> 0 | H20: Revolver undrawn.
A21: Current share price ($) | B21: =Comps!B56 -> 18.8 | H21: Input lives on Comps row 56.
A23: PROJECTIONS | B23: FY2025A | C23: FY2026E | D23: FY2027E | E23: FY2028E | F23: FY2029E | G23: FY2030E
A24: Net revenue growth | B24: ='Income Statement'!AD9/'Income Statement'!AC9-1 -> -0.028600269 | C24: 0.06 | D24: 0.1 | E24: 0.1 | F24: 0.09 | G24: 0.08 | H24: Placeholder: 6M26 net revenue was up 4.6% YoY (Q2 up 10.5%).
A25: Net revenue | B25: ='Income Statement'!AD9/1000 -> 282.926 | C25: =B25*(1+C24) -> 299.90156 | D25: =C25*(1+D24) -> 329.89172 | E25: =D25*(1+E24) -> 362.88089 | F25: =E25*(1+F24) -> 395.54017 | G25: =F25*(1+G24) -> 427.18338
A26: Adj. EBITDA margin | B26: =B27/B25 -> 0.21786616 | C26: 0.22 | D26: 0.24 | E26: 0.26 | F26: 0.27 | G26: 0.28 | H26: FY2025A was 21.8%; LTM about 19%.
A27: Adjusted EBITDA | B27: ='Income Statement'!AD51/1000 -> 61.64 | C27: =C25*C26 -> 65.978343 | D27: =D25*D26 -> 79.174012 | E27: =E25*E26 -> 94.349031 | F27: =F25*F26 -> 106.79585 | G27: =G25*G26 -> 119.61135
A28: SBC, % of net revenue | B28: =B29/B25 -> 0.13564678 | C28: 0.12 | D28: 0.11 | E28: 0.1 | F28: 0.09 | G28: 0.08
A29: Stock-based compensation | B29: ='Income Statement'!AD59/1000 -> 38.378 | C29: =C25*C28 -> 35.988187 | D29: =D25*D28 -> 36.288089 | E29: =E25*E28 -> 36.288089 | F29: =F25*F28 -> 35.598615 | G29: =G25*G28 -> 34.17467
A30: D&A, % of net revenue | B30: =B31/B25 -> 0.15470123 | C30: 0.14 | D30: 0.13 | E30: 0.12 | F30: 0.11 | G30: 0.1
A31: Depreciation and amortization | B31: ='Income Statement'!AD47/1000 -> 43.769 | C31: =C25*C30 -> 41.986218 | D31: =D25*D30 -> 42.885923 | E31: =E25*E30 -> 43.545707 | F31: =F25*F30 -> 43.509418 | G31: =G25*G30 -> 42.718338
A32: EBIT (Adj. EBITDA less SBC less D&A) | B32: =B27-B29-B31 -> -20.507 | C32: =C27-C29-C31 -> -11.996062 | D32: =D27-D29-D31 -> 0 | E32: =E27-E29-E31 -> 14.515236 | F32: =F27-F29-F31 -> 27.687812 | G32: =G27-G29-G31 -> 42.718338
A33: Cash taxes | C33: =MAX(0,C32)*$B$10 -> 0 | D33: =MAX(0,D32)*$B$10 -> 0 | E33: =MAX(0,E32)*$B$10 -> 3.6288089 | F33: =MAX(0,F32)*$B$10 -> 6.9219529 | G33: =MAX(0,G32)*$B$10 -> 10.679585
A34: Capex incl. capitalized software, % of net revenue | B34: =B35/B25 -> 0.12319829 | C34: 0.1 | D34: 0.1 | E34: 0.09 | F34: 0.09 | G34: 0.08
A35: Capex incl. capitalized software | B35: =-('Cash Flow'!AC26+'Cash Flow'!AC27)/1000 -> 34.856 | C35: =C25*C34 -> 29.990156 | D35: =D25*D34 -> 32.989172 | E35: =E25*E34 -> 32.65928 | F35: =F25*F34 -> 35.598615 | G35: =G25*G34 -> 34.17467
A36: Change in NWC, % of change in net revenue | C36: 0.1 | D36: 0.1 | E36: 0.1 | F36: 0.1 | G36: 0.1 | H36: Receivable and payable swings are large and lumpy at PUBM; replace with a days-based build if you want.
A37: Change in net working capital | C37: =(C25-B25)*C36 -> 1.697556 | D37: =(D25-C25)*D36 -> 2.9990156 | E37: =(E25-D25)*E36 -> 3.2989172 | F37: =(F25-E25)*F36 -> 3.265928 | G37: =(G25-F25)*G36 -> 3.1643213
A38: Unlevered free cash flow | C38: =C27-$B$11*C29-C33-C35-C37 -> -1.697556 | D38: =D27-$B$11*D29-D33-D35-D37 -> 6.8977359 | E38: =E27-$B$11*E29-E33-E35-E37 -> 18.473936 | F38: =F27-$B$11*F29-F33-F35-F37 -> 25.410734 | G38: =G27-$B$11*G29-G33-G35-G37 -> 37.4181
A39: Fraction of year included | C39: =MAX(0,MIN(1,(DATE(2026,12,31)-$B$5)/365)) -> 0.25205479 | D39: 1 | E39: 1 | F39: 1 | G39: 1 | H39: 2026E cash flow is prorated for the part of the year after the valuation date.
A40: Years from valuation date to year end | C40: =C39 -> 0.25205479 | D40: =C40+1 -> 1.2520548 | E40: =D40+1 -> 2.2520548 | F40: =E40+1 -> 3.2520548 | G40: =F40+1 -> 4.2520548
A41: Discount period (years) | C41: =C40-$B$12*0.5*C39 -> 0.1260274 | D41: =D40-$B$12*0.5*D39 -> 0.75205479 | E41: =E40-$B$12*0.5*E39 -> 1.7520548 | F41: =F40-$B$12*0.5*F39 -> 2.7520548 | G41: =G40-$B$12*0.5*G39 -> 3.7520548
A42: Discount factor | C42: =1/(1+$B$6)^C41 -> 0.98693389 | D42: =1/(1+$B$6)^D41 -> 0.92451644 | E42: =1/(1+$B$6)^E41 -> 0.83289769 | F42: =1/(1+$B$6)^F41 -> 0.75035828 | G42: =1/(1+$B$6)^G41 -> 0.67599845
A43: PV of unlevered FCF | C43: =C38*C39*C42 -> -0.42228644 | D43: =D38*D39*D42 -> 6.3770702 | E43: =E38*E39*E42 -> 15.386899 | F43: =F38*F39*F42 -> 19.067155 | G43: =G38*G39*G42 -> 25.294577
A45: VALUATION | B45: Value
A46: Sum of PV of FCF (stub 2026E to 2030E) | B46: =SUM(C43:G43) -> 65.703415
A47: Terminal value (undiscounted) | B47: =IF($B$8=1,G38*(1+B7)/(B6-B7),B9*G27) -> 481.75804 | H47: Method 1: Gordon growth on FY2030E UFCF. Method 2: multiple times FY2030E Adj. EBITDA.
A48: PV of terminal value | B48: =B47/(1+B6)^G40 -> 309.11009 | H48: Discounted from the end of FY2030E.
A49: Enterprise value | B49: =B46+B48 -> 374.8135
A50: Plus: cash less debt | B50: =B19-B20 -> 137.507
A51: Equity value | B51: =B49+B50 -> 512.3205
A52: Implied value per share ($), diluted | B52: =IF((B51+B16*B17)/(B15+B18+B16)>B17,(B51+B16*B17)/(B15+B18+B16),B51/(B15+B18)) -> 10.016041 | H52: Options via treasury method on the implied price, RSUs counted in full.
A53: Upside / (downside) vs current price | B53: =B52/B21-1 -> -0.46723186
A54: Terminal value as % of enterprise value | B54: =B48/B49 -> 0.82470371 | H54: Above about 75% means the answer is mostly the terminal assumption.
A55: Implied EV / LTM Adj. EBITDA | B55: =B49/Comps!B72 -> 6.1270066 | H55: Compare with the current 11.7x.
A56: Implied terminal EV / FY2030E Adj. EBITDA | B56: =B47/G27 -> 4.0276951
A57: Implied perpetual growth in exit-multiple case | B57: =(B47*B6-G38)/(B47+G38) -> 0.03 | H57: Sanity check: if this is above about 4%, the exit multiple is aggressive.
A59: SENSITIVITY 1: WACC vs TERMINAL GROWTH (perpetuity method)
A60: Implied value per share ($). Rows = WACC; columns = terminal growth
C61: 0.02 | D61: 0.025 | E61: 0.03 | F61: 0.035 | G61: 0.04
